Workbook

Sheet Open Positions
A2: All Accounts 08/07/2025 | B2: IndexIQ Advisors LLC
A3: COB Date | B3: Account | C3: Account Name | D3: Market | E3: Trade Date | F3: Long Qty | G3: Short Qty | H3: Curr | I3: GMI Exch Code | J3: GMI Prod Code | K3: Product | L3: Month | M3: Year | N3: Contract Day | O3: P/C | P3: Strike Price | Q3: Trade Price | R3: Stl Price
A4: 45875 | B4: 102702 | D4: CME (IMM) | E4: 45818 | F4: 1 | H4: USD | I4: 16 | J4: ES | K4: EMINI S&P 500 | L4: 9 | M4: 25 | Q4: 6079 | R4: 6371
A5: 45875 | B5: 102702 | D5: CME (IMM) | E5: 45818 | F5: 2 | H5: USD | I5: 16 | J5: ES | K5: EMINI S&P 500 | L5: 9 | M5: 25 | Q5: 6079.5 | R5: 6371
A6: 45875 | B6: 102703 | D6: CME (IMM) | E6: 45818 | F6: 25 | H6: USD | I6: 16 | J6: ES | K6: EMINI S&P 500 | L6: 9 | M6: 25 | Q6: 6064 | R6: 6371
A7: 45875 | B7: 102702 | D7: CME (IMM) | E7: 45818 | F7: 79 | H7: USD | I7: 16 | J7: ES | K7: EMINI S&P 500 | L7: 9 | M7: 25 | Q7: 6064 | R7: 6371
A8: 45875 | B8: 102702 | D8: CME (IMM) | E8: 45819 | F8: 1 | H8: USD | I8: 16 | J8: ES | K8: EMINI S&P 500 | L8: 9 | M8: 25 | Q8: 6112.25 | R8: 6371
A9: 45875 | B9: 102703 | D9: CME (IMM) | E9: 45820 | F9: 1 | H9: USD | I9: 16 | J9: ES | K9: EMINI S&P 500 | L9: 9 | M9: 25 | Q9: 6092.75 | R9: 6371
A10: 45875 | B10: 102702 | D10: CME (IMM) | E10: 45820 | F10: 2 | H10: USD | I10: 16 | J10: ES | K10: EMINI S&P 500 | L10: 9 | M10: 25 | Q10: 6092.75 | R10: 6371
A11: 45875 | B11: 102702 | D11: CME (IMM) | E11: 45821 | F11: 1 | H11: USD | I11: 16 | J11: ES | K11: EMINI S&P 500 | L11: 9 | M11: 25 | Q11: 6039.5 | R11: 6371
A12: 45875 | B12: 102702 | D12: CME (IMM) | E12: 45821 | F12: 1 | H12: USD | I12: 16 | J12: ES | K12: EMINI S&P 500 | L12: 9 | M12: 25 | Q12: 6040.5 | R12: 6371
A13: 45875 | B13: 102702 | D13: CME (IMM) | E13: 45821 | F13: 1 | H13: USD | I13: 16 | J13: ES | K13: EMINI S&P 500 | L13: 9 | M13: 25 | Q13: 6038.75 | R13: 6371
A14: 45875 | B14: 102702 | D14: CME (IMM) | E14: 45821 | F14: 2 | H14: USD | I14: 16 | J14: ES | K14: EMINI S&P 500 | L14: 9 | M14: 25 | Q14: 6039.75 | R14: 6371
A15: 45875 | B15: 102703 | D15: CME (IMM) | E15: 45824 | F15: 1 | H15: USD | I15: 16 | J15: ES | K15: EMINI S&P 500 | L15: 9 | M15: 25 | Q15: 6103 | R15: 6371
... A66: 45875 | B66: 102703 | D66: CME (IMM) | E66: 45874 | F66: 1 | H66: USD | I66: 16 | J66: ES | K66: EMINI S&P 500 | L66: 9 | M66: 25 | Q66: 6345 | R66: 6371

Sheet Purchase&Sales
A2: All Accounts 08/07/2025 | B2: IndexIQ Advisors LLC
A3: COB Date | B3: Trade Date | C3: Account | D3: Account name | E3: Trade Type | F3: Buy/Sell | G3: Quantity | H3: Market | I3: Product | J3: Contract Month | K3: Contract Year | L3: Put/Call Indicator | M3: Strike Price | N3: Contract Currency | O3: Trade Price | P3: Realized P&L (local) | Q3: Net Realized P&L (local) | R3: Clearing + Execution Commission (local) | S3: Total Fees (local)
A4: 45875 | B4: 45818 | C4: 102702 | E4: Purchase & Sale | F4: B | G4: 4 | H4: CME (IMM) | I4: EMINI S&P 500 | J4: 9 | K4: 25 | N4: USD | O4: 6064 | P4: -1212800 | Q4: -1212800 | R4: 0 | S4: 0
A5: 45875 | B5: 45875 | C5: 102702 | E5: Purchase & Sale | F5: S | G5: 4 | H5: CME (IMM) | I5: EMINI S&P 500 | J5: 9 | K5: 25 | N5: USD | O5: 6327.25 | P5: 1265450 | Q5: 1265450 | R5: 0 | S5: 0
A6: 45875 | B6: 45818 | C6: 102703 | E6: Purchase & Sale | F6: B | G6: 1 | H6: CME (IMM) | I6: EMINI S&P 500 | J6: 9 | K6: 25 | N6: USD | O6: 6064 | P6: -303200 | Q6: -303200 | R6: 0 | S6: 0
A7: 45875 | B7: 45875 | C7: 102703 | E7: Purchase & Sale | F7: S | G7: 1 | H7: CME (IMM) | I7: EMINI S&P 500 | J7: 9 | K7: 25 | N7: USD | O7: 6327 | P7: 316350 | Q7: 316350 | R7: 0 | S7: 0

Sheet Confirmed Trades
A2: All Accounts 08/07/2025 | B2: IndexIQ Advisors LLC
A3: COB Date | B3: Account | C3: Account Name | D3: Trade Type | E3: Buy/ Sell | F3: Quantity | G3: Market | H3: Product | I3: Contract Month | J3: Contract Year | K3: P/C | L3: Strike Price | M3: Contract Currency | N3: Trade Price | O3: Executing Broker | P3: Clearing + Execution Commission (local) | Q3: Total Fees (local) | R3: Option Premium (local) | S3: Trade Date
A4: 45875 | B4: 102702 | D4: New Trade | E4: S | F4: 4 | G4: CME (IMM) | H4: EMINI S&P 500 | I4: 9 | J4: 25 | M4: USD | N4: 6327.25 | O4: GOLDMAN SACHS | P4: -3.6 | Q4: -5.6 | R4: 0 | S4: 45875
A5: 45875 | B5: 102703 | D5: New Trade | E5: S | F5: 1 | G5: CME (IMM) | H5: EMINI S&P 500 | I5: 9 | J5: 25 | M5: USD | N5: 6327 | O5: GOLDMAN SACHS | P5: -0.9 | Q5: -1.4 | R5: 0 | S5: 45875

Sheet Intial Margin
A1: COB Date | B1: GS Account Number | C1: Client Account Name | D1: Account Type | E1: Currency | F1: Beginning Account Balance (Local) | G1: Ending Account Balance (Local) | H1: Gross Realized P&L (Local) | I1: Net Realized P&L (Local) | J1: Commission & Fees (Local) | K1: Open Trade Equity (Local) | L1: Total Equity (Local) | M1: Initial Margin Requirement (Local) | N1: Maintenance Margin Requirement (Local) | O1: Excess/Deficit (Local) | P1: Security on Deposit (Local)
A2: 45875 | B2: 102702 | D2: 1 | E2: USD | F2: -1928048 | G2: -1583484.2 | H2: 52650 | I2: 52640.8 | J2: -9.2 | K2: 2007062.5 | L2: 423578.3 | M2: 3947000.8 | N2: 3947000.8 | O2: 6471886.9 | P2: 9995309.4
A3: 45875 | B3: 102703 | D3: 1 | E3: USD | F3: -623661.07 | G3: -504852.3 | H3: 13150 | I3: 13147.7 | J3: -2.3 | K3: 660487.5 | L3: 155635.2 | M3: 1450789.5 | N3: 1450789.5 | O3: 1191403.4 | P3: 2486557.6

Sheet VM
A1: 00102702 | C1: Beginning Account Balance | D1: Total Comms/ Fees | E1: Gross P/L | F1: Net P/L | G1: Cash Amount (Trade Date-1 VM) | H1: Ending Account Balance/ Trade Date +1 Beginning Account Balance | I1: Open Trade Equity | J1: Total Equity (Trade Date VM) | K1: 00102703 | L1: Beginning Account Balance | M1: Total Comms/ Fees | N1: Gross P/L | O1: Net P/L | P1: Cash Amount (Trade Date-1 VM) | Q1: Ending Account Balance/ Trade Date +1 Beginning Account Balance | R1: Open Trade Equity | S1: Total Equity (Trade Date VM)
A2: 45183 | B2: VPIE | C2: -7463.12 | D2: -4.5 | E2: 0 | F2: =SUM(D2:E2) -> -4.5 | G2: 258992.91 | H2: 251525.29 | I2: 187495.21 | J2: 439020.5 | K2: MAINSP | L2: -2106.42 | M2: -2.25 | N2: 0 | O2: -2.25 | P2: 29094.6 | Q2: 26985.93 | R2: 20961.825 | S2: 47947.755
A3: 45184 | B3: VPIE | C3: =H2 -> 251525.29 | D3: -139.7 | E3: -114485.1 | F3: =SUM(D3:E3) -> -114624.8 | G3: =-J2 -> -439020.5 | H3: =SUM(C3+F3+G3) -> -302120.01 | I3: -375419.39 | J3: =SUM(H3:I3) -> -677539.4 | K3: MAINSP | L3: 26985.93 | M3: -85.5 | N3: 0 | O3: =SUM(M3:N3) -> -85.5 | P3: =-S2 -> -47947.755 | Q3: =SUM(L3+O3+P3) -> -21047.325 | R3: -53138.175 | S3: =SUM(Q3:R3) -> -74185.5
A4: 45187 | B4: VPIE | C4: =H3 -> -302120.01 | D4: -13.5 | E4: 0 | F4: =SUM(D4:E4) -> -13.5 | G4: =-J3 -> 677539.4 | H4: =SUM(C4+F4+G4) -> 375405.89 | I4: -345569.39 | J4: =SUM(H4:I4) -> 29836.5 | K4: MAINSP | L4: =Q3 -> -21047.325 | M4: -4.5 | N4: 0 | O4: =SUM(M4:N4) -> -4.5 | P4: =-S3 -> 74185.5 | Q4: =SUM(L4+O4+P4) -> 53133.675 | R4: -42388.175 | S4: =SUM(Q4:R4) -> 10745.5
A5: 45188 | B5: VPIE | C5: =H4 -> 375405.89 | D5: -134.28 | E5: =SUMIF('Purchase&Sales'!$C:$C,'VM'!$A$1,'Purchase&Sales'!$P:$P) -> 0 | F5: =SUM(D5:E5) -> -134.28 | G5: =-J4 -> -29836.5 | H5: =SUM(C5+F5+G5) -> 345435.11 | I5: -452369.39 | J5: =SUM(H5:I5) -> -106934.28 | K5: MAINSP | L5: =Q4 -> 53133.675 | M5: 0 | N5: 0 | O5: =SUM(M5:N5) -> 0 | P5: =-S4 -> -10745.5 | Q5: =SUM(L5+O5+P5) -> 42388.175 | R5: -80338.175 | S5: =SUM(Q5:R5) -> -37950 | U5: VPIE - HAD TO ADJUST COMMS WHICH AFFECTED VM BY $100
A6: 45189 | B6: VPIE | C6: 341351.06 | D6: -4.5 | E6: -4084.05 | F6: -4088.55 | G6: 111018.33 | H6: 448280.84 | I6: -853810.33 | J6: -405529.5 | K6: MAINSP | L6: 42388.175 | M6: -4.5 | N6: 0 | O6: -4.5 | P6: 37950 | Q6: 80333.675 | R6: -227613.18 | S6: -147279.5
B7: VPIE | C7: =H6 -> 448280.84 | D7: =(SUMIF('Confirmed Trades'!$B:$B,'VM'!$A$1,'Confirmed Trades'!$P:$P))+SUMIF('Confirmed Trades'!$B:$B,'VM'!$A$1,'Confirmed Trades'!$Q:$Q) -> 0 | E7: =SUMIF('Purchase&Sales'!$C:$C,'VM'!$A$1,'Purchase&Sales'!$P:$P) -> 0 | F7: =SUM(D7:E7) -> 0 | G7: =-J6 -> 405529.5 | H7: =SUM(C7+F7+G7) -> 853810.33 | I7: ='CALC'!$N$5 -> #NAME? | J7: =SUM(H7:I7) -> #NAME? | K7: MAINSP | L7: =Q6 -> 80333.675 | M7: =(SUMIF('Confirmed Trades'!$B:$B,'VM'!$K$1,'Confirmed Trades'!$P:$P))+SUMIF('Confirmed Trades'!$B:$B,'VM'!$K$1,'Confirmed Trades'!$Q:$Q) -> 0 | N7: =SUMIF('Purchase&Sales'!$C:$C,'VM'!$K$1,'Purchase&Sales'!$Q:$Q) -> 0 | O7: =SUM(M7:N7) -> 0 | P7: =-S6 -> 147279.5 | Q7: =SUM(L7+O7+P7) -> 227613.18 | R7: ='CALC'!$R$5 -> #NAME? | S7: =SUM(Q7:R7) -> #NAME?
B8: VPIE | C8: =H7 -> 853810.33 | D8: =(SUMIF('Confirmed Trades'!$B:$B,'VM'!$A$1,'Confirmed Trades'!$P:$P))+SUMIF('Confirmed Trades'!$B:$B,'VM'!$A$1,'Confirmed Trades'!$Q:$Q) -> 0 | E8: =SUMIF('Purchase&Sales'!$C:$C,'VM'!$A$1,'Purchase&Sales'!$P:$P) -> 0 | F8: =SUM(D8:E8) -> 0 | G8: =-J7 -> #NAME? | H8: =SUM(C8+F8+G8) -> #NAME? | I8: ='CALC'!$N$5 -> #NAME? | J8: =SUM(H8:I8) -> #NAME? | K8: MAINSP | L8: =Q7 -> 227613.18 | M8: =(SUMIF('Confirmed Trades'!$B:$B,'VM'!$K$1,'Confirmed Trades'!$P:$P))+SUMIF('Confirmed Trades'!$B:$B,'VM'!$K$1,'Confirmed Trades'!$Q:$Q) -> 0 | N8: =SUMIF('Purchase&Sales'!$C:$C,'VM'!$K$1,'Purchase&Sales'!$Q:$Q) -> 0 | O8: =SUM(M8:N8) -> 0 | P8: =-S7 -> #NAME? | Q8: =SUM(L8+O8+P8) -> #NAME? | R8: ='CALC'!$R$5 -> #NAME? | S8: =SUM(Q8:R8) -> #NAME?
B9: VPIE | C9: =H8 -> #NAME? | D9: =(SUMIF('Confirmed Trades'!$B:$B,'VM'!$A$1,'Confirmed Trades'!$P:$P))+SUMIF('Confirmed Trades'!$B:$B,'VM'!$A$1,'Confirmed Trades'!$Q:$Q) -> 0 | E9: =SUMIF('Purchase&Sales'!$C:$C,'VM'!$A$1,'Purchase&Sales'!$P:$P) -> 0 | F9: =SUM(D9:E9) -> 0 | G9: =-J8 -> #NAME? | H9: =SUM(C9+F9+G9) -> #NAME? | I9: ='CALC'!$N$5 -> #NAME? | J9: =SUM(H9:I9) -> #NAME? | K9: MAINSP | L9: =Q8 -> #NAME? | M9: =(SUMIF('Confirmed Trades'!$B:$B,'VM'!$K$1,'Confirmed Trades'!$P:$P))+SUMIF('Confirmed Trades'!$B:$B,'VM'!$K$1,'Confirmed Trades'!$Q:$Q) -> 0 | N9: =SUMIF('Purchase&Sales'!$C:$C,'VM'!$K$1,'Purchase&Sales'!$Q:$Q) -> 0 | O9: =SUM(M9:N9) -> 0 | P9: =-S8 -> #NAME? | Q9: =SUM(L9+O9+P9) -> #NAME? | R9: ='CALC'!$R$5 -> #NAME? | S9: =SUM(Q9:R9) -> #NAME?
B10: VPIE | C10: =H9 -> #NAME? | D10: =(SUMIF('Confirmed Trades'!$B:$B,'VM'!$A$1,'Confirmed Trades'!$P:$P))+SUMIF('Confirmed Trades'!$B:$B,'VM'!$A$1,'Confirmed Trades'!$Q:$Q) -> 0 | E10: =SUMIF('Purchase&Sales'!$C:$C,'VM'!$A$1,'Purchase&Sales'!$P:$P) -> 0 | F10: =SUM(D10:E10) -> 0 | G10: =-J9 -> #NAME? | H10: =SUM(C10+F10+G10) -> #NAME? | I10: ='CALC'!$N$5 -> #NAME? | J10: =SUM(H10:I10) -> #NAME? | K10: MAINSP | L10: =Q9 -> #NAME? | M10: =(SUMIF('Confirmed Trades'!$B:$B,'VM'!$K$1,'Confirmed Trades'!$P:$P))+SUMIF('Confirmed Trades'!$B:$B,'VM'!$K$1,'Confirmed Trades'!$Q:$Q) -> 0 | N10: =SUMIF('Purchase&Sales'!$C:$C,'VM'!$K$1,'Purchase&Sales'!$Q:$Q) -> 0 | O10: =SUM(M10:N10) -> 0 | P10: =-S9 -> #NAME? | Q10: =SUM(L10+O10+P10) -> #NAME? | R10: ='CALC'!$R$5 -> #NAME? | S10: =SUM(Q10:R10) -> #NAME?
B11: VPIE | C11: =H10 -> #NAME? | D11: =(SUMIF('Confirmed Trades'!$B:$B,'VM'!$A$1,'Confirmed Trades'!$P:$P))+SUMIF('Confirmed Trades'!$B:$B,'VM'!$A$1,'Confirmed Trades'!$Q:$Q) -> 0 | E11: =SUMIF('Purchase&Sales'!$C:$C,'VM'!$A$1,'Purchase&Sales'!$P:$P) -> 0 | F11: =SUM(D11:E11) -> 0 | G11: =-J10 -> #NAME? | H11: =SUM(C11+F11+G11) -> #NAME? | I11: ='CALC'!$N$5 -> #NAME? | J11: =SUM(H11:I11) -> #NAME? | K11: MAINSP | L11: =Q10 -> #NAME? | M11: =(SUMIF('Confirmed Trades'!$B:$B,'VM'!$K$1,'Confirmed Trades'!$P:$P))+SUMIF('Confirmed Trades'!$B:$B,'VM'!$K$1,'Confirmed Trades'!$Q:$Q) -> 0 | N11: =SUMIF('Purchase&Sales'!$C:$C,'VM'!$K$1,'Purchase&Sales'!$Q:$Q) -> 0 | O11: =SUM(M11:N11) -> 0 | P11: =-S10 -> #NAME? | Q11: =SUM(L11+O11+P11) -> #NAME? | R11: ='CALC'!$R$5 -> #NAME? | S11: =SUM(Q11:R11) -> #NAME?
B12: VPIE | C12: =H11 -> #NAME? | D12: =(SUMIF('Confirmed Trades'!$B:$B,'VM'!$A$1,'Confirmed Trades'!$P:$P))+SUMIF('Confirmed Trades'!$B:$B,'VM'!$A$1,'Confirmed Trades'!$Q:$Q) -> 0 | E12: =SUMIF('Purchase&Sales'!$C:$C,'VM'!$A$1,'Purchase&Sales'!$P:$P) -> 0 | F12: =SUM(D12:E12) -> 0 | G12: =-J11 -> #NAME? | H12: =SUM(C12+F12+G12) -> #NAME? | I12: ='CALC'!$N$5 -> #NAME? | J12: =SUM(H12:I12) -> #NAME? | K12: MAINSP | L12: =Q11 -> #NAME? | M12: =(SUMIF('Confirmed Trades'!$B:$B,'VM'!$K$1,'Confirmed Trades'!$P:$P))+SUMIF('Confirmed Trades'!$B:$B,'VM'!$K$1,'Confirmed Trades'!$Q:$Q) -> 0 | N12: =SUMIF('Purchase&Sales'!$C:$C,'VM'!$K$1,'Purchase&Sales'!$Q:$Q) -> 0 | O12: =SUM(M12:N12) -> 0 | P12: =-S11 -> #NAME? | Q12: =SUM(L12+O12+P12) -> #NAME? | R12: ='CALC'!$R$5 -> #NAME? | S12: =SUM(Q12:R12) -> #NAME?
B13: VPIE | C13: =H12 -> #NAME? | D13: =(SUMIF('Confirmed Trades'!$B:$B,'VM'!$A$1,'Confirmed Trades'!$P:$P))+SUMIF('Confirmed Trades'!$B:$B,'VM'!$A$1,'Confirmed Trades'!$Q:$Q) -> 0 | E13: =SUMIF('Purchase&Sales'!$C:$C,'VM'!$A$1,'Purchase&Sales'!$P:$P) -> 0 | F13: =SUM(D13:E13) -> 0 | G13: =-J12 -> #NAME? | H13: =SUM(C13+F13+G13) -> #NAME? | I13: ='CALC'!$N$5 -> #NAME? | J13: =SUM(H13:I13) -> #NAME? | K13: MAINSP | L13: =Q12 -> #NAME? | M13: =(SUMIF('Confirmed Trades'!$B:$B,'VM'!$K$1,'Confirmed Trades'!$P:$P))+SUMIF('Confirmed Trades'!$B:$B,'VM'!$K$1,'Confirmed Trades'!$Q:$Q) -> 0 | N13: =SUMIF('Purchase&Sales'!$C:$C,'VM'!$K$1,'Purchase&Sales'!$Q:$Q) -> 0 | O13: =SUM(M13:N13) -> 0 | P13: =-S12 -> #NAME? | Q13: =SUM(L13+O13+P13) -> #NAME? | R13: ='CALC'!$R$5 -> #NAME? | S13: =SUM(Q13:R13) -> #NAME?
B14: VPIE | C14: =H13 -> #NAME? | D14: =(SUMIF('Confirmed Trades'!$B:$B,'VM'!$A$1,'Confirmed Trades'!$P:$P))+SUMIF('Confirmed Trades'!$B:$B,'VM'!$A$1,'Confirmed Trades'!$Q:$Q) -> 0 | E14: =SUMIF('Purchase&Sales'!$C:$C,'VM'!$A$1,'Purchase&Sales'!$P:$P) -> 0 | F14: =SUM(D14:E14) -> 0 | G14: =-J13 -> #NAME? | H14: =SUM(C14+F14+G14) -> #NAME? | I14: ='CALC'!$N$5 -> #NAME? | J14: =SUM(H14:I14) -> #NAME? | K14: MAINSP | L14: =Q13 -> #NAME? | M14: =(SUMIF('Confirmed Trades'!$B:$B,'VM'!$K$1,'Confirmed Trades'!$P:$P))+SUMIF('Confirmed Trades'!$B:$B,'VM'!$K$1,'Confirmed Trades'!$Q:$Q) -> 0 | N14: =SUMIF('Purchase&Sales'!$C:$C,'VM'!$K$1,'Purchase&Sales'!$Q:$Q) -> 0 | O14: =SUM(M14:N14) -> 0 | P14: =-S13 -> #NAME? | Q14: =SUM(L14+O14+P14) -> #NAME? | R14: ='CALC'!$R$5 -> #NAME? | S14: =SUM(Q14:R14) -> #NAME?
B15: VPIE | C15: =H14 -> #NAME? | D15: =(SUMIF('Confirmed Trades'!$B:$B,'VM'!$A$1,'Confirmed Trades'!$P:$P))+SUMIF('Confirmed Trades'!$B:$B,'VM'!$A$1,'Confirmed Trades'!$Q:$Q) -> 0 | E15: =SUMIF('Purchase&Sales'!$C:$C,'VM'!$A$1,'Purchase&Sales'!$P:$P) -> 0 | F15: =SUM(D15:E15) -> 0 | G15: =-J14 -> #NAME? | H15: =SUM(C15+F15+G15) -> #NAME? | I15: ='CALC'!$N$5 -> #NAME? | J15: =SUM(H15:I15) -> #NAME? | K15: MAINSP | L15: =Q14 -> #NAME? | M15: =(SUMIF('Confirmed Trades'!$B:$B,'VM'!$K$1,'Confirmed Trades'!$P:$P))+SUMIF('Confirmed Trades'!$B:$B,'VM'!$K$1,'Confirmed Trades'!$Q:$Q) -> 0 | N15: =SUMIF('Purchase&Sales'!$C:$C,'VM'!$K$1,'Purchase&Sales'!$Q:$Q) -> 0 | O15: =SUM(M15:N15) -> 0 | P15: =-S14 -> #NAME? | Q15: =SUM(L15+O15+P15) -> #NAME? | R15: ='CALC'!$R$5 -> #NAME? | S15: =SUM(Q15:R15) -> #NAME?
B16: VPIE | C16: =H15 -> #NAME? | D16: =(SUMIF('Confirmed Trades'!$B:$B,'VM'!$A$1,'Confirmed Trades'!$P:$P))+SUMIF('Confirmed Trades'!$B:$B,'VM'!$A$1,'Confirmed Trades'!$Q:$Q) -> 0 | E16: =SUMIF('Purchase&Sales'!$C:$C,'VM'!$A$1,'Purchase&Sales'!$P:$P) -> 0 | F16: =SUM(D16:E16) -> 0 | G16: =-J15 -> #NAME? | H16: =SUM(C16+F16+G16) -> #NAME? | I16: ='CALC'!$N$5 -> #NAME? | J16: =SUM(H16:I16) -> #NAME? | K16: MAINSP | L16: =Q15 -> #NAME? | M16: =(SUMIF('Confirmed Trades'!$B:$B,'VM'!$K$1,'Confirmed Trades'!$P:$P))+SUMIF('Confirmed Trades'!$B:$B,'VM'!$K$1,'Confirmed Trades'!$Q:$Q) -> 0 | N16: =SUMIF('Purchase&Sales'!$C:$C,'VM'!$K$1,'Purchase&Sales'!$Q:$Q) -> 0 | O16: =SUM(M16:N16) -> 0 | P16: =-S15 -> #NAME? | Q16: =SUM(L16+O16+P16) -> #NAME? | R16: ='CALC'!$R$5 -> #NAME? | S16: =SUM(Q16:R16) -> #NAME?
B17: VPIE | C17: =H16 -> #NAME? | D17: =(SUMIF('Confirmed Trades'!$B:$B,'VM'!$A$1,'Confirmed Trades'!$P:$P))+SUMIF('Confirmed Trades'!$B:$B,'VM'!$A$1,'Confirmed Trades'!$Q:$Q) -> 0 | E17: =SUMIF('Purchase&Sales'!$C:$C,'VM'!$A$1,'Purchase&Sales'!$P:$P) -> 0 | F17: =SUM(D17:E17) -> 0 | G17: =-J16 -> #NAME? | H17: =SUM(C17+F17+G17) -> #NAME? | I17: ='CALC'!$N$5 -> #NAME? | J17: =SUM(H17:I17) -> #NAME? | K17: MAINSP | L17: =Q16 -> #NAME? | M17: =(SUMIF('Confirmed Trades'!$B:$B,'VM'!$K$1,'Confirmed Trades'!$P:$P))+SUMIF('Confirmed Trades'!$B:$B,'VM'!$K$1,'Confirmed Trades'!$Q:$Q) -> 0 | N17: =SUMIF('Purchase&Sales'!$C:$C,'VM'!$K$1,'Purchase&Sales'!$Q:$Q) -> 0 | O17: =SUM(M17:N17) -> 0 | P17: =-S16 -> #NAME? | Q17: =SUM(L17+O17+P17) -> #NAME? | R17: ='CALC'!$R$5 -> #NAME? | S17: =SUM(Q17:R17) -> #NAME?
B18: VPIE | C18: =H17 -> #NAME? | D18: =(SUMIF('Confirmed Trades'!$B:$B,'VM'!$A$1,'Confirmed Trades'!$P:$P))+SUMIF('Confirmed Trades'!$B:$B,'VM'!$A$1,'Confirmed Trades'!$Q:$Q) -> 0 | E18: =SUMIF('Purchase&Sales'!$C:$C,'VM'!$A$1,'Purchase&Sales'!$P:$P) -> 0 | F18: =SUM(D18:E18) -> 0 | G18: =-J17 -> #NAME? | H18: =SUM(C18+F18+G18) -> #NAME? | I18: ='CALC'!$N$5 -> #NAME? | J18: =SUM(H18:I18) -> #NAME? | K18: MAINSP | L18: =Q17 -> #NAME? | M18: =(SUMIF('Confirmed Trades'!$B:$B,'VM'!$K$1,'Confirmed Trades'!$P:$P))+SUMIF('Confirmed Trades'!$B:$B,'VM'!$K$1,'Confirmed Trades'!$Q:$Q) -> 0 | N18: =SUMIF('Purchase&Sales'!$C:$C,'VM'!$K$1,'Purchase&Sales'!$Q:$Q) -> 0 | O18: =SUM(M18:N18) -> 0 | P18: =-S17 -> #NAME? | Q18: =SUM(L18+O18+P18) -> #NAME? | R18: ='CALC'!$R$5 -> #NAME? | S18: =SUM(Q18:R18) -> #NAME?
... B26: VPIE | C26: =H25 -> #NAME? | D26: =(SUMIF('Confirmed Trades'!$B:$B,'VM'!$A$1,'Confirmed Trades'!$P:$P))+SUMIF('Confirmed Trades'!$B:$B,'VM'!$A$1,'Confirmed Trades'!$Q:$Q) -> 0 | E26: =SUMIF('Purchase&Sales'!$C:$C,'VM'!$A$1,'Purchase&Sales'!$P:$P) -> 0 | F26: =SUM(D26:E26) -> 0 | G26: =-J25 -> #NAME? | H26: =SUM(C26+F26+G26) -> #NAME? | I26: ='CALC'!$N$5 -> #NAME? | J26: =SUM(H26:I26) -> #NAME? | K26: MAINSP | L26: =Q25 -> #NAME? | M26: =(SUMIF('Confirmed Trades'!$B:$B,'VM'!$K$1,'Confirmed Trades'!$P:$P))+SUMIF('Confirmed Trades'!$B:$B,'VM'!$K$1,'Confirmed Trades'!$Q:$Q) -> 0 | N26: =SUMIF('Purchase&Sales'!$C:$C,'VM'!$K$1,'Purchase&Sales'!$Q:$Q) -> 0 | O26: =SUM(M26:N26) -> 0 | P26: =-S25 -> #NAME? | Q26: =SUM(L26+O26+P26) -> #NAME? | R26: ='CALC'!$R$5 -> #NAME? | S26: =SUM(Q26:R26) -> #NAME?

Sheet Calc
M1: 00102702 | Q1: 00102703 | V1: ESU5 | W1: SETTLEMENT PRICE | X1: =_xll.BDP(V1&" EQUITY","px_yest_close") -> #NAME?
M2: Contracts | N2: =SUMIF($A:$A,M1,$B:$B) -> 0 | Q2: Contracts | R2: =SUMIF($A:$A,Q1,$B:$B) -> 0
M3: Total Notional Long | N3: =SUMIF($A:$A,M1,$D:$D) -> 0 | Q3: Total Notional Long | R3: =SUMIF($A:$A,Q1,$D:$D) -> 0
M4: Avg Long Px | N4: =N3/N2 -> #DIV/0! | Q4: Avg Long Px | R4: =R3/R2 -> #DIV/0!
A5: Account | B5: Long Qty | C5: Trade Price | D5: Notional | M5: TOTAL OTE | N5: =($X$1-N4)*50*N2 -> #NAME? | Q5: TOTAL OTE | R5: =($X$1-R4)*50*R2 -> #NAME? | U5: REFRESH BB
A6: =IF(LEN('Open Positions'!B4)>0,'Open Positions'!B4,"") | B6: =IF(LEN('CALC'!A6)>0,'Open Positions'!F4,"") | C6: =IF(LEN(A6)>0,'Open Positions'!Q4,"") | D6: =IF(LEN(A6)>0,(B6*C6),"")
A7: =IF(LEN('Open Positions'!B5)>0,'Open Positions'!B5,"") | B7: =IF(LEN('CALC'!A7)>0,'Open Positions'!F5,"") | C7: =IF(LEN(A7)>0,'Open Positions'!Q5,"") | D7: =IF(LEN(A7)>0,(B7*C7),"")
A8: =IF(LEN('Open Positions'!B6)>0,'Open Positions'!B6,"") | B8: =IF(LEN('CALC'!A8)>0,'Open Positions'!F6,"") | C8: =IF(LEN(A8)>0,'Open Positions'!Q6,"") | D8: =IF(LEN(A8)>0,(B8*C8),"")
A9: =IF(LEN('Open Positions'!B7)>0,'Open Positions'!B7,"") | B9: =IF(LEN('CALC'!A9)>0,'Open Positions'!F7,"") | C9: =IF(LEN(A9)>0,'Open Positions'!Q7,"") | D9: =IF(LEN(A9)>0,(B9*C9),"")
A10: =IF(LEN('Open Positions'!B8)>0,'Open Positions'!B8,"") | B10: =IF(LEN('CALC'!A10)>0,'Open Positions'!F8,"") | C10: =IF(LEN(A10)>0,'Open Positions'!Q8,"") | D10: =IF(LEN(A10)>0,B10*C10,"")
A11: =IF(LEN('Open Positions'!B9)>0,'Open Positions'!B9,"") | B11: =IF(LEN('CALC'!A11)>0,'Open Positions'!F9,"") | C11: =IF(LEN(A11)>0,'Open Positions'!Q9,"") | D11: =IF(LEN(A11)>0,B11*C11,"")
A12: =IF(LEN('Open Positions'!B10)>0,'Open Positions'!B10,"") | B12: =IF(LEN('CALC'!A12)>0,'Open Positions'!F10,"") | C12: =IF(LEN(A12)>0,'Open Positions'!Q10,"") | D12: =IF(LEN(A12)>0,B12*C12,"")
A13: =IF(LEN('Open Positions'!B11)>0,'Open Positions'!B11,"") | B13: =IF(LEN('CALC'!A13)>0,'Open Positions'!F11,"") | C13: =IF(LEN(A13)>0,'Open Positions'!Q11,"") | D13: =IF(LEN(A13)>0,B13*C13,"")
A14: =IF(LEN('Open Positions'!B12)>0,'Open Positions'!B12,"") | B14: =IF(LEN('CALC'!A14)>0,'Open Positions'!F12,"") | C14: =IF(LEN(A14)>0,'Open Positions'!Q12,"") | D14: =IF(LEN(A14)>0,B14*C14,"")
A15: =IF(LEN('Open Positions'!B13)>0,'Open Positions'!B13,"") | B15: =IF(LEN('CALC'!A15)>0,'Open Positions'!F13,"") | C15: =IF(LEN(A15)>0,'Open Positions'!Q13,"") | D15: =IF(LEN(A15)>0,B15*C15,"")
A16: =IF(LEN('Open Positions'!B14)>0,'Open Positions'!B14,"") | B16: =IF(LEN('CALC'!A16)>0,'Open Positions'!F14,"") | C16: =IF(LEN(A16)>0,'Open Positions'!Q14,"") | D16: =IF(LEN(A16)>0,B16*C16,"")
A17: =IF(LEN('Open Positions'!B15)>0,'Open Positions'!B15,"") | B17: =IF(LEN('CALC'!A17)>0,'Open Positions'!F15,"") | C17: =IF(LEN(A17)>0,'Open Positions'!Q15,"") | D17: =IF(LEN(A17)>0,B17*C17,"")
A18: =IF(LEN('Open Positions'!B16)>0,'Open Positions'!B16,"") | B18: =IF(LEN('CALC'!A18)>0,'Open Positions'!F16,"") | C18: =IF(LEN(A18)>0,'Open Positions'!Q16,"") | D18: =IF(LEN(A18)>0,B18*C18,"")
A19: =IF(LEN('Open Positions'!B17)>0,'Open Positions'!B17,"") | B19: =IF(LEN('CALC'!A19)>0,'Open Positions'!F17,"") | C19: =IF(LEN(A19)>0,'Open Positions'!Q17,"") | D19: =IF(LEN(A19)>0,B19*C19,"")
A20: =IF(LEN('Open Positions'!B18)>0,'Open Positions'!B18,"") | B20: =IF(LEN('CALC'!A20)>0,'Open Positions'!F18,"") | C20: =IF(LEN(A20)>0,'Open Positions'!Q18,"") | D20: =IF(LEN(A20)>0,B20*C20,"")
A21: =IF(LEN('Open Positions'!B19)>0,'Open Positions'!B19,"") | B21: =IF(LEN('CALC'!A21)>0,'Open Positions'!F19,"") | C21: =IF(LEN(A21)>0,'Open Positions'!Q19,"") | D21: =IF(LEN(A21)>0,B21*C21,"")
... A858: =IF(LEN('Open Positions'!B856)>0,'Open Positions'!B856,"") | B858: =IF(LEN('CALC'!A858)>0,'Open Positions'!F856,"") | C858: =IF(LEN(A858)>0,'Open Positions'!Q856,"") | D858: =IF(LEN(A858)>0,B858*C858,"")

Sheet VM_2
A1: =TODAY() -> 45819 | J1: On Tuesday's change date in A3 to match Sat date
A2: 00102702 | C2: Beginning Account Balance | D2: Total Comms/ Fees | E2: Gross P/L | F2: Net P/L | G2: Cash Amount (Trade Date-1 VM) | H2: Ending Account Balance/ Trade Date +1 Beginning Account Balance | I2: Open Trade Equity | J2: Total Equity (Trade Date VM) | K2: 00102703 | L2: Beginning Account Balance | M2: Total Comms/ Fees | N2: Gross P/L | O2: Net P/L | P2: Cash Amount (Trade Date-1 VM) | Q2: Ending Account Balance/ Trade Date +1 Beginning Account Balance | R2: Open Trade Equity | S2: Total Equity (Trade Date VM) | U2: If doesn't Match see if diff is off by yesterdays wires. Call GS | Y2: EMAIL:
A3: =WORKDAY($A$1,-1,'HOLIDAYS'!$A:$A) -> 45818 | B3: VPIE | C3: =VLOOKUP(($A$3)-1,'VM HISTORY '!$A:$J,8,0) -> #N/A | D3: =(SUMIF('Confirmed Trades'!$B:$B,'VM'!$A$1,'Confirmed Trades'!$P:$P))+SUMIF('Confirmed Trades'!$B:$B,'VM'!$A$1,'Confirmed Trades'!$Q:$Q) -> 0 | E3: =SUMIF('Purchase&Sales'!$C:$C,'VM'!$A$1,'Purchase&Sales'!$P:$P) -> 0 | F3: =SUM(D3:E3) -> 0 | G3: =-VLOOKUP(($A$3)-1,'VM HISTORY '!$A:$J,10,0) -> #N/A | H3: =SUM(C3+F3+G3) -> #N/A | I3: ='CALC'!$N$5 -> #NAME? | J3: =SUM(H3:I3) -> #N/A | K3: MAINSP | L3: =VLOOKUP(($A$3)-1,'VM HISTORY '!$A:$Q,17,0) -> #N/A | M3: =(SUMIF('Confirmed Trades'!$B:$B,'VM'!$K$1,'Confirmed Trades'!$P:$P))+SUMIF('Confirmed Trades'!$B:$B,'VM'!$K$1,'Confirmed Trades'!$Q:$Q) -> 0 | N3: =SUMIF('Purchase&Sales'!$C:$C,'VM'!$K$1,'Purchase&Sales'!$Q:$Q) -> 0 | O3: =SUM(M3:N3) -> 0 | P3: =-VLOOKUP(($A$3)-1,'VM HISTORY '!$A:$S,19,0) -> #N/A | Q3: =SUM(L3+O3+P3) -> #N/A | R3: ='CALC'!$R$5 -> #NAME? | S3: =SUM(Q3:R3) -> #N/A | U3: Make sure matches GS statement | Y3: SA2 pls set up the below:
U4: VPIE | V4: =J3 -> #N/A | W4: =IF(V4>0,"RECEIVES","PAYS") -> #N/A | Y4: ="VPIE (001 02702) – NYLI "&W4&" "&DOLLAR(Z4) -> #N/A | Z4: =J3 -> #N/A
U5: =K3 -> MAINSP | V5: =S3 -> #N/A | W5: =IF(V5>0,"RECEIVES","PAYS") -> #N/A | Y5: ="MAINSP (001 02703) – NYLI "&W5&" "&DOLLAR(Z5) -> #N/A | Z5: =S3 -> #N/A
A6: Tuesday, enter Sat date above | H6: REFRESH BB CODES
A7: =WORKDAY($A$1,-1,'HOLIDAYS'!$A:$A) -> 45818 | B7: Formula
A9: *Any differences, plug into Beg bal in VM history so it doesn't carry each day | U9: Account | V9: GS Account | W9: Securites on Deposit | X9: Initial Margin Requirement | Y9: Initial Margin Call
U10: VPIE | V10: 102702 | W10: =VLOOKUP(V10,'Intial Margin'!$B$2:$P$3,15,0) -> #N/A | X10: =VLOOKUP(V10,'Intial Margin'!$B$2:$M$3,12,0) -> #N/A | Y10: =W10-X10 -> #N/A
U11: MAINSP | V11: 102703 | W11: =VLOOKUP(V11,'Intial Margin'!$B$2:$P$3,15,0) -> #N/A | X11: =VLOOKUP(V11,'Intial Margin'!$B$2:$M$3,12,0) -> #N/A | Y11: =W11-X11 -> #N/A

Sheet VM HISTORY 
A1: VM Formula: | B1: Ending Balance + Open Trade Equity | F1: OTE: | G1: (Settlement Price - Trade Price)*# of contracts*contract size | L1: Ending Balance: | M1: Beginning Cash Balance+/-any realized cash movements (PNL,cash movements,fees,comms) | T1: MONTH END INTEREST HITS ON THE 3RD BIZZ DAY OF THE MONTH
A2: 00102702 | C2: Beginning Account Balance | D2: Total Comms/ Fees | E2: Gross P/L | F2: Net P/L | G2: Cash Amount (Trade Date-1 VM) | H2: Ending Account Balance/ Trade Date +1 Beginning Account Balance | I2: Open Trade Equity | J2: Total Equity (Trade Date VM) | K2: 00102703 | L2: Beginning Account Balance | M2: Total Comms/ Fees | N2: Gross P/L | O2: Net P/L | P2: Cash Amount (Trade Date-1 VM) | Q2: Ending Account Balance/ Trade Date +1 Beginning Account Balance | R2: Open Trade Equity | S2: Total Equity (Trade Date VM)
U6: VPIE - HAD TO ADJUST COMMS WHICH AFFECTED VM BY $100
U7: MAINSP - GS DIDN’T INCLUDE PRIOR DAY VM IN CALC
U9: BNYMO - Didn’t send out 9/22 VM. Have to adjust to keep running sheet going
U27: VM DIDN’T GO OUT - DELETED FROM SHEET
U236: Make sure matches GS statement | Y236: SA2 pls set up the below:
U237: Make sure matches GS statement | Y237: SA2 pls set up the below:
U238: Make sure matches GS statement | Y238: SA2 pls set up the below:
U239: Make sure matches GS statement | Y239: SA2 pls set up the below:
U240: Make sure matches GS statement | Y240: SA2 pls set up the below:
U241: Make sure matches GS statement | Y241: SA2 pls set up the below:
U242: Make sure matches GS statement | Y242: SA2 pls set up the below:
U243: Make sure matches GS statement | Y243: SA2 pls set up the below:
U244: Make sure matches GS statement | Y244: SA2 pls set up the below:
U245: Make sure matches GS statement | Y245: SA2 pls set up the below:
U246: Make sure matches GS statement | Y246: SA2 pls set up the below:
U247: Make sure matches GS statement | Y247: SA2 pls set up the below:
... U351: Make sure matches GS statement | Y351: SA2 pls set up the below:
U352: Make sure matches GS statement | Y352: SA2 pls set up the below: | AB352: Adjusted for IME FEE ON STATEMENT
U353: Make sure matches GS statement | Y353: SA2 pls set up the below: | AB353: Was off slighly again | AD353: -296.3814 | AE353: IMR FEE
AB354: Adjusted beg bal this time, diff was carryingeach day due to formula | AD354: -86.54 | AE354: IMR FEE
U355: Matched
U359: Make sure matches GS statement | Y359: SA2 pls set up the below:
U360: Make sure matches GS statement | Y360: SA2 pls set up the below:
U361: Make sure matches GS statement | Y361: SA2 pls set up the below:
U362: Make sure matches GS statement | Y362: SA2 pls set up the below:
U363: Make sure matches GS statement | Y363: SA2 pls set up the below:
U364: Make sure matches GS statement | Y364: SA2 pls set up the below:
U365: Make sure matches GS statement | Y365: SA2 pls set up the below:
U366: Make sure matches GS statement | Y366: SA2 pls set up the below:
U367: Make sure matches GS statement | Y367: SA2 pls set up the below:
U368: Make sure matches GS statement | Y368: SA2 pls set up the below:
U369: Make sure matches GS statement | Y369: SA2 pls set up the below:

Sheet Holidays
A1: 45253
A2: 45285
A3: 45292
A4: 45306
A5: 45341
A6: 45380
A7: 45439
A8: 45462
A9: 45477
A10: 45537
A11: 45624
A12: 45651
