Workbook

Sheet (FA) IQ
A1: Custody Acc # | B1: Account | C1: AD | D1: Total Cash USD | E1: Foreign Currency | F1: SWEEP | G1: Collateral & MD | H1: Variation Margin | I1: Unrl Loss On FFX | J1: TR Swaps Sheet | K1: Net Cash | L1: Equity MV | M1: Market Value | N1: Percent Cash | O1: 15% Illiquidity Test | Q1: SWAP WEIGHT | S1: % Custody Cash (USD) | T1: % Custody Cash (CCY) | V1: ='(Custody) IQ'!I1 | Y1: ='(Custody) IQ'!L1
A2: 139473 | B2: IQSI | C2: NYLI Candriam International Equity ETF | D2: =VLOOKUP(A2,'BNY FA Cash'!$C$27:$Y$1048576,23,0) | E2: =VLOOKUP(A2,'BNY FA Cash'!$C$27:$F$634,4,0) | F2: =VLOOKUP(A2,'BNY FA Cash'!$C$27:$H$1048576,6,0) | G2: =VLOOKUP(A2,'BNY FA Cash'!$C$27:$I$1048576,7,0) | H2: =VLOOKUP(A2,'BNY FA Cash'!$C$27:$J$1048576,8,0) | I2: =VLOOKUP(A2,'BNY FA Cash'!$C$27:$N$1048576,12,0)+VLOOKUP(A2,'BNY FA Cash'!$C$27:$T$1048576,18,0) | J2: =VLOOKUP(A2,'BNY FA Cash'!$C$27:$AA$1048576,25,0) | K2: =SUM(D2:J2) | L2: =M2-K2 | M2: =VLOOKUP(A2,'BNY FA Cash'!$C$27:$Z$1048576,24,0) | N2: =K2/M2 | O2: =ABS(J2)/M2 | S2: ='(Custody) IQ'!F2 | T2: ='(Custody) IQ'!G2 | V2: ='(Custody) IQ'!I2 | W2: ='(Custody) IQ'!J2 | X2: ='(Custody) IQ'!K2 | Y2: ='(Custody) IQ'!L2 | Z2: ='(Custody) IQ'!M2
A3: 139522 | B3: IQSU | C3: NYLI Candriam U.S. Large Cap Equity ETF | D3: =VLOOKUP(A3,'BNY FA Cash'!$C$27:$Y$1048576,23,0) | E3: =VLOOKUP(A3,'BNY FA Cash'!$C$27:$F$634,4,0) | F3: =VLOOKUP(A3,'BNY FA Cash'!$C$27:$H$1048576,6,0) | G3: =VLOOKUP(A3,'BNY FA Cash'!$C$27:$I$1048576,7,0) | H3: =VLOOKUP(A3,'BNY FA Cash'!$C$27:$J$1048576,8,0) | I3: =VLOOKUP(A3,'BNY FA Cash'!$C$27:$N$1048576,12,0)+VLOOKUP(A3,'BNY FA Cash'!$C$27:$T$1048576,18,0) | J3: =VLOOKUP(A3,'BNY FA Cash'!$C$27:$AA$1048576,25,0) | K3: =SUM(D3:J3) | L3: =M3-K3 | M3: =VLOOKUP(A3,'BNY FA Cash'!$C$27:$Z$1048576,24,0) | N3: =K3/M3 | O3: =ABS(J3)/M3 | S3: ='(Custody) IQ'!F3 | T3: ='(Custody) IQ'!G3 | V3: ='(Custody) IQ'!I3 | W3: ='(Custody) IQ'!J3 | Z3: ='(Custody) IQ'!M3
A4: 156481 | B4: HART | C4: NYLI Healthy Hearts ETF | D4: =VLOOKUP(A4,'BNY FA Cash'!$C$27:$Y$1048576,23,0) | E4: =VLOOKUP(A4,'BNY FA Cash'!$C$27:$F$634,4,0) | F4: =VLOOKUP(A4,'BNY FA Cash'!$C$27:$H$1048576,6,0) | G4: =VLOOKUP(A4,'BNY FA Cash'!$C$27:$I$1048576,7,0) | H4: =VLOOKUP(A4,'BNY FA Cash'!$C$27:$J$1048576,8,0) | I4: =VLOOKUP(A4,'BNY FA Cash'!$C$27:$N$1048576,12,0)+VLOOKUP(A4,'BNY FA Cash'!$C$27:$T$1048576,18,0) | J4: =VLOOKUP(A4,'BNY FA Cash'!$C$27:$AA$1048576,25,0) | K4: =SUM(D4:J4) | L4: =M4-K4 | M4: =VLOOKUP(A4,'BNY FA Cash'!$C$27:$Z$1048576,24,0) | N4: =K4/M4 | O4: =ABS(J4)/M4 | S4: ='(Custody) IQ'!F4 | T4: ='(Custody) IQ'!G4 | V4: ='(Custody) IQ'!I4 | W4: ='(Custody) IQ'!J4 | X4: ='(Custody) IQ'!K4 | Y4: ='(Custody) IQ'!L4 | Z4: ='(Custody) IQ'!M4
A5: 212156 | B5: MNA | C5: NYLI Merger Arbitrage ETF | D5: =VLOOKUP(A5,'BNY FA Cash'!$C$27:$Y$1048576,23,0) | E5: =VLOOKUP(A5,'BNY FA Cash'!$C$27:$F$634,4,0) | F5: =VLOOKUP(A5,'BNY FA Cash'!$C$27:$H$1048576,6,0) | G5: =VLOOKUP(A5,'BNY FA Cash'!$C$27:$I$1048576,7,0) | H5: =VLOOKUP(A5,'BNY FA Cash'!$C$27:$J$1048576,8,0) | I5: =VLOOKUP(A5,'BNY FA Cash'!$C$27:$N$1048576,12,0)+VLOOKUP(A5,'BNY FA Cash'!$C$27:$T$1048576,18,0) | J5: =VLOOKUP(A5,'BNY FA Cash'!$C$27:$AA$1048576,25,0) | K5: =SUM(D5:J5) | L5: =M5-K5 | M5: =VLOOKUP(A5,'BNY FA Cash'!$C$27:$Z$1048576,24,0) | N5: =K5/M5 | O5: =ABS(J5)/M5 | S5: ='(Custody) IQ'!F5 | T5: ='(Custody) IQ'!G5 | V5: ='(Custody) IQ'!I5 | W5: ='(Custody) IQ'!J5 | X5: ='(Custody) IQ'!K5 | Y5: ='(Custody) IQ'!L5 | Z5: ='(Custody) IQ'!M5
A6: 222959 | B6: LRND | C6: NYLI U.S. Large Cap R&D Leaders ETF | D6: =VLOOKUP(A6,'BNY FA Cash'!$C$27:$Y$1048576,23,0) | E6: =VLOOKUP(A6,'BNY FA Cash'!$C$27:$F$634,4,0) | F6: =VLOOKUP(A6,'BNY FA Cash'!$C$27:$H$1048576,6,0) | G6: =VLOOKUP(A6,'BNY FA Cash'!$C$27:$I$1048576,7,0) | H6: =VLOOKUP(A6,'BNY FA Cash'!$C$27:$J$1048576,8,0) | I6: =VLOOKUP(A6,'BNY FA Cash'!$C$27:$N$1048576,12,0)+VLOOKUP(A6,'BNY FA Cash'!$C$27:$T$1048576,18,0) | J6: =VLOOKUP(A6,'BNY FA Cash'!$C$27:$AA$1048576,25,0) | K6: =SUM(D6:J6) | L6: =M6-K6 | M6: =VLOOKUP(A6,'BNY FA Cash'!$C$27:$Z$1048576,24,0) | N6: =K6/M6 | O6: =ABS(J6)/M6 | S6: ='(Custody) IQ'!F6 | T6: ='(Custody) IQ'!G6 | V6: ='(Custody) IQ'!I6 | W6: ='(Custody) IQ'!J6 | Z6: ='(Custody) IQ'!M6
A7: 222963 | B7: WRND | C7: NYLI Global Equity R&D Leaders ETF | D7: =VLOOKUP(A7,'BNY FA Cash'!$C$27:$Y$1048576,23,0) | E7: =VLOOKUP(A7,'BNY FA Cash'!$C$27:$F$634,4,0) | F7: =VLOOKUP(A7,'BNY FA Cash'!$C$27:$H$1048576,6,0) | G7: =VLOOKUP(A7,'BNY FA Cash'!$C$27:$I$1048576,7,0) | H7: =VLOOKUP(A7,'BNY FA Cash'!$C$27:$J$1048576,8,0) | I7: =VLOOKUP(A7,'BNY FA Cash'!$C$27:$N$1048576,12,0)+VLOOKUP(A7,'BNY FA Cash'!$C$27:$T$1048576,18,0) | J7: =VLOOKUP(A7,'BNY FA Cash'!$C$27:$AA$1048576,25,0) | K7: =SUM(D7:J7) | L7: =M7-K7 | M7: =VLOOKUP(A7,'BNY FA Cash'!$C$27:$Z$1048576,24,0) | N7: =K7/M7 | O7: =ABS(J7)/M7 | S7: ='(Custody) IQ'!F7 | T7: ='(Custody) IQ'!G7 | V7: ='(Custody) IQ'!I7 | W7: ='(Custody) IQ'!J7 | X7: ='(Custody) IQ'!K7 | Y7: ='(Custody) IQ'!L7 | Z7: ='(Custody) IQ'!M7
A8: 240413 | B8: IQSM | C8: NYLI Candriam U.S. Mid Cap Equity ETF | D8: =VLOOKUP(A8,'BNY FA Cash'!$C$27:$Y$1048576,23,0) | E8: =VLOOKUP(A8,'BNY FA Cash'!$C$27:$F$634,4,0) | F8: =VLOOKUP(A8,'BNY FA Cash'!$C$27:$H$1048576,6,0) | G8: =VLOOKUP(A8,'BNY FA Cash'!$C$27:$I$1048576,7,0) | H8: =VLOOKUP(A8,'BNY FA Cash'!$C$27:$J$1048576,8,0) | I8: =VLOOKUP(A8,'BNY FA Cash'!$C$27:$N$1048576,12,0)+VLOOKUP(A8,'BNY FA Cash'!$C$27:$T$1048576,18,0) | J8: =VLOOKUP(A8,'BNY FA Cash'!$C$27:$AA$1048576,25,0) | K8: =SUM(D8:J8) | L8: =M8-K8 | M8: =VLOOKUP(A8,'BNY FA Cash'!$C$27:$Z$1048576,24,0) | N8: =K8/M8 | O8: =ABS(J8)/M8 | S8: ='(Custody) IQ'!F8 | T8: ='(Custody) IQ'!G8 | V8: ='(Custody) IQ'!I8 | W8: ='(Custody) IQ'!J8 | Z8: ='(Custody) IQ'!M8
A9: 263076 | B9: QAI | C9: NYLI Hedge Multi-Strategy Tracker ETF | D9: =VLOOKUP(A9,'BNY FA Cash'!$C$27:$Y$1048576,23,0) | E9: =VLOOKUP(A9,'BNY FA Cash'!$C$27:$F$634,4,0) | F9: =VLOOKUP(A9,'BNY FA Cash'!$C$27:$H$1048576,6,0) | G9: =VLOOKUP(A9,'BNY FA Cash'!$C$27:$I$1048576,7,0) | H9: =VLOOKUP(A9,'BNY FA Cash'!$C$27:$J$1048576,8,0) | I9: =VLOOKUP(A9,'BNY FA Cash'!$C$27:$N$1048576,12,0)+VLOOKUP(A9,'BNY FA Cash'!$C$27:$T$1048576,18,0) | J9: =VLOOKUP(A9,'BNY FA Cash'!$C$27:$AA$1048576,25,0) | K9: =SUM(D9:J9) | L9: =M9-K9 | M9: =VLOOKUP(A9,'BNY FA Cash'!$C$27:$Z$1048576,24,0) | N9: =K9/M9 | O9: =ABS(J9)/M9 | S9: ='(Custody) IQ'!F9 | T9: ='(Custody) IQ'!G9 | V9: ='(Custody) IQ'!I9 | W9: ='(Custody) IQ'!J9 | Z9: ='(Custody) IQ'!M9
A10: 447594 | B10: HFXI | C10: NYLI FTSE International Equity Currency Neutral ETF | D10: =VLOOKUP(A10,'BNY FA Cash'!$C$27:$Y$1048576,23,0) | E10: =VLOOKUP(A10,'BNY FA Cash'!$C$27:$F$634,4,0) | F10: =VLOOKUP(A10,'BNY FA Cash'!$C$27:$H$1048576,6,0) | G10: =VLOOKUP(A10,'BNY FA Cash'!$C$27:$I$1048576,7,0) | H10: =VLOOKUP(A10,'BNY FA Cash'!$C$27:$J$1048576,8,0) | I10: =VLOOKUP(A10,'BNY FA Cash'!$C$27:$AD$54,28,0) | J10: =VLOOKUP(A10,'BNY FA Cash'!$C$27:$AA$1048576,25,0) | K10: =SUM(D10:J10) | L10: =M10-K10 | M10: =VLOOKUP(A10,'BNY FA Cash'!$C$27:$Z$1048576,24,0) | N10: =K10/M10 | O10: =ABS(J10)/M10 | S10: ='(Custody) IQ'!F10 | T10: ='(Custody) IQ'!G10 | V10: ='(Custody) IQ'!I10 | W10: ='(Custody) IQ'!J10 | X10: ='(Custody) IQ'!K10 | Y10: ='(Custody) IQ'!L10 | Z10: ='(Custody) IQ'!M10
A11: G 26785 | B11: VP Mutual Fund | C11: NYLI VP Hedge Multi-Strategy Portfolio | D11: =M11-L11-J11-F11 | E11: 0 | F11: =IFERROR(VLOOKUP("CASH EQUIVALENTS-SHORT-TERM INVEST FUNDS",'VP FA Holdings'!G:U,15,0),0) | G11: =SUMIFS('VP FA Holdings'!K:K,'VP FA Holdings'!C:C,"ITX1",'VP FA Holdings'!F:F,"US DOLLAR") | H11: 0 | I11: 0 | J11: =SUMIF('VP FA Holdings'!G:G,"DERIVATIVES-OTC EXPOSURE",'VP FA Holdings'!V:V) | K11: =SUM(D11:J11) | L11: =SUMIF('VP FA Holdings'!G:G,"INVESTMENT COMPANIES-EXCHANGE TRADED FUN",'VP FA Holdings'!U:U) | M11: =SUM('VP FA Holdings'!AG:AG) | N11: =K11/M11 | O11: =ABS(J11)/M11
C14: symbol | D14: portCd | E14: custCd | F14: position | G14: shares | H14: localGrossCost | I14: localSodprice | J14: strategy1 | K14: strategy2
C15: LOOKFWD_CASH | D15: MNA | E15: Index | F15: 1 | G15: =VLOOKUP(D15,$B$1:$K$11,10,0)+E23 | H15: 1 | I15: 1
C16: LOOKFWD_CASH | D16: QAI | E16: Index | F16: 1 | G16: =VLOOKUP(D16,$B$1:$K$13,10,0)+E24 | H16: 1 | I16: 1
C17: LOOKFWD_CASH | D17: HFXI | E17: Index | F17: 1 | G17: =VLOOKUP(D17,$B$1:$K$13,10,0)+E21 | H17: 1 | I17: 1
D19: HFXI P&L
D20: HFXI TRADES
E21: =SUM(E19:E20)
D23: MNA TRADES
D24: QAI TRADES

Sheet (Custody) IQ
A1: Custody Acc # | B1: Account | C1: AD | D1: USD Cash | E1: Foreign CCY Cash | F1: % Custody Cash (USD) | G1: % Custody Cash (CCY) | I1: Largest Local Balances (USD) | L1: Smallest Local Balances (USD)
A2: 139473 | B2: IQSI | C2: NYLI Candriam International Equity ETF | D2: =SUMIFS('BNY Daily Settled Cash Balance'!F:F,'BNY Daily Settled Cash Balance'!A:A,'(Custody) IQ'!A2,'BNY Daily Settled Cash Balance'!C:C,"USD") | E2: =SUMIFS('BNY Daily Settled Cash Balance'!F:F,'BNY Daily Settled Cash Balance'!A:A,'(Custody) IQ'!A2,'BNY Daily Settled Cash Balance'!C:C,"<>USD") | F2: =D2/'(FA) IQ'!M2 | G2: =E2/'(FA) IQ'!M2 | I2: =_xlfn.MAXIFS('BNY Daily Settled Cash Balance'!F:F, 'BNY Daily Settled Cash Balance'!A:A, '(Custody) IQ'!A2, 'BNY Daily Settled Cash Balance'!C:C, "<>USD") | J2: =I2/VLOOKUP(A2,'(FA) IQ'!$A$2:$M$11,13,0) | K2: {=INDEX( _xlfn._xlws.FILTER('BNY Daily Settled Cash Balance'!C:C, ('BNY Daily Settled Cash Balance'!A:A='(Custody) IQ'!A2) * ('BNY Daily Settled Cash Balance'!C:C<>"USD")), MATCH( _xlfn.MAXIFS('BNY Daily Settled Cash Balance'!F:F, 'BNY Daily Settled Cash Balance'!A:A, '(Custody) IQ'!A2, 'BNY Daily Settled Cash Balance'!C:C, "<>USD"), _xlfn._xlws.FILTER('BNY Daily Settled Cash Balance'!F:F, ('BNY Daily Settled Cash Balance'!A:A='(Custody) IQ'!A2) * ('BNY Daily Settled Cash Balance'!C:C<>"USD")), 0) )} | L2: =_xlfn.MINIFS('BNY Daily Settled Cash Balance'!F:F, 'BNY Daily Settled Cash Balance'!A:A, '(Custody) IQ'!A2, 'BNY Daily Settled Cash Balance'!C:C, "<>USD") | M2: =L2/VLOOKUP(A2,'(FA) IQ'!$A$2:$M$11,13,0) | N2: {=INDEX( _xlfn._xlws.FILTER('BNY Daily Settled Cash Balance'!C:C, ('BNY Daily Settled Cash Balance'!A:A='(Custody) IQ'!A2) * ('BNY Daily Settled Cash Balance'!C:C<>"USD")), MATCH( _xlfn.MINIFS('BNY Daily Settled Cash Balance'!F:F, 'BNY Daily Settled Cash Balance'!A:A, '(Custody) IQ'!A2, 'BNY Daily Settled Cash Balance'!C:C, "<>USD"), _xlfn._xlws.FILTER('BNY Daily Settled Cash Balance'!F:F, ('BNY Daily Settled Cash Balance'!A:A='(Custody) IQ'!A2) * ('BNY Daily Settled Cash Balance'!C:C<>"USD")), 0) )}
A3: 139522 | B3: IQSU | C3: NYLI Candriam U.S. Large Cap Equity ETF | D3: =SUMIFS('BNY Daily Settled Cash Balance'!F:F,'BNY Daily Settled Cash Balance'!A:A,'(Custody) IQ'!A3,'BNY Daily Settled Cash Balance'!C:C,"USD") | E3: =SUMIFS('BNY Daily Settled Cash Balance'!F:F,'BNY Daily Settled Cash Balance'!A:A,'(Custody) IQ'!A3,'BNY Daily Settled Cash Balance'!C:C,"<>USD") | F3: =D3/'(FA) IQ'!M3 | G3: =E3/'(FA) IQ'!M3
A4: 156481 | B4: HART | C4: NYLI Healthy Hearts ETF | D4: =SUMIFS('BNY Daily Settled Cash Balance'!F:F,'BNY Daily Settled Cash Balance'!A:A,'(Custody) IQ'!A4,'BNY Daily Settled Cash Balance'!C:C,"USD") | E4: =SUMIFS('BNY Daily Settled Cash Balance'!F:F,'BNY Daily Settled Cash Balance'!A:A,'(Custody) IQ'!A4,'BNY Daily Settled Cash Balance'!C:C,"<>USD") | F4: =D4/'(FA) IQ'!M4 | G4: =E4/'(FA) IQ'!M4 | I4: =_xlfn.MAXIFS('BNY Daily Settled Cash Balance'!F:F, 'BNY Daily Settled Cash Balance'!A:A, '(Custody) IQ'!A4, 'BNY Daily Settled Cash Balance'!C:C, "<>USD") | J4: =I4/VLOOKUP(A4,'(FA) IQ'!$A$2:$M$11,13,0) | K4: {=INDEX( _xlfn._xlws.FILTER('BNY Daily Settled Cash Balance'!C:C, ('BNY Daily Settled Cash Balance'!A:A='(Custody) IQ'!A4) * ('BNY Daily Settled Cash Balance'!C:C<>"USD")), MATCH( _xlfn.MAXIFS('BNY Daily Settled Cash Balance'!F:F, 'BNY Daily Settled Cash Balance'!A:A, '(Custody) IQ'!A4, 'BNY Daily Settled Cash Balance'!C:C, "<>USD"), _xlfn._xlws.FILTER('BNY Daily Settled Cash Balance'!F:F, ('BNY Daily Settled Cash Balance'!A:A='(Custody) IQ'!A4) * ('BNY Daily Settled Cash Balance'!C:C<>"USD")), 0) )} | L4: =_xlfn.MINIFS('BNY Daily Settled Cash Balance'!F:F, 'BNY Daily Settled Cash Balance'!A:A, '(Custody) IQ'!A4, 'BNY Daily Settled Cash Balance'!C:C, "<>USD") | M4: =L4/VLOOKUP(A4,'(FA) IQ'!$A$2:$M$11,13,0) | N4: {=INDEX( _xlfn._xlws.FILTER('BNY Daily Settled Cash Balance'!C:C, ('BNY Daily Settled Cash Balance'!A:A='(Custody) IQ'!A4) * ('BNY Daily Settled Cash Balance'!C:C<>"USD")), MATCH( _xlfn.MINIFS('BNY Daily Settled Cash Balance'!F:F, 'BNY Daily Settled Cash Balance'!A:A, '(Custody) IQ'!A4, 'BNY Daily Settled Cash Balance'!C:C, "<>USD"), _xlfn._xlws.FILTER('BNY Daily Settled Cash Balance'!F:F, ('BNY Daily Settled Cash Balance'!A:A='(Custody) IQ'!A4) * ('BNY Daily Settled Cash Balance'!C:C<>"USD")), 0) )}
A5: 212156 | B5: MNA | C5: NYLI Merger Arbitrage ETF | D5: =SUMIFS('BNY Daily Settled Cash Balance'!F:F,'BNY Daily Settled Cash Balance'!A:A,'(Custody) IQ'!A5,'BNY Daily Settled Cash Balance'!C:C,"USD") | E5: =SUMIFS('BNY Daily Settled Cash Balance'!F:F,'BNY Daily Settled Cash Balance'!A:A,'(Custody) IQ'!A5,'BNY Daily Settled Cash Balance'!C:C,"<>USD") | F5: =D5/'(FA) IQ'!M5 | G5: =E5/'(FA) IQ'!M5 | I5: =_xlfn.MAXIFS('BNY Daily Settled Cash Balance'!F:F, 'BNY Daily Settled Cash Balance'!A:A, '(Custody) IQ'!A5, 'BNY Daily Settled Cash Balance'!C:C, "<>USD") | J5: =I5/VLOOKUP(A5,'(FA) IQ'!$A$2:$M$11,13,0) | K5: {=INDEX( _xlfn._xlws.FILTER('BNY Daily Settled Cash Balance'!C:C, ('BNY Daily Settled Cash Balance'!A:A='(Custody) IQ'!A5) * ('BNY Daily Settled Cash Balance'!C:C<>"USD")), MATCH( _xlfn.MAXIFS('BNY Daily Settled Cash Balance'!F:F, 'BNY Daily Settled Cash Balance'!A:A, '(Custody) IQ'!A5, 'BNY Daily Settled Cash Balance'!C:C, "<>USD"), _xlfn._xlws.FILTER('BNY Daily Settled Cash Balance'!F:F, ('BNY Daily Settled Cash Balance'!A:A='(Custody) IQ'!A5) * ('BNY Daily Settled Cash Balance'!C:C<>"USD")), 0) )} | L5: =_xlfn.MINIFS('BNY Daily Settled Cash Balance'!F:F, 'BNY Daily Settled Cash Balance'!A:A, '(Custody) IQ'!A5, 'BNY Daily Settled Cash Balance'!C:C, "<>USD") | M5: =L5/VLOOKUP(A5,'(FA) IQ'!$A$2:$M$11,13,0) | N5: {=INDEX( _xlfn._xlws.FILTER('BNY Daily Settled Cash Balance'!C:C, ('BNY Daily Settled Cash Balance'!A:A='(Custody) IQ'!A5) * ('BNY Daily Settled Cash Balance'!C:C<>"USD")), MATCH( _xlfn.MINIFS('BNY Daily Settled Cash Balance'!F:F, 'BNY Daily Settled Cash Balance'!A:A, '(Custody) IQ'!A5, 'BNY Daily Settled Cash Balance'!C:C, "<>USD"), _xlfn._xlws.FILTER('BNY Daily Settled Cash Balance'!F:F, ('BNY Daily Settled Cash Balance'!A:A='(Custody) IQ'!A5) * ('BNY Daily Settled Cash Balance'!C:C<>"USD")), 0) )}
A6: 222959 | B6: LRND | C6: NYLI U.S. Large Cap R&D Leaders ETF | D6: =SUMIFS('BNY Daily Settled Cash Balance'!F:F,'BNY Daily Settled Cash Balance'!A:A,'(Custody) IQ'!A6,'BNY Daily Settled Cash Balance'!C:C,"USD") | E6: =SUMIFS('BNY Daily Settled Cash Balance'!F:F,'BNY Daily Settled Cash Balance'!A:A,'(Custody) IQ'!A6,'BNY Daily Settled Cash Balance'!C:C,"<>USD") | F6: =D6/'(FA) IQ'!M6 | G6: =E6/'(FA) IQ'!M6
A7: 222963 | B7: WRND | C7: NYLI Global Equity R&D Leaders ETF | D7: =SUMIFS('BNY Daily Settled Cash Balance'!F:F,'BNY Daily Settled Cash Balance'!A:A,'(Custody) IQ'!A7,'BNY Daily Settled Cash Balance'!C:C,"USD") | E7: =SUMIFS('BNY Daily Settled Cash Balance'!F:F,'BNY Daily Settled Cash Balance'!A:A,'(Custody) IQ'!A7,'BNY Daily Settled Cash Balance'!C:C,"<>USD") | F7: =D7/'(FA) IQ'!M7 | G7: =E7/'(FA) IQ'!M7 | I7: =_xlfn.MAXIFS('BNY Daily Settled Cash Balance'!F:F, 'BNY Daily Settled Cash Balance'!A:A, '(Custody) IQ'!A7, 'BNY Daily Settled Cash Balance'!C:C, "<>USD") | J7: =I7/VLOOKUP(A7,'(FA) IQ'!$A$2:$M$11,13,0) | K7: {=INDEX( _xlfn._xlws.FILTER('BNY Daily Settled Cash Balance'!C:C, ('BNY Daily Settled Cash Balance'!A:A='(Custody) IQ'!A7) * ('BNY Daily Settled Cash Balance'!C:C<>"USD")), MATCH( _xlfn.MAXIFS('BNY Daily Settled Cash Balance'!F:F, 'BNY Daily Settled Cash Balance'!A:A, '(Custody) IQ'!A7, 'BNY Daily Settled Cash Balance'!C:C, "<>USD"), _xlfn._xlws.FILTER('BNY Daily Settled Cash Balance'!F:F, ('BNY Daily Settled Cash Balance'!A:A='(Custody) IQ'!A7) * ('BNY Daily Settled Cash Balance'!C:C<>"USD")), 0) )} | L7: =_xlfn.MINIFS('BNY Daily Settled Cash Balance'!F:F, 'BNY Daily Settled Cash Balance'!A:A, '(Custody) IQ'!A7, 'BNY Daily Settled Cash Balance'!C:C, "<>USD") | M7: =L7/VLOOKUP(A7,'(FA) IQ'!$A$2:$M$11,13,0) | N7: {=INDEX( _xlfn._xlws.FILTER('BNY Daily Settled Cash Balance'!C:C, ('BNY Daily Settled Cash Balance'!A:A='(Custody) IQ'!A7) * ('BNY Daily Settled Cash Balance'!C:C<>"USD")), MATCH( _xlfn.MINIFS('BNY Daily Settled Cash Balance'!F:F, 'BNY Daily Settled Cash Balance'!A:A, '(Custody) IQ'!A7, 'BNY Daily Settled Cash Balance'!C:C, "<>USD"), _xlfn._xlws.FILTER('BNY Daily Settled Cash Balance'!F:F, ('BNY Daily Settled Cash Balance'!A:A='(Custody) IQ'!A7) * ('BNY Daily Settled Cash Balance'!C:C<>"USD")), 0) )}
A8: 240413 | B8: IQSM | C8: NYLI Candriam U.S. Mid Cap Equity ETF | D8: =SUMIFS('BNY Daily Settled Cash Balance'!F:F,'BNY Daily Settled Cash Balance'!A:A,'(Custody) IQ'!A8,'BNY Daily Settled Cash Balance'!C:C,"USD") | E8: =SUMIFS('BNY Daily Settled Cash Balance'!F:F,'BNY Daily Settled Cash Balance'!A:A,'(Custody) IQ'!A8,'BNY Daily Settled Cash Balance'!C:C,"<>USD") | F8: =D8/'(FA) IQ'!M8 | G8: =E8/'(FA) IQ'!M8
A9: 263076 | B9: QAI | C9: NYLI Hedge Multi-Strategy Tracker ETF | D9: =SUMIFS('BNY Daily Settled Cash Balance'!F:F,'BNY Daily Settled Cash Balance'!A:A,'(Custody) IQ'!A9,'BNY Daily Settled Cash Balance'!C:C,"USD") | E9: =SUMIFS('BNY Daily Settled Cash Balance'!F:F,'BNY Daily Settled Cash Balance'!A:A,'(Custody) IQ'!A9,'BNY Daily Settled Cash Balance'!C:C,"<>USD") | F9: =D9/'(FA) IQ'!M9 | G9: =E9/'(FA) IQ'!M9
A10: 447594 | B10: HFXI | C10: NYLI FTSE International Equity Currency Neutral ETF | D10: =SUMIFS('BNY Daily Settled Cash Balance'!F:F,'BNY Daily Settled Cash Balance'!A:A,'(Custody) IQ'!A10,'BNY Daily Settled Cash Balance'!C:C,"USD") | E10: =SUMIFS('BNY Daily Settled Cash Balance'!F:F,'BNY Daily Settled Cash Balance'!A:A,'(Custody) IQ'!A10,'BNY Daily Settled Cash Balance'!C:C,"<>USD") | F10: =D10/'(FA) IQ'!M10 | G10: =E10/'(FA) IQ'!M10 | I10: =_xlfn.MAXIFS('BNY Daily Settled Cash Balance'!F:F, 'BNY Daily Settled Cash Balance'!A:A, '(Custody) IQ'!A10, 'BNY Daily Settled Cash Balance'!C:C, "<>USD") | J10: =I10/VLOOKUP(A10,'(FA) IQ'!$A$2:$M$11,13,0) | K10: {=INDEX( _xlfn._xlws.FILTER('BNY Daily Settled Cash Balance'!C:C, ('BNY Daily Settled Cash Balance'!A:A='(Custody) IQ'!A10) * ('BNY Daily Settled Cash Balance'!C:C<>"USD")), MATCH( _xlfn.MAXIFS('BNY Daily Settled Cash Balance'!F:F, 'BNY Daily Settled Cash Balance'!A:A, '(Custody) IQ'!A10, 'BNY Daily Settled Cash Balance'!C:C, "<>USD"), _xlfn._xlws.FILTER('BNY Daily Settled Cash Balance'!F:F, ('BNY Daily Settled Cash Balance'!A:A='(Custody) IQ'!A10) * ('BNY Daily Settled Cash Balance'!C:C<>"USD")), 0) )} | L10: =_xlfn.MINIFS('BNY Daily Settled Cash Balance'!F:F, 'BNY Daily Settled Cash Balance'!A:A, '(Custody) IQ'!A10, 'BNY Daily Settled Cash Balance'!C:C, "<>USD") | M10: =L10/VLOOKUP(A10,'(FA) IQ'!$A$2:$M$11,13,0) | N10: {=INDEX( _xlfn._xlws.FILTER('BNY Daily Settled Cash Balance'!C:C, ('BNY Daily Settled Cash Balance'!A:A='(Custody) IQ'!A10) * ('BNY Daily Settled Cash Balance'!C:C<>"USD")), MATCH( _xlfn.MINIFS('BNY Daily Settled Cash Balance'!F:F, 'BNY Daily Settled Cash Balance'!A:A, '(Custody) IQ'!A10, 'BNY Daily Settled Cash Balance'!C:C, "<>USD"), _xlfn._xlws.FILTER('BNY Daily Settled Cash Balance'!F:F, ('BNY Daily Settled Cash Balance'!A:A='(Custody) IQ'!A10) * ('BNY Daily Settled Cash Balance'!C:C<>"USD")), 0) )}
D14: Overdraft $ | E14: =SUMIF(E2:E10, "<0") | L14: =SUMIF(L2:L10, "<0") | M14: Overdraft $
C15: OD Fee Annaul | D15: 0.05 | E15: =E14*D15 | L15: =L14*M15 | M15: 0.05 | N15: OD Fee Annaul
C16: OD Fee Daily | E16: =E15/365 | L16: =L15/365 | N16: OD Fee Daily

Sheet (FA - Income) IQ 
A1: Custody Acc # | B1: Account | C1: AD | D1: Accrued Income | E1: Reclaim Rec | G1: AUM | H1: AI % | I1: RC% | J1: Total | L1: FA CASH % | N1: FA CASH
A2: 139473 | B2: IQSI | C2: NYLI Candriam International Equity ETF | D2: =VLOOKUP(A2,'BNY FA Cash'!$C$27:$K$1048576,9,0) | E2: =VLOOKUP(A2,'BNY FA Cash'!$C$27:$O$1048576,13,0) | G2: =VLOOKUP(B2,'(FA) IQ'!$B$2:$M$11,12,0) | H2: =D2/G2 | I2: =E2/G2 | J2: =H2+I2 | L2: =N2/G2 | N2: {=SUM(VLOOKUP(B2, '(FA) IQ'!$B$2:$F$11, {3,4,5}, FALSE))}
A3: 139522 | B3: IQSU | C3: NYLI Candriam U.S. Large Cap Equity ETF | D3: =VLOOKUP(A3,'BNY FA Cash'!$C$27:$K$1048576,9,0) | E3: =VLOOKUP(A3,'BNY FA Cash'!$C$27:$O$1048576,13,0) | G3: =VLOOKUP(B3,'(FA) IQ'!$B$2:$M$11,12,0) | H3: =D3/G3 | I3: =E3/G3 | J3: =H3+I3 | L3: =N3/G3 | N3: {=SUM(VLOOKUP(B3, '(FA) IQ'!$B$2:$F$11, {3,4,5}, FALSE))}
A4: 156481 | B4: HART | C4: NYLI Healthy Hearts ETF | D4: =VLOOKUP(A4,'BNY FA Cash'!$C$27:$K$1048576,9,0) | E4: =VLOOKUP(A4,'BNY FA Cash'!$C$27:$O$1048576,13,0) | G4: =VLOOKUP(B4,'(FA) IQ'!$B$2:$M$11,12,0) | H4: =D4/G4 | I4: =E4/G4 | J4: =H4+I4 | L4: =N4/G4 | N4: {=SUM(VLOOKUP(B4, '(FA) IQ'!$B$2:$F$11, {3,4,5}, FALSE))}
A5: 212156 | B5: MNA | C5: NYLI Merger Arbitrage ETF | D5: =VLOOKUP(A5,'BNY FA Cash'!$C$27:$K$1048576,9,0) | E5: =VLOOKUP(A5,'BNY FA Cash'!$C$27:$O$1048576,13,0) | G5: =VLOOKUP(B5,'(FA) IQ'!$B$2:$M$11,12,0) | H5: =D5/G5 | I5: =E5/G5 | J5: =H5+I5 | L5: =N5/G5 | N5: {=SUM(VLOOKUP(B5, '(FA) IQ'!$B$2:$F$11, {3,4,5}, FALSE))}
A6: 222959 | B6: LRND | C6: NYLI U.S. Large Cap R&D Leaders ETF | D6: =VLOOKUP(A6,'BNY FA Cash'!$C$27:$K$1048576,9,0) | E6: =VLOOKUP(A6,'BNY FA Cash'!$C$27:$O$1048576,13,0) | G6: =VLOOKUP(B6,'(FA) IQ'!$B$2:$M$11,12,0) | H6: =D6/G6 | I6: =E6/G6 | J6: =H6+I6 | L6: =N6/G6 | N6: {=SUM(VLOOKUP(B6, '(FA) IQ'!$B$2:$F$11, {3,4,5}, FALSE))}
A7: 222963 | B7: WRND | C7: NYLI Global Equity R&D Leaders ETF | D7: =VLOOKUP(A7,'BNY FA Cash'!$C$27:$K$1048576,9,0) | E7: =VLOOKUP(A7,'BNY FA Cash'!$C$27:$O$1048576,13,0) | G7: =VLOOKUP(B7,'(FA) IQ'!$B$2:$M$11,12,0) | H7: =D7/G7 | I7: =E7/G7 | J7: =H7+I7 | L7: =N7/G7 | N7: {=SUM(VLOOKUP(B7, '(FA) IQ'!$B$2:$F$11, {3,4,5}, FALSE))}
A8: 240413 | B8: IQSM | C8: NYLI Candriam U.S. Mid Cap Equity ETF | D8: =VLOOKUP(A8,'BNY FA Cash'!$C$27:$K$1048576,9,0) | E8: =VLOOKUP(A8,'BNY FA Cash'!$C$27:$O$1048576,13,0) | G8: =VLOOKUP(B8,'(FA) IQ'!$B$2:$M$11,12,0) | H8: =D8/G8 | I8: =E8/G8 | J8: =H8+I8 | L8: =N8/G8 | N8: {=SUM(VLOOKUP(B8, '(FA) IQ'!$B$2:$F$11, {3,4,5}, FALSE))}
A9: 263076 | B9: QAI | C9: NYLI Hedge Multi-Strategy Tracker ETF | D9: =VLOOKUP(A9,'BNY FA Cash'!$C$27:$K$1048576,9,0) | E9: =VLOOKUP(A9,'BNY FA Cash'!$C$27:$O$1048576,13,0) | G9: =VLOOKUP(B9,'(FA) IQ'!$B$2:$M$11,12,0) | H9: =D9/G9 | I9: =E9/G9 | J9: =H9+I9 | L9: =N9/G9 | N9: {=SUM(VLOOKUP(B9, '(FA) IQ'!$B$2:$F$11, {3,4,5}, FALSE))}
A10: 447594 | B10: HFXI | C10: NYLI FTSE International Equity Currency Neutral ETF | D10: =VLOOKUP(A10,'BNY FA Cash'!$C$27:$K$1048576,9,0) | E10: =VLOOKUP(A10,'BNY FA Cash'!$C$27:$O$1048576,13,0) | G10: =VLOOKUP(B10,'(FA) IQ'!$B$2:$M$11,12,0) | H10: =D10/G10 | I10: =E10/G10 | J10: =H10+I10 | L10: =N10/G10 | N10: {=SUM(VLOOKUP(B10, '(FA) IQ'!$B$2:$F$11, {3,4,5}, FALSE))}

Sheet Pending Failed Trade Matrix
A1: PENDING | C1: =VLOOKUP(C2,'Currency Rates'!$A$3:$C$32,3,0) | D1: =VLOOKUP(D2,'Currency Rates'!$A$3:$C$32,3,0) | E1: =VLOOKUP(E2,'Currency Rates'!$A$3:$C$32,3,0) | F1: =VLOOKUP(F2,'Currency Rates'!$A$3:$C$32,3,0) | G1: =VLOOKUP(G2,'Currency Rates'!$A$3:$C$32,3,0) | H1: =VLOOKUP(H2,'Currency Rates'!$A$3:$C$32,3,0) | I1: =VLOOKUP(I2,'Currency Rates'!$A$3:$C$32,3,0) | J1: =VLOOKUP(J2,'Currency Rates'!$A$3:$C$32,3,0) | ... AE1: =VLOOKUP(AE2,'Currency Rates'!$A$3:$C$32,3,0)
B2: Fund | C2: AUD | D2: BRL | E2: CAD | F2: CHF | G2: CLP | H2: COP | I2: CZK | J2: DKK | K2: EUR | L2: GBP | M2: HKD | N2: HUF | O2: IDR | P2: ILS | Q2: INR | R2: JPY | S2: KRW | T2: MXN | U2: MYR | V2: NOK | W2: NZD | X2: PHP | Y2: PLN | Z2: SEK | AA2: SGD | AB2: THB | AC2: TWD | AD2: ZAR | AE2: TRY | AF2: USD | AG2: TOTAL AMOUNT USD
A3: 139473 | B3: =VLOOKUP(A3,'IQ Equitizer'!$A$3:$B$12,2,0) | C3: =SUMIFS('BNY Unsettled Trades'!$AS:$AS,'BNY Unsettled Trades'!$N:$N,'Pending Failed Trade Matrix'!C$2,'BNY Unsettled Trades'!$X:$X,"Pending",'BNY Unsettled Trades'!$A:$A,'Pending Failed Trade Matrix'!$A3) | D3: =SUMIFS('BNY Unsettled Trades'!$AS:$AS,'BNY Unsettled Trades'!$N:$N,'Pending Failed Trade Matrix'!D$2,'BNY Unsettled Trades'!$X:$X,"Pending",'BNY Unsettled Trades'!$A:$A,'Pending Failed Trade Matrix'!$A3) | E3: =SUMIFS('BNY Unsettled Trades'!$AS:$AS,'BNY Unsettled Trades'!$N:$N,'Pending Failed Trade Matrix'!E$2,'BNY Unsettled Trades'!$X:$X,"Pending",'BNY Unsettled Trades'!$A:$A,'Pending Failed Trade Matrix'!$A3) | F3: =SUMIFS('BNY Unsettled Trades'!$AS:$AS,'BNY Unsettled Trades'!$N:$N,'Pending Failed Trade Matrix'!F$2,'BNY Unsettled Trades'!$X:$X,"Pending",'BNY Unsettled Trades'!$A:$A,'Pending Failed Trade Matrix'!$A3) | G3: =SUMIFS('BNY Unsettled Trades'!$AS:$AS,'BNY Unsettled Trades'!$N:$N,'Pending Failed Trade Matrix'!G$2,'BNY Unsettled Trades'!$X:$X,"Pending",'BNY Unsettled Trades'!$A:$A,'Pending Failed Trade Matrix'!$A3) | H3: =SUMIFS('BNY Unsettled Trades'!$AS:$AS,'BNY Unsettled Trades'!$N:$N,'Pending Failed Trade Matrix'!H$2,'BNY Unsettled Trades'!$X:$X,"Pending",'BNY Unsettled Trades'!$A:$A,'Pending Failed Trade Matrix'!$A3) | I3: =SUMIFS('BNY Unsettled Trades'!$AS:$AS,'BNY Unsettled Trades'!$N:$N,'Pending Failed Trade Matrix'!I$2,'BNY Unsettled Trades'!$X:$X,"Pending",'BNY Unsettled Trades'!$A:$A,'Pending Failed Trade Matrix'!$A3) | J3: =SUMIFS('BNY Unsettled Trades'!$AS:$AS,'BNY Unsettled Trades'!$N:$N,'Pending Failed Trade Matrix'!J$2,'BNY Unsettled Trades'!$X:$X,"Pending",'BNY Unsettled Trades'!$A:$A,'Pending Failed Trade Matrix'!$A3) | ... AF3: =SUMIFS('BNY Unsettled Trades'!$AS:$AS,'BNY Unsettled Trades'!$N:$N,'Pending Failed Trade Matrix'!AF$2,'BNY Unsettled Trades'!$X:$X,"Pending",'BNY Unsettled Trades'!$A:$A,'Pending Failed Trade Matrix'!$A3) | AG3: =AF3+SUM(C3/$C$1,D3/$D$1,E3/$E$1,F3/$F$1,G3/$G$1,H3/$H$1,I3/$I$1,J3/$J$1,K3/$K$1,L3/$L$1,M3/$M$1,N3/$N$1,O3/$O$1,P3/$P$1,Q3/$Q$1,R3/$R$1,S3/$S$1,T3/$T$1,U3/$U$1,V3/$V$1,W3/$W$1,X3/$X$1,Y3/$Y$1,Z3/$Z$1,AA3/$AA$1,AB3/$AB$1,AC3/$AC$1,AD3/$AD$1,AE3/$AE$1)
A4: 139522 | B4: =VLOOKUP(A4,'IQ Equitizer'!$A$3:$B$12,2,0) | C4: =SUMIFS('BNY Unsettled Trades'!$AS:$AS,'BNY Unsettled Trades'!$N:$N,'Pending Failed Trade Matrix'!C$2,'BNY Unsettled Trades'!$X:$X,"Pending",'BNY Unsettled Trades'!$A:$A,'Pending Failed Trade Matrix'!$A4) | D4: =SUMIFS('BNY Unsettled Trades'!$AS:$AS,'BNY Unsettled Trades'!$N:$N,'Pending Failed Trade Matrix'!D$2,'BNY Unsettled Trades'!$X:$X,"Pending",'BNY Unsettled Trades'!$A:$A,'Pending Failed Trade Matrix'!$A4) | E4: =SUMIFS('BNY Unsettled Trades'!$AS:$AS,'BNY Unsettled Trades'!$N:$N,'Pending Failed Trade Matrix'!E$2,'BNY Unsettled Trades'!$X:$X,"Pending",'BNY Unsettled Trades'!$A:$A,'Pending Failed Trade Matrix'!$A4) | F4: =SUMIFS('BNY Unsettled Trades'!$AS:$AS,'BNY Unsettled Trades'!$N:$N,'Pending Failed Trade Matrix'!F$2,'BNY Unsettled Trades'!$X:$X,"Pending",'BNY Unsettled Trades'!$A:$A,'Pending Failed Trade Matrix'!$A4) | G4: =SUMIFS('BNY Unsettled Trades'!$AS:$AS,'BNY Unsettled Trades'!$N:$N,'Pending Failed Trade Matrix'!G$2,'BNY Unsettled Trades'!$X:$X,"Pending",'BNY Unsettled Trades'!$A:$A,'Pending Failed Trade Matrix'!$A4) | H4: =SUMIFS('BNY Unsettled Trades'!$AS:$AS,'BNY Unsettled Trades'!$N:$N,'Pending Failed Trade Matrix'!H$2,'BNY Unsettled Trades'!$X:$X,"Pending",'BNY Unsettled Trades'!$A:$A,'Pending Failed Trade Matrix'!$A4) | I4: =SUMIFS('BNY Unsettled Trades'!$AS:$AS,'BNY Unsettled Trades'!$N:$N,'Pending Failed Trade Matrix'!I$2,'BNY Unsettled Trades'!$X:$X,"Pending",'BNY Unsettled Trades'!$A:$A,'Pending Failed Trade Matrix'!$A4) | J4: =SUMIFS('BNY Unsettled Trades'!$AS:$AS,'BNY Unsettled Trades'!$N:$N,'Pending Failed Trade Matrix'!J$2,'BNY Unsettled Trades'!$X:$X,"Pending",'BNY Unsettled Trades'!$A:$A,'Pending Failed Trade Matrix'!$A4) | ... AF4: =SUMIFS('BNY Unsettled Trades'!$AS:$AS,'BNY Unsettled Trades'!$N:$N,'Pending Failed Trade Matrix'!AF$2,'BNY Unsettled Trades'!$X:$X,"Pending",'BNY Unsettled Trades'!$A:$A,'Pending Failed Trade Matrix'!$A4) | AG4: =AF4+SUM(C4/$C$1,D4/$D$1,E4/$E$1,F4/$F$1,G4/$G$1,H4/$H$1,I4/$I$1,J4/$J$1,K4/$K$1,L4/$L$1,M4/$M$1,N4/$N$1,O4/$O$1,P4/$P$1,Q4/$Q$1,R4/$R$1,S4/$S$1,T4/$T$1,U4/$U$1,V4/$V$1,W4/$W$1,X4/$X$1,Y4/$Y$1,Z4/$Z$1,AA4/$AA$1,AB4/$AB$1,AC4/$AC$1,AD4/$AD$1,AE4/$AE$1)
A5: 156481 | B5: =VLOOKUP(A5,'IQ Equitizer'!$A$3:$B$12,2,0) | C5: =SUMIFS('BNY Unsettled Trades'!$AS:$AS,'BNY Unsettled Trades'!$N:$N,'Pending Failed Trade Matrix'!C$2,'BNY Unsettled Trades'!$X:$X,"Pending",'BNY Unsettled Trades'!$A:$A,'Pending Failed Trade Matrix'!$A5) | D5: =SUMIFS('BNY Unsettled Trades'!$AS:$AS,'BNY Unsettled Trades'!$N:$N,'Pending Failed Trade Matrix'!D$2,'BNY Unsettled Trades'!$X:$X,"Pending",'BNY Unsettled Trades'!$A:$A,'Pending Failed Trade Matrix'!$A5) | E5: =SUMIFS('BNY Unsettled Trades'!$AS:$AS,'BNY Unsettled Trades'!$N:$N,'Pending Failed Trade Matrix'!E$2,'BNY Unsettled Trades'!$X:$X,"Pending",'BNY Unsettled Trades'!$A:$A,'Pending Failed Trade Matrix'!$A5) | F5: =SUMIFS('BNY Unsettled Trades'!$AS:$AS,'BNY Unsettled Trades'!$N:$N,'Pending Failed Trade Matrix'!F$2,'BNY Unsettled Trades'!$X:$X,"Pending",'BNY Unsettled Trades'!$A:$A,'Pending Failed Trade Matrix'!$A5) | G5: =SUMIFS('BNY Unsettled Trades'!$AS:$AS,'BNY Unsettled Trades'!$N:$N,'Pending Failed Trade Matrix'!G$2,'BNY Unsettled Trades'!$X:$X,"Pending",'BNY Unsettled Trades'!$A:$A,'Pending Failed Trade Matrix'!$A5) | H5: =SUMIFS('BNY Unsettled Trades'!$AS:$AS,'BNY Unsettled Trades'!$N:$N,'Pending Failed Trade Matrix'!H$2,'BNY Unsettled Trades'!$X:$X,"Pending",'BNY Unsettled Trades'!$A:$A,'Pending Failed Trade Matrix'!$A5) | I5: =SUMIFS('BNY Unsettled Trades'!$AS:$AS,'BNY Unsettled Trades'!$N:$N,'Pending Failed Trade Matrix'!I$2,'BNY Unsettled Trades'!$X:$X,"Pending",'BNY Unsettled Trades'!$A:$A,'Pending Failed Trade Matrix'!$A5) | J5: =SUMIFS('BNY Unsettled Trades'!$AS:$AS,'BNY Unsettled Trades'!$N:$N,'Pending Failed Trade Matrix'!J$2,'BNY Unsettled Trades'!$X:$X,"Pending",'BNY Unsettled Trades'!$A:$A,'Pending Failed Trade Matrix'!$A5) | ... AF5: =SUMIFS('BNY Unsettled Trades'!$AS:$AS,'BNY Unsettled Trades'!$N:$N,'Pending Failed Trade Matrix'!AF$2,'BNY Unsettled Trades'!$X:$X,"Pending",'BNY Unsettled Trades'!$A:$A,'Pending Failed Trade Matrix'!$A5) | AG5: =AF5+SUM(C5/$C$1,D5/$D$1,E5/$E$1,F5/$F$1,G5/$G$1,H5/$H$1,I5/$I$1,J5/$J$1,K5/$K$1,L5/$L$1,M5/$M$1,N5/$N$1,O5/$O$1,P5/$P$1,Q5/$Q$1,R5/$R$1,S5/$S$1,T5/$T$1,U5/$U$1,V5/$V$1,W5/$W$1,X5/$X$1,Y5/$Y$1,Z5/$Z$1,AA5/$AA$1,AB5/$AB$1,AC5/$AC$1,AD5/$AD$1,AE5/$AE$1)
A6: 212156 | B6: =VLOOKUP(A6,'IQ Equitizer'!$A$3:$B$12,2,0) | C6: =SUMIFS('BNY Unsettled Trades'!$AS:$AS,'BNY Unsettled Trades'!$N:$N,'Pending Failed Trade Matrix'!C$2,'BNY Unsettled Trades'!$X:$X,"Pending",'BNY Unsettled Trades'!$A:$A,'Pending Failed Trade Matrix'!$A6) | D6: =SUMIFS('BNY Unsettled Trades'!$AS:$AS,'BNY Unsettled Trades'!$N:$N,'Pending Failed Trade Matrix'!D$2,'BNY Unsettled Trades'!$X:$X,"Pending",'BNY Unsettled Trades'!$A:$A,'Pending Failed Trade Matrix'!$A6) | E6: =SUMIFS('BNY Unsettled Trades'!$AS:$AS,'BNY Unsettled Trades'!$N:$N,'Pending Failed Trade Matrix'!E$2,'BNY Unsettled Trades'!$X:$X,"Pending",'BNY Unsettled Trades'!$A:$A,'Pending Failed Trade Matrix'!$A6) | F6: =SUMIFS('BNY Unsettled Trades'!$AS:$AS,'BNY Unsettled Trades'!$N:$N,'Pending Failed Trade Matrix'!F$2,'BNY Unsettled Trades'!$X:$X,"Pending",'BNY Unsettled Trades'!$A:$A,'Pending Failed Trade Matrix'!$A6) | G6: =SUMIFS('BNY Unsettled Trades'!$AS:$AS,'BNY Unsettled Trades'!$N:$N,'Pending Failed Trade Matrix'!G$2,'BNY Unsettled Trades'!$X:$X,"Pending",'BNY Unsettled Trades'!$A:$A,'Pending Failed Trade Matrix'!$A6) | H6: =SUMIFS('BNY Unsettled Trades'!$AS:$AS,'BNY Unsettled Trades'!$N:$N,'Pending Failed Trade Matrix'!H$2,'BNY Unsettled Trades'!$X:$X,"Pending",'BNY Unsettled Trades'!$A:$A,'Pending Failed Trade Matrix'!$A6) | I6: =SUMIFS('BNY Unsettled Trades'!$AS:$AS,'BNY Unsettled Trades'!$N:$N,'Pending Failed Trade Matrix'!I$2,'BNY Unsettled Trades'!$X:$X,"Pending",'BNY Unsettled Trades'!$A:$A,'Pending Failed Trade Matrix'!$A6) | J6: =SUMIFS('BNY Unsettled Trades'!$AS:$AS,'BNY Unsettled Trades'!$N:$N,'Pending Failed Trade Matrix'!J$2,'BNY Unsettled Trades'!$X:$X,"Pending",'BNY Unsettled Trades'!$A:$A,'Pending Failed Trade Matrix'!$A6) | ... AF6: =SUMIFS('BNY Unsettled Trades'!$AS:$AS,'BNY Unsettled Trades'!$N:$N,'Pending Failed Trade Matrix'!AF$2,'BNY Unsettled Trades'!$X:$X,"Pending",'BNY Unsettled Trades'!$A:$A,'Pending Failed Trade Matrix'!$A6) | AG6: =AF6+SUM(C6/$C$1,D6/$D$1,E6/$E$1,F6/$F$1,G6/$G$1,H6/$H$1,I6/$I$1,J6/$J$1,K6/$K$1,L6/$L$1,M6/$M$1,N6/$N$1,O6/$O$1,P6/$P$1,Q6/$Q$1,R6/$R$1,S6/$S$1,T6/$T$1,U6/$U$1,V6/$V$1,W6/$W$1,X6/$X$1,Y6/$Y$1,Z6/$Z$1,AA6/$AA$1,AB6/$AB$1,AC6/$AC$1,AD6/$AD$1,AE6/$AE$1)
A7: 222959 | B7: =VLOOKUP(A7,'IQ Equitizer'!$A$3:$B$12,2,0) | C7: =SUMIFS('BNY Unsettled Trades'!$AS:$AS,'BNY Unsettled Trades'!$N:$N,'Pending Failed Trade Matrix'!C$2,'BNY Unsettled Trades'!$X:$X,"Pending",'BNY Unsettled Trades'!$A:$A,'Pending Failed Trade Matrix'!$A7) | D7: =SUMIFS('BNY Unsettled Trades'!$AS:$AS,'BNY Unsettled Trades'!$N:$N,'Pending Failed Trade Matrix'!D$2,'BNY Unsettled Trades'!$X:$X,"Pending",'BNY Unsettled Trades'!$A:$A,'Pending Failed Trade Matrix'!$A7) | E7: =SUMIFS('BNY Unsettled Trades'!$AS:$AS,'BNY Unsettled Trades'!$N:$N,'Pending Failed Trade Matrix'!E$2,'BNY Unsettled Trades'!$X:$X,"Pending",'BNY Unsettled Trades'!$A:$A,'Pending Failed Trade Matrix'!$A7) | F7: =SUMIFS('BNY Unsettled Trades'!$AS:$AS,'BNY Unsettled Trades'!$N:$N,'Pending Failed Trade Matrix'!F$2,'BNY Unsettled Trades'!$X:$X,"Pending",'BNY Unsettled Trades'!$A:$A,'Pending Failed Trade Matrix'!$A7) | G7: =SUMIFS('BNY Unsettled Trades'!$AS:$AS,'BNY Unsettled Trades'!$N:$N,'Pending Failed Trade Matrix'!G$2,'BNY Unsettled Trades'!$X:$X,"Pending",'BNY Unsettled Trades'!$A:$A,'Pending Failed Trade Matrix'!$A7) | H7: =SUMIFS('BNY Unsettled Trades'!$AS:$AS,'BNY Unsettled Trades'!$N:$N,'Pending Failed Trade Matrix'!H$2,'BNY Unsettled Trades'!$X:$X,"Pending",'BNY Unsettled Trades'!$A:$A,'Pending Failed Trade Matrix'!$A7) | I7: =SUMIFS('BNY Unsettled Trades'!$AS:$AS,'BNY Unsettled Trades'!$N:$N,'Pending Failed Trade Matrix'!I$2,'BNY Unsettled Trades'!$X:$X,"Pending",'BNY Unsettled Trades'!$A:$A,'Pending Failed Trade Matrix'!$A7) | J7: =SUMIFS('BNY Unsettled Trades'!$AS:$AS,'BNY Unsettled Trades'!$N:$N,'Pending Failed Trade Matrix'!J$2,'BNY Unsettled Trades'!$X:$X,"Pending",'BNY Unsettled Trades'!$A:$A,'Pending Failed Trade Matrix'!$A7) | ... AF7: =SUMIFS('BNY Unsettled Trades'!$AS:$AS,'BNY Unsettled Trades'!$N:$N,'Pending Failed Trade Matrix'!AF$2,'BNY Unsettled Trades'!$X:$X,"Pending",'BNY Unsettled Trades'!$A:$A,'Pending Failed Trade Matrix'!$A7) | AG7: =AF7+SUM(C7/$C$1,D7/$D$1,E7/$E$1,F7/$F$1,G7/$G$1,H7/$H$1,I7/$I$1,J7/$J$1,K7/$K$1,L7/$L$1,M7/$M$1,N7/$N$1,O7/$O$1,P7/$P$1,Q7/$Q$1,R7/$R$1,S7/$S$1,T7/$T$1,U7/$U$1,V7/$V$1,W7/$W$1,X7/$X$1,Y7/$Y$1,Z7/$Z$1,AA7/$AA$1,AB7/$AB$1,AC7/$AC$1,AD7/$AD$1,AE7/$AE$1)
A8: 222963 | B8: =VLOOKUP(A8,'IQ Equitizer'!$A$3:$B$12,2,0) | C8: =SUMIFS('BNY Unsettled Trades'!$AS:$AS,'BNY Unsettled Trades'!$N:$N,'Pending Failed Trade Matrix'!C$2,'BNY Unsettled Trades'!$X:$X,"Pending",'BNY Unsettled Trades'!$A:$A,'Pending Failed Trade Matrix'!$A8) | D8: =SUMIFS('BNY Unsettled Trades'!$AS:$AS,'BNY Unsettled Trades'!$N:$N,'Pending Failed Trade Matrix'!D$2,'BNY Unsettled Trades'!$X:$X,"Pending",'BNY Unsettled Trades'!$A:$A,'Pending Failed Trade Matrix'!$A8) | E8: =SUMIFS('BNY Unsettled Trades'!$AS:$AS,'BNY Unsettled Trades'!$N:$N,'Pending Failed Trade Matrix'!E$2,'BNY Unsettled Trades'!$X:$X,"Pending",'BNY Unsettled Trades'!$A:$A,'Pending Failed Trade Matrix'!$A8) | F8: =SUMIFS('BNY Unsettled Trades'!$AS:$AS,'BNY Unsettled Trades'!$N:$N,'Pending Failed Trade Matrix'!F$2,'BNY Unsettled Trades'!$X:$X,"Pending",'BNY Unsettled Trades'!$A:$A,'Pending Failed Trade Matrix'!$A8) | G8: =SUMIFS('BNY Unsettled Trades'!$AS:$AS,'BNY Unsettled Trades'!$N:$N,'Pending Failed Trade Matrix'!G$2,'BNY Unsettled Trades'!$X:$X,"Pending",'BNY Unsettled Trades'!$A:$A,'Pending Failed Trade Matrix'!$A8) | H8: =SUMIFS('BNY Unsettled Trades'!$AS:$AS,'BNY Unsettled Trades'!$N:$N,'Pending Failed Trade Matrix'!H$2,'BNY Unsettled Trades'!$X:$X,"Pending",'BNY Unsettled Trades'!$A:$A,'Pending Failed Trade Matrix'!$A8) | I8: =SUMIFS('BNY Unsettled Trades'!$AS:$AS,'BNY Unsettled Trades'!$N:$N,'Pending Failed Trade Matrix'!I$2,'BNY Unsettled Trades'!$X:$X,"Pending",'BNY Unsettled Trades'!$A:$A,'Pending Failed Trade Matrix'!$A8) | J8: =SUMIFS('BNY Unsettled Trades'!$AS:$AS,'BNY Unsettled Trades'!$N:$N,'Pending Failed Trade Matrix'!J$2,'BNY Unsettled Trades'!$X:$X,"Pending",'BNY Unsettled Trades'!$A:$A,'Pending Failed Trade Matrix'!$A8) | ... AF8: =SUMIFS('BNY Unsettled Trades'!$AS:$AS,'BNY Unsettled Trades'!$N:$N,'Pending Failed Trade Matrix'!AF$2,'BNY Unsettled Trades'!$X:$X,"Pending",'BNY Unsettled Trades'!$A:$A,'Pending Failed Trade Matrix'!$A8) | AG8: =AF8+SUM(C8/$C$1,D8/$D$1,E8/$E$1,F8/$F$1,G8/$G$1,H8/$H$1,I8/$I$1,J8/$J$1,K8/$K$1,L8/$L$1,M8/$M$1,N8/$N$1,O8/$O$1,P8/$P$1,Q8/$Q$1,R8/$R$1,S8/$S$1,T8/$T$1,U8/$U$1,V8/$V$1,W8/$W$1,X8/$X$1,Y8/$Y$1,Z8/$Z$1,AA8/$AA$1,AB8/$AB$1,AC8/$AC$1,AD8/$AD$1,AE8/$AE$1)
A9: 240413 | B9: =VLOOKUP(A9,'IQ Equitizer'!$A$3:$B$12,2,0) | C9: =SUMIFS('BNY Unsettled Trades'!$AS:$AS,'BNY Unsettled Trades'!$N:$N,'Pending Failed Trade Matrix'!C$2,'BNY Unsettled Trades'!$X:$X,"Pending",'BNY Unsettled Trades'!$A:$A,'Pending Failed Trade Matrix'!$A9) | D9: =SUMIFS('BNY Unsettled Trades'!$AS:$AS,'BNY Unsettled Trades'!$N:$N,'Pending Failed Trade Matrix'!D$2,'BNY Unsettled Trades'!$X:$X,"Pending",'BNY Unsettled Trades'!$A:$A,'Pending Failed Trade Matrix'!$A9) | E9: =SUMIFS('BNY Unsettled Trades'!$AS:$AS,'BNY Unsettled Trades'!$N:$N,'Pending Failed Trade Matrix'!E$2,'BNY Unsettled Trades'!$X:$X,"Pending",'BNY Unsettled Trades'!$A:$A,'Pending Failed Trade Matrix'!$A9) | F9: =SUMIFS('BNY Unsettled Trades'!$AS:$AS,'BNY Unsettled Trades'!$N:$N,'Pending Failed Trade Matrix'!F$2,'BNY Unsettled Trades'!$X:$X,"Pending",'BNY Unsettled Trades'!$A:$A,'Pending Failed Trade Matrix'!$A9) | G9: =SUMIFS('BNY Unsettled Trades'!$AS:$AS,'BNY Unsettled Trades'!$N:$N,'Pending Failed Trade Matrix'!G$2,'BNY Unsettled Trades'!$X:$X,"Pending",'BNY Unsettled Trades'!$A:$A,'Pending Failed Trade Matrix'!$A9) | H9: =SUMIFS('BNY Unsettled Trades'!$AS:$AS,'BNY Unsettled Trades'!$N:$N,'Pending Failed Trade Matrix'!H$2,'BNY Unsettled Trades'!$X:$X,"Pending",'BNY Unsettled Trades'!$A:$A,'Pending Failed Trade Matrix'!$A9) | I9: =SUMIFS('BNY Unsettled Trades'!$AS:$AS,'BNY Unsettled Trades'!$N:$N,'Pending Failed Trade Matrix'!I$2,'BNY Unsettled Trades'!$X:$X,"Pending",'BNY Unsettled Trades'!$A:$A,'Pending Failed Trade Matrix'!$A9) | J9: =SUMIFS('BNY Unsettled Trades'!$AS:$AS,'BNY Unsettled Trades'!$N:$N,'Pending Failed Trade Matrix'!J$2,'BNY Unsettled Trades'!$X:$X,"Pending",'BNY Unsettled Trades'!$A:$A,'Pending Failed Trade Matrix'!$A9) | ... AF9: =SUMIFS('BNY Unsettled Trades'!$AS:$AS,'BNY Unsettled Trades'!$N:$N,'Pending Failed Trade Matrix'!AF$2,'BNY Unsettled Trades'!$X:$X,"Pending",'BNY Unsettled Trades'!$A:$A,'Pending Failed Trade Matrix'!$A9) | AG9: =AF9+SUM(C9/$C$1,D9/$D$1,E9/$E$1,F9/$F$1,G9/$G$1,H9/$H$1,I9/$I$1,J9/$J$1,K9/$K$1,L9/$L$1,M9/$M$1,N9/$N$1,O9/$O$1,P9/$P$1,Q9/$Q$1,R9/$R$1,S9/$S$1,T9/$T$1,U9/$U$1,V9/$V$1,W9/$W$1,X9/$X$1,Y9/$Y$1,Z9/$Z$1,AA9/$AA$1,AB9/$AB$1,AC9/$AC$1,AD9/$AD$1,AE9/$AE$1)
A10: 263076 | B10: =VLOOKUP(A10,'IQ Equitizer'!$A$3:$B$12,2,0) | C10: =SUMIFS('BNY Unsettled Trades'!$AS:$AS,'BNY Unsettled Trades'!$N:$N,'Pending Failed Trade Matrix'!C$2,'BNY Unsettled Trades'!$X:$X,"Pending",'BNY Unsettled Trades'!$A:$A,'Pending Failed Trade Matrix'!$A10) | D10: =SUMIFS('BNY Unsettled Trades'!$AS:$AS,'BNY Unsettled Trades'!$N:$N,'Pending Failed Trade Matrix'!D$2,'BNY Unsettled Trades'!$X:$X,"Pending",'BNY Unsettled Trades'!$A:$A,'Pending Failed Trade Matrix'!$A10) | E10: =SUMIFS('BNY Unsettled Trades'!$AS:$AS,'BNY Unsettled Trades'!$N:$N,'Pending Failed Trade Matrix'!E$2,'BNY Unsettled Trades'!$X:$X,"Pending",'BNY Unsettled Trades'!$A:$A,'Pending Failed Trade Matrix'!$A10) | F10: =SUMIFS('BNY Unsettled Trades'!$AS:$AS,'BNY Unsettled Trades'!$N:$N,'Pending Failed Trade Matrix'!F$2,'BNY Unsettled Trades'!$X:$X,"Pending",'BNY Unsettled Trades'!$A:$A,'Pending Failed Trade Matrix'!$A10) | G10: =SUMIFS('BNY Unsettled Trades'!$AS:$AS,'BNY Unsettled Trades'!$N:$N,'Pending Failed Trade Matrix'!G$2,'BNY Unsettled Trades'!$X:$X,"Pending",'BNY Unsettled Trades'!$A:$A,'Pending Failed Trade Matrix'!$A10) | H10: =SUMIFS('BNY Unsettled Trades'!$AS:$AS,'BNY Unsettled Trades'!$N:$N,'Pending Failed Trade Matrix'!H$2,'BNY Unsettled Trades'!$X:$X,"Pending",'BNY Unsettled Trades'!$A:$A,'Pending Failed Trade Matrix'!$A10) | I10: =SUMIFS('BNY Unsettled Trades'!$AS:$AS,'BNY Unsettled Trades'!$N:$N,'Pending Failed Trade Matrix'!I$2,'BNY Unsettled Trades'!$X:$X,"Pending",'BNY Unsettled Trades'!$A:$A,'Pending Failed Trade Matrix'!$A10) | J10: =SUMIFS('BNY Unsettled Trades'!$AS:$AS,'BNY Unsettled Trades'!$N:$N,'Pending Failed Trade Matrix'!J$2,'BNY Unsettled Trades'!$X:$X,"Pending",'BNY Unsettled Trades'!$A:$A,'Pending Failed Trade Matrix'!$A10) | ... AF10: =SUMIFS('BNY Unsettled Trades'!$AS:$AS,'BNY Unsettled Trades'!$N:$N,'Pending Failed Trade Matrix'!AF$2,'BNY Unsettled Trades'!$X:$X,"Pending",'BNY Unsettled Trades'!$A:$A,'Pending Failed Trade Matrix'!$A10) | AG10: =AF10+SUM(C10/$C$1,D10/$D$1,E10/$E$1,F10/$F$1,G10/$G$1,H10/$H$1,I10/$I$1,J10/$J$1,K10/$K$1,L10/$L$1,M10/$M$1,N10/$N$1,O10/$O$1,P10/$P$1,Q10/$Q$1,R10/$R$1,S10/$S$1,T10/$T$1,U10/$U$1,V10/$V$1,W10/$W$1,X10/$X$1,Y10/$Y$1,Z10/$Z$1,AA10/$AA$1,AB10/$AB$1,AC10/$AC$1,AD10/$AD$1,AE10/$AE$1)
A11: 447594 | B11: =VLOOKUP(A11,'IQ Equitizer'!$A$3:$B$12,2,0) | C11: =SUMIFS('BNY Unsettled Trades'!$AS:$AS,'BNY Unsettled Trades'!$N:$N,'Pending Failed Trade Matrix'!C$2,'BNY Unsettled Trades'!$X:$X,"Pending",'BNY Unsettled Trades'!$A:$A,'Pending Failed Trade Matrix'!$A11) | D11: =SUMIFS('BNY Unsettled Trades'!$AS:$AS,'BNY Unsettled Trades'!$N:$N,'Pending Failed Trade Matrix'!D$2,'BNY Unsettled Trades'!$X:$X,"Pending",'BNY Unsettled Trades'!$A:$A,'Pending Failed Trade Matrix'!$A11) | E11: =SUMIFS('BNY Unsettled Trades'!$AS:$AS,'BNY Unsettled Trades'!$N:$N,'Pending Failed Trade Matrix'!E$2,'BNY Unsettled Trades'!$X:$X,"Pending",'BNY Unsettled Trades'!$A:$A,'Pending Failed Trade Matrix'!$A11) | F11: =SUMIFS('BNY Unsettled Trades'!$AS:$AS,'BNY Unsettled Trades'!$N:$N,'Pending Failed Trade Matrix'!F$2,'BNY Unsettled Trades'!$X:$X,"Pending",'BNY Unsettled Trades'!$A:$A,'Pending Failed Trade Matrix'!$A11) | G11: =SUMIFS('BNY Unsettled Trades'!$AS:$AS,'BNY Unsettled Trades'!$N:$N,'Pending Failed Trade Matrix'!G$2,'BNY Unsettled Trades'!$X:$X,"Pending",'BNY Unsettled Trades'!$A:$A,'Pending Failed Trade Matrix'!$A11) | H11: =SUMIFS('BNY Unsettled Trades'!$AS:$AS,'BNY Unsettled Trades'!$N:$N,'Pending Failed Trade Matrix'!H$2,'BNY Unsettled Trades'!$X:$X,"Pending",'BNY Unsettled Trades'!$A:$A,'Pending Failed Trade Matrix'!$A11) | I11: =SUMIFS('BNY Unsettled Trades'!$AS:$AS,'BNY Unsettled Trades'!$N:$N,'Pending Failed Trade Matrix'!I$2,'BNY Unsettled Trades'!$X:$X,"Pending",'BNY Unsettled Trades'!$A:$A,'Pending Failed Trade Matrix'!$A11) | J11: =SUMIFS('BNY Unsettled Trades'!$AS:$AS,'BNY Unsettled Trades'!$N:$N,'Pending Failed Trade Matrix'!J$2,'BNY Unsettled Trades'!$X:$X,"Pending",'BNY Unsettled Trades'!$A:$A,'Pending Failed Trade Matrix'!$A11) | ... AF11: =SUMIFS('BNY Unsettled Trades'!$AS:$AS,'BNY Unsettled Trades'!$N:$N,'Pending Failed Trade Matrix'!AF$2,'BNY Unsettled Trades'!$X:$X,"Pending",'BNY Unsettled Trades'!$A:$A,'Pending Failed Trade Matrix'!$A11) | AG11: =AF11+SUM(C11/$C$1,D11/$D$1,E11/$E$1,F11/$F$1,G11/$G$1,H11/$H$1,I11/$I$1,J11/$J$1,K11/$K$1,L11/$L$1,M11/$M$1,N11/$N$1,O11/$O$1,P11/$P$1,Q11/$Q$1,R11/$R$1,S11/$S$1,T11/$T$1,U11/$U$1,V11/$V$1,W11/$W$1,X11/$X$1,Y11/$Y$1,Z11/$Z$1,AA11/$AA$1,AB11/$AB$1,AC11/$AC$1,AD11/$AD$1,AE11/$AE$1)
A12: G 26785 | B12: VP Mutual Fund | C12: 0 | D12: 0 | E12: 0 | F12: 0 | G12: 0 | H12: 0 | I12: 0 | J12: 0 | K12: 0 | L12: 0 | M12: 0 | N12: 0 | O12: 0 | P12: 0 | Q12: 0 | R12: 0 | S12: 0 | T12: 0 | U12: 0 | V12: 0 | W12: 0 | X12: 0 | Y12: 0 | Z12: 0 | AA12: 0 | AB12: 0 | AC12: 0 | AD12: 0 | AE12: 0 | AF12: =SUMIF('VP Proj Cash Statement (8am)'!C:C,A12,'VP Proj Cash Statement (8am)'!L:L)+SUMIF('VP Proj Cash Statement (8am)'!C:C,A12,'VP Proj Cash Statement (8am)'!M:M)+SUMIF('VP Proj Cash Statement (8am)'!C:C,A12,'VP Proj Cash Statement (8am)'!Y:Y)+SUMIF('VP Proj Cash Statement (8am)'!C:C,A12,'VP Proj Cash Statement (8am)'!Z:Z)-((SUMIFS('VP Proj Cash Statement (8am)'!$AK$5:$AK$65525,'VP Proj Cash Detail (10am)'!$I$5:$I$65525,A12,'VP Proj Cash Detail (10am)'!$Y$5:$Y$65525,"JPMORGAN SHORT TERM INVESTMENT FUNDS",'VP Proj Cash Detail (10am)'!$C$5:$C$65525,"PURCHASES")+SUMIFS('VP Proj Cash Detail (10am)'!$AK$5:$AK$65525,'VP Proj Cash Detail (10am)'!$I$5:$I$65525,A12,'VP Proj Cash Detail (10am)'!$AE$5:$AE$65525,"MUSXX",'VP Proj Cash Detail (10am)'!$C$5:$C$65525,"PURCHASES"))+SUMIFS('VP Proj Cash Detail (10am)'!$AK$5:$AK$65525,'VP Proj Cash Detail (10am)'!$I$5:$I$65525,A12,'VP Proj Cash Detail (10am)'!$Y$5:$Y$65525,"JPMORGAN SHORT TERM INVESTMENT FUNDS",'VP Proj Cash Detail (10am)'!$C$5:$C$65525,"Sales")+SUMIFS('VP Proj Cash Detail (10am)'!$AK$5:$AK$65525,'VP Proj Cash Detail (10am)'!$I$5:$I$65525,A12,'VP Proj Cash Detail (10am)'!$AE$5:$AE$65525,"MUSXX",'VP Proj Cash Detail (10am)'!$C$5:$C$65525,"Sales")) | AG12: =AF12+SUM(C12/$C$1,D12/$D$1,E12/$E$1,F12/$F$1,G12/$G$1,H12/$H$1,I12/$I$1,J12/$J$1,K12/$K$1,L12/$L$1,M12/$M$1,N12/$N$1,O12/$O$1,P12/$P$1,Q12/$Q$1,R12/$R$1,S12/$S$1,T12/$T$1,U12/$U$1,V12/$V$1,W12/$W$1,X12/$X$1,Y12/$Y$1,Z12/$Z$1,AA12/$AA$1,AB12/$AB$1,AC12/$AC$1,AD12/$AD$1,AE12/$AE$1)
A15: Failing
B16: Fund | C16: AUD | D16: BRL | E16: CAD | F16: CHF | G16: CLP | H16: COP | I16: CZK | J16: DKK | K16: EUR | L16: GBP | M16: HKD | N16: HUF | O16: IDR | P16: ILS | Q16: INR | R16: JPY | S16: KRW | T16: MXN | U16: MYR | V16: NOK | W16: NZD | X16: PHP | Y16: PLN | Z16: SEK | AA16: SGD | AB16: THB | AC16: TWD | AD16: ZAR | AE16: TRY | AF16: USD | AG16: TOTAL AMOUNT USD
A17: 139473 | B17: =VLOOKUP(A17,'IQ Equitizer'!$A$3:$B$12,2,0) | C17: =SUMIFS('BNY Unsettled Trades'!$AS:$AS,'BNY Unsettled Trades'!$N:$N,'Pending Failed Trade Matrix'!C$16,'BNY Unsettled Trades'!$X:$X,"Failing",'BNY Unsettled Trades'!$A:$A,'Pending Failed Trade Matrix'!$A17) | D17: =SUMIFS('BNY Unsettled Trades'!$AS:$AS,'BNY Unsettled Trades'!$N:$N,'Pending Failed Trade Matrix'!D$16,'BNY Unsettled Trades'!$X:$X,"Failing",'BNY Unsettled Trades'!$A:$A,'Pending Failed Trade Matrix'!$A17) | E17: =SUMIFS('BNY Unsettled Trades'!$AS:$AS,'BNY Unsettled Trades'!$N:$N,'Pending Failed Trade Matrix'!E$16,'BNY Unsettled Trades'!$X:$X,"Failing",'BNY Unsettled Trades'!$A:$A,'Pending Failed Trade Matrix'!$A17) | F17: =SUMIFS('BNY Unsettled Trades'!$AS:$AS,'BNY Unsettled Trades'!$N:$N,'Pending Failed Trade Matrix'!F$16,'BNY Unsettled Trades'!$X:$X,"Failing",'BNY Unsettled Trades'!$A:$A,'Pending Failed Trade Matrix'!$A17) | G17: =SUMIFS('BNY Unsettled Trades'!$AS:$AS,'BNY Unsettled Trades'!$N:$N,'Pending Failed Trade Matrix'!G$16,'BNY Unsettled Trades'!$X:$X,"Failing",'BNY Unsettled Trades'!$A:$A,'Pending Failed Trade Matrix'!$A17) | H17: =SUMIFS('BNY Unsettled Trades'!$AS:$AS,'BNY Unsettled Trades'!$N:$N,'Pending Failed Trade Matrix'!H$16,'BNY Unsettled Trades'!$X:$X,"Failing",'BNY Unsettled Trades'!$A:$A,'Pending Failed Trade Matrix'!$A17) | I17: =SUMIFS('BNY Unsettled Trades'!$AS:$AS,'BNY Unsettled Trades'!$N:$N,'Pending Failed Trade Matrix'!I$16,'BNY Unsettled Trades'!$X:$X,"Failing",'BNY Unsettled Trades'!$A:$A,'Pending Failed Trade Matrix'!$A17) | J17: =SUMIFS('BNY Unsettled Trades'!$AS:$AS,'BNY Unsettled Trades'!$N:$N,'Pending Failed Trade Matrix'!J$16,'BNY Unsettled Trades'!$X:$X,"Failing",'BNY Unsettled Trades'!$A:$A,'Pending Failed Trade Matrix'!$A17) | ... AF17: =SUMIFS('BNY Unsettled Trades'!$AS:$AS,'BNY Unsettled Trades'!$N:$N,'Pending Failed Trade Matrix'!AF$16,'BNY Unsettled Trades'!$X:$X,"Failing",'BNY Unsettled Trades'!$A:$A,'Pending Failed Trade Matrix'!$A17) | AG17: =AF17+SUM(C17/$C$1,D17/$D$1,E17/$E$1,F17/$F$1,G17/$G$1,H17/$H$1,I17/$I$1,J17/$J$1,K17/$K$1,L17/$L$1,M17/$M$1,N17/$N$1,O17/$O$1,P17/$P$1,Q17/$Q$1,R17/$R$1,S17/$S$1,T17/$T$1,U17/$U$1,V17/$V$1,W17/$W$1,X17/$X$1,Y17/$Y$1,Z17/$Z$1,AA17/$AA$1,AB17/$AB$1,AC17/$AC$1,AD17/$AD$1,AE17/$AE$1)
A18: 139522 | B18: =VLOOKUP(A18,'IQ Equitizer'!$A$3:$B$12,2,0) | C18: =SUMIFS('BNY Unsettled Trades'!$AS:$AS,'BNY Unsettled Trades'!$N:$N,'Pending Failed Trade Matrix'!C$16,'BNY Unsettled Trades'!$X:$X,"Failing",'BNY Unsettled Trades'!$A:$A,'Pending Failed Trade Matrix'!$A18) | D18: =SUMIFS('BNY Unsettled Trades'!$AS:$AS,'BNY Unsettled Trades'!$N:$N,'Pending Failed Trade Matrix'!D$16,'BNY Unsettled Trades'!$X:$X,"Failing",'BNY Unsettled Trades'!$A:$A,'Pending Failed Trade Matrix'!$A18) | E18: =SUMIFS('BNY Unsettled Trades'!$AS:$AS,'BNY Unsettled Trades'!$N:$N,'Pending Failed Trade Matrix'!E$16,'BNY Unsettled Trades'!$X:$X,"Failing",'BNY Unsettled Trades'!$A:$A,'Pending Failed Trade Matrix'!$A18) | F18: =SUMIFS('BNY Unsettled Trades'!$AS:$AS,'BNY Unsettled Trades'!$N:$N,'Pending Failed Trade Matrix'!F$16,'BNY Unsettled Trades'!$X:$X,"Failing",'BNY Unsettled Trades'!$A:$A,'Pending Failed Trade Matrix'!$A18) | G18: =SUMIFS('BNY Unsettled Trades'!$AS:$AS,'BNY Unsettled Trades'!$N:$N,'Pending Failed Trade Matrix'!G$16,'BNY Unsettled Trades'!$X:$X,"Failing",'BNY Unsettled Trades'!$A:$A,'Pending Failed Trade Matrix'!$A18) | H18: =SUMIFS('BNY Unsettled Trades'!$AS:$AS,'BNY Unsettled Trades'!$N:$N,'Pending Failed Trade Matrix'!H$16,'BNY Unsettled Trades'!$X:$X,"Failing",'BNY Unsettled Trades'!$A:$A,'Pending Failed Trade Matrix'!$A18) | I18: =SUMIFS('BNY Unsettled Trades'!$AS:$AS,'BNY Unsettled Trades'!$N:$N,'Pending Failed Trade Matrix'!I$16,'BNY Unsettled Trades'!$X:$X,"Failing",'BNY Unsettled Trades'!$A:$A,'Pending Failed Trade Matrix'!$A18) | J18: =SUMIFS('BNY Unsettled Trades'!$AS:$AS,'BNY Unsettled Trades'!$N:$N,'Pending Failed Trade Matrix'!J$16,'BNY Unsettled Trades'!$X:$X,"Failing",'BNY Unsettled Trades'!$A:$A,'Pending Failed Trade Matrix'!$A18) | ... AF18: =SUMIFS('BNY Unsettled Trades'!$AS:$AS,'BNY Unsettled Trades'!$N:$N,'Pending Failed Trade Matrix'!AF$16,'BNY Unsettled Trades'!$X:$X,"Failing",'BNY Unsettled Trades'!$A:$A,'Pending Failed Trade Matrix'!$A18) | AG18: =AF18+SUM(C18/$C$1,D18/$D$1,E18/$E$1,F18/$F$1,G18/$G$1,H18/$H$1,I18/$I$1,J18/$J$1,K18/$K$1,L18/$L$1,M18/$M$1,N18/$N$1,O18/$O$1,P18/$P$1,Q18/$Q$1,R18/$R$1,S18/$S$1,T18/$T$1,U18/$U$1,V18/$V$1,W18/$W$1,X18/$X$1,Y18/$Y$1,Z18/$Z$1,AA18/$AA$1,AB18/$AB$1,AC18/$AC$1,AD18/$AD$1,AE18/$AE$1)
A19: 156481 | B19: =VLOOKUP(A19,'IQ Equitizer'!$A$3:$B$12,2,0) | C19: =SUMIFS('BNY Unsettled Trades'!$AS:$AS,'BNY Unsettled Trades'!$N:$N,'Pending Failed Trade Matrix'!C$16,'BNY Unsettled Trades'!$X:$X,"Failing",'BNY Unsettled Trades'!$A:$A,'Pending Failed Trade Matrix'!$A19) | D19: =SUMIFS('BNY Unsettled Trades'!$AS:$AS,'BNY Unsettled Trades'!$N:$N,'Pending Failed Trade Matrix'!D$16,'BNY Unsettled Trades'!$X:$X,"Failing",'BNY Unsettled Trades'!$A:$A,'Pending Failed Trade Matrix'!$A19) | E19: =SUMIFS('BNY Unsettled Trades'!$AS:$AS,'BNY Unsettled Trades'!$N:$N,'Pending Failed Trade Matrix'!E$16,'BNY Unsettled Trades'!$X:$X,"Failing",'BNY Unsettled Trades'!$A:$A,'Pending Failed Trade Matrix'!$A19) | F19: =SUMIFS('BNY Unsettled Trades'!$AS:$AS,'BNY Unsettled Trades'!$N:$N,'Pending Failed Trade Matrix'!F$16,'BNY Unsettled Trades'!$X:$X,"Failing",'BNY Unsettled Trades'!$A:$A,'Pending Failed Trade Matrix'!$A19) | G19: =SUMIFS('BNY Unsettled Trades'!$AS:$AS,'BNY Unsettled Trades'!$N:$N,'Pending Failed Trade Matrix'!G$16,'BNY Unsettled Trades'!$X:$X,"Failing",'BNY Unsettled Trades'!$A:$A,'Pending Failed Trade Matrix'!$A19) | H19: =SUMIFS('BNY Unsettled Trades'!$AS:$AS,'BNY Unsettled Trades'!$N:$N,'Pending Failed Trade Matrix'!H$16,'BNY Unsettled Trades'!$X:$X,"Failing",'BNY Unsettled Trades'!$A:$A,'Pending Failed Trade Matrix'!$A19) | I19: =SUMIFS('BNY Unsettled Trades'!$AS:$AS,'BNY Unsettled Trades'!$N:$N,'Pending Failed Trade Matrix'!I$16,'BNY Unsettled Trades'!$X:$X,"Failing",'BNY Unsettled Trades'!$A:$A,'Pending Failed Trade Matrix'!$A19) | J19: =SUMIFS('BNY Unsettled Trades'!$AS:$AS,'BNY Unsettled Trades'!$N:$N,'Pending Failed Trade Matrix'!J$16,'BNY Unsettled Trades'!$X:$X,"Failing",'BNY Unsettled Trades'!$A:$A,'Pending Failed Trade Matrix'!$A19) | ... AF19: =SUMIFS('BNY Unsettled Trades'!$AS:$AS,'BNY Unsettled Trades'!$N:$N,'Pending Failed Trade Matrix'!AF$16,'BNY Unsettled Trades'!$X:$X,"Failing",'BNY Unsettled Trades'!$A:$A,'Pending Failed Trade Matrix'!$A19) | AG19: =AF19+SUM(C19/$C$1,D19/$D$1,E19/$E$1,F19/$F$1,G19/$G$1,H19/$H$1,I19/$I$1,J19/$J$1,K19/$K$1,L19/$L$1,M19/$M$1,N19/$N$1,O19/$O$1,P19/$P$1,Q19/$Q$1,R19/$R$1,S19/$S$1,T19/$T$1,U19/$U$1,V19/$V$1,W19/$W$1,X19/$X$1,Y19/$Y$1,Z19/$Z$1,AA19/$AA$1,AB19/$AB$1,AC19/$AC$1,AD19/$AD$1,AE19/$AE$1)
A20: 212156 | B20: =VLOOKUP(A20,'IQ Equitizer'!$A$3:$B$12,2,0) | C20: =SUMIFS('BNY Unsettled Trades'!$AS:$AS,'BNY Unsettled Trades'!$N:$N,'Pending Failed Trade Matrix'!C$16,'BNY Unsettled Trades'!$X:$X,"Failing",'BNY Unsettled Trades'!$A:$A,'Pending Failed Trade Matrix'!$A20) | D20: =SUMIFS('BNY Unsettled Trades'!$AS:$AS,'BNY Unsettled Trades'!$N:$N,'Pending Failed Trade Matrix'!D$16,'BNY Unsettled Trades'!$X:$X,"Failing",'BNY Unsettled Trades'!$A:$A,'Pending Failed Trade Matrix'!$A20) | E20: =SUMIFS('BNY Unsettled Trades'!$AS:$AS,'BNY Unsettled Trades'!$N:$N,'Pending Failed Trade Matrix'!E$16,'BNY Unsettled Trades'!$X:$X,"Failing",'BNY Unsettled Trades'!$A:$A,'Pending Failed Trade Matrix'!$A20) | F20: =SUMIFS('BNY Unsettled Trades'!$AS:$AS,'BNY Unsettled Trades'!$N:$N,'Pending Failed Trade Matrix'!F$16,'BNY Unsettled Trades'!$X:$X,"Failing",'BNY Unsettled Trades'!$A:$A,'Pending Failed Trade Matrix'!$A20) | G20: =SUMIFS('BNY Unsettled Trades'!$AS:$AS,'BNY Unsettled Trades'!$N:$N,'Pending Failed Trade Matrix'!G$16,'BNY Unsettled Trades'!$X:$X,"Failing",'BNY Unsettled Trades'!$A:$A,'Pending Failed Trade Matrix'!$A20) | H20: =SUMIFS('BNY Unsettled Trades'!$AS:$AS,'BNY Unsettled Trades'!$N:$N,'Pending Failed Trade Matrix'!H$16,'BNY Unsettled Trades'!$X:$X,"Failing",'BNY Unsettled Trades'!$A:$A,'Pending Failed Trade Matrix'!$A20) | I20: =SUMIFS('BNY Unsettled Trades'!$AS:$AS,'BNY Unsettled Trades'!$N:$N,'Pending Failed Trade Matrix'!I$16,'BNY Unsettled Trades'!$X:$X,"Failing",'BNY Unsettled Trades'!$A:$A,'Pending Failed Trade Matrix'!$A20) | J20: =SUMIFS('BNY Unsettled Trades'!$AS:$AS,'BNY Unsettled Trades'!$N:$N,'Pending Failed Trade Matrix'!J$16,'BNY Unsettled Trades'!$X:$X,"Failing",'BNY Unsettled Trades'!$A:$A,'Pending Failed Trade Matrix'!$A20) | ... AF20: =SUMIFS('BNY Unsettled Trades'!$AS:$AS,'BNY Unsettled Trades'!$N:$N,'Pending Failed Trade Matrix'!AF$16,'BNY Unsettled Trades'!$X:$X,"Failing",'BNY Unsettled Trades'!$A:$A,'Pending Failed Trade Matrix'!$A20) | AG20: =AF20+SUM(C20/$C$1,D20/$D$1,E20/$E$1,F20/$F$1,G20/$G$1,H20/$H$1,I20/$I$1,J20/$J$1,K20/$K$1,L20/$L$1,M20/$M$1,N20/$N$1,O20/$O$1,P20/$P$1,Q20/$Q$1,R20/$R$1,S20/$S$1,T20/$T$1,U20/$U$1,V20/$V$1,W20/$W$1,X20/$X$1,Y20/$Y$1,Z20/$Z$1,AA20/$AA$1,AB20/$AB$1,AC20/$AC$1,AD20/$AD$1,AE20/$AE$1)
A21: 222959 | B21: =VLOOKUP(A21,'IQ Equitizer'!$A$3:$B$12,2,0) | C21: =SUMIFS('BNY Unsettled Trades'!$AS:$AS,'BNY Unsettled Trades'!$N:$N,'Pending Failed Trade Matrix'!C$16,'BNY Unsettled Trades'!$X:$X,"Failing",'BNY Unsettled Trades'!$A:$A,'Pending Failed Trade Matrix'!$A21) | D21: =SUMIFS('BNY Unsettled Trades'!$AS:$AS,'BNY Unsettled Trades'!$N:$N,'Pending Failed Trade Matrix'!D$16,'BNY Unsettled Trades'!$X:$X,"Failing",'BNY Unsettled Trades'!$A:$A,'Pending Failed Trade Matrix'!$A21) | E21: =SUMIFS('BNY Unsettled Trades'!$AS:$AS,'BNY Unsettled Trades'!$N:$N,'Pending Failed Trade Matrix'!E$16,'BNY Unsettled Trades'!$X:$X,"Failing",'BNY Unsettled Trades'!$A:$A,'Pending Failed Trade Matrix'!$A21) | F21: =SUMIFS('BNY Unsettled Trades'!$AS:$AS,'BNY Unsettled Trades'!$N:$N,'Pending Failed Trade Matrix'!F$16,'BNY Unsettled Trades'!$X:$X,"Failing",'BNY Unsettled Trades'!$A:$A,'Pending Failed Trade Matrix'!$A21) | G21: =SUMIFS('BNY Unsettled Trades'!$AS:$AS,'BNY Unsettled Trades'!$N:$N,'Pending Failed Trade Matrix'!G$16,'BNY Unsettled Trades'!$X:$X,"Failing",'BNY Unsettled Trades'!$A:$A,'Pending Failed Trade Matrix'!$A21) | H21: =SUMIFS('BNY Unsettled Trades'!$AS:$AS,'BNY Unsettled Trades'!$N:$N,'Pending Failed Trade Matrix'!H$16,'BNY Unsettled Trades'!$X:$X,"Failing",'BNY Unsettled Trades'!$A:$A,'Pending Failed Trade Matrix'!$A21) | I21: =SUMIFS('BNY Unsettled Trades'!$AS:$AS,'BNY Unsettled Trades'!$N:$N,'Pending Failed Trade Matrix'!I$16,'BNY Unsettled Trades'!$X:$X,"Failing",'BNY Unsettled Trades'!$A:$A,'Pending Failed Trade Matrix'!$A21) | J21: =SUMIFS('BNY Unsettled Trades'!$AS:$AS,'BNY Unsettled Trades'!$N:$N,'Pending Failed Trade Matrix'!J$16,'BNY Unsettled Trades'!$X:$X,"Failing",'BNY Unsettled Trades'!$A:$A,'Pending Failed Trade Matrix'!$A21) | ... AF21: =SUMIFS('BNY Unsettled Trades'!$AS:$AS,'BNY Unsettled Trades'!$N:$N,'Pending Failed Trade Matrix'!AF$16,'BNY Unsettled Trades'!$X:$X,"Failing",'BNY Unsettled Trades'!$A:$A,'Pending Failed Trade Matrix'!$A21) | AG21: =AF21+SUM(C21/$C$1,D21/$D$1,E21/$E$1,F21/$F$1,G21/$G$1,H21/$H$1,I21/$I$1,J21/$J$1,K21/$K$1,L21/$L$1,M21/$M$1,N21/$N$1,O21/$O$1,P21/$P$1,Q21/$Q$1,R21/$R$1,S21/$S$1,T21/$T$1,U21/$U$1,V21/$V$1,W21/$W$1,X21/$X$1,Y21/$Y$1,Z21/$Z$1,AA21/$AA$1,AB21/$AB$1,AC21/$AC$1,AD21/$AD$1,AE21/$AE$1)
A22: 222963 | B22: =VLOOKUP(A22,'IQ Equitizer'!$A$3:$B$12,2,0) | C22: =SUMIFS('BNY Unsettled Trades'!$AS:$AS,'BNY Unsettled Trades'!$N:$N,'Pending Failed Trade Matrix'!C$16,'BNY Unsettled Trades'!$X:$X,"Failing",'BNY Unsettled Trades'!$A:$A,'Pending Failed Trade Matrix'!$A22) | D22: =SUMIFS('BNY Unsettled Trades'!$AS:$AS,'BNY Unsettled Trades'!$N:$N,'Pending Failed Trade Matrix'!D$16,'BNY Unsettled Trades'!$X:$X,"Failing",'BNY Unsettled Trades'!$A:$A,'Pending Failed Trade Matrix'!$A22) | E22: =SUMIFS('BNY Unsettled Trades'!$AS:$AS,'BNY Unsettled Trades'!$N:$N,'Pending Failed Trade Matrix'!E$16,'BNY Unsettled Trades'!$X:$X,"Failing",'BNY Unsettled Trades'!$A:$A,'Pending Failed Trade Matrix'!$A22) | F22: =SUMIFS('BNY Unsettled Trades'!$AS:$AS,'BNY Unsettled Trades'!$N:$N,'Pending Failed Trade Matrix'!F$16,'BNY Unsettled Trades'!$X:$X,"Failing",'BNY Unsettled Trades'!$A:$A,'Pending Failed Trade Matrix'!$A22) | G22: =SUMIFS('BNY Unsettled Trades'!$AS:$AS,'BNY Unsettled Trades'!$N:$N,'Pending Failed Trade Matrix'!G$16,'BNY Unsettled Trades'!$X:$X,"Failing",'BNY Unsettled Trades'!$A:$A,'Pending Failed Trade Matrix'!$A22) | H22: =SUMIFS('BNY Unsettled Trades'!$AS:$AS,'BNY Unsettled Trades'!$N:$N,'Pending Failed Trade Matrix'!H$16,'BNY Unsettled Trades'!$X:$X,"Failing",'BNY Unsettled Trades'!$A:$A,'Pending Failed Trade Matrix'!$A22) | I22: =SUMIFS('BNY Unsettled Trades'!$AS:$AS,'BNY Unsettled Trades'!$N:$N,'Pending Failed Trade Matrix'!I$16,'BNY Unsettled Trades'!$X:$X,"Failing",'BNY Unsettled Trades'!$A:$A,'Pending Failed Trade Matrix'!$A22) | J22: =SUMIFS('BNY Unsettled Trades'!$AS:$AS,'BNY Unsettled Trades'!$N:$N,'Pending Failed Trade Matrix'!J$16,'BNY Unsettled Trades'!$X:$X,"Failing",'BNY Unsettled Trades'!$A:$A,'Pending Failed Trade Matrix'!$A22) | ... AF22: =SUMIFS('BNY Unsettled Trades'!$AS:$AS,'BNY Unsettled Trades'!$N:$N,'Pending Failed Trade Matrix'!AF$16,'BNY Unsettled Trades'!$X:$X,"Failing",'BNY Unsettled Trades'!$A:$A,'Pending Failed Trade Matrix'!$A22) | AG22: =AF22+SUM(C22/$C$1,D22/$D$1,E22/$E$1,F22/$F$1,G22/$G$1,H22/$H$1,I22/$I$1,J22/$J$1,K22/$K$1,L22/$L$1,M22/$M$1,N22/$N$1,O22/$O$1,P22/$P$1,Q22/$Q$1,R22/$R$1,S22/$S$1,T22/$T$1,U22/$U$1,V22/$V$1,W22/$W$1,X22/$X$1,Y22/$Y$1,Z22/$Z$1,AA22/$AA$1,AB22/$AB$1,AC22/$AC$1,AD22/$AD$1,AE22/$AE$1)
A23: 240413 | B23: =VLOOKUP(A23,'IQ Equitizer'!$A$3:$B$12,2,0) | C23: =SUMIFS('BNY Unsettled Trades'!$AS:$AS,'BNY Unsettled Trades'!$N:$N,'Pending Failed Trade Matrix'!C$16,'BNY Unsettled Trades'!$X:$X,"Failing",'BNY Unsettled Trades'!$A:$A,'Pending Failed Trade Matrix'!$A23) | D23: =SUMIFS('BNY Unsettled Trades'!$AS:$AS,'BNY Unsettled Trades'!$N:$N,'Pending Failed Trade Matrix'!D$16,'BNY Unsettled Trades'!$X:$X,"Failing",'BNY Unsettled Trades'!$A:$A,'Pending Failed Trade Matrix'!$A23) | E23: =SUMIFS('BNY Unsettled Trades'!$AS:$AS,'BNY Unsettled Trades'!$N:$N,'Pending Failed Trade Matrix'!E$16,'BNY Unsettled Trades'!$X:$X,"Failing",'BNY Unsettled Trades'!$A:$A,'Pending Failed Trade Matrix'!$A23) | F23: =SUMIFS('BNY Unsettled Trades'!$AS:$AS,'BNY Unsettled Trades'!$N:$N,'Pending Failed Trade Matrix'!F$16,'BNY Unsettled Trades'!$X:$X,"Failing",'BNY Unsettled Trades'!$A:$A,'Pending Failed Trade Matrix'!$A23) | G23: =SUMIFS('BNY Unsettled Trades'!$AS:$AS,'BNY Unsettled Trades'!$N:$N,'Pending Failed Trade Matrix'!G$16,'BNY Unsettled Trades'!$X:$X,"Failing",'BNY Unsettled Trades'!$A:$A,'Pending Failed Trade Matrix'!$A23) | H23: =SUMIFS('BNY Unsettled Trades'!$AS:$AS,'BNY Unsettled Trades'!$N:$N,'Pending Failed Trade Matrix'!H$16,'BNY Unsettled Trades'!$X:$X,"Failing",'BNY Unsettled Trades'!$A:$A,'Pending Failed Trade Matrix'!$A23) | I23: =SUMIFS('BNY Unsettled Trades'!$AS:$AS,'BNY Unsettled Trades'!$N:$N,'Pending Failed Trade Matrix'!I$16,'BNY Unsettled Trades'!$X:$X,"Failing",'BNY Unsettled Trades'!$A:$A,'Pending Failed Trade Matrix'!$A23) | J23: =SUMIFS('BNY Unsettled Trades'!$AS:$AS,'BNY Unsettled Trades'!$N:$N,'Pending Failed Trade Matrix'!J$16,'BNY Unsettled Trades'!$X:$X,"Failing",'BNY Unsettled Trades'!$A:$A,'Pending Failed Trade Matrix'!$A23) | ... AF23: =SUMIFS('BNY Unsettled Trades'!$AS:$AS,'BNY Unsettled Trades'!$N:$N,'Pending Failed Trade Matrix'!AF$16,'BNY Unsettled Trades'!$X:$X,"Failing",'BNY Unsettled Trades'!$A:$A,'Pending Failed Trade Matrix'!$A23) | AG23: =AF23+SUM(C23/$C$1,D23/$D$1,E23/$E$1,F23/$F$1,G23/$G$1,H23/$H$1,I23/$I$1,J23/$J$1,K23/$K$1,L23/$L$1,M23/$M$1,N23/$N$1,O23/$O$1,P23/$P$1,Q23/$Q$1,R23/$R$1,S23/$S$1,T23/$T$1,U23/$U$1,V23/$V$1,W23/$W$1,X23/$X$1,Y23/$Y$1,Z23/$Z$1,AA23/$AA$1,AB23/$AB$1,AC23/$AC$1,AD23/$AD$1,AE23/$AE$1)
A24: 263076 | B24: =VLOOKUP(A24,'IQ Equitizer'!$A$3:$B$12,2,0) | C24: =SUMIFS('BNY Unsettled Trades'!$AS:$AS,'BNY Unsettled Trades'!$N:$N,'Pending Failed Trade Matrix'!C$16,'BNY Unsettled Trades'!$X:$X,"Failing",'BNY Unsettled Trades'!$A:$A,'Pending Failed Trade Matrix'!$A24) | D24: =SUMIFS('BNY Unsettled Trades'!$AS:$AS,'BNY Unsettled Trades'!$N:$N,'Pending Failed Trade Matrix'!D$16,'BNY Unsettled Trades'!$X:$X,"Failing",'BNY Unsettled Trades'!$A:$A,'Pending Failed Trade Matrix'!$A24) | E24: =SUMIFS('BNY Unsettled Trades'!$AS:$AS,'BNY Unsettled Trades'!$N:$N,'Pending Failed Trade Matrix'!E$16,'BNY Unsettled Trades'!$X:$X,"Failing",'BNY Unsettled Trades'!$A:$A,'Pending Failed Trade Matrix'!$A24) | F24: =SUMIFS('BNY Unsettled Trades'!$AS:$AS,'BNY Unsettled Trades'!$N:$N,'Pending Failed Trade Matrix'!F$16,'BNY Unsettled Trades'!$X:$X,"Failing",'BNY Unsettled Trades'!$A:$A,'Pending Failed Trade Matrix'!$A24) | G24: =SUMIFS('BNY Unsettled Trades'!$AS:$AS,'BNY Unsettled Trades'!$N:$N,'Pending Failed Trade Matrix'!G$16,'BNY Unsettled Trades'!$X:$X,"Failing",'BNY Unsettled Trades'!$A:$A,'Pending Failed Trade Matrix'!$A24) | H24: =SUMIFS('BNY Unsettled Trades'!$AS:$AS,'BNY Unsettled Trades'!$N:$N,'Pending Failed Trade Matrix'!H$16,'BNY Unsettled Trades'!$X:$X,"Failing",'BNY Unsettled Trades'!$A:$A,'Pending Failed Trade Matrix'!$A24) | I24: =SUMIFS('BNY Unsettled Trades'!$AS:$AS,'BNY Unsettled Trades'!$N:$N,'Pending Failed Trade Matrix'!I$16,'BNY Unsettled Trades'!$X:$X,"Failing",'BNY Unsettled Trades'!$A:$A,'Pending Failed Trade Matrix'!$A24) | J24: =SUMIFS('BNY Unsettled Trades'!$AS:$AS,'BNY Unsettled Trades'!$N:$N,'Pending Failed Trade Matrix'!J$16,'BNY Unsettled Trades'!$X:$X,"Failing",'BNY Unsettled Trades'!$A:$A,'Pending Failed Trade Matrix'!$A24) | ... AF24: =SUMIFS('BNY Unsettled Trades'!$AS:$AS,'BNY Unsettled Trades'!$N:$N,'Pending Failed Trade Matrix'!AF$16,'BNY Unsettled Trades'!$X:$X,"Failing",'BNY Unsettled Trades'!$A:$A,'Pending Failed Trade Matrix'!$A24) | AG24: =AF24+SUM(C24/$C$1,D24/$D$1,E24/$E$1,F24/$F$1,G24/$G$1,H24/$H$1,I24/$I$1,J24/$J$1,K24/$K$1,L24/$L$1,M24/$M$1,N24/$N$1,O24/$O$1,P24/$P$1,Q24/$Q$1,R24/$R$1,S24/$S$1,T24/$T$1,U24/$U$1,V24/$V$1,W24/$W$1,X24/$X$1,Y24/$Y$1,Z24/$Z$1,AA24/$AA$1,AB24/$AB$1,AC24/$AC$1,AD24/$AD$1,AE24/$AE$1)
A25: 447594 | B25: =VLOOKUP(A25,'IQ Equitizer'!$A$3:$B$12,2,0) | C25: =SUMIFS('BNY Unsettled Trades'!$AS:$AS,'BNY Unsettled Trades'!$N:$N,'Pending Failed Trade Matrix'!C$16,'BNY Unsettled Trades'!$X:$X,"Failing",'BNY Unsettled Trades'!$A:$A,'Pending Failed Trade Matrix'!$A25) | D25: =SUMIFS('BNY Unsettled Trades'!$AS:$AS,'BNY Unsettled Trades'!$N:$N,'Pending Failed Trade Matrix'!D$16,'BNY Unsettled Trades'!$X:$X,"Failing",'BNY Unsettled Trades'!$A:$A,'Pending Failed Trade Matrix'!$A25) | E25: =SUMIFS('BNY Unsettled Trades'!$AS:$AS,'BNY Unsettled Trades'!$N:$N,'Pending Failed Trade Matrix'!E$16,'BNY Unsettled Trades'!$X:$X,"Failing",'BNY Unsettled Trades'!$A:$A,'Pending Failed Trade Matrix'!$A25) | F25: =SUMIFS('BNY Unsettled Trades'!$AS:$AS,'BNY Unsettled Trades'!$N:$N,'Pending Failed Trade Matrix'!F$16,'BNY Unsettled Trades'!$X:$X,"Failing",'BNY Unsettled Trades'!$A:$A,'Pending Failed Trade Matrix'!$A25) | G25: =SUMIFS('BNY Unsettled Trades'!$AS:$AS,'BNY Unsettled Trades'!$N:$N,'Pending Failed Trade Matrix'!G$16,'BNY Unsettled Trades'!$X:$X,"Failing",'BNY Unsettled Trades'!$A:$A,'Pending Failed Trade Matrix'!$A25) | H25: =SUMIFS('BNY Unsettled Trades'!$AS:$AS,'BNY Unsettled Trades'!$N:$N,'Pending Failed Trade Matrix'!H$16,'BNY Unsettled Trades'!$X:$X,"Failing",'BNY Unsettled Trades'!$A:$A,'Pending Failed Trade Matrix'!$A25) | I25: =SUMIFS('BNY Unsettled Trades'!$AS:$AS,'BNY Unsettled Trades'!$N:$N,'Pending Failed Trade Matrix'!I$16,'BNY Unsettled Trades'!$X:$X,"Failing",'BNY Unsettled Trades'!$A:$A,'Pending Failed Trade Matrix'!$A25) | J25: =SUMIFS('BNY Unsettled Trades'!$AS:$AS,'BNY Unsettled Trades'!$N:$N,'Pending Failed Trade Matrix'!J$16,'BNY Unsettled Trades'!$X:$X,"Failing",'BNY Unsettled Trades'!$A:$A,'Pending Failed Trade Matrix'!$A25) | ... AF25: =SUMIFS('BNY Unsettled Trades'!$AS:$AS,'BNY Unsettled Trades'!$N:$N,'Pending Failed Trade Matrix'!AF$16,'BNY Unsettled Trades'!$X:$X,"Failing",'BNY Unsettled Trades'!$A:$A,'Pending Failed Trade Matrix'!$A25) | AG25: =AF25+SUM(C25/$C$1,D25/$D$1,E25/$E$1,F25/$F$1,G25/$G$1,H25/$H$1,I25/$I$1,J25/$J$1,K25/$K$1,L25/$L$1,M25/$M$1,N25/$N$1,O25/$O$1,P25/$P$1,Q25/$Q$1,R25/$R$1,S25/$S$1,T25/$T$1,U25/$U$1,V25/$V$1,W25/$W$1,X25/$X$1,Y25/$Y$1,Z25/$Z$1,AA25/$AA$1,AB25/$AB$1,AC25/$AC$1,AD25/$AD$1,AE25/$AE$1)
A26: G 26785 | B26: VP Mutual Fund | C26: 0 | D26: 0 | E26: 0 | F26: 0 | G26: 0 | H26: 0 | I26: 0 | J26: 0 | K26: 0 | L26: 0 | M26: 0 | N26: 0 | O26: 0 | P26: 0 | Q26: 0 | R26: 0 | S26: 0 | T26: 0 | U26: 0 | V26: 0 | W26: 0 | X26: 0 | Y26: 0 | Z26: 0 | AA26: 0 | AB26: 0 | AC26: 0 | AD26: 0 | AE26: 0 | AF26: =(SUMIFS('VP Outstanding Trades'!W:W,'VP Outstanding Trades'!A:A,A26,'VP Outstanding Trades'!D:D,"PURCHASE",'VP Outstanding Trades'!E:E,"OUTSTANDING"))+(SUMIFS('VP Outstanding Trades'!W:W,'VP Outstanding Trades'!A:A,A26,'VP Outstanding Trades'!D:D,"SALE",'VP Outstanding Trades'!E:E,"OUTSTANDING")) | AG26: =AF26+SUM(C26/$C$1,D26/$D$1,E26/$E$1,F26/$F$1,G26/$G$1,H26/$H$1,I26/$I$1,J26/$J$1,K26/$K$1,L26/$L$1,M26/$M$1,N26/$N$1,O26/$O$1,P26/$P$1,Q26/$Q$1,R26/$R$1,S26/$S$1,T26/$T$1,U26/$U$1,V26/$V$1,W26/$W$1,X26/$X$1,Y26/$Y$1,Z26/$Z$1,AA26/$AA$1,AB26/$AB$1,AC26/$AC$1,AD26/$AD$1,AE26/$AE$1)

Sheet IQ Equitizer
B1: =TODAY() | C1: Drives Sheet | G1: (Global & Domestic) | O1: Target | T1: TOTAL_NUMBER_OF_HOLDINGS_IN_PORT | W1: Income | AJ1: EOW
A2: Custody # | B2: Portfolio | C2: Name of Fund | D2: SOD Cash(USD: cash projections) | E2: SOD Cash FX (base) | F2: Pending Trades +Failing (BNY/JPM) | G2: Income (projections today) | H2: Total Cash | I2: Equity MV (custody valuation) | J2: Total Assets | K2: Percent Cash | M2: P5 AUM | N2: % of Custody Cash | O2: 0.0006 | P2: Trade | Q2: Target Trade $ | R2: Direction | S2: Fund | T2: Holdings In Portfolio | U2: Equitize Options | W2: =E30 | X2: =F30 | Y2: =G30 | Z2: =H30 | AA2: =I30 | AB2: =J30 | AC2: Total Projected Income (paydate) | AD2: % of AUM | AG2: =D30 | AH2: Today Income Impact | AJ2: Projected Cash % | AO2: NAV | AP2: EQY_SH_OUT_REAL | AQ2: P5
A3: 139473 | B3: IQSI | C3: NYLI Candriam International Equity ETF | D3: =SUMIFS('BNY Cash Projection'!AR:AR,'BNY Cash Projection'!A:A,'IQ Equitizer'!A3,'BNY Cash Projection'!E:E,"<>",'BNY Cash Projection'!N:N,'IQ Equitizer'!$D$30)/(COUNTIFS('BNY Cash Projection'!A:A,'IQ Equitizer'!A3,'BNY Cash Projection'!E:E,"<>",'BNY Cash Projection'!N:N,'IQ Equitizer'!$D$30)) | F3: =SUMIFS('BNY Cash Projection'!AV:AV,'BNY Cash Projection'!A:A,'IQ Equitizer'!A3,'BNY Cash Projection'!U:U,"BUY",'BNY Cash Projection'!AF:AF,">="&TODAY())+SUMIFS('BNY Cash Projection'!AV:AV,'BNY Cash Projection'!A:A,'IQ Equitizer'!A3,'BNY Cash Projection'!U:U,"SELL",'BNY Cash Projection'!AF:AF,">="&TODAY()) | G3: =SUMIFS('BNY Cash Projection'!AV:AV,'BNY Cash Projection'!A:A,'IQ Equitizer'!A3,'BNY Cash Projection'!AF:AF,'IQ Equitizer'!$D$30,'BNY Cash Projection'!U:U,"DIVIDEND",'BNY Cash Projection'!AH:AH,">0") | H3: =D3+F3+G3 | I3: =SUMIFS('BNY Custody Valuation'!AB:AB,'BNY Custody Valuation'!A:A,'IQ Equitizer'!A3,'BNY Custody Valuation'!U:U,"common")+SUMIFS('BNY Custody Valuation'!AB:AB,'BNY Custody Valuation'!A:A,'IQ Equitizer'!A3,'BNY Custody Valuation'!U:U,"mutual funds")+SUMIFS('BNY Custody Valuation'!AB:AB,'BNY Custody Valuation'!A:A,'IQ Equitizer'!A3,'BNY Custody Valuation'!U:U,"PREFERRED")+SUMIFS('BNY Custody Valuation'!AB:AB,'BNY Custody Valuation'!A:A,'IQ Equitizer'!A3,'BNY Custody Valuation'!U:U,"RIGHTS")+SUMIFS('BNY Custody Valuation'!AB:AB,'BNY Custody Valuation'!A:A,'IQ Equitizer'!A3,'BNY Custody Valuation'!U:U,"PARTNERSHIPS")+SUMIFS('BNY Custody Valuation'!AB:AB,'BNY Custody Valuation'!A:A,'IQ Equitizer'!A3,'BNY Custody Valuation'!U:U,"NOTES - SOVEREIGN DEBT")+SUMIFS('BNY Custody Valuation'!AB:AB,'BNY Custody Valuation'!A:A,'IQ Equitizer'!A3,'BNY Custody Valuation'!U:U,"BONDS - SOVEREIGN DEBT")+SUMIFS('BNY Custody Valuation'!AB:AB,'BNY Custody Valuation'!A:A,'IQ Equitizer'!A3,'BNY Custody Valuation'!U:U,"UNITS")+SUMIFS('BNY Custody Valuation'!AB:AB,'BNY Custody Valuation'!A:A,'IQ Equitizer'!A3,'BNY Custody Valuation'!U:U,"WARRANTS") | J3: =I3+H3 | K3: =H3/J3 | M3: =AQ3 | N3: =H3/M3 | O3: =IF(AND(N3>0,N3<0.06%),"T","F") | P3: =IF(O3="t","No Trade",N3-$O$2) | Q3: =IF(P3="No Trade",0,P3*M3) | R3: {=_xlfn.IFS(P3="no trade","-",Q3<0,"Raise",Q3>0,"Spend")} | S3: =AE3 | T3: {=_xll.BDP(S3&" equity",$T$1)} | U3: 1. VEA (SWAP) | W3: =SUMIFS('BNY Cash Projection'!$AV:$AV,'BNY Cash Projection'!$A:$A,'IQ Equitizer'!A3,'BNY Cash Projection'!$AF:$AF,'IQ Equitizer'!$W$2,'BNY Cash Projection'!$U:$U,"DIVIDEND",'BNY Cash Projection'!$AH:$AH,">0") | X3: =SUMIFS('BNY Cash Projection'!$AV:$AV,'BNY Cash Projection'!$A:$A,'IQ Equitizer'!A3,'BNY Cash Projection'!$AF:$AF,'IQ Equitizer'!$X$2,'BNY Cash Projection'!$U:$U,"DIVIDEND",'BNY Cash Projection'!$AH:$AH,">0") | Y3: =SUMIFS('BNY Cash Projection'!$AV:$AV,'BNY Cash Projection'!$A:$A,'IQ Equitizer'!A3,'BNY Cash Projection'!$AF:$AF,'IQ Equitizer'!$Y$2,'BNY Cash Projection'!$U:$U,"DIVIDEND",'BNY Cash Projection'!$AH:$AH,">0") | Z3: =SUMIFS('BNY Cash Projection'!$AV:$AV,'BNY Cash Projection'!$A:$A,'IQ Equitizer'!A3,'BNY Cash Projection'!$AF:$AF,'IQ Equitizer'!$Z$2,'BNY Cash Projection'!$U:$U,"DIVIDEND",'BNY Cash Projection'!$AH:$AH,">0") | AA3: =SUMIFS('BNY Cash Projection'!$AV:$AV,'BNY Cash Projection'!$A:$A,'IQ Equitizer'!A3,'BNY Cash Projection'!$AF:$AF,'IQ Equitizer'!$AA$2,'BNY Cash Projection'!$U:$U,"DIVIDEND",'BNY Cash Projection'!$AH:$AH,">0") | AB3: =SUMIFS('BNY Cash Projection'!$AV:$AV,'BNY Cash Projection'!$A:$A,'IQ Equitizer'!A3,'BNY Cash Projection'!$AF:$AF,'IQ Equitizer'!$AB$2,'BNY Cash Projection'!$U:$U,"DIVIDEND",'BNY Cash Projection'!$AH:$AH,">0") | AC3: =SUM(W3:AB3) | AD3: =AC3/J3 | AE3: =B3 | AG3: =SUMIFS('BNY Cash Projection'!$AV:$AV,'BNY Cash Projection'!$A:$A,'IQ Equitizer'!A3,'BNY Cash Projection'!$AF:$AF,'IQ Equitizer'!$AG$2,'BNY Cash Projection'!$U:$U,"DIVIDEND",'BNY Cash Projection'!$AH:$AH,">0") | AH3: =AG3/M3 | AJ3: =N3+AD3 | AK3: =AE3 | AN3: =B3&"NV" | AO3: {=_xll.BDP(AN3&" index","PX_LAST")} | AP3: {=_xll.BDP(B3&" equity",$AP$2)} | AQ3: =AO3*AP3
A4: 139522 | B4: IQSU | C4: NYLI Candriam U.S. Large Cap Equity ETF | D4: =SUMIFS('BNY Cash Projection'!AR:AR,'BNY Cash Projection'!A:A,'IQ Equitizer'!A4,'BNY Cash Projection'!E:E,"<>",'BNY Cash Projection'!N:N,'IQ Equitizer'!$D$30)/(COUNTIFS('BNY Cash Projection'!A:A,'IQ Equitizer'!A4,'BNY Cash Projection'!E:E,"<>",'BNY Cash Projection'!N:N,'IQ Equitizer'!$D$30)) | F4: =SUMIFS('BNY Cash Projection'!AV:AV,'BNY Cash Projection'!A:A,'IQ Equitizer'!A4,'BNY Cash Projection'!U:U,"BUY",'BNY Cash Projection'!AF:AF,">="&TODAY())+SUMIFS('BNY Cash Projection'!AV:AV,'BNY Cash Projection'!A:A,'IQ Equitizer'!A4,'BNY Cash Projection'!U:U,"SELL",'BNY Cash Projection'!AF:AF,">="&TODAY()) | G4: =SUMIFS('BNY Cash Projection'!AV:AV,'BNY Cash Projection'!A:A,'IQ Equitizer'!A4,'BNY Cash Projection'!AF:AF,'IQ Equitizer'!$D$30,'BNY Cash Projection'!U:U,"DIVIDEND",'BNY Cash Projection'!AH:AH,">0") | H4: =D4+F4+G4 | I4: =SUMIFS('BNY Custody Valuation'!AB:AB,'BNY Custody Valuation'!A:A,'IQ Equitizer'!A4,'BNY Custody Valuation'!U:U,"common")+SUMIFS('BNY Custody Valuation'!AB:AB,'BNY Custody Valuation'!A:A,'IQ Equitizer'!A4,'BNY Custody Valuation'!U:U,"mutual funds")+SUMIFS('BNY Custody Valuation'!AB:AB,'BNY Custody Valuation'!A:A,'IQ Equitizer'!A4,'BNY Custody Valuation'!U:U,"PREFERRED")+SUMIFS('BNY Custody Valuation'!AB:AB,'BNY Custody Valuation'!A:A,'IQ Equitizer'!A4,'BNY Custody Valuation'!U:U,"RIGHTS")+SUMIFS('BNY Custody Valuation'!AB:AB,'BNY Custody Valuation'!A:A,'IQ Equitizer'!A4,'BNY Custody Valuation'!U:U,"PARTNERSHIPS")+SUMIFS('BNY Custody Valuation'!AB:AB,'BNY Custody Valuation'!A:A,'IQ Equitizer'!A4,'BNY Custody Valuation'!U:U,"NOTES - SOVEREIGN DEBT")+SUMIFS('BNY Custody Valuation'!AB:AB,'BNY Custody Valuation'!A:A,'IQ Equitizer'!A4,'BNY Custody Valuation'!U:U,"BONDS - SOVEREIGN DEBT")+SUMIFS('BNY Custody Valuation'!AB:AB,'BNY Custody Valuation'!A:A,'IQ Equitizer'!A4,'BNY Custody Valuation'!U:U,"UNITS")+SUMIFS('BNY Custody Valuation'!AB:AB,'BNY Custody Valuation'!A:A,'IQ Equitizer'!A4,'BNY Custody Valuation'!U:U,"WARRANTS") | J4: =I4+H4 | K4: =H4/J4 | M4: =AQ4 | N4: =H4/M4 | O4: =IF(AND(N4>0,N4<0.06%),"T","F") | P4: =IF(O4="t","No Trade",N4-$O$2) | Q4: =IF(P4="No Trade",0,P4*M4) | R4: {=_xlfn.IFS(P4="no trade","-",Q4<0,"Raise",Q4>0,"Spend")} | S4: =AE4 | T4: {=_xll.BDP(S4&" equity",$T$1)} | U4: SPLG | W4: =SUMIFS('BNY Cash Projection'!$AV:$AV,'BNY Cash Projection'!$A:$A,'IQ Equitizer'!A4,'BNY Cash Projection'!$AF:$AF,'IQ Equitizer'!$W$2,'BNY Cash Projection'!$U:$U,"DIVIDEND",'BNY Cash Projection'!$AH:$AH,">0") | X4: =SUMIFS('BNY Cash Projection'!$AV:$AV,'BNY Cash Projection'!$A:$A,'IQ Equitizer'!A4,'BNY Cash Projection'!$AF:$AF,'IQ Equitizer'!$X$2,'BNY Cash Projection'!$U:$U,"DIVIDEND",'BNY Cash Projection'!$AH:$AH,">0") | Y4: =SUMIFS('BNY Cash Projection'!$AV:$AV,'BNY Cash Projection'!$A:$A,'IQ Equitizer'!A4,'BNY Cash Projection'!$AF:$AF,'IQ Equitizer'!$Y$2,'BNY Cash Projection'!$U:$U,"DIVIDEND",'BNY Cash Projection'!$AH:$AH,">0") | Z4: =SUMIFS('BNY Cash Projection'!$AV:$AV,'BNY Cash Projection'!$A:$A,'IQ Equitizer'!A4,'BNY Cash Projection'!$AF:$AF,'IQ Equitizer'!$Z$2,'BNY Cash Projection'!$U:$U,"DIVIDEND",'BNY Cash Projection'!$AH:$AH,">0") | AA4: =SUMIFS('BNY Cash Projection'!$AV:$AV,'BNY Cash Projection'!$A:$A,'IQ Equitizer'!A4,'BNY Cash Projection'!$AF:$AF,'IQ Equitizer'!$AA$2,'BNY Cash Projection'!$U:$U,"DIVIDEND",'BNY Cash Projection'!$AH:$AH,">0") | AB4: =SUMIFS('BNY Cash Projection'!$AV:$AV,'BNY Cash Projection'!$A:$A,'IQ Equitizer'!A4,'BNY Cash Projection'!$AF:$AF,'IQ Equitizer'!$AB$2,'BNY Cash Projection'!$U:$U,"DIVIDEND",'BNY Cash Projection'!$AH:$AH,">0") | AC4: =SUM(W4:AB4) | AD4: =AC4/J4 | AE4: =B4 | AG4: =SUMIFS('BNY Cash Projection'!$AV:$AV,'BNY Cash Projection'!$A:$A,'IQ Equitizer'!A4,'BNY Cash Projection'!$AF:$AF,'IQ Equitizer'!$AG$2,'BNY Cash Projection'!$U:$U,"DIVIDEND",'BNY Cash Projection'!$AH:$AH,">0") | AH4: =AG4/M4 | AJ4: =N4+AD4 | AK4: =AE4 | AN4: =B4&"NV" | AO4: {=_xll.BDP(AN4&" index","PX_LAST")} | AP4: {=_xll.BDP(B4&" equity",$AP$2)} | AQ4: =AO4*AP4
A5: 156481 | B5: HART | C5: NYLI Healthy Hearts ETF | D5: =SUMIFS('BNY Cash Projection'!AR:AR,'BNY Cash Projection'!A:A,'IQ Equitizer'!A5,'BNY Cash Projection'!E:E,"<>",'BNY Cash Projection'!N:N,'IQ Equitizer'!$D$30)/(COUNTIFS('BNY Cash Projection'!A:A,'IQ Equitizer'!A5,'BNY Cash Projection'!E:E,"<>",'BNY Cash Projection'!N:N,'IQ Equitizer'!$D$30)) | F5: =SUMIFS('BNY Cash Projection'!AV:AV,'BNY Cash Projection'!A:A,'IQ Equitizer'!A5,'BNY Cash Projection'!U:U,"BUY",'BNY Cash Projection'!AF:AF,">="&TODAY())+SUMIFS('BNY Cash Projection'!AV:AV,'BNY Cash Projection'!A:A,'IQ Equitizer'!A5,'BNY Cash Projection'!U:U,"SELL",'BNY Cash Projection'!AF:AF,">="&TODAY()) | G5: =SUMIFS('BNY Cash Projection'!AV:AV,'BNY Cash Projection'!A:A,'IQ Equitizer'!A5,'BNY Cash Projection'!AF:AF,'IQ Equitizer'!$D$30,'BNY Cash Projection'!U:U,"DIVIDEND",'BNY Cash Projection'!AH:AH,">0") | H5: =D5+F5+G5 | I5: =SUMIFS('BNY Custody Valuation'!AB:AB,'BNY Custody Valuation'!A:A,'IQ Equitizer'!A5,'BNY Custody Valuation'!U:U,"common")+SUMIFS('BNY Custody Valuation'!AB:AB,'BNY Custody Valuation'!A:A,'IQ Equitizer'!A5,'BNY Custody Valuation'!U:U,"mutual funds")+SUMIFS('BNY Custody Valuation'!AB:AB,'BNY Custody Valuation'!A:A,'IQ Equitizer'!A5,'BNY Custody Valuation'!U:U,"PREFERRED")+SUMIFS('BNY Custody Valuation'!AB:AB,'BNY Custody Valuation'!A:A,'IQ Equitizer'!A5,'BNY Custody Valuation'!U:U,"RIGHTS")+SUMIFS('BNY Custody Valuation'!AB:AB,'BNY Custody Valuation'!A:A,'IQ Equitizer'!A5,'BNY Custody Valuation'!U:U,"PARTNERSHIPS")+SUMIFS('BNY Custody Valuation'!AB:AB,'BNY Custody Valuation'!A:A,'IQ Equitizer'!A5,'BNY Custody Valuation'!U:U,"NOTES - SOVEREIGN DEBT")+SUMIFS('BNY Custody Valuation'!AB:AB,'BNY Custody Valuation'!A:A,'IQ Equitizer'!A5,'BNY Custody Valuation'!U:U,"BONDS - SOVEREIGN DEBT")+SUMIFS('BNY Custody Valuation'!AB:AB,'BNY Custody Valuation'!A:A,'IQ Equitizer'!A5,'BNY Custody Valuation'!U:U,"UNITS")+SUMIFS('BNY Custody Valuation'!AB:AB,'BNY Custody Valuation'!A:A,'IQ Equitizer'!A5,'BNY Custody Valuation'!U:U,"WARRANTS") | J5: =I5+H5 | K5: =H5/J5 | M5: =AQ5 | N5: =H5/M5 | O5: =IF(AND(N5>0,N5<0.06%),"T","F") | P5: =IF(O5="t","No Trade",N5-$O$2) | Q5: =IF(P5="No Trade",0,P5*M5) | R5: {=_xlfn.IFS(P5="no trade","-",Q5<0,"Raise",Q5>0,"Spend")} | S5: =AE5 | T5: {=_xll.BDP(S5&" equity",$T$1)} | U5: OD | W5: =SUMIFS('BNY Cash Projection'!$AV:$AV,'BNY Cash Projection'!$A:$A,'IQ Equitizer'!A5,'BNY Cash Projection'!$AF:$AF,'IQ Equitizer'!$W$2,'BNY Cash Projection'!$U:$U,"DIVIDEND",'BNY Cash Projection'!$AH:$AH,">0") | X5: =SUMIFS('BNY Cash Projection'!$AV:$AV,'BNY Cash Projection'!$A:$A,'IQ Equitizer'!A5,'BNY Cash Projection'!$AF:$AF,'IQ Equitizer'!$X$2,'BNY Cash Projection'!$U:$U,"DIVIDEND",'BNY Cash Projection'!$AH:$AH,">0") | Y5: =SUMIFS('BNY Cash Projection'!$AV:$AV,'BNY Cash Projection'!$A:$A,'IQ Equitizer'!A5,'BNY Cash Projection'!$AF:$AF,'IQ Equitizer'!$Y$2,'BNY Cash Projection'!$U:$U,"DIVIDEND",'BNY Cash Projection'!$AH:$AH,">0") | Z5: =SUMIFS('BNY Cash Projection'!$AV:$AV,'BNY Cash Projection'!$A:$A,'IQ Equitizer'!A5,'BNY Cash Projection'!$AF:$AF,'IQ Equitizer'!$Z$2,'BNY Cash Projection'!$U:$U,"DIVIDEND",'BNY Cash Projection'!$AH:$AH,">0") | AA5: =SUMIFS('BNY Cash Projection'!$AV:$AV,'BNY Cash Projection'!$A:$A,'IQ Equitizer'!A5,'BNY Cash Projection'!$AF:$AF,'IQ Equitizer'!$AA$2,'BNY Cash Projection'!$U:$U,"DIVIDEND",'BNY Cash Projection'!$AH:$AH,">0") | AB5: =SUMIFS('BNY Cash Projection'!$AV:$AV,'BNY Cash Projection'!$A:$A,'IQ Equitizer'!A5,'BNY Cash Projection'!$AF:$AF,'IQ Equitizer'!$AB$2,'BNY Cash Projection'!$U:$U,"DIVIDEND",'BNY Cash Projection'!$AH:$AH,">0") | AC5: =SUM(W5:AB5) | AD5: =AC5/J5 | AE5: =B5 | AG5: =SUMIFS('BNY Cash Projection'!$AV:$AV,'BNY Cash Projection'!$A:$A,'IQ Equitizer'!A5,'BNY Cash Projection'!$AF:$AF,'IQ Equitizer'!$AG$2,'BNY Cash Projection'!$U:$U,"DIVIDEND",'BNY Cash Projection'!$AH:$AH,">0") | AH5: =AG5/M5 | AJ5: =N5+AD5 | AK5: =AE5 | AN5: =B5&"NV" | AO5: {=_xll.BDP(AN5&" index","PX_LAST")} | AP5: {=_xll.BDP(B5&" equity",$AP$2)} | AQ5: =AO5*AP5
A6: 212156 | B6: MNA | C6: NYLI Merger Arbitrage ETF | D6: =SUMIFS('BNY Cash Projection'!AR:AR,'BNY Cash Projection'!A:A,'IQ Equitizer'!A6,'BNY Cash Projection'!E:E,"<>",'BNY Cash Projection'!N:N,'IQ Equitizer'!$D$30)/(COUNTIFS('BNY Cash Projection'!A:A,'IQ Equitizer'!A6,'BNY Cash Projection'!E:E,"<>",'BNY Cash Projection'!N:N,'IQ Equitizer'!$D$30)) | F6: =SUMIFS('BNY Cash Projection'!AV:AV,'BNY Cash Projection'!A:A,'IQ Equitizer'!A6,'BNY Cash Projection'!U:U,"BUY",'BNY Cash Projection'!AF:AF,">="&TODAY())+SUMIFS('BNY Cash Projection'!AV:AV,'BNY Cash Projection'!A:A,'IQ Equitizer'!A6,'BNY Cash Projection'!U:U,"SELL",'BNY Cash Projection'!AF:AF,">="&TODAY()) | G6: =SUMIFS('BNY Cash Projection'!AV:AV,'BNY Cash Projection'!A:A,'IQ Equitizer'!A6,'BNY Cash Projection'!AF:AF,'IQ Equitizer'!$D$30,'BNY Cash Projection'!U:U,"DIVIDEND",'BNY Cash Projection'!AH:AH,">0") | H6: =D6+F6+G6 | I6: =SUMIFS('BNY Custody Valuation'!AB:AB,'BNY Custody Valuation'!A:A,'IQ Equitizer'!A6,'BNY Custody Valuation'!U:U,"common")+SUMIFS('BNY Custody Valuation'!AB:AB,'BNY Custody Valuation'!A:A,'IQ Equitizer'!A6,'BNY Custody Valuation'!U:U,"mutual funds")+SUMIFS('BNY Custody Valuation'!AB:AB,'BNY Custody Valuation'!A:A,'IQ Equitizer'!A6,'BNY Custody Valuation'!U:U,"PREFERRED")+SUMIFS('BNY Custody Valuation'!AB:AB,'BNY Custody Valuation'!A:A,'IQ Equitizer'!A6,'BNY Custody Valuation'!U:U,"RIGHTS")+SUMIFS('BNY Custody Valuation'!AB:AB,'BNY Custody Valuation'!A:A,'IQ Equitizer'!A6,'BNY Custody Valuation'!U:U,"PARTNERSHIPS")+SUMIFS('BNY Custody Valuation'!AB:AB,'BNY Custody Valuation'!A:A,'IQ Equitizer'!A6,'BNY Custody Valuation'!U:U,"NOTES - SOVEREIGN DEBT")+SUMIFS('BNY Custody Valuation'!AB:AB,'BNY Custody Valuation'!A:A,'IQ Equitizer'!A6,'BNY Custody Valuation'!U:U,"BONDS - SOVEREIGN DEBT")+SUMIFS('BNY Custody Valuation'!AB:AB,'BNY Custody Valuation'!A:A,'IQ Equitizer'!A6,'BNY Custody Valuation'!U:U,"UNITS")+SUMIFS('BNY Custody Valuation'!AB:AB,'BNY Custody Valuation'!A:A,'IQ Equitizer'!A6,'BNY Custody Valuation'!U:U,"WARRANTS") | J6: =I6+H6 | K6: =H6/J6 | M6: =AQ6 | N6: =H6/M6 | Q6: =IF(P6="No Trade",0,P6*M6) | S6: MNA | W6: =SUMIFS('BNY Cash Projection'!$AV:$AV,'BNY Cash Projection'!$A:$A,'IQ Equitizer'!A6,'BNY Cash Projection'!$AF:$AF,'IQ Equitizer'!$W$2,'BNY Cash Projection'!$U:$U,"DIVIDEND",'BNY Cash Projection'!$AH:$AH,">0") | X6: =SUMIFS('BNY Cash Projection'!$AV:$AV,'BNY Cash Projection'!$A:$A,'IQ Equitizer'!A6,'BNY Cash Projection'!$AF:$AF,'IQ Equitizer'!$X$2,'BNY Cash Projection'!$U:$U,"DIVIDEND",'BNY Cash Projection'!$AH:$AH,">0") | Y6: =SUMIFS('BNY Cash Projection'!$AV:$AV,'BNY Cash Projection'!$A:$A,'IQ Equitizer'!A6,'BNY Cash Projection'!$AF:$AF,'IQ Equitizer'!$Y$2,'BNY Cash Projection'!$U:$U,"DIVIDEND",'BNY Cash Projection'!$AH:$AH,">0") | Z6: =SUMIFS('BNY Cash Projection'!$AV:$AV,'BNY Cash Projection'!$A:$A,'IQ Equitizer'!A6,'BNY Cash Projection'!$AF:$AF,'IQ Equitizer'!$Z$2,'BNY Cash Projection'!$U:$U,"DIVIDEND",'BNY Cash Projection'!$AH:$AH,">0") | AA6: =SUMIFS('BNY Cash Projection'!$AV:$AV,'BNY Cash Projection'!$A:$A,'IQ Equitizer'!A6,'BNY Cash Projection'!$AF:$AF,'IQ Equitizer'!$AA$2,'BNY Cash Projection'!$U:$U,"DIVIDEND",'BNY Cash Projection'!$AH:$AH,">0") | AB6: =SUMIFS('BNY Cash Projection'!$AV:$AV,'BNY Cash Projection'!$A:$A,'IQ Equitizer'!A6,'BNY Cash Projection'!$AF:$AF,'IQ Equitizer'!$AB$2,'BNY Cash Projection'!$U:$U,"DIVIDEND",'BNY Cash Projection'!$AH:$AH,">0") | AC6: =SUM(W6:AB6) | AD6: =AC6/J6 | AE6: =B6 | AG6: =SUMIFS('BNY Cash Projection'!$AV:$AV,'BNY Cash Projection'!$A:$A,'IQ Equitizer'!A6,'BNY Cash Projection'!$AF:$AF,'IQ Equitizer'!$AG$2,'BNY Cash Projection'!$U:$U,"DIVIDEND",'BNY Cash Projection'!$AH:$AH,">0") | AH6: =AG6/M6 | AK6: =AE6 | AN6: MNANV | AO6: {=_xll.BDP(AN6&" index","PX_LAST")} | AP6: {=_xll.BDP(B6&" equity",$AP$2)} | AQ6: =AO6*AP6
A7: 222959 | B7: LRND | C7: NYLI U.S. Large Cap R&D Leaders ETF | D7: =SUMIFS('BNY Cash Projection'!AR:AR,'BNY Cash Projection'!A:A,'IQ Equitizer'!A7,'BNY Cash Projection'!E:E,"<>",'BNY Cash Projection'!N:N,'IQ Equitizer'!$D$30)/(COUNTIFS('BNY Cash Projection'!A:A,'IQ Equitizer'!A7,'BNY Cash Projection'!E:E,"<>",'BNY Cash Projection'!N:N,'IQ Equitizer'!$D$30)) | F7: =SUMIFS('BNY Cash Projection'!AV:AV,'BNY Cash Projection'!A:A,'IQ Equitizer'!A7,'BNY Cash Projection'!U:U,"BUY",'BNY Cash Projection'!AF:AF,">="&TODAY())+SUMIFS('BNY Cash Projection'!AV:AV,'BNY Cash Projection'!A:A,'IQ Equitizer'!A7,'BNY Cash Projection'!U:U,"SELL",'BNY Cash Projection'!AF:AF,">="&TODAY()) | G7: =SUMIFS('BNY Cash Projection'!AV:AV,'BNY Cash Projection'!A:A,'IQ Equitizer'!A7,'BNY Cash Projection'!AF:AF,'IQ Equitizer'!$D$30,'BNY Cash Projection'!U:U,"DIVIDEND",'BNY Cash Projection'!AH:AH,">0") | H7: =D7+F7+G7 | I7: =SUMIFS('BNY Custody Valuation'!AB:AB,'BNY Custody Valuation'!A:A,'IQ Equitizer'!A7,'BNY Custody Valuation'!U:U,"common")+SUMIFS('BNY Custody Valuation'!AB:AB,'BNY Custody Valuation'!A:A,'IQ Equitizer'!A7,'BNY Custody Valuation'!U:U,"mutual funds")+SUMIFS('BNY Custody Valuation'!AB:AB,'BNY Custody Valuation'!A:A,'IQ Equitizer'!A7,'BNY Custody Valuation'!U:U,"PREFERRED")+SUMIFS('BNY Custody Valuation'!AB:AB,'BNY Custody Valuation'!A:A,'IQ Equitizer'!A7,'BNY Custody Valuation'!U:U,"RIGHTS")+SUMIFS('BNY Custody Valuation'!AB:AB,'BNY Custody Valuation'!A:A,'IQ Equitizer'!A7,'BNY Custody Valuation'!U:U,"PARTNERSHIPS")+SUMIFS('BNY Custody Valuation'!AB:AB,'BNY Custody Valuation'!A:A,'IQ Equitizer'!A7,'BNY Custody Valuation'!U:U,"NOTES - SOVEREIGN DEBT")+SUMIFS('BNY Custody Valuation'!AB:AB,'BNY Custody Valuation'!A:A,'IQ Equitizer'!A7,'BNY Custody Valuation'!U:U,"BONDS - SOVEREIGN DEBT")+SUMIFS('BNY Custody Valuation'!AB:AB,'BNY Custody Valuation'!A:A,'IQ Equitizer'!A7,'BNY Custody Valuation'!U:U,"UNITS")+SUMIFS('BNY Custody Valuation'!AB:AB,'BNY Custody Valuation'!A:A,'IQ Equitizer'!A7,'BNY Custody Valuation'!U:U,"WARRANTS") | J7: =I7+H7 | K7: =H7/J7 | M7: =AQ7 | N7: =H7/M7 | O7: =IF(AND(N7>0,N7<0.06%),"T","F") | P7: =IF(O7="t","No Trade",N7-$O$2) | Q7: =IF(P7="No Trade",0,P7*M7) | R7: {=_xlfn.IFS(P7="no trade","-",Q7<0,"Raise",Q7>0,"Spend")} | S7: =AE7 | T7: {=_xll.BDP(S7&" equity",$T$1)} | U7: BKLC, MGC | W7: =SUMIFS('BNY Cash Projection'!$AV:$AV,'BNY Cash Projection'!$A:$A,'IQ Equitizer'!A7,'BNY Cash Projection'!$AF:$AF,'IQ Equitizer'!$W$2,'BNY Cash Projection'!$U:$U,"DIVIDEND",'BNY Cash Projection'!$AH:$AH,">0") | X7: =SUMIFS('BNY Cash Projection'!$AV:$AV,'BNY Cash Projection'!$A:$A,'IQ Equitizer'!A7,'BNY Cash Projection'!$AF:$AF,'IQ Equitizer'!$X$2,'BNY Cash Projection'!$U:$U,"DIVIDEND",'BNY Cash Projection'!$AH:$AH,">0") | Y7: =SUMIFS('BNY Cash Projection'!$AV:$AV,'BNY Cash Projection'!$A:$A,'IQ Equitizer'!A7,'BNY Cash Projection'!$AF:$AF,'IQ Equitizer'!$Y$2,'BNY Cash Projection'!$U:$U,"DIVIDEND",'BNY Cash Projection'!$AH:$AH,">0") | Z7: =SUMIFS('BNY Cash Projection'!$AV:$AV,'BNY Cash Projection'!$A:$A,'IQ Equitizer'!A7,'BNY Cash Projection'!$AF:$AF,'IQ Equitizer'!$Z$2,'BNY Cash Projection'!$U:$U,"DIVIDEND",'BNY Cash Projection'!$AH:$AH,">0") | AA7: =SUMIFS('BNY Cash Projection'!$AV:$AV,'BNY Cash Projection'!$A:$A,'IQ Equitizer'!A7,'BNY Cash Projection'!$AF:$AF,'IQ Equitizer'!$AA$2,'BNY Cash Projection'!$U:$U,"DIVIDEND",'BNY Cash Projection'!$AH:$AH,">0") | AB7: =SUMIFS('BNY Cash Projection'!$AV:$AV,'BNY Cash Projection'!$A:$A,'IQ Equitizer'!A7,'BNY Cash Projection'!$AF:$AF,'IQ Equitizer'!$AB$2,'BNY Cash Projection'!$U:$U,"DIVIDEND",'BNY Cash Projection'!$AH:$AH,">0") | AC7: =SUM(W7:AB7) | AD7: =AC7/J7 | AE7: =B7 | AG7: =SUMIFS('BNY Cash Projection'!$AV:$AV,'BNY Cash Projection'!$A:$A,'IQ Equitizer'!A7,'BNY Cash Projection'!$AF:$AF,'IQ Equitizer'!$AG$2,'BNY Cash Projection'!$U:$U,"DIVIDEND",'BNY Cash Projection'!$AH:$AH,">0") | AH7: =AG7/M7 | AJ7: =N7+AD7 | AK7: =AE7 | AN7: =B7&"NV" | AO7: {=_xll.BDP(AN7&" index","PX_LAST")} | AP7: {=_xll.BDP(B7&" equity",$AP$2)} | AQ7: =AO7*AP7
A8: 222963 | B8: WRND | C8: NYLI Global Equity R&D Leaders ETF | D8: =SUMIFS('BNY Cash Projection'!AR:AR,'BNY Cash Projection'!A:A,'IQ Equitizer'!A8,'BNY Cash Projection'!E:E,"<>",'BNY Cash Projection'!N:N,'IQ Equitizer'!$D$30)/(COUNTIFS('BNY Cash Projection'!A:A,'IQ Equitizer'!A8,'BNY Cash Projection'!E:E,"<>",'BNY Cash Projection'!N:N,'IQ Equitizer'!$D$30)) | F8: =SUMIFS('BNY Cash Projection'!AV:AV,'BNY Cash Projection'!A:A,'IQ Equitizer'!A8,'BNY Cash Projection'!U:U,"BUY",'BNY Cash Projection'!AF:AF,">="&TODAY())+SUMIFS('BNY Cash Projection'!AV:AV,'BNY Cash Projection'!A:A,'IQ Equitizer'!A8,'BNY Cash Projection'!U:U,"SELL",'BNY Cash Projection'!AF:AF,">="&TODAY()) | G8: =SUMIFS('BNY Cash Projection'!AV:AV,'BNY Cash Projection'!A:A,'IQ Equitizer'!A8,'BNY Cash Projection'!AF:AF,'IQ Equitizer'!$D$30,'BNY Cash Projection'!U:U,"DIVIDEND",'BNY Cash Projection'!AH:AH,">0") | H8: =D8+F8+G8 | I8: =SUMIFS('BNY Custody Valuation'!AB:AB,'BNY Custody Valuation'!A:A,'IQ Equitizer'!A8,'BNY Custody Valuation'!U:U,"common")+SUMIFS('BNY Custody Valuation'!AB:AB,'BNY Custody Valuation'!A:A,'IQ Equitizer'!A8,'BNY Custody Valuation'!U:U,"mutual funds")+SUMIFS('BNY Custody Valuation'!AB:AB,'BNY Custody Valuation'!A:A,'IQ Equitizer'!A8,'BNY Custody Valuation'!U:U,"PREFERRED")+SUMIFS('BNY Custody Valuation'!AB:AB,'BNY Custody Valuation'!A:A,'IQ Equitizer'!A8,'BNY Custody Valuation'!U:U,"RIGHTS")+SUMIFS('BNY Custody Valuation'!AB:AB,'BNY Custody Valuation'!A:A,'IQ Equitizer'!A8,'BNY Custody Valuation'!U:U,"PARTNERSHIPS")+SUMIFS('BNY Custody Valuation'!AB:AB,'BNY Custody Valuation'!A:A,'IQ Equitizer'!A8,'BNY Custody Valuation'!U:U,"NOTES - SOVEREIGN DEBT")+SUMIFS('BNY Custody Valuation'!AB:AB,'BNY Custody Valuation'!A:A,'IQ Equitizer'!A8,'BNY Custody Valuation'!U:U,"BONDS - SOVEREIGN DEBT")+SUMIFS('BNY Custody Valuation'!AB:AB,'BNY Custody Valuation'!A:A,'IQ Equitizer'!A8,'BNY Custody Valuation'!U:U,"UNITS")+SUMIFS('BNY Custody Valuation'!AB:AB,'BNY Custody Valuation'!A:A,'IQ Equitizer'!A8,'BNY Custody Valuation'!U:U,"WARRANTS") | J8: =I8+H8 | K8: =H8/J8 | M8: =AQ8 | N8: =H8/M8 | O8: =IF(AND(N8>0,N8<0.06%),"T","F") | P8: =IF(O8="t","No Trade",N8-$O$2) | Q8: =IF(P8="No Trade",0,P8*M8) | R8: {=_xlfn.IFS(P8="no trade","-",Q8<0,"Raise",Q8>0,"Spend")} | S8: =AE8 | T8: {=_xll.BDP(S8&" equity",$T$1)} | U8: OD | W8: =SUMIFS('BNY Cash Projection'!$AV:$AV,'BNY Cash Projection'!$A:$A,'IQ Equitizer'!A8,'BNY Cash Projection'!$AF:$AF,'IQ Equitizer'!$W$2,'BNY Cash Projection'!$U:$U,"DIVIDEND",'BNY Cash Projection'!$AH:$AH,">0") | X8: =SUMIFS('BNY Cash Projection'!$AV:$AV,'BNY Cash Projection'!$A:$A,'IQ Equitizer'!A8,'BNY Cash Projection'!$AF:$AF,'IQ Equitizer'!$X$2,'BNY Cash Projection'!$U:$U,"DIVIDEND",'BNY Cash Projection'!$AH:$AH,">0") | Y8: =SUMIFS('BNY Cash Projection'!$AV:$AV,'BNY Cash Projection'!$A:$A,'IQ Equitizer'!A8,'BNY Cash Projection'!$AF:$AF,'IQ Equitizer'!$Y$2,'BNY Cash Projection'!$U:$U,"DIVIDEND",'BNY Cash Projection'!$AH:$AH,">0") | Z8: =SUMIFS('BNY Cash Projection'!$AV:$AV,'BNY Cash Projection'!$A:$A,'IQ Equitizer'!A8,'BNY Cash Projection'!$AF:$AF,'IQ Equitizer'!$Z$2,'BNY Cash Projection'!$U:$U,"DIVIDEND",'BNY Cash Projection'!$AH:$AH,">0") | AA8: =SUMIFS('BNY Cash Projection'!$AV:$AV,'BNY Cash Projection'!$A:$A,'IQ Equitizer'!A8,'BNY Cash Projection'!$AF:$AF,'IQ Equitizer'!$AA$2,'BNY Cash Projection'!$U:$U,"DIVIDEND",'BNY Cash Projection'!$AH:$AH,">0") | AB8: =SUMIFS('BNY Cash Projection'!$AV:$AV,'BNY Cash Projection'!$A:$A,'IQ Equitizer'!A8,'BNY Cash Projection'!$AF:$AF,'IQ Equitizer'!$AB$2,'BNY Cash Projection'!$U:$U,"DIVIDEND",'BNY Cash Projection'!$AH:$AH,">0") | AC8: =SUM(W8:AB8) | AD8: =AC8/J8 | AE8: =B8 | AG8: =SUMIFS('BNY Cash Projection'!$AV:$AV,'BNY Cash Projection'!$A:$A,'IQ Equitizer'!A8,'BNY Cash Projection'!$AF:$AF,'IQ Equitizer'!$AG$2,'BNY Cash Projection'!$U:$U,"DIVIDEND",'BNY Cash Projection'!$AH:$AH,">0") | AH8: =AG8/M8 | AJ8: =N8+AD8 | AK8: =AE8 | AN8: =B8&"NV" | AO8: {=_xll.BDP(AN8&" index","PX_LAST")} | AP8: {=_xll.BDP(B8&" equity",$AP$2)} | AQ8: =AO8*AP8
A9: 240413 | B9: IQSM | C9: NYLI Candriam U.S. Mid Cap Equity ETF | D9: =SUMIFS('BNY Cash Projection'!AR:AR,'BNY Cash Projection'!A:A,'IQ Equitizer'!A9,'BNY Cash Projection'!E:E,"<>",'BNY Cash Projection'!N:N,'IQ Equitizer'!$D$30)/(COUNTIFS('BNY Cash Projection'!A:A,'IQ Equitizer'!A9,'BNY Cash Projection'!E:E,"<>",'BNY Cash Projection'!N:N,'IQ Equitizer'!$D$30)) | F9: =SUMIFS('BNY Cash Projection'!AV:AV,'BNY Cash Projection'!A:A,'IQ Equitizer'!A9,'BNY Cash Projection'!U:U,"BUY",'BNY Cash Projection'!AF:AF,">="&TODAY())+SUMIFS('BNY Cash Projection'!AV:AV,'BNY Cash Projection'!A:A,'IQ Equitizer'!A9,'BNY Cash Projection'!U:U,"SELL",'BNY Cash Projection'!AF:AF,">="&TODAY()) | G9: =SUMIFS('BNY Cash Projection'!AV:AV,'BNY Cash Projection'!A:A,'IQ Equitizer'!A9,'BNY Cash Projection'!AF:AF,'IQ Equitizer'!$D$30,'BNY Cash Projection'!U:U,"DIVIDEND",'BNY Cash Projection'!AH:AH,">0") | H9: =D9+F9+G9 | I9: =SUMIFS('BNY Custody Valuation'!AB:AB,'BNY Custody Valuation'!A:A,'IQ Equitizer'!A9,'BNY Custody Valuation'!U:U,"common")+SUMIFS('BNY Custody Valuation'!AB:AB,'BNY Custody Valuation'!A:A,'IQ Equitizer'!A9,'BNY Custody Valuation'!U:U,"mutual funds")+SUMIFS('BNY Custody Valuation'!AB:AB,'BNY Custody Valuation'!A:A,'IQ Equitizer'!A9,'BNY Custody Valuation'!U:U,"PREFERRED")+SUMIFS('BNY Custody Valuation'!AB:AB,'BNY Custody Valuation'!A:A,'IQ Equitizer'!A9,'BNY Custody Valuation'!U:U,"RIGHTS")+SUMIFS('BNY Custody Valuation'!AB:AB,'BNY Custody Valuation'!A:A,'IQ Equitizer'!A9,'BNY Custody Valuation'!U:U,"PARTNERSHIPS")+SUMIFS('BNY Custody Valuation'!AB:AB,'BNY Custody Valuation'!A:A,'IQ Equitizer'!A9,'BNY Custody Valuation'!U:U,"NOTES - SOVEREIGN DEBT")+SUMIFS('BNY Custody Valuation'!AB:AB,'BNY Custody Valuation'!A:A,'IQ Equitizer'!A9,'BNY Custody Valuation'!U:U,"BONDS - SOVEREIGN DEBT")+SUMIFS('BNY Custody Valuation'!AB:AB,'BNY Custody Valuation'!A:A,'IQ Equitizer'!A9,'BNY Custody Valuation'!U:U,"UNITS")+SUMIFS('BNY Custody Valuation'!AB:AB,'BNY Custody Valuation'!A:A,'IQ Equitizer'!A9,'BNY Custody Valuation'!U:U,"WARRANTS") | J9: =I9+H9 | K9: =H9/J9 | M9: =AQ9 | N9: =H9/M9 | O9: =IF(AND(N9>0,N9<0.06%),"T","F") | P9: =IF(O9="t","No Trade",N9-$O$2) | Q9: =IF(P9="No Trade",0,P9*M9) | R9: {=_xlfn.IFS(P9="no trade","-",Q9<0,"Raise",Q9>0,"Spend")} | S9: =AE9 | T9: {=_xll.BDP(S9&" equity",$T$1)} | U9: SCHM, SPMD, IJH | W9: =SUMIFS('BNY Cash Projection'!$AV:$AV,'BNY Cash Projection'!$A:$A,'IQ Equitizer'!A9,'BNY Cash Projection'!$AF:$AF,'IQ Equitizer'!$W$2,'BNY Cash Projection'!$U:$U,"DIVIDEND",'BNY Cash Projection'!$AH:$AH,">0") | X9: =SUMIFS('BNY Cash Projection'!$AV:$AV,'BNY Cash Projection'!$A:$A,'IQ Equitizer'!A9,'BNY Cash Projection'!$AF:$AF,'IQ Equitizer'!$X$2,'BNY Cash Projection'!$U:$U,"DIVIDEND",'BNY Cash Projection'!$AH:$AH,">0") | Y9: =SUMIFS('BNY Cash Projection'!$AV:$AV,'BNY Cash Projection'!$A:$A,'IQ Equitizer'!A9,'BNY Cash Projection'!$AF:$AF,'IQ Equitizer'!$Y$2,'BNY Cash Projection'!$U:$U,"DIVIDEND",'BNY Cash Projection'!$AH:$AH,">0") | Z9: =SUMIFS('BNY Cash Projection'!$AV:$AV,'BNY Cash Projection'!$A:$A,'IQ Equitizer'!A9,'BNY Cash Projection'!$AF:$AF,'IQ Equitizer'!$Z$2,'BNY Cash Projection'!$U:$U,"DIVIDEND",'BNY Cash Projection'!$AH:$AH,">0") | AA9: =SUMIFS('BNY Cash Projection'!$AV:$AV,'BNY Cash Projection'!$A:$A,'IQ Equitizer'!A9,'BNY Cash Projection'!$AF:$AF,'IQ Equitizer'!$AA$2,'BNY Cash Projection'!$U:$U,"DIVIDEND",'BNY Cash Projection'!$AH:$AH,">0") | AB9: =SUMIFS('BNY Cash Projection'!$AV:$AV,'BNY Cash Projection'!$A:$A,'IQ Equitizer'!A9,'BNY Cash Projection'!$AF:$AF,'IQ Equitizer'!$AB$2,'BNY Cash Projection'!$U:$U,"DIVIDEND",'BNY Cash Projection'!$AH:$AH,">0") | AC9: =SUM(W9:AB9) | AD9: =AC9/J9 | AE9: =B9 | AG9: =SUMIFS('BNY Cash Projection'!$AV:$AV,'BNY Cash Projection'!$A:$A,'IQ Equitizer'!A9,'BNY Cash Projection'!$AF:$AF,'IQ Equitizer'!$AG$2,'BNY Cash Projection'!$U:$U,"DIVIDEND",'BNY Cash Projection'!$AH:$AH,">0") | AH9: =AG9/M9 | AJ9: =N9+AD9 | AK9: =AE9 | AN9: =B9&"NV" | AO9: {=_xll.BDP(AN9&" index","PX_LAST")} | AP9: {=_xll.BDP(B9&" equity",$AP$2)} | AQ9: =AO9*AP9
A10: 263076 | B10: QAI | C10: NYLI Hedge Multi-Strategy Tracker ETF | D10: =SUMIFS('BNY Cash Projection'!AR:AR,'BNY Cash Projection'!A:A,'IQ Equitizer'!A10,'BNY Cash Projection'!E:E,"<>",'BNY Cash Projection'!N:N,'IQ Equitizer'!$D$30)/(COUNTIFS('BNY Cash Projection'!A:A,'IQ Equitizer'!A10,'BNY Cash Projection'!E:E,"<>",'BNY Cash Projection'!N:N,'IQ Equitizer'!$D$30)) | F10: =SUMIFS('BNY Cash Projection'!AV:AV,'BNY Cash Projection'!A:A,'IQ Equitizer'!A10,'BNY Cash Projection'!U:U,"BUY",'BNY Cash Projection'!AF:AF,">="&TODAY())+SUMIFS('BNY Cash Projection'!AV:AV,'BNY Cash Projection'!A:A,'IQ Equitizer'!A10,'BNY Cash Projection'!U:U,"SELL",'BNY Cash Projection'!AF:AF,">="&TODAY()) | G10: =SUMIFS('BNY Cash Projection'!AV:AV,'BNY Cash Projection'!A:A,'IQ Equitizer'!A10,'BNY Cash Projection'!AF:AF,'IQ Equitizer'!$D$30,'BNY Cash Projection'!U:U,"DIVIDEND",'BNY Cash Projection'!AH:AH,">0") | H10: =D10+F10+G10 | I10: =SUMIFS('BNY Custody Valuation'!AB:AB,'BNY Custody Valuation'!A:A,'IQ Equitizer'!A10,'BNY Custody Valuation'!U:U,"common")+SUMIFS('BNY Custody Valuation'!AB:AB,'BNY Custody Valuation'!A:A,'IQ Equitizer'!A10,'BNY Custody Valuation'!U:U,"mutual funds")+SUMIFS('BNY Custody Valuation'!AB:AB,'BNY Custody Valuation'!A:A,'IQ Equitizer'!A10,'BNY Custody Valuation'!U:U,"PREFERRED")+SUMIFS('BNY Custody Valuation'!AB:AB,'BNY Custody Valuation'!A:A,'IQ Equitizer'!A10,'BNY Custody Valuation'!U:U,"RIGHTS")+SUMIFS('BNY Custody Valuation'!AB:AB,'BNY Custody Valuation'!A:A,'IQ Equitizer'!A10,'BNY Custody Valuation'!U:U,"PARTNERSHIPS")+SUMIFS('BNY Custody Valuation'!AB:AB,'BNY Custody Valuation'!A:A,'IQ Equitizer'!A10,'BNY Custody Valuation'!U:U,"NOTES - SOVEREIGN DEBT")+SUMIFS('BNY Custody Valuation'!AB:AB,'BNY Custody Valuation'!A:A,'IQ Equitizer'!A10,'BNY Custody Valuation'!U:U,"BONDS - SOVEREIGN DEBT")+SUMIFS('BNY Custody Valuation'!AB:AB,'BNY Custody Valuation'!A:A,'IQ Equitizer'!A10,'BNY Custody Valuation'!U:U,"UNITS")+SUMIFS('BNY Custody Valuation'!AB:AB,'BNY Custody Valuation'!A:A,'IQ Equitizer'!A10,'BNY Custody Valuation'!U:U,"WARRANTS") | J10: =I10+H10 | K10: =H10/J10 | M10: =AQ10 | N10: =H10/M10 | O10: =IF(AND(N10>0,N10<0.06%),"T","F") | P10: =IF(O10="t","No Trade",N10-$O$2) | Q10: =IF(P10="No Trade",0,P10*M10) | R10: {=_xlfn.IFS(P10="no trade","-",Q10<0,"Raise",Q10>0,"Spend")} | S10: =AE10 | T10: {=_xll.BDP(S10&" equity",$T$1)} | W10: =SUMIFS('BNY Cash Projection'!$AV:$AV,'BNY Cash Projection'!$A:$A,'IQ Equitizer'!A10,'BNY Cash Projection'!$AF:$AF,'IQ Equitizer'!$W$2,'BNY Cash Projection'!$U:$U,"DIVIDEND",'BNY Cash Projection'!$AH:$AH,">0") | X10: =SUMIFS('BNY Cash Projection'!$AV:$AV,'BNY Cash Projection'!$A:$A,'IQ Equitizer'!A10,'BNY Cash Projection'!$AF:$AF,'IQ Equitizer'!$X$2,'BNY Cash Projection'!$U:$U,"DIVIDEND",'BNY Cash Projection'!$AH:$AH,">0") | Y10: =SUMIFS('BNY Cash Projection'!$AV:$AV,'BNY Cash Projection'!$A:$A,'IQ Equitizer'!A10,'BNY Cash Projection'!$AF:$AF,'IQ Equitizer'!$Y$2,'BNY Cash Projection'!$U:$U,"DIVIDEND",'BNY Cash Projection'!$AH:$AH,">0") | Z10: =SUMIFS('BNY Cash Projection'!$AV:$AV,'BNY Cash Projection'!$A:$A,'IQ Equitizer'!A10,'BNY Cash Projection'!$AF:$AF,'IQ Equitizer'!$Z$2,'BNY Cash Projection'!$U:$U,"DIVIDEND",'BNY Cash Projection'!$AH:$AH,">0") | AA10: =SUMIFS('BNY Cash Projection'!$AV:$AV,'BNY Cash Projection'!$A:$A,'IQ Equitizer'!A10,'BNY Cash Projection'!$AF:$AF,'IQ Equitizer'!$AA$2,'BNY Cash Projection'!$U:$U,"DIVIDEND",'BNY Cash Projection'!$AH:$AH,">0") | AB10: =SUMIFS('BNY Cash Projection'!$AV:$AV,'BNY Cash Projection'!$A:$A,'IQ Equitizer'!A10,'BNY Cash Projection'!$AF:$AF,'IQ Equitizer'!$AB$2,'BNY Cash Projection'!$U:$U,"DIVIDEND",'BNY Cash Projection'!$AH:$AH,">0") | AC10: =SUM(W10:AB10) | AD10: =AC10/J10 | AE10: =B10 | AG10: =SUMIFS('BNY Cash Projection'!$AV:$AV,'BNY Cash Projection'!$A:$A,'IQ Equitizer'!A10,'BNY Cash Projection'!$AF:$AF,'IQ Equitizer'!$AG$2,'BNY Cash Projection'!$U:$U,"DIVIDEND",'BNY Cash Projection'!$AH:$AH,">0") | AH10: =AG10/M10 | AJ10: =N10+AD10 | AK10: =AE10 | AN10: =B10&"NV" | AO10: {=_xll.BDP(AN10&" index","PX_LAST")} | AP10: {=_xll.BDP(B10&" equity",$AP$2)} | AQ10: =AO10*AP10
A11: 447594 | B11: HFXI | C11: NYLI FTSE International Equity Currency Neutral ETF | D11: =SUMIFS('BNY Cash Projection'!AR:AR,'BNY Cash Projection'!A:A,'IQ Equitizer'!A11,'BNY Cash Projection'!E:E,"<>",'BNY Cash Projection'!N:N,'IQ Equitizer'!$D$30)/(COUNTIFS('BNY Cash Projection'!A:A,'IQ Equitizer'!A11,'BNY Cash Projection'!E:E,"<>",'BNY Cash Projection'!N:N,'IQ Equitizer'!$D$30)) | F11: =SUMIFS('BNY Cash Projection'!AV:AV,'BNY Cash Projection'!A:A,'IQ Equitizer'!A11,'BNY Cash Projection'!U:U,"BUY",'BNY Cash Projection'!AF:AF,">="&TODAY())+SUMIFS('BNY Cash Projection'!AV:AV,'BNY Cash Projection'!A:A,'IQ Equitizer'!A11,'BNY Cash Projection'!U:U,"SELL",'BNY Cash Projection'!AF:AF,">="&TODAY()) | G11: =SUMIFS('BNY Cash Projection'!AV:AV,'BNY Cash Projection'!A:A,'IQ Equitizer'!A11,'BNY Cash Projection'!AF:AF,'IQ Equitizer'!$D$30,'BNY Cash Projection'!U:U,"DIVIDEND",'BNY Cash Projection'!AH:AH,">0") | H11: =D11+F11+G11 | I11: =SUMIFS('BNY Custody Valuation'!AB:AB,'BNY Custody Valuation'!A:A,'IQ Equitizer'!A11,'BNY Custody Valuation'!U:U,"common")+SUMIFS('BNY Custody Valuation'!AB:AB,'BNY Custody Valuation'!A:A,'IQ Equitizer'!A11,'BNY Custody Valuation'!U:U,"mutual funds")+SUMIFS('BNY Custody Valuation'!AB:AB,'BNY Custody Valuation'!A:A,'IQ Equitizer'!A11,'BNY Custody Valuation'!U:U,"PREFERRED")+SUMIFS('BNY Custody Valuation'!AB:AB,'BNY Custody Valuation'!A:A,'IQ Equitizer'!A11,'BNY Custody Valuation'!U:U,"RIGHTS")+SUMIFS('BNY Custody Valuation'!AB:AB,'BNY Custody Valuation'!A:A,'IQ Equitizer'!A11,'BNY Custody Valuation'!U:U,"PARTNERSHIPS")+SUMIFS('BNY Custody Valuation'!AB:AB,'BNY Custody Valuation'!A:A,'IQ Equitizer'!A11,'BNY Custody Valuation'!U:U,"NOTES - SOVEREIGN DEBT")+SUMIFS('BNY Custody Valuation'!AB:AB,'BNY Custody Valuation'!A:A,'IQ Equitizer'!A11,'BNY Custody Valuation'!U:U,"BONDS - SOVEREIGN DEBT")+SUMIFS('BNY Custody Valuation'!AB:AB,'BNY Custody Valuation'!A:A,'IQ Equitizer'!A11,'BNY Custody Valuation'!U:U,"UNITS")+SUMIFS('BNY Custody Valuation'!AB:AB,'BNY Custody Valuation'!A:A,'IQ Equitizer'!A11,'BNY Custody Valuation'!U:U,"WARRANTS") | J11: =I11+H11 | K11: =H11/J11 | M11: =AQ11 | N11: =H11/M11 | O11: =IF(AND(N11>0,N11<0.06%),"T","F") | P11: =IF(O11="t","No Trade",N11-$O$2) | Q11: =IF(P11="No Trade",0,P11*M11) | R11: {=_xlfn.IFS(P11="no trade","-",Q11<0,"Raise",Q11>0,"Spend")} | S11: =AE11 | T11: {=_xll.BDP(S11&" equity",$T$1)} | U11: 1.VEA | W11: =SUMIFS('BNY Cash Projection'!$AV:$AV,'BNY Cash Projection'!$A:$A,'IQ Equitizer'!A11,'BNY Cash Projection'!$AF:$AF,'IQ Equitizer'!$W$2,'BNY Cash Projection'!$U:$U,"DIVIDEND",'BNY Cash Projection'!$AH:$AH,">0") | X11: =SUMIFS('BNY Cash Projection'!$AV:$AV,'BNY Cash Projection'!$A:$A,'IQ Equitizer'!A11,'BNY Cash Projection'!$AF:$AF,'IQ Equitizer'!$X$2,'BNY Cash Projection'!$U:$U,"DIVIDEND",'BNY Cash Projection'!$AH:$AH,">0") | Y11: =SUMIFS('BNY Cash Projection'!$AV:$AV,'BNY Cash Projection'!$A:$A,'IQ Equitizer'!A11,'BNY Cash Projection'!$AF:$AF,'IQ Equitizer'!$Y$2,'BNY Cash Projection'!$U:$U,"DIVIDEND",'BNY Cash Projection'!$AH:$AH,">0") | Z11: =SUMIFS('BNY Cash Projection'!$AV:$AV,'BNY Cash Projection'!$A:$A,'IQ Equitizer'!A11,'BNY Cash Projection'!$AF:$AF,'IQ Equitizer'!$Z$2,'BNY Cash Projection'!$U:$U,"DIVIDEND",'BNY Cash Projection'!$AH:$AH,">0") | AA11: =SUMIFS('BNY Cash Projection'!$AV:$AV,'BNY Cash Projection'!$A:$A,'IQ Equitizer'!A11,'BNY Cash Projection'!$AF:$AF,'IQ Equitizer'!$AA$2,'BNY Cash Projection'!$U:$U,"DIVIDEND",'BNY Cash Projection'!$AH:$AH,">0") | AB11: =SUMIFS('BNY Cash Projection'!$AV:$AV,'BNY Cash Projection'!$A:$A,'IQ Equitizer'!A11,'BNY Cash Projection'!$AF:$AF,'IQ Equitizer'!$AB$2,'BNY Cash Projection'!$U:$U,"DIVIDEND",'BNY Cash Projection'!$AH:$AH,">0") | AC11: =SUM(W11:AB11) | AD11: =AC11/J11 | AE11: =B11 | AG11: =SUMIFS('BNY Cash Projection'!$AV:$AV,'BNY Cash Projection'!$A:$A,'IQ Equitizer'!A11,'BNY Cash Projection'!$AF:$AF,'IQ Equitizer'!$AG$2,'BNY Cash Projection'!$U:$U,"DIVIDEND",'BNY Cash Projection'!$AH:$AH,">0") | AH11: =AG11/M11 | AJ11: =N11+AD11 | AK11: =AE11 | AN11: =B11&"NV" | AO11: {=_xll.BDP(AN11&" index","PX_LAST")} | AP11: {=_xll.BDP(B11&" equity",$AP$2)} | AQ11: =AO11*AP11
A12: G 26785 | B12: VP Mutual Fund | C12: NYLI VP Hedge Multi-Strategy Portfolio | D12: =SUMIFS('VP Proj Cash Statement (8am)'!F:F,'VP Proj Cash Statement (8am)'!E:E,'IQ Equitizer'!B1,'VP Proj Cash Statement (8am)'!C:C,'IQ Equitizer'!A12)+SUMIFS('VP Priced Positions'!AO:AO,'VP Priced Positions'!A:A,'IQ Equitizer'!A12,'VP Priced Positions'!L:L,"JPMORGAN SHORT TERM INVESTMENT FUNDS")+SUMIFS('VP Priced Positions'!AO:AO,'VP Priced Positions'!A:A,'IQ Equitizer'!A12,'VP Priced Positions'!O:O,"MUSXX") | F12: =B53+E53 | G12: =SUMIFS('VP Proj Cash Statement (8am)'!N:N,'VP Proj Cash Statement (8am)'!E:E,'IQ Equitizer'!B1,'VP Proj Cash Statement (8am)'!C:C,'IQ Equitizer'!A12)+SUMIFS('VP Proj Cash Statement (8am)'!O:O,'VP Proj Cash Statement (8am)'!E:E,'IQ Equitizer'!B1,'VP Proj Cash Statement (8am)'!C:C,'IQ Equitizer'!A12)+SUMIFS('VP Proj Cash Statement (8am)'!R:R,'VP Proj Cash Statement (8am)'!E:E,'IQ Equitizer'!B1,'VP Proj Cash Statement (8am)'!C:C,'IQ Equitizer'!A12)+SUMIFS('VP Proj Cash Statement (8am)'!AA:AA,'VP Proj Cash Statement (8am)'!E:E,'IQ Equitizer'!B1,'VP Proj Cash Statement (8am)'!C:C,'IQ Equitizer'!A12)+SUMIFS('VP Proj Cash Statement (8am)'!AB:AB,'VP Proj Cash Statement (8am)'!E:E,'IQ Equitizer'!B1,'VP Proj Cash Statement (8am)'!C:C,'IQ Equitizer'!A12)+SUMIFS('VP Proj Cash Statement (8am)'!AE:AE,'VP Proj Cash Statement (8am)'!E:E,'IQ Equitizer'!B1,'VP Proj Cash Statement (8am)'!C:C,'IQ Equitizer'!A12) | H12: =SUM(D12:G12) | I12: =VLOOKUP('IQ Equitizer'!B12,'(FA) IQ'!B11:L11,11,0) | J12: =I12+H12 | K12: =H12/J12 | M12: ='(FA) IQ'!M11 | N12: =H12/M12 | O12: =IF(AND(N12>0,N12<0.06%),"T","F") | P12: =IF(O12="t","No Trade",N12-$O$2) | Q12: =IF(P12="No Trade",0,P12*M12) | R12: {=_xlfn.IFS(P12="no trade","-",Q12<0,"Raise",Q12>0,"Spend")} | S12: VP | W12: =SUMIFS('VP Proj Cash Detail (10am)'!$AV:$AV,'VP Proj Cash Detail (10am)'!$I:$I,'IQ Equitizer'!$A$12,'VP Proj Cash Detail (10am)'!$E:$E,'IQ Equitizer'!W2,'VP Proj Cash Detail (10am)'!$C:$C,"DIVIDEND PAYMENTS") | X12: =SUMIFS('VP Proj Cash Detail (10am)'!$AV:$AV,'VP Proj Cash Detail (10am)'!$I:$I,'IQ Equitizer'!$A$12,'VP Proj Cash Detail (10am)'!$E:$E,'IQ Equitizer'!X2,'VP Proj Cash Detail (10am)'!$C:$C,"DIVIDEND PAYMENTS") | Y12: =SUMIFS('VP Proj Cash Detail (10am)'!$AV:$AV,'VP Proj Cash Detail (10am)'!$I:$I,'IQ Equitizer'!$A$12,'VP Proj Cash Detail (10am)'!$E:$E,'IQ Equitizer'!Y2,'VP Proj Cash Detail (10am)'!$C:$C,"DIVIDEND PAYMENTS") | Z12: =SUMIFS('VP Proj Cash Detail (10am)'!$AV:$AV,'VP Proj Cash Detail (10am)'!$I:$I,'IQ Equitizer'!$A$12,'VP Proj Cash Detail (10am)'!$E:$E,'IQ Equitizer'!Z2,'VP Proj Cash Detail (10am)'!$C:$C,"DIVIDEND PAYMENTS") | AA12: =SUMIFS('VP Proj Cash Detail (10am)'!$AV:$AV,'VP Proj Cash Detail (10am)'!$I:$I,'IQ Equitizer'!$A$12,'VP Proj Cash Detail (10am)'!$E:$E,'IQ Equitizer'!AA2,'VP Proj Cash Detail (10am)'!$C:$C,"DIVIDEND PAYMENTS") | AB12: =SUMIFS('VP Proj Cash Detail (10am)'!$AV:$AV,'VP Proj Cash Detail (10am)'!$I:$I,'IQ Equitizer'!$A$12,'VP Proj Cash Detail (10am)'!$E:$E,'IQ Equitizer'!AB2,'VP Proj Cash Detail (10am)'!$C:$C,"DIVIDEND PAYMENTS") | AC12: =SUM(W12:AB12) | AD12: =AC12/J12 | AG12: =SUMIFS('VP Proj Cash Detail (10am)'!$AV:$AV,'VP Proj Cash Detail (10am)'!$I:$I,'IQ Equitizer'!$A$12,'VP Proj Cash Detail (10am)'!$E:$E,'IQ Equitizer'!AG2,'VP Proj Cash Detail (10am)'!$C:$C,"DIVIDEND PAYMENTS") | AH12: =AG12/M12 | AJ12: =N12+AD12
I13: Missing Stock Loan | J13: Missing Accrued Income
A14: VP QAI NET FLOWS | I14: Use FA | J14: Use FA or p5
A15: SUBSCRIPTION TO FUND | B15: =SUMIFS('VP Proj Cash Detail (10am)'!AK:AK,'VP Proj Cash Detail (10am)'!I:I,'IQ Equitizer'!A12,'VP Proj Cash Detail (10am)'!W:W,'IQ Equitizer'!A15)
A16: REDEMPTION TO FUND | B16: =SUMIFS('VP Proj Cash Detail (10am)'!AK:AK,'VP Proj Cash Detail (10am)'!I:I,'IQ Equitizer'!A12,'VP Proj Cash Detail (10am)'!W:W,'IQ Equitizer'!A16) | G16: Overdraft $ (not including HFXI) | H16: =SUMIF(H3:H10,"<0",H3:H10)+SUMIF(H12:H12,"<0",H12:H12)
A17: CASH DEBIT OTHER DISBURSEMENTS | B17: =SUMIFS('VP Proj Cash Detail (10am)'!AV:AV,'VP Proj Cash Detail (10am)'!I:I,'IQ Equitizer'!A12,'VP Proj Cash Detail (10am)'!W:W,'IQ Equitizer'!A17) | F17: OD Fee Annaul | G17: 0.05 | H17: =H16*G17
A18: TOTAL NET FLOW | B18: =SUM(B15:B17) | F18: OD Fee Daily | H18: =H17/365
A19: EOD CASH | B19: =H12+B18
A20: % Cash | B20: =B19/J12
A22: VP TRADE | AN22: =SUMIFS('BNY Cash Projection'!AV:AV,'BNY Cash Projection'!A:A,'IQ Equitizer'!A3,'BNY Cash Projection'!U:U,"BUY",'BNY Cash Projection'!AF:AF,">="&TODAY())+SUMIFS('BNY Cash Projection'!AV:AV,'BNY Cash Projection'!A:A,'IQ Equitizer'!A3,'BNY Cash Projection'!U:U,"SELL",'BNY Cash Projection'!AF:AF,">="&TODAY())
A23: Target | B23: 0.0075 | C23: =B23*J12 | M23: 1 day off cu/ru
A24: Trade | B24: =IF(C24<0,"Spend Cash (Buy)","Raise Cash (Sell)") | C24: =C23-B19
B26: Eze Plug Trade | C26: =-C24
A29: T-0 | C29: EZE Trades
A30: =D30-1 | B30: S/D | D30: =B1 | E30: =D30+1 | F30: =E30+1 | G30: =F30+1 | H30: =G30+1 | I30: =H30+1 | J30: =I30+1 | K30: Total Pending | M30: Custody Pending Trades | O30: Breaks
A31: =SUMIFS('Historical Trades Calc'!$R:$R,'Historical Trades Calc'!$B:$B,'IQ Equitizer'!B31,'Historical Trades Calc'!$E:$E,'IQ Equitizer'!$A$30,'Historical Trades Calc'!$D:$D,"GB")+SUMIFS('Historical Trades Calc'!$R:$R,'Historical Trades Calc'!$B:$B,'IQ Equitizer'!B31,'Historical Trades Calc'!$E:$E,'IQ Equitizer'!$A$30,'Historical Trades Calc'!$D:$D,"MT")+SUMIFS('Historical Trades Calc'!$R:$R,'Historical Trades Calc'!$B:$B,'IQ Equitizer'!B31,'Historical Trades Calc'!$E:$E,'IQ Equitizer'!$A$30,'Historical Trades Calc'!$D:$D,"FO") | B31: IQSI | D31: =SUMIFS('Historical Trades Calc'!$R:$R,'Historical Trades Calc'!$B:$B,'IQ Equitizer'!B31,'Historical Trades Calc'!$E:$E,'IQ Equitizer'!$D$30,'Historical Trades Calc'!$D:$D,"GB")+SUMIFS('Historical Trades Calc'!$R:$R,'Historical Trades Calc'!$B:$B,'IQ Equitizer'!B31,'Historical Trades Calc'!$E:$E,'IQ Equitizer'!$D$30,'Historical Trades Calc'!$D:$D,"MT")+SUMIFS('Historical Trades Calc'!$R:$R,'Historical Trades Calc'!$B:$B,'IQ Equitizer'!B31,'Historical Trades Calc'!$E:$E,'IQ Equitizer'!$D$30,'Historical Trades Calc'!$D:$D,"FO") | E31: =SUMIFS('Historical Trades Calc'!$R:$R,'Historical Trades Calc'!$B:$B,'IQ Equitizer'!B31,'Historical Trades Calc'!$E:$E,'IQ Equitizer'!$E$30,'Historical Trades Calc'!$D:$D,"GB")+SUMIFS('Historical Trades Calc'!$R:$R,'Historical Trades Calc'!$B:$B,'IQ Equitizer'!B31,'Historical Trades Calc'!$E:$E,'IQ Equitizer'!$E$30,'Historical Trades Calc'!$D:$D,"MT")+SUMIFS('Historical Trades Calc'!$R:$R,'Historical Trades Calc'!$B:$B,'IQ Equitizer'!B31,'Historical Trades Calc'!$E:$E,'IQ Equitizer'!$E$30,'Historical Trades Calc'!$D:$D,"FO") | F31: =SUMIFS('Historical Trades Calc'!$R:$R,'Historical Trades Calc'!$B:$B,'IQ Equitizer'!B31,'Historical Trades Calc'!$E:$E,'IQ Equitizer'!$F$30,'Historical Trades Calc'!$D:$D,"GB")+SUMIFS('Historical Trades Calc'!$R:$R,'Historical Trades Calc'!$B:$B,'IQ Equitizer'!B31,'Historical Trades Calc'!$E:$E,'IQ Equitizer'!$F$30,'Historical Trades Calc'!$D:$D,"MT")+SUMIFS('Historical Trades Calc'!$R:$R,'Historical Trades Calc'!$B:$B,'IQ Equitizer'!B31,'Historical Trades Calc'!$E:$E,'IQ Equitizer'!$F$30,'Historical Trades Calc'!$D:$D,"FO") | G31: =SUMIFS('Historical Trades Calc'!$R:$R,'Historical Trades Calc'!$B:$B,'IQ Equitizer'!B31,'Historical Trades Calc'!$E:$E,'IQ Equitizer'!$G$30,'Historical Trades Calc'!$D:$D,"GB")+SUMIFS('Historical Trades Calc'!$R:$R,'Historical Trades Calc'!$B:$B,'IQ Equitizer'!B31,'Historical Trades Calc'!$E:$E,'IQ Equitizer'!$G$30,'Historical Trades Calc'!$D:$D,"MT")+SUMIFS('Historical Trades Calc'!$R:$R,'Historical Trades Calc'!$B:$B,'IQ Equitizer'!B31,'Historical Trades Calc'!$E:$E,'IQ Equitizer'!$G$30,'Historical Trades Calc'!$D:$D,"FO") | H31: =SUMIFS('Historical Trades Calc'!$R:$R,'Historical Trades Calc'!$B:$B,'IQ Equitizer'!B31,'Historical Trades Calc'!$E:$E,'IQ Equitizer'!$H$30,'Historical Trades Calc'!$D:$D,"GB")+SUMIFS('Historical Trades Calc'!$R:$R,'Historical Trades Calc'!$B:$B,'IQ Equitizer'!B31,'Historical Trades Calc'!$E:$E,'IQ Equitizer'!$H$30,'Historical Trades Calc'!$D:$D,"MT")+SUMIFS('Historical Trades Calc'!$R:$R,'Historical Trades Calc'!$B:$B,'IQ Equitizer'!B31,'Historical Trades Calc'!$E:$E,'IQ Equitizer'!$H$30,'Historical Trades Calc'!$D:$D,"FO") | I31: =SUMIFS('Historical Trades Calc'!$R:$R,'Historical Trades Calc'!$B:$B,'IQ Equitizer'!B31,'Historical Trades Calc'!$E:$E,'IQ Equitizer'!$I$30,'Historical Trades Calc'!$D:$D,"GB")+SUMIFS('Historical Trades Calc'!$R:$R,'Historical Trades Calc'!$B:$B,'IQ Equitizer'!B31,'Historical Trades Calc'!$E:$E,'IQ Equitizer'!$I$30,'Historical Trades Calc'!$D:$D,"MT")+SUMIFS('Historical Trades Calc'!$R:$R,'Historical Trades Calc'!$B:$B,'IQ Equitizer'!B31,'Historical Trades Calc'!$E:$E,'IQ Equitizer'!$I$30,'Historical Trades Calc'!$D:$D,"FO") | J31: =SUMIFS('Historical Trades Calc'!$R:$R,'Historical Trades Calc'!$B:$B,'IQ Equitizer'!B31,'Historical Trades Calc'!$E:$E,'IQ Equitizer'!$J$30,'Historical Trades Calc'!$D:$D,"GB")+SUMIFS('Historical Trades Calc'!$R:$R,'Historical Trades Calc'!$B:$B,'IQ Equitizer'!B31,'Historical Trades Calc'!$E:$E,'IQ Equitizer'!$J$30,'Historical Trades Calc'!$D:$D,"MT")+SUMIFS('Historical Trades Calc'!$R:$R,'Historical Trades Calc'!$B:$B,'IQ Equitizer'!B31,'Historical Trades Calc'!$E:$E,'IQ Equitizer'!$J$30,'Historical Trades Calc'!$D:$D,"FO") | K31: =SUM(D31:J31) | M31: =VLOOKUP(B31,$B$3:$F$11,5,0) | O31: =K31-M31
A32: =SUMIFS('Historical Trades Calc'!$R:$R,'Historical Trades Calc'!$B:$B,'IQ Equitizer'!B32,'Historical Trades Calc'!$E:$E,'IQ Equitizer'!$A$30,'Historical Trades Calc'!$D:$D,"GB")+SUMIFS('Historical Trades Calc'!$R:$R,'Historical Trades Calc'!$B:$B,'IQ Equitizer'!B32,'Historical Trades Calc'!$E:$E,'IQ Equitizer'!$A$30,'Historical Trades Calc'!$D:$D,"MT")+SUMIFS('Historical Trades Calc'!$R:$R,'Historical Trades Calc'!$B:$B,'IQ Equitizer'!B32,'Historical Trades Calc'!$E:$E,'IQ Equitizer'!$A$30,'Historical Trades Calc'!$D:$D,"FO") | B32: IQSU | D32: =SUMIFS('Historical Trades Calc'!$R:$R,'Historical Trades Calc'!$B:$B,'IQ Equitizer'!B32,'Historical Trades Calc'!$E:$E,'IQ Equitizer'!$D$30,'Historical Trades Calc'!$D:$D,"GB")+SUMIFS('Historical Trades Calc'!$R:$R,'Historical Trades Calc'!$B:$B,'IQ Equitizer'!B32,'Historical Trades Calc'!$E:$E,'IQ Equitizer'!$D$30,'Historical Trades Calc'!$D:$D,"MT")+SUMIFS('Historical Trades Calc'!$R:$R,'Historical Trades Calc'!$B:$B,'IQ Equitizer'!B32,'Historical Trades Calc'!$E:$E,'IQ Equitizer'!$D$30,'Historical Trades Calc'!$D:$D,"FO") | E32: =SUMIFS('Historical Trades Calc'!$R:$R,'Historical Trades Calc'!$B:$B,'IQ Equitizer'!B32,'Historical Trades Calc'!$E:$E,'IQ Equitizer'!$E$30,'Historical Trades Calc'!$D:$D,"GB")+SUMIFS('Historical Trades Calc'!$R:$R,'Historical Trades Calc'!$B:$B,'IQ Equitizer'!B32,'Historical Trades Calc'!$E:$E,'IQ Equitizer'!$E$30,'Historical Trades Calc'!$D:$D,"MT")+SUMIFS('Historical Trades Calc'!$R:$R,'Historical Trades Calc'!$B:$B,'IQ Equitizer'!B32,'Historical Trades Calc'!$E:$E,'IQ Equitizer'!$E$30,'Historical Trades Calc'!$D:$D,"FO") | F32: =SUMIFS('Historical Trades Calc'!$R:$R,'Historical Trades Calc'!$B:$B,'IQ Equitizer'!B32,'Historical Trades Calc'!$E:$E,'IQ Equitizer'!$F$30,'Historical Trades Calc'!$D:$D,"GB")+SUMIFS('Historical Trades Calc'!$R:$R,'Historical Trades Calc'!$B:$B,'IQ Equitizer'!B32,'Historical Trades Calc'!$E:$E,'IQ Equitizer'!$F$30,'Historical Trades Calc'!$D:$D,"MT")+SUMIFS('Historical Trades Calc'!$R:$R,'Historical Trades Calc'!$B:$B,'IQ Equitizer'!B32,'Historical Trades Calc'!$E:$E,'IQ Equitizer'!$F$30,'Historical Trades Calc'!$D:$D,"FO") | G32: =SUMIFS('Historical Trades Calc'!$R:$R,'Historical Trades Calc'!$B:$B,'IQ Equitizer'!B32,'Historical Trades Calc'!$E:$E,'IQ Equitizer'!$G$30,'Historical Trades Calc'!$D:$D,"GB")+SUMIFS('Historical Trades Calc'!$R:$R,'Historical Trades Calc'!$B:$B,'IQ Equitizer'!B32,'Historical Trades Calc'!$E:$E,'IQ Equitizer'!$G$30,'Historical Trades Calc'!$D:$D,"MT")+SUMIFS('Historical Trades Calc'!$R:$R,'Historical Trades Calc'!$B:$B,'IQ Equitizer'!B32,'Historical Trades Calc'!$E:$E,'IQ Equitizer'!$G$30,'Historical Trades Calc'!$D:$D,"FO") | H32: =SUMIFS('Historical Trades Calc'!$R:$R,'Historical Trades Calc'!$B:$B,'IQ Equitizer'!B32,'Historical Trades Calc'!$E:$E,'IQ Equitizer'!$H$30,'Historical Trades Calc'!$D:$D,"GB")+SUMIFS('Historical Trades Calc'!$R:$R,'Historical Trades Calc'!$B:$B,'IQ Equitizer'!B32,'Historical Trades Calc'!$E:$E,'IQ Equitizer'!$H$30,'Historical Trades Calc'!$D:$D,"MT")+SUMIFS('Historical Trades Calc'!$R:$R,'Historical Trades Calc'!$B:$B,'IQ Equitizer'!B32,'Historical Trades Calc'!$E:$E,'IQ Equitizer'!$H$30,'Historical Trades Calc'!$D:$D,"FO") | I32: =SUMIFS('Historical Trades Calc'!$R:$R,'Historical Trades Calc'!$B:$B,'IQ Equitizer'!B32,'Historical Trades Calc'!$E:$E,'IQ Equitizer'!$I$30,'Historical Trades Calc'!$D:$D,"GB")+SUMIFS('Historical Trades Calc'!$R:$R,'Historical Trades Calc'!$B:$B,'IQ Equitizer'!B32,'Historical Trades Calc'!$E:$E,'IQ Equitizer'!$I$30,'Historical Trades Calc'!$D:$D,"MT")+SUMIFS('Historical Trades Calc'!$R:$R,'Historical Trades Calc'!$B:$B,'IQ Equitizer'!B32,'Historical Trades Calc'!$E:$E,'IQ Equitizer'!$I$30,'Historical Trades Calc'!$D:$D,"FO") | J32: =SUMIFS('Historical Trades Calc'!$R:$R,'Historical Trades Calc'!$B:$B,'IQ Equitizer'!B32,'Historical Trades Calc'!$E:$E,'IQ Equitizer'!$J$30,'Historical Trades Calc'!$D:$D,"GB")+SUMIFS('Historical Trades Calc'!$R:$R,'Historical Trades Calc'!$B:$B,'IQ Equitizer'!B32,'Historical Trades Calc'!$E:$E,'IQ Equitizer'!$J$30,'Historical Trades Calc'!$D:$D,"MT")+SUMIFS('Historical Trades Calc'!$R:$R,'Historical Trades Calc'!$B:$B,'IQ Equitizer'!B32,'Historical Trades Calc'!$E:$E,'IQ Equitizer'!$J$30,'Historical Trades Calc'!$D:$D,"FO") | K32: =SUM(D32:J32) | M32: =VLOOKUP(B32,$B$3:$F$11,5,0) | O32: =K32-M32
A33: =SUMIFS('Historical Trades Calc'!$R:$R,'Historical Trades Calc'!$B:$B,'IQ Equitizer'!B33,'Historical Trades Calc'!$E:$E,'IQ Equitizer'!$A$30,'Historical Trades Calc'!$D:$D,"GB")+SUMIFS('Historical Trades Calc'!$R:$R,'Historical Trades Calc'!$B:$B,'IQ Equitizer'!B33,'Historical Trades Calc'!$E:$E,'IQ Equitizer'!$A$30,'Historical Trades Calc'!$D:$D,"MT")+SUMIFS('Historical Trades Calc'!$R:$R,'Historical Trades Calc'!$B:$B,'IQ Equitizer'!B33,'Historical Trades Calc'!$E:$E,'IQ Equitizer'!$A$30,'Historical Trades Calc'!$D:$D,"FO") | B33: HART | D33: =SUMIFS('Historical Trades Calc'!$R:$R,'Historical Trades Calc'!$B:$B,'IQ Equitizer'!B33,'Historical Trades Calc'!$E:$E,'IQ Equitizer'!$D$30,'Historical Trades Calc'!$D:$D,"GB")+SUMIFS('Historical Trades Calc'!$R:$R,'Historical Trades Calc'!$B:$B,'IQ Equitizer'!B33,'Historical Trades Calc'!$E:$E,'IQ Equitizer'!$D$30,'Historical Trades Calc'!$D:$D,"MT")+SUMIFS('Historical Trades Calc'!$R:$R,'Historical Trades Calc'!$B:$B,'IQ Equitizer'!B33,'Historical Trades Calc'!$E:$E,'IQ Equitizer'!$D$30,'Historical Trades Calc'!$D:$D,"FO") | E33: =SUMIFS('Historical Trades Calc'!$R:$R,'Historical Trades Calc'!$B:$B,'IQ Equitizer'!B33,'Historical Trades Calc'!$E:$E,'IQ Equitizer'!$E$30,'Historical Trades Calc'!$D:$D,"GB")+SUMIFS('Historical Trades Calc'!$R:$R,'Historical Trades Calc'!$B:$B,'IQ Equitizer'!B33,'Historical Trades Calc'!$E:$E,'IQ Equitizer'!$E$30,'Historical Trades Calc'!$D:$D,"MT")+SUMIFS('Historical Trades Calc'!$R:$R,'Historical Trades Calc'!$B:$B,'IQ Equitizer'!B33,'Historical Trades Calc'!$E:$E,'IQ Equitizer'!$E$30,'Historical Trades Calc'!$D:$D,"FO") | F33: =SUMIFS('Historical Trades Calc'!$R:$R,'Historical Trades Calc'!$B:$B,'IQ Equitizer'!B33,'Historical Trades Calc'!$E:$E,'IQ Equitizer'!$F$30,'Historical Trades Calc'!$D:$D,"GB")+SUMIFS('Historical Trades Calc'!$R:$R,'Historical Trades Calc'!$B:$B,'IQ Equitizer'!B33,'Historical Trades Calc'!$E:$E,'IQ Equitizer'!$F$30,'Historical Trades Calc'!$D:$D,"MT")+SUMIFS('Historical Trades Calc'!$R:$R,'Historical Trades Calc'!$B:$B,'IQ Equitizer'!B33,'Historical Trades Calc'!$E:$E,'IQ Equitizer'!$F$30,'Historical Trades Calc'!$D:$D,"FO") | G33: =SUMIFS('Historical Trades Calc'!$R:$R,'Historical Trades Calc'!$B:$B,'IQ Equitizer'!B33,'Historical Trades Calc'!$E:$E,'IQ Equitizer'!$G$30,'Historical Trades Calc'!$D:$D,"GB")+SUMIFS('Historical Trades Calc'!$R:$R,'Historical Trades Calc'!$B:$B,'IQ Equitizer'!B33,'Historical Trades Calc'!$E:$E,'IQ Equitizer'!$G$30,'Historical Trades Calc'!$D:$D,"MT")+SUMIFS('Historical Trades Calc'!$R:$R,'Historical Trades Calc'!$B:$B,'IQ Equitizer'!B33,'Historical Trades Calc'!$E:$E,'IQ Equitizer'!$G$30,'Historical Trades Calc'!$D:$D,"FO") | H33: =SUMIFS('Historical Trades Calc'!$R:$R,'Historical Trades Calc'!$B:$B,'IQ Equitizer'!B33,'Historical Trades Calc'!$E:$E,'IQ Equitizer'!$H$30,'Historical Trades Calc'!$D:$D,"GB")+SUMIFS('Historical Trades Calc'!$R:$R,'Historical Trades Calc'!$B:$B,'IQ Equitizer'!B33,'Historical Trades Calc'!$E:$E,'IQ Equitizer'!$H$30,'Historical Trades Calc'!$D:$D,"MT")+SUMIFS('Historical Trades Calc'!$R:$R,'Historical Trades Calc'!$B:$B,'IQ Equitizer'!B33,'Historical Trades Calc'!$E:$E,'IQ Equitizer'!$H$30,'Historical Trades Calc'!$D:$D,"FO") | I33: =SUMIFS('Historical Trades Calc'!$R:$R,'Historical Trades Calc'!$B:$B,'IQ Equitizer'!B33,'Historical Trades Calc'!$E:$E,'IQ Equitizer'!$I$30,'Historical Trades Calc'!$D:$D,"GB")+SUMIFS('Historical Trades Calc'!$R:$R,'Historical Trades Calc'!$B:$B,'IQ Equitizer'!B33,'Historical Trades Calc'!$E:$E,'IQ Equitizer'!$I$30,'Historical Trades Calc'!$D:$D,"MT")+SUMIFS('Historical Trades Calc'!$R:$R,'Historical Trades Calc'!$B:$B,'IQ Equitizer'!B33,'Historical Trades Calc'!$E:$E,'IQ Equitizer'!$I$30,'Historical Trades Calc'!$D:$D,"FO") | J33: =SUMIFS('Historical Trades Calc'!$R:$R,'Historical Trades Calc'!$B:$B,'IQ Equitizer'!B33,'Historical Trades Calc'!$E:$E,'IQ Equitizer'!$J$30,'Historical Trades Calc'!$D:$D,"GB")+SUMIFS('Historical Trades Calc'!$R:$R,'Historical Trades Calc'!$B:$B,'IQ Equitizer'!B33,'Historical Trades Calc'!$E:$E,'IQ Equitizer'!$J$30,'Historical Trades Calc'!$D:$D,"MT")+SUMIFS('Historical Trades Calc'!$R:$R,'Historical Trades Calc'!$B:$B,'IQ Equitizer'!B33,'Historical Trades Calc'!$E:$E,'IQ Equitizer'!$J$30,'Historical Trades Calc'!$D:$D,"FO") | K33: =SUM(D33:J33) | M33: =VLOOKUP(B33,$B$3:$F$11,5,0) | O33: =K33-M33
A34: =SUMIFS('Historical Trades Calc'!$R:$R,'Historical Trades Calc'!$B:$B,'IQ Equitizer'!B34,'Historical Trades Calc'!$E:$E,'IQ Equitizer'!$A$30,'Historical Trades Calc'!$D:$D,"GB")+SUMIFS('Historical Trades Calc'!$R:$R,'Historical Trades Calc'!$B:$B,'IQ Equitizer'!B34,'Historical Trades Calc'!$E:$E,'IQ Equitizer'!$A$30,'Historical Trades Calc'!$D:$D,"MT")+SUMIFS('Historical Trades Calc'!$R:$R,'Historical Trades Calc'!$B:$B,'IQ Equitizer'!B34,'Historical Trades Calc'!$E:$E,'IQ Equitizer'!$A$30,'Historical Trades Calc'!$D:$D,"FO") | B34: MNA | D34: =SUMIFS('Historical Trades Calc'!$R:$R,'Historical Trades Calc'!$B:$B,'IQ Equitizer'!B34,'Historical Trades Calc'!$E:$E,'IQ Equitizer'!$D$30,'Historical Trades Calc'!$D:$D,"GB")+SUMIFS('Historical Trades Calc'!$R:$R,'Historical Trades Calc'!$B:$B,'IQ Equitizer'!B34,'Historical Trades Calc'!$E:$E,'IQ Equitizer'!$D$30,'Historical Trades Calc'!$D:$D,"MT")+SUMIFS('Historical Trades Calc'!$R:$R,'Historical Trades Calc'!$B:$B,'IQ Equitizer'!B34,'Historical Trades Calc'!$E:$E,'IQ Equitizer'!$D$30,'Historical Trades Calc'!$D:$D,"FO") | E34: =SUMIFS('Historical Trades Calc'!$R:$R,'Historical Trades Calc'!$B:$B,'IQ Equitizer'!B34,'Historical Trades Calc'!$E:$E,'IQ Equitizer'!$E$30,'Historical Trades Calc'!$D:$D,"GB")+SUMIFS('Historical Trades Calc'!$R:$R,'Historical Trades Calc'!$B:$B,'IQ Equitizer'!B34,'Historical Trades Calc'!$E:$E,'IQ Equitizer'!$E$30,'Historical Trades Calc'!$D:$D,"MT")+SUMIFS('Historical Trades Calc'!$R:$R,'Historical Trades Calc'!$B:$B,'IQ Equitizer'!B34,'Historical Trades Calc'!$E:$E,'IQ Equitizer'!$E$30,'Historical Trades Calc'!$D:$D,"FO") | F34: =SUMIFS('Historical Trades Calc'!$R:$R,'Historical Trades Calc'!$B:$B,'IQ Equitizer'!B34,'Historical Trades Calc'!$E:$E,'IQ Equitizer'!$F$30,'Historical Trades Calc'!$D:$D,"GB")+SUMIFS('Historical Trades Calc'!$R:$R,'Historical Trades Calc'!$B:$B,'IQ Equitizer'!B34,'Historical Trades Calc'!$E:$E,'IQ Equitizer'!$F$30,'Historical Trades Calc'!$D:$D,"MT")+SUMIFS('Historical Trades Calc'!$R:$R,'Historical Trades Calc'!$B:$B,'IQ Equitizer'!B34,'Historical Trades Calc'!$E:$E,'IQ Equitizer'!$F$30,'Historical Trades Calc'!$D:$D,"FO") | G34: =SUMIFS('Historical Trades Calc'!$R:$R,'Historical Trades Calc'!$B:$B,'IQ Equitizer'!B34,'Historical Trades Calc'!$E:$E,'IQ Equitizer'!$G$30,'Historical Trades Calc'!$D:$D,"GB")+SUMIFS('Historical Trades Calc'!$R:$R,'Historical Trades Calc'!$B:$B,'IQ Equitizer'!B34,'Historical Trades Calc'!$E:$E,'IQ Equitizer'!$G$30,'Historical Trades Calc'!$D:$D,"MT")+SUMIFS('Historical Trades Calc'!$R:$R,'Historical Trades Calc'!$B:$B,'IQ Equitizer'!B34,'Historical Trades Calc'!$E:$E,'IQ Equitizer'!$G$30,'Historical Trades Calc'!$D:$D,"FO") | H34: =SUMIFS('Historical Trades Calc'!$R:$R,'Historical Trades Calc'!$B:$B,'IQ Equitizer'!B34,'Historical Trades Calc'!$E:$E,'IQ Equitizer'!$H$30,'Historical Trades Calc'!$D:$D,"GB")+SUMIFS('Historical Trades Calc'!$R:$R,'Historical Trades Calc'!$B:$B,'IQ Equitizer'!B34,'Historical Trades Calc'!$E:$E,'IQ Equitizer'!$H$30,'Historical Trades Calc'!$D:$D,"MT")+SUMIFS('Historical Trades Calc'!$R:$R,'Historical Trades Calc'!$B:$B,'IQ Equitizer'!B34,'Historical Trades Calc'!$E:$E,'IQ Equitizer'!$H$30,'Historical Trades Calc'!$D:$D,"FO") | I34: =SUMIFS('Historical Trades Calc'!$R:$R,'Historical Trades Calc'!$B:$B,'IQ Equitizer'!B34,'Historical Trades Calc'!$E:$E,'IQ Equitizer'!$I$30,'Historical Trades Calc'!$D:$D,"GB")+SUMIFS('Historical Trades Calc'!$R:$R,'Historical Trades Calc'!$B:$B,'IQ Equitizer'!B34,'Historical Trades Calc'!$E:$E,'IQ Equitizer'!$I$30,'Historical Trades Calc'!$D:$D,"MT")+SUMIFS('Historical Trades Calc'!$R:$R,'Historical Trades Calc'!$B:$B,'IQ Equitizer'!B34,'Historical Trades Calc'!$E:$E,'IQ Equitizer'!$I$30,'Historical Trades Calc'!$D:$D,"FO") | J34: =SUMIFS('Historical Trades Calc'!$R:$R,'Historical Trades Calc'!$B:$B,'IQ Equitizer'!B34,'Historical Trades Calc'!$E:$E,'IQ Equitizer'!$J$30,'Historical Trades Calc'!$D:$D,"GB")+SUMIFS('Historical Trades Calc'!$R:$R,'Historical Trades Calc'!$B:$B,'IQ Equitizer'!B34,'Historical Trades Calc'!$E:$E,'IQ Equitizer'!$J$30,'Historical Trades Calc'!$D:$D,"MT")+SUMIFS('Historical Trades Calc'!$R:$R,'Historical Trades Calc'!$B:$B,'IQ Equitizer'!B34,'Historical Trades Calc'!$E:$E,'IQ Equitizer'!$J$30,'Historical Trades Calc'!$D:$D,"FO") | K34: =SUM(D34:J34) | M34: =VLOOKUP(B34,$B$3:$F$11,5,0) | O34: =K34-M34
A35: =SUMIFS('Historical Trades Calc'!$R:$R,'Historical Trades Calc'!$B:$B,'IQ Equitizer'!B35,'Historical Trades Calc'!$E:$E,'IQ Equitizer'!$A$30,'Historical Trades Calc'!$D:$D,"GB")+SUMIFS('Historical Trades Calc'!$R:$R,'Historical Trades Calc'!$B:$B,'IQ Equitizer'!B35,'Historical Trades Calc'!$E:$E,'IQ Equitizer'!$A$30,'Historical Trades Calc'!$D:$D,"MT")+SUMIFS('Historical Trades Calc'!$R:$R,'Historical Trades Calc'!$B:$B,'IQ Equitizer'!B35,'Historical Trades Calc'!$E:$E,'IQ Equitizer'!$A$30,'Historical Trades Calc'!$D:$D,"FO") | B35: LRND | D35: =SUMIFS('Historical Trades Calc'!$R:$R,'Historical Trades Calc'!$B:$B,'IQ Equitizer'!B35,'Historical Trades Calc'!$E:$E,'IQ Equitizer'!$D$30,'Historical Trades Calc'!$D:$D,"GB")+SUMIFS('Historical Trades Calc'!$R:$R,'Historical Trades Calc'!$B:$B,'IQ Equitizer'!B35,'Historical Trades Calc'!$E:$E,'IQ Equitizer'!$D$30,'Historical Trades Calc'!$D:$D,"MT")+SUMIFS('Historical Trades Calc'!$R:$R,'Historical Trades Calc'!$B:$B,'IQ Equitizer'!B35,'Historical Trades Calc'!$E:$E,'IQ Equitizer'!$D$30,'Historical Trades Calc'!$D:$D,"FO") | E35: =SUMIFS('Historical Trades Calc'!$R:$R,'Historical Trades Calc'!$B:$B,'IQ Equitizer'!B35,'Historical Trades Calc'!$E:$E,'IQ Equitizer'!$E$30,'Historical Trades Calc'!$D:$D,"GB")+SUMIFS('Historical Trades Calc'!$R:$R,'Historical Trades Calc'!$B:$B,'IQ Equitizer'!B35,'Historical Trades Calc'!$E:$E,'IQ Equitizer'!$E$30,'Historical Trades Calc'!$D:$D,"MT")+SUMIFS('Historical Trades Calc'!$R:$R,'Historical Trades Calc'!$B:$B,'IQ Equitizer'!B35,'Historical Trades Calc'!$E:$E,'IQ Equitizer'!$E$30,'Historical Trades Calc'!$D:$D,"FO") | F35: =SUMIFS('Historical Trades Calc'!$R:$R,'Historical Trades Calc'!$B:$B,'IQ Equitizer'!B35,'Historical Trades Calc'!$E:$E,'IQ Equitizer'!$F$30,'Historical Trades Calc'!$D:$D,"GB")+SUMIFS('Historical Trades Calc'!$R:$R,'Historical Trades Calc'!$B:$B,'IQ Equitizer'!B35,'Historical Trades Calc'!$E:$E,'IQ Equitizer'!$F$30,'Historical Trades Calc'!$D:$D,"MT")+SUMIFS('Historical Trades Calc'!$R:$R,'Historical Trades Calc'!$B:$B,'IQ Equitizer'!B35,'Historical Trades Calc'!$E:$E,'IQ Equitizer'!$F$30,'Historical Trades Calc'!$D:$D,"FO") | G35: =SUMIFS('Historical Trades Calc'!$R:$R,'Historical Trades Calc'!$B:$B,'IQ Equitizer'!B35,'Historical Trades Calc'!$E:$E,'IQ Equitizer'!$G$30,'Historical Trades Calc'!$D:$D,"GB")+SUMIFS('Historical Trades Calc'!$R:$R,'Historical Trades Calc'!$B:$B,'IQ Equitizer'!B35,'Historical Trades Calc'!$E:$E,'IQ Equitizer'!$G$30,'Historical Trades Calc'!$D:$D,"MT")+SUMIFS('Historical Trades Calc'!$R:$R,'Historical Trades Calc'!$B:$B,'IQ Equitizer'!B35,'Historical Trades Calc'!$E:$E,'IQ Equitizer'!$G$30,'Historical Trades Calc'!$D:$D,"FO") | H35: =SUMIFS('Historical Trades Calc'!$R:$R,'Historical Trades Calc'!$B:$B,'IQ Equitizer'!B35,'Historical Trades Calc'!$E:$E,'IQ Equitizer'!$H$30,'Historical Trades Calc'!$D:$D,"GB")+SUMIFS('Historical Trades Calc'!$R:$R,'Historical Trades Calc'!$B:$B,'IQ Equitizer'!B35,'Historical Trades Calc'!$E:$E,'IQ Equitizer'!$H$30,'Historical Trades Calc'!$D:$D,"MT")+SUMIFS('Historical Trades Calc'!$R:$R,'Historical Trades Calc'!$B:$B,'IQ Equitizer'!B35,'Historical Trades Calc'!$E:$E,'IQ Equitizer'!$H$30,'Historical Trades Calc'!$D:$D,"FO") | I35: =SUMIFS('Historical Trades Calc'!$R:$R,'Historical Trades Calc'!$B:$B,'IQ Equitizer'!B35,'Historical Trades Calc'!$E:$E,'IQ Equitizer'!$I$30,'Historical Trades Calc'!$D:$D,"GB")+SUMIFS('Historical Trades Calc'!$R:$R,'Historical Trades Calc'!$B:$B,'IQ Equitizer'!B35,'Historical Trades Calc'!$E:$E,'IQ Equitizer'!$I$30,'Historical Trades Calc'!$D:$D,"MT")+SUMIFS('Historical Trades Calc'!$R:$R,'Historical Trades Calc'!$B:$B,'IQ Equitizer'!B35,'Historical Trades Calc'!$E:$E,'IQ Equitizer'!$I$30,'Historical Trades Calc'!$D:$D,"FO") | J35: =SUMIFS('Historical Trades Calc'!$R:$R,'Historical Trades Calc'!$B:$B,'IQ Equitizer'!B35,'Historical Trades Calc'!$E:$E,'IQ Equitizer'!$J$30,'Historical Trades Calc'!$D:$D,"GB")+SUMIFS('Historical Trades Calc'!$R:$R,'Historical Trades Calc'!$B:$B,'IQ Equitizer'!B35,'Historical Trades Calc'!$E:$E,'IQ Equitizer'!$J$30,'Historical Trades Calc'!$D:$D,"MT")+SUMIFS('Historical Trades Calc'!$R:$R,'Historical Trades Calc'!$B:$B,'IQ Equitizer'!B35,'Historical Trades Calc'!$E:$E,'IQ Equitizer'!$J$30,'Historical Trades Calc'!$D:$D,"FO") | K35: =SUM(D35:J35) | M35: =VLOOKUP(B35,$B$3:$F$11,5,0) | O35: =K35-M35
A36: =SUMIFS('Historical Trades Calc'!$R:$R,'Historical Trades Calc'!$B:$B,'IQ Equitizer'!B36,'Historical Trades Calc'!$E:$E,'IQ Equitizer'!$A$30,'Historical Trades Calc'!$D:$D,"GB")+SUMIFS('Historical Trades Calc'!$R:$R,'Historical Trades Calc'!$B:$B,'IQ Equitizer'!B36,'Historical Trades Calc'!$E:$E,'IQ Equitizer'!$A$30,'Historical Trades Calc'!$D:$D,"MT")+SUMIFS('Historical Trades Calc'!$R:$R,'Historical Trades Calc'!$B:$B,'IQ Equitizer'!B36,'Historical Trades Calc'!$E:$E,'IQ Equitizer'!$A$30,'Historical Trades Calc'!$D:$D,"FO") | B36: WRND | D36: =SUMIFS('Historical Trades Calc'!$R:$R,'Historical Trades Calc'!$B:$B,'IQ Equitizer'!B36,'Historical Trades Calc'!$E:$E,'IQ Equitizer'!$D$30,'Historical Trades Calc'!$D:$D,"GB")+SUMIFS('Historical Trades Calc'!$R:$R,'Historical Trades Calc'!$B:$B,'IQ Equitizer'!B36,'Historical Trades Calc'!$E:$E,'IQ Equitizer'!$D$30,'Historical Trades Calc'!$D:$D,"MT")+SUMIFS('Historical Trades Calc'!$R:$R,'Historical Trades Calc'!$B:$B,'IQ Equitizer'!B36,'Historical Trades Calc'!$E:$E,'IQ Equitizer'!$D$30,'Historical Trades Calc'!$D:$D,"FO") | E36: =SUMIFS('Historical Trades Calc'!$R:$R,'Historical Trades Calc'!$B:$B,'IQ Equitizer'!B36,'Historical Trades Calc'!$E:$E,'IQ Equitizer'!$E$30,'Historical Trades Calc'!$D:$D,"GB")+SUMIFS('Historical Trades Calc'!$R:$R,'Historical Trades Calc'!$B:$B,'IQ Equitizer'!B36,'Historical Trades Calc'!$E:$E,'IQ Equitizer'!$E$30,'Historical Trades Calc'!$D:$D,"MT")+SUMIFS('Historical Trades Calc'!$R:$R,'Historical Trades Calc'!$B:$B,'IQ Equitizer'!B36,'Historical Trades Calc'!$E:$E,'IQ Equitizer'!$E$30,'Historical Trades Calc'!$D:$D,"FO") | F36: =SUMIFS('Historical Trades Calc'!$R:$R,'Historical Trades Calc'!$B:$B,'IQ Equitizer'!B36,'Historical Trades Calc'!$E:$E,'IQ Equitizer'!$F$30,'Historical Trades Calc'!$D:$D,"GB")+SUMIFS('Historical Trades Calc'!$R:$R,'Historical Trades Calc'!$B:$B,'IQ Equitizer'!B36,'Historical Trades Calc'!$E:$E,'IQ Equitizer'!$F$30,'Historical Trades Calc'!$D:$D,"MT")+SUMIFS('Historical Trades Calc'!$R:$R,'Historical Trades Calc'!$B:$B,'IQ Equitizer'!B36,'Historical Trades Calc'!$E:$E,'IQ Equitizer'!$F$30,'Historical Trades Calc'!$D:$D,"FO") | G36: =SUMIFS('Historical Trades Calc'!$R:$R,'Historical Trades Calc'!$B:$B,'IQ Equitizer'!B36,'Historical Trades Calc'!$E:$E,'IQ Equitizer'!$G$30,'Historical Trades Calc'!$D:$D,"GB")+SUMIFS('Historical Trades Calc'!$R:$R,'Historical Trades Calc'!$B:$B,'IQ Equitizer'!B36,'Historical Trades Calc'!$E:$E,'IQ Equitizer'!$G$30,'Historical Trades Calc'!$D:$D,"MT")+SUMIFS('Historical Trades Calc'!$R:$R,'Historical Trades Calc'!$B:$B,'IQ Equitizer'!B36,'Historical Trades Calc'!$E:$E,'IQ Equitizer'!$G$30,'Historical Trades Calc'!$D:$D,"FO") | H36: =SUMIFS('Historical Trades Calc'!$R:$R,'Historical Trades Calc'!$B:$B,'IQ Equitizer'!B36,'Historical Trades Calc'!$E:$E,'IQ Equitizer'!$H$30,'Historical Trades Calc'!$D:$D,"GB")+SUMIFS('Historical Trades Calc'!$R:$R,'Historical Trades Calc'!$B:$B,'IQ Equitizer'!B36,'Historical Trades Calc'!$E:$E,'IQ Equitizer'!$H$30,'Historical Trades Calc'!$D:$D,"MT")+SUMIFS('Historical Trades Calc'!$R:$R,'Historical Trades Calc'!$B:$B,'IQ Equitizer'!B36,'Historical Trades Calc'!$E:$E,'IQ Equitizer'!$H$30,'Historical Trades Calc'!$D:$D,"FO") | I36: =SUMIFS('Historical Trades Calc'!$R:$R,'Historical Trades Calc'!$B:$B,'IQ Equitizer'!B36,'Historical Trades Calc'!$E:$E,'IQ Equitizer'!$I$30,'Historical Trades Calc'!$D:$D,"GB")+SUMIFS('Historical Trades Calc'!$R:$R,'Historical Trades Calc'!$B:$B,'IQ Equitizer'!B36,'Historical Trades Calc'!$E:$E,'IQ Equitizer'!$I$30,'Historical Trades Calc'!$D:$D,"MT")+SUMIFS('Historical Trades Calc'!$R:$R,'Historical Trades Calc'!$B:$B,'IQ Equitizer'!B36,'Historical Trades Calc'!$E:$E,'IQ Equitizer'!$I$30,'Historical Trades Calc'!$D:$D,"FO") | J36: =SUMIFS('Historical Trades Calc'!$R:$R,'Historical Trades Calc'!$B:$B,'IQ Equitizer'!B36,'Historical Trades Calc'!$E:$E,'IQ Equitizer'!$J$30,'Historical Trades Calc'!$D:$D,"GB")+SUMIFS('Historical Trades Calc'!$R:$R,'Historical Trades Calc'!$B:$B,'IQ Equitizer'!B36,'Historical Trades Calc'!$E:$E,'IQ Equitizer'!$J$30,'Historical Trades Calc'!$D:$D,"MT")+SUMIFS('Historical Trades Calc'!$R:$R,'Historical Trades Calc'!$B:$B,'IQ Equitizer'!B36,'Historical Trades Calc'!$E:$E,'IQ Equitizer'!$J$30,'Historical Trades Calc'!$D:$D,"FO") | K36: =SUM(D36:J36) | M36: =VLOOKUP(B36,$B$3:$F$11,5,0) | O36: =K36-M36
A37: =SUMIFS('Historical Trades Calc'!$R:$R,'Historical Trades Calc'!$B:$B,'IQ Equitizer'!B37,'Historical Trades Calc'!$E:$E,'IQ Equitizer'!$A$30,'Historical Trades Calc'!$D:$D,"GB")+SUMIFS('Historical Trades Calc'!$R:$R,'Historical Trades Calc'!$B:$B,'IQ Equitizer'!B37,'Historical Trades Calc'!$E:$E,'IQ Equitizer'!$A$30,'Historical Trades Calc'!$D:$D,"MT")+SUMIFS('Historical Trades Calc'!$R:$R,'Historical Trades Calc'!$B:$B,'IQ Equitizer'!B37,'Historical Trades Calc'!$E:$E,'IQ Equitizer'!$A$30,'Historical Trades Calc'!$D:$D,"FO") | B37: IQSM | D37: =SUMIFS('Historical Trades Calc'!$R:$R,'Historical Trades Calc'!$B:$B,'IQ Equitizer'!B37,'Historical Trades Calc'!$E:$E,'IQ Equitizer'!$D$30,'Historical Trades Calc'!$D:$D,"GB")+SUMIFS('Historical Trades Calc'!$R:$R,'Historical Trades Calc'!$B:$B,'IQ Equitizer'!B37,'Historical Trades Calc'!$E:$E,'IQ Equitizer'!$D$30,'Historical Trades Calc'!$D:$D,"MT")+SUMIFS('Historical Trades Calc'!$R:$R,'Historical Trades Calc'!$B:$B,'IQ Equitizer'!B37,'Historical Trades Calc'!$E:$E,'IQ Equitizer'!$D$30,'Historical Trades Calc'!$D:$D,"FO") | E37: =SUMIFS('Historical Trades Calc'!$R:$R,'Historical Trades Calc'!$B:$B,'IQ Equitizer'!B37,'Historical Trades Calc'!$E:$E,'IQ Equitizer'!$E$30,'Historical Trades Calc'!$D:$D,"GB")+SUMIFS('Historical Trades Calc'!$R:$R,'Historical Trades Calc'!$B:$B,'IQ Equitizer'!B37,'Historical Trades Calc'!$E:$E,'IQ Equitizer'!$E$30,'Historical Trades Calc'!$D:$D,"MT")+SUMIFS('Historical Trades Calc'!$R:$R,'Historical Trades Calc'!$B:$B,'IQ Equitizer'!B37,'Historical Trades Calc'!$E:$E,'IQ Equitizer'!$E$30,'Historical Trades Calc'!$D:$D,"FO") | F37: =SUMIFS('Historical Trades Calc'!$R:$R,'Historical Trades Calc'!$B:$B,'IQ Equitizer'!B37,'Historical Trades Calc'!$E:$E,'IQ Equitizer'!$F$30,'Historical Trades Calc'!$D:$D,"GB")+SUMIFS('Historical Trades Calc'!$R:$R,'Historical Trades Calc'!$B:$B,'IQ Equitizer'!B37,'Historical Trades Calc'!$E:$E,'IQ Equitizer'!$F$30,'Historical Trades Calc'!$D:$D,"MT")+SUMIFS('Historical Trades Calc'!$R:$R,'Historical Trades Calc'!$B:$B,'IQ Equitizer'!B37,'Historical Trades Calc'!$E:$E,'IQ Equitizer'!$F$30,'Historical Trades Calc'!$D:$D,"FO") | G37: =SUMIFS('Historical Trades Calc'!$R:$R,'Historical Trades Calc'!$B:$B,'IQ Equitizer'!B37,'Historical Trades Calc'!$E:$E,'IQ Equitizer'!$G$30,'Historical Trades Calc'!$D:$D,"GB")+SUMIFS('Historical Trades Calc'!$R:$R,'Historical Trades Calc'!$B:$B,'IQ Equitizer'!B37,'Historical Trades Calc'!$E:$E,'IQ Equitizer'!$G$30,'Historical Trades Calc'!$D:$D,"MT")+SUMIFS('Historical Trades Calc'!$R:$R,'Historical Trades Calc'!$B:$B,'IQ Equitizer'!B37,'Historical Trades Calc'!$E:$E,'IQ Equitizer'!$G$30,'Historical Trades Calc'!$D:$D,"FO") | H37: =SUMIFS('Historical Trades Calc'!$R:$R,'Historical Trades Calc'!$B:$B,'IQ Equitizer'!B37,'Historical Trades Calc'!$E:$E,'IQ Equitizer'!$H$30,'Historical Trades Calc'!$D:$D,"GB")+SUMIFS('Historical Trades Calc'!$R:$R,'Historical Trades Calc'!$B:$B,'IQ Equitizer'!B37,'Historical Trades Calc'!$E:$E,'IQ Equitizer'!$H$30,'Historical Trades Calc'!$D:$D,"MT")+SUMIFS('Historical Trades Calc'!$R:$R,'Historical Trades Calc'!$B:$B,'IQ Equitizer'!B37,'Historical Trades Calc'!$E:$E,'IQ Equitizer'!$H$30,'Historical Trades Calc'!$D:$D,"FO") | I37: =SUMIFS('Historical Trades Calc'!$R:$R,'Historical Trades Calc'!$B:$B,'IQ Equitizer'!B37,'Historical Trades Calc'!$E:$E,'IQ Equitizer'!$I$30,'Historical Trades Calc'!$D:$D,"GB")+SUMIFS('Historical Trades Calc'!$R:$R,'Historical Trades Calc'!$B:$B,'IQ Equitizer'!B37,'Historical Trades Calc'!$E:$E,'IQ Equitizer'!$I$30,'Historical Trades Calc'!$D:$D,"MT")+SUMIFS('Historical Trades Calc'!$R:$R,'Historical Trades Calc'!$B:$B,'IQ Equitizer'!B37,'Historical Trades Calc'!$E:$E,'IQ Equitizer'!$I$30,'Historical Trades Calc'!$D:$D,"FO") | J37: =SUMIFS('Historical Trades Calc'!$R:$R,'Historical Trades Calc'!$B:$B,'IQ Equitizer'!B37,'Historical Trades Calc'!$E:$E,'IQ Equitizer'!$J$30,'Historical Trades Calc'!$D:$D,"GB")+SUMIFS('Historical Trades Calc'!$R:$R,'Historical Trades Calc'!$B:$B,'IQ Equitizer'!B37,'Historical Trades Calc'!$E:$E,'IQ Equitizer'!$J$30,'Historical Trades Calc'!$D:$D,"MT")+SUMIFS('Historical Trades Calc'!$R:$R,'Historical Trades Calc'!$B:$B,'IQ Equitizer'!B37,'Historical Trades Calc'!$E:$E,'IQ Equitizer'!$J$30,'Historical Trades Calc'!$D:$D,"FO") | K37: =SUM(D37:J37) | M37: =VLOOKUP(B37,$B$3:$F$11,5,0) | O37: =K37-M37
A38: =SUMIFS('Historical Trades Calc'!$R:$R,'Historical Trades Calc'!$B:$B,'IQ Equitizer'!B38,'Historical Trades Calc'!$E:$E,'IQ Equitizer'!$A$30,'Historical Trades Calc'!$D:$D,"GB")+SUMIFS('Historical Trades Calc'!$R:$R,'Historical Trades Calc'!$B:$B,'IQ Equitizer'!B38,'Historical Trades Calc'!$E:$E,'IQ Equitizer'!$A$30,'Historical Trades Calc'!$D:$D,"MT")+SUMIFS('Historical Trades Calc'!$R:$R,'Historical Trades Calc'!$B:$B,'IQ Equitizer'!B38,'Historical Trades Calc'!$E:$E,'IQ Equitizer'!$A$30,'Historical Trades Calc'!$D:$D,"FO") | B38: QAI | D38: =SUMIFS('Historical Trades Calc'!$R:$R,'Historical Trades Calc'!$B:$B,'IQ Equitizer'!B38,'Historical Trades Calc'!$E:$E,'IQ Equitizer'!$D$30,'Historical Trades Calc'!$D:$D,"GB")+SUMIFS('Historical Trades Calc'!$R:$R,'Historical Trades Calc'!$B:$B,'IQ Equitizer'!B38,'Historical Trades Calc'!$E:$E,'IQ Equitizer'!$D$30,'Historical Trades Calc'!$D:$D,"MT")+SUMIFS('Historical Trades Calc'!$R:$R,'Historical Trades Calc'!$B:$B,'IQ Equitizer'!B38,'Historical Trades Calc'!$E:$E,'IQ Equitizer'!$D$30,'Historical Trades Calc'!$D:$D,"FO") | E38: =SUMIFS('Historical Trades Calc'!$R:$R,'Historical Trades Calc'!$B:$B,'IQ Equitizer'!B38,'Historical Trades Calc'!$E:$E,'IQ Equitizer'!$E$30,'Historical Trades Calc'!$D:$D,"GB")+SUMIFS('Historical Trades Calc'!$R:$R,'Historical Trades Calc'!$B:$B,'IQ Equitizer'!B38,'Historical Trades Calc'!$E:$E,'IQ Equitizer'!$E$30,'Historical Trades Calc'!$D:$D,"MT")+SUMIFS('Historical Trades Calc'!$R:$R,'Historical Trades Calc'!$B:$B,'IQ Equitizer'!B38,'Historical Trades Calc'!$E:$E,'IQ Equitizer'!$E$30,'Historical Trades Calc'!$D:$D,"FO") | F38: =SUMIFS('Historical Trades Calc'!$R:$R,'Historical Trades Calc'!$B:$B,'IQ Equitizer'!B38,'Historical Trades Calc'!$E:$E,'IQ Equitizer'!$F$30,'Historical Trades Calc'!$D:$D,"GB")+SUMIFS('Historical Trades Calc'!$R:$R,'Historical Trades Calc'!$B:$B,'IQ Equitizer'!B38,'Historical Trades Calc'!$E:$E,'IQ Equitizer'!$F$30,'Historical Trades Calc'!$D:$D,"MT")+SUMIFS('Historical Trades Calc'!$R:$R,'Historical Trades Calc'!$B:$B,'IQ Equitizer'!B38,'Historical Trades Calc'!$E:$E,'IQ Equitizer'!$F$30,'Historical Trades Calc'!$D:$D,"FO") | G38: =SUMIFS('Historical Trades Calc'!$R:$R,'Historical Trades Calc'!$B:$B,'IQ Equitizer'!B38,'Historical Trades Calc'!$E:$E,'IQ Equitizer'!$G$30,'Historical Trades Calc'!$D:$D,"GB")+SUMIFS('Historical Trades Calc'!$R:$R,'Historical Trades Calc'!$B:$B,'IQ Equitizer'!B38,'Historical Trades Calc'!$E:$E,'IQ Equitizer'!$G$30,'Historical Trades Calc'!$D:$D,"MT")+SUMIFS('Historical Trades Calc'!$R:$R,'Historical Trades Calc'!$B:$B,'IQ Equitizer'!B38,'Historical Trades Calc'!$E:$E,'IQ Equitizer'!$G$30,'Historical Trades Calc'!$D:$D,"FO") | H38: =SUMIFS('Historical Trades Calc'!$R:$R,'Historical Trades Calc'!$B:$B,'IQ Equitizer'!B38,'Historical Trades Calc'!$E:$E,'IQ Equitizer'!$H$30,'Historical Trades Calc'!$D:$D,"GB")+SUMIFS('Historical Trades Calc'!$R:$R,'Historical Trades Calc'!$B:$B,'IQ Equitizer'!B38,'Historical Trades Calc'!$E:$E,'IQ Equitizer'!$H$30,'Historical Trades Calc'!$D:$D,"MT")+SUMIFS('Historical Trades Calc'!$R:$R,'Historical Trades Calc'!$B:$B,'IQ Equitizer'!B38,'Historical Trades Calc'!$E:$E,'IQ Equitizer'!$H$30,'Historical Trades Calc'!$D:$D,"FO") | I38: =SUMIFS('Historical Trades Calc'!$R:$R,'Historical Trades Calc'!$B:$B,'IQ Equitizer'!B38,'Historical Trades Calc'!$E:$E,'IQ Equitizer'!$I$30,'Historical Trades Calc'!$D:$D,"GB")+SUMIFS('Historical Trades Calc'!$R:$R,'Historical Trades Calc'!$B:$B,'IQ Equitizer'!B38,'Historical Trades Calc'!$E:$E,'IQ Equitizer'!$I$30,'Historical Trades Calc'!$D:$D,"MT")+SUMIFS('Historical Trades Calc'!$R:$R,'Historical Trades Calc'!$B:$B,'IQ Equitizer'!B38,'Historical Trades Calc'!$E:$E,'IQ Equitizer'!$I$30,'Historical Trades Calc'!$D:$D,"FO") | J38: =SUMIFS('Historical Trades Calc'!$R:$R,'Historical Trades Calc'!$B:$B,'IQ Equitizer'!B38,'Historical Trades Calc'!$E:$E,'IQ Equitizer'!$J$30,'Historical Trades Calc'!$D:$D,"GB")+SUMIFS('Historical Trades Calc'!$R:$R,'Historical Trades Calc'!$B:$B,'IQ Equitizer'!B38,'Historical Trades Calc'!$E:$E,'IQ Equitizer'!$J$30,'Historical Trades Calc'!$D:$D,"MT")+SUMIFS('Historical Trades Calc'!$R:$R,'Historical Trades Calc'!$B:$B,'IQ Equitizer'!B38,'Historical Trades Calc'!$E:$E,'IQ Equitizer'!$J$30,'Historical Trades Calc'!$D:$D,"FO") | K38: =SUM(D38:J38) | M38: =VLOOKUP(B38,$B$3:$F$11,5,0) | O38: =K38-M38
A39: =SUMIFS('Historical Trades Calc'!$R:$R,'Historical Trades Calc'!$B:$B,'IQ Equitizer'!B39,'Historical Trades Calc'!$E:$E,'IQ Equitizer'!$A$30,'Historical Trades Calc'!$D:$D,"GB")+SUMIFS('Historical Trades Calc'!$R:$R,'Historical Trades Calc'!$B:$B,'IQ Equitizer'!B39,'Historical Trades Calc'!$E:$E,'IQ Equitizer'!$A$30,'Historical Trades Calc'!$D:$D,"MT")+SUMIFS('Historical Trades Calc'!$R:$R,'Historical Trades Calc'!$B:$B,'IQ Equitizer'!B39,'Historical Trades Calc'!$E:$E,'IQ Equitizer'!$A$30,'Historical Trades Calc'!$D:$D,"FO") | B39: HFXI | D39: =SUMIFS('Historical Trades Calc'!$R:$R,'Historical Trades Calc'!$B:$B,'IQ Equitizer'!B39,'Historical Trades Calc'!$E:$E,'IQ Equitizer'!$D$30,'Historical Trades Calc'!$D:$D,"GB")+SUMIFS('Historical Trades Calc'!$R:$R,'Historical Trades Calc'!$B:$B,'IQ Equitizer'!B39,'Historical Trades Calc'!$E:$E,'IQ Equitizer'!$D$30,'Historical Trades Calc'!$D:$D,"MT")+SUMIFS('Historical Trades Calc'!$R:$R,'Historical Trades Calc'!$B:$B,'IQ Equitizer'!B39,'Historical Trades Calc'!$E:$E,'IQ Equitizer'!$D$30,'Historical Trades Calc'!$D:$D,"FO") | E39: =SUMIFS('Historical Trades Calc'!$R:$R,'Historical Trades Calc'!$B:$B,'IQ Equitizer'!B39,'Historical Trades Calc'!$E:$E,'IQ Equitizer'!$E$30,'Historical Trades Calc'!$D:$D,"GB")+SUMIFS('Historical Trades Calc'!$R:$R,'Historical Trades Calc'!$B:$B,'IQ Equitizer'!B39,'Historical Trades Calc'!$E:$E,'IQ Equitizer'!$E$30,'Historical Trades Calc'!$D:$D,"MT")+SUMIFS('Historical Trades Calc'!$R:$R,'Historical Trades Calc'!$B:$B,'IQ Equitizer'!B39,'Historical Trades Calc'!$E:$E,'IQ Equitizer'!$E$30,'Historical Trades Calc'!$D:$D,"FO") | F39: =SUMIFS('Historical Trades Calc'!$R:$R,'Historical Trades Calc'!$B:$B,'IQ Equitizer'!B39,'Historical Trades Calc'!$E:$E,'IQ Equitizer'!$F$30,'Historical Trades Calc'!$D:$D,"GB")+SUMIFS('Historical Trades Calc'!$R:$R,'Historical Trades Calc'!$B:$B,'IQ Equitizer'!B39,'Historical Trades Calc'!$E:$E,'IQ Equitizer'!$F$30,'Historical Trades Calc'!$D:$D,"MT")+SUMIFS('Historical Trades Calc'!$R:$R,'Historical Trades Calc'!$B:$B,'IQ Equitizer'!B39,'Historical Trades Calc'!$E:$E,'IQ Equitizer'!$F$30,'Historical Trades Calc'!$D:$D,"FO") | G39: =SUMIFS('Historical Trades Calc'!$R:$R,'Historical Trades Calc'!$B:$B,'IQ Equitizer'!B39,'Historical Trades Calc'!$E:$E,'IQ Equitizer'!$G$30,'Historical Trades Calc'!$D:$D,"GB")+SUMIFS('Historical Trades Calc'!$R:$R,'Historical Trades Calc'!$B:$B,'IQ Equitizer'!B39,'Historical Trades Calc'!$E:$E,'IQ Equitizer'!$G$30,'Historical Trades Calc'!$D:$D,"MT")+SUMIFS('Historical Trades Calc'!$R:$R,'Historical Trades Calc'!$B:$B,'IQ Equitizer'!B39,'Historical Trades Calc'!$E:$E,'IQ Equitizer'!$G$30,'Historical Trades Calc'!$D:$D,"FO") | H39: =SUMIFS('Historical Trades Calc'!$R:$R,'Historical Trades Calc'!$B:$B,'IQ Equitizer'!B39,'Historical Trades Calc'!$E:$E,'IQ Equitizer'!$H$30,'Historical Trades Calc'!$D:$D,"GB")+SUMIFS('Historical Trades Calc'!$R:$R,'Historical Trades Calc'!$B:$B,'IQ Equitizer'!B39,'Historical Trades Calc'!$E:$E,'IQ Equitizer'!$H$30,'Historical Trades Calc'!$D:$D,"MT")+SUMIFS('Historical Trades Calc'!$R:$R,'Historical Trades Calc'!$B:$B,'IQ Equitizer'!B39,'Historical Trades Calc'!$E:$E,'IQ Equitizer'!$H$30,'Historical Trades Calc'!$D:$D,"FO") | I39: =SUMIFS('Historical Trades Calc'!$R:$R,'Historical Trades Calc'!$B:$B,'IQ Equitizer'!B39,'Historical Trades Calc'!$E:$E,'IQ Equitizer'!$I$30,'Historical Trades Calc'!$D:$D,"GB")+SUMIFS('Historical Trades Calc'!$R:$R,'Historical Trades Calc'!$B:$B,'IQ Equitizer'!B39,'Historical Trades Calc'!$E:$E,'IQ Equitizer'!$I$30,'Historical Trades Calc'!$D:$D,"MT")+SUMIFS('Historical Trades Calc'!$R:$R,'Historical Trades Calc'!$B:$B,'IQ Equitizer'!B39,'Historical Trades Calc'!$E:$E,'IQ Equitizer'!$I$30,'Historical Trades Calc'!$D:$D,"FO") | J39: =SUMIFS('Historical Trades Calc'!$R:$R,'Historical Trades Calc'!$B:$B,'IQ Equitizer'!B39,'Historical Trades Calc'!$E:$E,'IQ Equitizer'!$J$30,'Historical Trades Calc'!$D:$D,"GB")+SUMIFS('Historical Trades Calc'!$R:$R,'Historical Trades Calc'!$B:$B,'IQ Equitizer'!B39,'Historical Trades Calc'!$E:$E,'IQ Equitizer'!$J$30,'Historical Trades Calc'!$D:$D,"MT")+SUMIFS('Historical Trades Calc'!$R:$R,'Historical Trades Calc'!$B:$B,'IQ Equitizer'!B39,'Historical Trades Calc'!$E:$E,'IQ Equitizer'!$J$30,'Historical Trades Calc'!$D:$D,"FO") | K39: =SUM(D39:J39) | M39: =VLOOKUP(B39,$B$3:$F$11,5,0) | O39: =K39-M39
A40: =SUMIFS('Historical Trades Calc'!$R:$R,'Historical Trades Calc'!$B:$B,'IQ Equitizer'!B40,'Historical Trades Calc'!$E:$E,'IQ Equitizer'!$A$30,'Historical Trades Calc'!$D:$D,"GB")+SUMIFS('Historical Trades Calc'!$R:$R,'Historical Trades Calc'!$B:$B,'IQ Equitizer'!B40,'Historical Trades Calc'!$E:$E,'IQ Equitizer'!$A$30,'Historical Trades Calc'!$D:$D,"MT")+SUMIFS('Historical Trades Calc'!$R:$R,'Historical Trades Calc'!$B:$B,'IQ Equitizer'!B40,'Historical Trades Calc'!$E:$E,'IQ Equitizer'!$A$30,'Historical Trades Calc'!$D:$D,"FO") | B40: VP Mutual Fund | D40: =SUMIFS('Historical Trades Calc'!$R:$R,'Historical Trades Calc'!$B:$B,'IQ Equitizer'!B40,'Historical Trades Calc'!$E:$E,'IQ Equitizer'!$D$30,'Historical Trades Calc'!$D:$D,"GB")+SUMIFS('Historical Trades Calc'!$R:$R,'Historical Trades Calc'!$B:$B,'IQ Equitizer'!B40,'Historical Trades Calc'!$E:$E,'IQ Equitizer'!$D$30,'Historical Trades Calc'!$D:$D,"MT")+SUMIFS('Historical Trades Calc'!$R:$R,'Historical Trades Calc'!$B:$B,'IQ Equitizer'!B40,'Historical Trades Calc'!$E:$E,'IQ Equitizer'!$D$30,'Historical Trades Calc'!$D:$D,"FO") | E40: =SUMIFS('Historical Trades Calc'!$R:$R,'Historical Trades Calc'!$B:$B,'IQ Equitizer'!B40,'Historical Trades Calc'!$E:$E,'IQ Equitizer'!$E$30,'Historical Trades Calc'!$D:$D,"GB")+SUMIFS('Historical Trades Calc'!$R:$R,'Historical Trades Calc'!$B:$B,'IQ Equitizer'!B40,'Historical Trades Calc'!$E:$E,'IQ Equitizer'!$E$30,'Historical Trades Calc'!$D:$D,"MT")+SUMIFS('Historical Trades Calc'!$R:$R,'Historical Trades Calc'!$B:$B,'IQ Equitizer'!B40,'Historical Trades Calc'!$E:$E,'IQ Equitizer'!$E$30,'Historical Trades Calc'!$D:$D,"FO") | F40: =SUMIFS('Historical Trades Calc'!$R:$R,'Historical Trades Calc'!$B:$B,'IQ Equitizer'!B40,'Historical Trades Calc'!$E:$E,'IQ Equitizer'!$F$30,'Historical Trades Calc'!$D:$D,"GB")+SUMIFS('Historical Trades Calc'!$R:$R,'Historical Trades Calc'!$B:$B,'IQ Equitizer'!B40,'Historical Trades Calc'!$E:$E,'IQ Equitizer'!$F$30,'Historical Trades Calc'!$D:$D,"MT")+SUMIFS('Historical Trades Calc'!$R:$R,'Historical Trades Calc'!$B:$B,'IQ Equitizer'!B40,'Historical Trades Calc'!$E:$E,'IQ Equitizer'!$F$30,'Historical Trades Calc'!$D:$D,"FO") | G40: =SUMIFS('Historical Trades Calc'!$R:$R,'Historical Trades Calc'!$B:$B,'IQ Equitizer'!B40,'Historical Trades Calc'!$E:$E,'IQ Equitizer'!$G$30,'Historical Trades Calc'!$D:$D,"GB")+SUMIFS('Historical Trades Calc'!$R:$R,'Historical Trades Calc'!$B:$B,'IQ Equitizer'!B40,'Historical Trades Calc'!$E:$E,'IQ Equitizer'!$G$30,'Historical Trades Calc'!$D:$D,"MT")+SUMIFS('Historical Trades Calc'!$R:$R,'Historical Trades Calc'!$B:$B,'IQ Equitizer'!B40,'Historical Trades Calc'!$E:$E,'IQ Equitizer'!$G$30,'Historical Trades Calc'!$D:$D,"FO") | H40: =SUMIFS('Historical Trades Calc'!$R:$R,'Historical Trades Calc'!$B:$B,'IQ Equitizer'!B40,'Historical Trades Calc'!$E:$E,'IQ Equitizer'!$H$30,'Historical Trades Calc'!$D:$D,"GB")+SUMIFS('Historical Trades Calc'!$R:$R,'Historical Trades Calc'!$B:$B,'IQ Equitizer'!B40,'Historical Trades Calc'!$E:$E,'IQ Equitizer'!$H$30,'Historical Trades Calc'!$D:$D,"MT")+SUMIFS('Historical Trades Calc'!$R:$R,'Historical Trades Calc'!$B:$B,'IQ Equitizer'!B40,'Historical Trades Calc'!$E:$E,'IQ Equitizer'!$H$30,'Historical Trades Calc'!$D:$D,"FO") | I40: =SUMIFS('Historical Trades Calc'!$R:$R,'Historical Trades Calc'!$B:$B,'IQ Equitizer'!B40,'Historical Trades Calc'!$E:$E,'IQ Equitizer'!$I$30,'Historical Trades Calc'!$D:$D,"GB")+SUMIFS('Historical Trades Calc'!$R:$R,'Historical Trades Calc'!$B:$B,'IQ Equitizer'!B40,'Historical Trades Calc'!$E:$E,'IQ Equitizer'!$I$30,'Historical Trades Calc'!$D:$D,"MT")+SUMIFS('Historical Trades Calc'!$R:$R,'Historical Trades Calc'!$B:$B,'IQ Equitizer'!B40,'Historical Trades Calc'!$E:$E,'IQ Equitizer'!$I$30,'Historical Trades Calc'!$D:$D,"FO") | J40: =SUMIFS('Historical Trades Calc'!$R:$R,'Historical Trades Calc'!$B:$B,'IQ Equitizer'!B40,'Historical Trades Calc'!$E:$E,'IQ Equitizer'!$J$30,'Historical Trades Calc'!$D:$D,"GB")+SUMIFS('Historical Trades Calc'!$R:$R,'Historical Trades Calc'!$B:$B,'IQ Equitizer'!B40,'Historical Trades Calc'!$E:$E,'IQ Equitizer'!$J$30,'Historical Trades Calc'!$D:$D,"MT")+SUMIFS('Historical Trades Calc'!$R:$R,'Historical Trades Calc'!$B:$B,'IQ Equitizer'!B40,'Historical Trades Calc'!$E:$E,'IQ Equitizer'!$J$30,'Historical Trades Calc'!$D:$D,"FO") | K40: =SUM(D40:J40) | M40: =F12 | O40: =K40-M40
A43: PENDING TRADES | D43: FAILING TRADES
A44: IQSI | B44: =VLOOKUP(A44,'Pending Failed Trade Matrix'!$B$3:$AG$12,32,0) | D44: IQSI | E44: =VLOOKUP(A44,'Pending Failed Trade Matrix'!$B$17:$AG$26,32,0)
A45: IQSU | B45: =VLOOKUP(A45,'Pending Failed Trade Matrix'!$B$3:$AG$12,32,0) | D45: IQSU | E45: =VLOOKUP(A45,'Pending Failed Trade Matrix'!$B$17:$AG$26,32,0)
A46: HART | B46: =VLOOKUP(A46,'Pending Failed Trade Matrix'!$B$3:$AG$12,32,0) | D46: HART | E46: =VLOOKUP(A46,'Pending Failed Trade Matrix'!$B$17:$AG$26,32,0)
A47: MNA | B47: =VLOOKUP(A47,'Pending Failed Trade Matrix'!$B$3:$AG$12,32,0) | D47: MNA | E47: =VLOOKUP(A47,'Pending Failed Trade Matrix'!$B$17:$AG$26,32,0)
A48: LRND | B48: =VLOOKUP(A48,'Pending Failed Trade Matrix'!$B$3:$AG$12,32,0) | D48: LRND | E48: =VLOOKUP(A48,'Pending Failed Trade Matrix'!$B$17:$AG$26,32,0)
A49: WRND | B49: =VLOOKUP(A49,'Pending Failed Trade Matrix'!$B$3:$AG$12,32,0) | D49: WRND | E49: =VLOOKUP(A49,'Pending Failed Trade Matrix'!$B$17:$AG$26,32,0)
A50: IQSM | B50: =VLOOKUP(A50,'Pending Failed Trade Matrix'!$B$3:$AG$12,32,0) | D50: IQSM | E50: =VLOOKUP(A50,'Pending Failed Trade Matrix'!$B$17:$AG$26,32,0)
A51: QAI | B51: =VLOOKUP(A51,'Pending Failed Trade Matrix'!$B$3:$AG$12,32,0) | D51: QAI | E51: =VLOOKUP(A51,'Pending Failed Trade Matrix'!$B$17:$AG$26,32,0)
A52: HFXI | B52: =VLOOKUP(A52,'Pending Failed Trade Matrix'!$B$3:$AG$12,32,0) | D52: HFXI | E52: =VLOOKUP(A52,'Pending Failed Trade Matrix'!$B$17:$AG$26,32,0)
A53: VP Mutual Fund | B53: =VLOOKUP(A53,'Pending Failed Trade Matrix'!$B$3:$AG$12,32,0) | D53: VP Mutual Fund | E53: =VLOOKUP(A53,'Pending Failed Trade Matrix'!$B$17:$AG$26,32,0)
D55: SOD Cash(USD: cash projections) | F55: Pending Trades +Failing (JP/BNY) | G55: Income (projections today)
D56: BNY Projected Cash Statement | F56: BNY Projected Cash Statement | G56: BNY Projected Cash Statement
D57: Consolidate Sweep and Cash | F57: Buy+Sells W/ settled date today and beyond (today date built into code) | G57: Dividends: Income paying today: based off today's date)
D58: Sum opening balance if E in NOT blank | F58: Transaction Amount Reporting Equivalent | G58: Transaction Amount Reporting Equivalent
D59: Bony sometimes reflects two Swwp accounts, causing formula to dupe #
D60: Formula will now determine number of dupes for today and divide by the number of dupes to get correct SOD cash
D61: Based off of today date: in formula

Sheet (FA) Sub-Advised
A1: Custody Acc # | B1: Account | C1: AD | D1: Total Cash USD | E1: Foreign Currency | F1: SWEEP | G1: Collateral & MD | H1: Variation Margin | I1: Unrl Loss On FFX | J1: TR Swaps Sheet | K1: Net Cash | L1: Equity MV | M1: Market Value | N1: Percent Cash | O1: 15% Illiquidity Test
A2: 217661 | B2: MMCA | C2: NYLI MacKay California Muni Intermediate ETF | D2: =VLOOKUP(A2,'BNY FA Cash'!$C$27:$Y$1048576,23,0) | E2: =VLOOKUP(A2,'BNY FA Cash'!$C$27:$F$634,4,0) | F2: =VLOOKUP(A2,'BNY FA Cash'!$C$27:$H$1048576,6,0) | G2: =VLOOKUP(A2,'BNY FA Cash'!$C$27:$I$1048576,7,0) | H2: =VLOOKUP(A2,'BNY FA Cash'!$C$27:$J$1048576,8,0) | I2: =VLOOKUP(A2,'BNY FA Cash'!$C$27:$N$1048576,12,0)+VLOOKUP(A2,'BNY FA Cash'!$C$27:$T$1048576,18,0) | J2: =VLOOKUP(A2,'BNY FA Cash'!$C$27:$AA$1048576,25,0) | K2: =SUM(D2:J2) | L2: =M2-K2 | M2: =VLOOKUP(A2,'BNY FA Cash'!$C$27:$Z$1048576,24,0) | N2: =K2/M2 | O2: =ABS(J2)/M2
A3: 240412 | B3: IQHI | C3: NYLI MacKay ESG High Income ETF | D3: =VLOOKUP(A3,'BNY FA Cash'!$C$27:$Y$1048576,23,0) | E3: =VLOOKUP(A3,'BNY FA Cash'!$C$27:$F$634,4,0) | F3: =VLOOKUP(A3,'BNY FA Cash'!$C$27:$H$1048576,6,0) | G3: =VLOOKUP(A3,'BNY FA Cash'!$C$27:$I$1048576,7,0) | H3: =VLOOKUP(A3,'BNY FA Cash'!$C$27:$J$1048576,8,0) | I3: =VLOOKUP(A3,'BNY FA Cash'!$C$27:$N$1048576,12,0)+VLOOKUP(A3,'BNY FA Cash'!$C$27:$T$1048576,18,0) | J3: =VLOOKUP(A3,'BNY FA Cash'!$C$27:$AA$1048576,25,0) | K3: =SUM(D3:J3) | L3: =M3-K3 | M3: =VLOOKUP(A3,'BNY FA Cash'!$C$27:$Z$1048576,24,0) | N3: =K3/M3 | O3: =ABS(J3)/M3
A4: 682403 | B4: MMIT | C4: NYLI MacKay Muni Intermediate ETF | D4: =VLOOKUP(A4,'BNY FA Cash'!$C$27:$Y$1048576,23,0) | E4: =VLOOKUP(A4,'BNY FA Cash'!$C$27:$F$634,4,0) | F4: =VLOOKUP(A4,'BNY FA Cash'!$C$27:$H$1048576,6,0) | G4: =VLOOKUP(A4,'BNY FA Cash'!$C$27:$I$1048576,7,0) | H4: =VLOOKUP(A4,'BNY FA Cash'!$C$27:$J$1048576,8,0) | I4: =VLOOKUP(A4,'BNY FA Cash'!$C$27:$N$1048576,12,0)+VLOOKUP(A4,'BNY FA Cash'!$C$27:$T$1048576,18,0) | J4: =VLOOKUP(A4,'BNY FA Cash'!$C$27:$AA$1048576,25,0) | K4: =SUM(D4:J4) | L4: =M4-K4 | M4: =VLOOKUP(A4,'BNY FA Cash'!$C$27:$Z$1048576,24,0) | N4: =K4/M4 | O4: =ABS(J4)/M4
A5: 682447 | B5: MMIN | C5: NYLI MacKay Muni Insured ETF | D5: =VLOOKUP(A5,'BNY FA Cash'!$C$27:$Y$1048576,23,0) | E5: =VLOOKUP(A5,'BNY FA Cash'!$C$27:$F$634,4,0) | F5: =VLOOKUP(A5,'BNY FA Cash'!$C$27:$H$1048576,6,0) | G5: =VLOOKUP(A5,'BNY FA Cash'!$C$27:$I$1048576,7,0) | H5: =VLOOKUP(A5,'BNY FA Cash'!$C$27:$J$1048576,8,0) | I5: =VLOOKUP(A5,'BNY FA Cash'!$C$27:$N$1048576,12,0)+VLOOKUP(A5,'BNY FA Cash'!$C$27:$T$1048576,18,0) | J5: =VLOOKUP(A5,'BNY FA Cash'!$C$27:$AA$1048576,25,0) | K5: =SUM(D5:J5) | L5: =M5-K5 | M5: =VLOOKUP(A5,'BNY FA Cash'!$C$27:$Z$1048576,24,0) | N5: =K5/M5 | O5: =ABS(J5)/M5
A6: 943872 | B6: CPLB | C6: NYLI MacKay Core Plus Bond ETF | D6: =VLOOKUP(A6,'BNY FA Cash'!$C$27:$Y$1048576,23,0) | E6: =VLOOKUP(A6,'BNY FA Cash'!$C$27:$F$634,4,0) | F6: =VLOOKUP(A6,'BNY FA Cash'!$C$27:$H$1048576,6,0) | G6: =VLOOKUP(A6,'BNY FA Cash'!$C$27:$I$1048576,7,0) | H6: =VLOOKUP(A6,'BNY FA Cash'!$C$27:$J$1048576,8,0) | I6: =VLOOKUP(A6,'BNY FA Cash'!$C$27:$N$1048576,12,0)+VLOOKUP(A6,'BNY FA Cash'!$C$27:$T$1048576,18,0) | J6: =VLOOKUP(A6,'BNY FA Cash'!$C$27:$AA$1048576,25,0) | K6: =SUM(D6:J6) | L6: =M6-K6 | M6: =VLOOKUP(A6,'BNY FA Cash'!$C$27:$Z$1048576,24,0) | N6: =K6/M6 | O6: =ABS(J6)/M6
A7: 425269 | B7: IQRA | C7: NYLI CBRE Real Assets ETF | D7: =VLOOKUP(A7,'BNY FA Cash'!$C$27:$Y$1048576,23,0) | E7: =VLOOKUP(A7,'BNY FA Cash'!$C$27:$F$634,4,0) | F7: =VLOOKUP(A7,'BNY FA Cash'!$C$27:$H$1048576,6,0) | G7: =VLOOKUP(A7,'BNY FA Cash'!$C$27:$I$1048576,7,0) | H7: =VLOOKUP(A7,'BNY FA Cash'!$C$27:$J$1048576,8,0) | I7: =VLOOKUP(A7,'BNY FA Cash'!$C$27:$N$1048576,12,0)+VLOOKUP(A7,'BNY FA Cash'!$C$27:$T$1048576,18,0) | J7: =VLOOKUP(A7,'BNY FA Cash'!$C$27:$AA$1048576,25,0) | K7: =SUM(D7:J7) | L7: =M7-K7 | M7: =VLOOKUP(A7,'BNY FA Cash'!$C$27:$Z$1048576,24,0) | N7: =K7/M7 | O7: =ABS(J7)/M7
A8: 796950 | B8: SECR | C8: NYLI MacKay Securitized Income ETF | D8: =VLOOKUP(A8,'BNY FA Cash'!$C$27:$Y$1048576,23,0) | E8: =VLOOKUP(A8,'BNY FA Cash'!$C$27:$F$634,4,0) | F8: =VLOOKUP(A8,'BNY FA Cash'!$C$27:$H$1048576,6,0) | G8: =VLOOKUP(A8,'BNY FA Cash'!$C$27:$I$1048576,7,0) | H8: =VLOOKUP(A8,'BNY FA Cash'!$C$27:$J$1048576,8,0) | I8: =VLOOKUP(A8,'BNY FA Cash'!$C$27:$N$1048576,12,0)+VLOOKUP(A8,'BNY FA Cash'!$C$27:$T$1048576,18,0) | J8: =VLOOKUP(A8,'BNY FA Cash'!$C$27:$AA$1048576,25,0) | K8: =SUM(D8:J8) | L8: =M8-K8 | M8: =VLOOKUP(A8,'BNY FA Cash'!$C$27:$Z$1048576,24,0) | N8: =K8/M8 | O8: =ABS(J8)/M8
A9: 440519 | B9: IWLG | C9: NYLI Winslow Large Cap Growth ETF | D9: =VLOOKUP(A9,'BNY FA Cash'!$C$27:$Y$1048576,23,0) | E9: =VLOOKUP(A9,'BNY FA Cash'!$C$27:$F$634,4,0) | F9: =VLOOKUP(A9,'BNY FA Cash'!$C$27:$H$1048576,6,0) | G9: =VLOOKUP(A9,'BNY FA Cash'!$C$27:$I$1048576,7,0) | H9: =VLOOKUP(A9,'BNY FA Cash'!$C$27:$J$1048576,8,0) | I9: =VLOOKUP(A9,'BNY FA Cash'!$C$27:$N$1048576,12,0)+VLOOKUP(A9,'BNY FA Cash'!$C$27:$T$1048576,18,0) | J9: =VLOOKUP(A9,'BNY FA Cash'!$C$27:$AA$1048576,25,0) | K9: =SUM(D9:J9) | L9: =M9-K9 | M9: =VLOOKUP(A9,'BNY FA Cash'!$C$27:$Z$1048576,24,0) | N9: =K9/M9 | O9: =ABS(J9)/M9
A10: 440520 | B10: IWFG | C10: NYLI Winslow Focused Large Cap Growth ETF | D10: =VLOOKUP(A10,'BNY FA Cash'!$C$27:$Y$1048576,23,0) | E10: =VLOOKUP(A10,'BNY FA Cash'!$C$27:$F$634,4,0) | F10: =VLOOKUP(A10,'BNY FA Cash'!$C$27:$H$1048576,6,0) | G10: =VLOOKUP(A10,'BNY FA Cash'!$C$27:$I$1048576,7,0) | H10: =VLOOKUP(A10,'BNY FA Cash'!$C$27:$J$1048576,8,0) | I10: =VLOOKUP(A10,'BNY FA Cash'!$C$27:$N$1048576,12,0)+VLOOKUP(A10,'BNY FA Cash'!$C$27:$T$1048576,18,0) | J10: =VLOOKUP(A10,'BNY FA Cash'!$C$27:$AA$1048576,25,0) | K10: =SUM(D10:J10) | L10: =M10-K10 | M10: =VLOOKUP(A10,'BNY FA Cash'!$C$27:$Z$1048576,24,0) | N10: =K10/M10 | O10: =ABS(J10)/M10
A11: 9067598 | B11: MMSD | C11: NYLI MacKay Muni Short Duration ETF | D11: =VLOOKUP(A11,'BNY FA Cash'!$C$27:$Y$1048576,23,0) | E11: =VLOOKUP(A11,'BNY FA Cash'!$C$27:$F$634,4,0) | F11: =VLOOKUP(A11,'BNY FA Cash'!$C$27:$H$1048576,6,0) | G11: =VLOOKUP(A11,'BNY FA Cash'!$C$27:$I$1048576,7,0) | H11: =VLOOKUP(A11,'BNY FA Cash'!$C$27:$J$1048576,8,0) | I11: =VLOOKUP(A11,'BNY FA Cash'!$C$27:$N$1048576,12,0)+VLOOKUP(A11,'BNY FA Cash'!$C$27:$T$1048576,18,0) | J11: =VLOOKUP(A11,'BNY FA Cash'!$C$27:$AA$1048576,25,0) | K11: =SUM(D11:J11) | L11: =M11-K11 | M11: =VLOOKUP(A11,'BNY FA Cash'!$C$27:$Z$1048576,24,0) | N11: =K11/M11 | O11: =ABS(J11)/M11

Sheet (Custody) Sub-Advised
A1: Custody Acc # | B1: Account | C1: AD | D1: USD Cash | E1: Foreign CCY Cash
A2: 217661 | B2: MMCA | C2: NYLI MacKay California Muni Intermediate ETF | D2: =SUMIFS('BNY Daily Settled Cash Balance'!F:F,'BNY Daily Settled Cash Balance'!A:A,A2,'BNY Daily Settled Cash Balance'!C:C,"USD") | E2: =SUMIFS('BNY Daily Settled Cash Balance'!F:F,'BNY Daily Settled Cash Balance'!A:A,A2,'BNY Daily Settled Cash Balance'!C:C,"<>USD")
A3: 240412 | B3: IQHI | C3: NYLI MacKay ESG High Income ETF | D3: =SUMIFS('BNY Daily Settled Cash Balance'!F:F,'BNY Daily Settled Cash Balance'!A:A,A3,'BNY Daily Settled Cash Balance'!C:C,"USD") | E3: =SUMIFS('BNY Daily Settled Cash Balance'!F:F,'BNY Daily Settled Cash Balance'!A:A,A3,'BNY Daily Settled Cash Balance'!C:C,"<>USD")
A4: 682403 | B4: MMIT | C4: NYLI MacKay Muni Intermediate ETF | D4: =SUMIFS('BNY Daily Settled Cash Balance'!F:F,'BNY Daily Settled Cash Balance'!A:A,A4,'BNY Daily Settled Cash Balance'!C:C,"USD") | E4: =SUMIFS('BNY Daily Settled Cash Balance'!F:F,'BNY Daily Settled Cash Balance'!A:A,A4,'BNY Daily Settled Cash Balance'!C:C,"<>USD")
A5: 682447 | B5: MMIN | C5: NYLI MacKay Muni Insured ETF | D5: =SUMIFS('BNY Daily Settled Cash Balance'!F:F,'BNY Daily Settled Cash Balance'!A:A,A5,'BNY Daily Settled Cash Balance'!C:C,"USD") | E5: =SUMIFS('BNY Daily Settled Cash Balance'!F:F,'BNY Daily Settled Cash Balance'!A:A,A5,'BNY Daily Settled Cash Balance'!C:C,"<>USD")
A6: 943872 | B6: CPLB | C6: NYLI MacKay Core Plus Bond ETF | D6: =SUMIFS('BNY Daily Settled Cash Balance'!F:F,'BNY Daily Settled Cash Balance'!A:A,A6,'BNY Daily Settled Cash Balance'!C:C,"USD") | E6: =SUMIFS('BNY Daily Settled Cash Balance'!F:F,'BNY Daily Settled Cash Balance'!A:A,A6,'BNY Daily Settled Cash Balance'!C:C,"<>USD")
A7: 425269 | B7: IQRA | C7: NYLI CBRE Real Assets ETF | D7: =SUMIFS('BNY Daily Settled Cash Balance'!F:F,'BNY Daily Settled Cash Balance'!A:A,A7,'BNY Daily Settled Cash Balance'!C:C,"USD") | E7: =SUMIFS('BNY Daily Settled Cash Balance'!F:F,'BNY Daily Settled Cash Balance'!A:A,A7,'BNY Daily Settled Cash Balance'!C:C,"<>USD")
A8: 796950 | B8: SECR | C8: NYLI MacKay Securitized Income ETF | D8: =SUMIFS('BNY Daily Settled Cash Balance'!F:F,'BNY Daily Settled Cash Balance'!A:A,A8,'BNY Daily Settled Cash Balance'!C:C,"USD") | E8: =SUMIFS('BNY Daily Settled Cash Balance'!F:F,'BNY Daily Settled Cash Balance'!A:A,A8,'BNY Daily Settled Cash Balance'!C:C,"<>USD")
A9: 440519 | B9: IWLG | C9: NYLI Winslow Large Cap Growth ETF | D9: =SUMIFS('BNY Daily Settled Cash Balance'!F:F,'BNY Daily Settled Cash Balance'!A:A,A9,'BNY Daily Settled Cash Balance'!C:C,"USD") | E9: =SUMIFS('BNY Daily Settled Cash Balance'!F:F,'BNY Daily Settled Cash Balance'!A:A,A9,'BNY Daily Settled Cash Balance'!C:C,"<>USD")
A10: 440520 | B10: IWFG | C10: NYLI Winslow Focused Large Cap Growth ETF | D10: =SUMIFS('BNY Daily Settled Cash Balance'!F:F,'BNY Daily Settled Cash Balance'!A:A,A10,'BNY Daily Settled Cash Balance'!C:C,"USD") | E10: =SUMIFS('BNY Daily Settled Cash Balance'!F:F,'BNY Daily Settled Cash Balance'!A:A,A10,'BNY Daily Settled Cash Balance'!C:C,"<>USD")
A11: 9067598 | B11: MMSD | C11: NYLI MacKay Muni Short Duration ETF | D11: =SUMIFS('BNY Daily Settled Cash Balance'!F:F,'BNY Daily Settled Cash Balance'!A:A,A11,'BNY Daily Settled Cash Balance'!C:C,"USD") | E11: =SUMIFS('BNY Daily Settled Cash Balance'!F:F,'BNY Daily Settled Cash Balance'!A:A,A11,'BNY Daily Settled Cash Balance'!C:C,"<>USD")

Sheet (FA - Income) Sub Advised
A1: Custody Acc # | B1: Account | C1: AD | D1: Accrued Income | E1: Reclaim Rec
A2: 217661 | B2: MMCA | C2: NYLI MacKay California Muni Intermediate ETF | D2: =VLOOKUP(A2,'BNY FA Cash'!$C$27:$K$1048576,9,0) | E2: =VLOOKUP(A2,'BNY FA Cash'!$C$27:$O$1048576,13,0)
A3: 240412 | B3: IQHI | C3: NYLI MacKay ESG High Income ETF | D3: =VLOOKUP(A3,'BNY FA Cash'!$C$27:$K$1048576,9,0) | E3: =VLOOKUP(A3,'BNY FA Cash'!$C$27:$O$1048576,13,0)
A4: 682403 | B4: MMIT | C4: NYLI MacKay Muni Intermediate ETF | D4: =VLOOKUP(A4,'BNY FA Cash'!$C$27:$K$1048576,9,0) | E4: =VLOOKUP(A4,'BNY FA Cash'!$C$27:$O$1048576,13,0)
A5: 682447 | B5: MMIN | C5: NYLI MacKay Muni Insured ETF | D5: =VLOOKUP(A5,'BNY FA Cash'!$C$27:$K$1048576,9,0) | E5: =VLOOKUP(A5,'BNY FA Cash'!$C$27:$O$1048576,13,0)
A6: 943872 | B6: CPLB | C6: NYLI MacKay Core Plus Bond ETF | D6: =VLOOKUP(A6,'BNY FA Cash'!$C$27:$K$1048576,9,0) | E6: =VLOOKUP(A6,'BNY FA Cash'!$C$27:$O$1048576,13,0)
A7: 425269 | B7: IQRA | C7: NYLI CBRE Real Assets ETF | D7: =VLOOKUP(A7,'BNY FA Cash'!$C$27:$K$1048576,9,0) | E7: =VLOOKUP(A7,'BNY FA Cash'!$C$27:$O$1048576,13,0)
A8: 796950 | B8: SECR | C8: NYLI MacKay Securitized Income ETF | D8: =VLOOKUP(A8,'BNY FA Cash'!$C$27:$K$1048576,9,0) | E8: =VLOOKUP(A8,'BNY FA Cash'!$C$27:$O$1048576,13,0)
A9: 440519 | B9: IWLG | C9: NYLI Winslow Large Cap Growth ETF | D9: =VLOOKUP(A9,'BNY FA Cash'!$C$27:$K$1048576,9,0) | E9: =VLOOKUP(A9,'BNY FA Cash'!$C$27:$O$1048576,13,0)
A10: 440520 | B10: IWFG | C10: NYLI Winslow Focused Large Cap Growth ETF | D10: =VLOOKUP(A10,'BNY FA Cash'!$C$27:$K$1048576,9,0) | E10: =VLOOKUP(A10,'BNY FA Cash'!$C$27:$O$1048576,13,0)
A11: 9067598 | B11: MMSD | C11: NYLI MacKay Muni Short Duration ETF | D11: =VLOOKUP(A11,'BNY FA Cash'!$C$27:$K$1048576,9,0) | E11: =VLOOKUP(A11,'BNY FA Cash'!$C$27:$O$1048576,13,0)

Sheet BNY FA Cash

Sheet BNY Daily Settled Cash Balance

Sheet BNY Cash Projection

Sheet BNY Custody Valuation

Sheet BNY Unsettled Trades

Sheet Historical Trades
A1: SecType | B1: Portfolio | C1: TradeDate | D1: Trdr | E1: SettleDate | F1: Dest | G1: Side | H1: SecurityDesc | I1: Symbol | J1: AvgPrc | K1: Amount | L1: Done | M1: NetMoney | O1: Currency
K1871: Page 1

Sheet Historical Trades Calc
A1: SecType | B1: Portfolio | C1: TradeDate | D1: Trdr | E1: SettleDate | F1: Dest | G1: Side | H1: SecurityDesc | I1: Symbol | J1: AvgPrc | K1: Amount | L1: Done | M1: NetMoney | N1: Currency | P1: LOCAL | Q1: FX RATE | R1: USD (Zero's SPUS Type)
A2: ='Historical Trades'!A2 | B2: ='Historical Trades'!B2 | C2: ='Historical Trades'!C2 | D2: ='Historical Trades'!D2 | E2: ='Historical Trades'!E2 | F2: ='Historical Trades'!F2 | G2: ='Historical Trades'!G2 | H2: ='Historical Trades'!H2 | ... M2: ='Historical Trades'!M2 | N2: =CLEAN('Historical Trades'!O2) | P2: =IF(G2="sell",M2,-M2) | Q2: =VLOOKUP(N2,'Currency Rates'!$A$3:$C$32,3,0) | R2: =IF(A2="SPUS",0,IF(A2="FWD",0,P2/Q2))
A3: ='Historical Trades'!A3 | B3: ='Historical Trades'!B3 | C3: ='Historical Trades'!C3 | D3: ='Historical Trades'!D3 | E3: ='Historical Trades'!E3 | F3: ='Historical Trades'!F3 | G3: ='Historical Trades'!G3 | H3: ='Historical Trades'!H3 | ... M3: ='Historical Trades'!M3 | N3: =CLEAN('Historical Trades'!O3) | P3: =IF(G3="sell",M3,-M3) | Q3: =VLOOKUP(N3,'Currency Rates'!$A$3:$C$32,3,0) | R3: =IF(A3="SPUS",0,IF(A3="FWD",0,P3/Q3))
A4: ='Historical Trades'!A4 | B4: ='Historical Trades'!B4 | C4: ='Historical Trades'!C4 | D4: ='Historical Trades'!D4 | E4: ='Historical Trades'!E4 | F4: ='Historical Trades'!F4 | G4: ='Historical Trades'!G4 | H4: ='Historical Trades'!H4 | ... M4: ='Historical Trades'!M4 | N4: =CLEAN('Historical Trades'!O4) | P4: =IF(G4="sell",M4,-M4) | Q4: =VLOOKUP(N4,'Currency Rates'!$A$3:$C$32,3,0) | R4: =IF(A4="SPUS",0,IF(A4="FWD",0,P4/Q4))
A5: ='Historical Trades'!A5 | B5: ='Historical Trades'!B5 | C5: ='Historical Trades'!C5 | D5: ='Historical Trades'!D5 | E5: ='Historical Trades'!E5 | F5: ='Historical Trades'!F5 | G5: ='Historical Trades'!G5 | H5: ='Historical Trades'!H5 | ... M5: ='Historical Trades'!M5 | N5: =CLEAN('Historical Trades'!O5) | P5: =IF(G5="sell",M5,-M5) | Q5: =VLOOKUP(N5,'Currency Rates'!$A$3:$C$32,3,0) | R5: =IF(A5="SPUS",0,IF(A5="FWD",0,P5/Q5))
A6: ='Historical Trades'!A6 | B6: ='Historical Trades'!B6 | C6: ='Historical Trades'!C6 | D6: ='Historical Trades'!D6 | E6: ='Historical Trades'!E6 | F6: ='Historical Trades'!F6 | G6: ='Historical Trades'!G6 | H6: ='Historical Trades'!H6 | ... M6: ='Historical Trades'!M6 | N6: =CLEAN('Historical Trades'!O6) | P6: =IF(G6="sell",M6,-M6) | Q6: =VLOOKUP(N6,'Currency Rates'!$A$3:$C$32,3,0) | R6: =IF(A6="SPUS",0,IF(A6="FWD",0,P6/Q6))
A7: ='Historical Trades'!A7 | B7: ='Historical Trades'!B7 | C7: ='Historical Trades'!C7 | D7: ='Historical Trades'!D7 | E7: ='Historical Trades'!E7 | F7: ='Historical Trades'!F7 | G7: ='Historical Trades'!G7 | H7: ='Historical Trades'!H7 | ... M7: ='Historical Trades'!M7 | N7: =CLEAN('Historical Trades'!O7) | P7: =IF(G7="sell",M7,-M7) | Q7: =VLOOKUP(N7,'Currency Rates'!$A$3:$C$32,3,0) | R7: =IF(A7="SPUS",0,IF(A7="FWD",0,P7/Q7))
A8: ='Historical Trades'!A8 | B8: ='Historical Trades'!B8 | C8: ='Historical Trades'!C8 | D8: ='Historical Trades'!D8 | E8: ='Historical Trades'!E8 | F8: ='Historical Trades'!F8 | G8: ='Historical Trades'!G8 | H8: ='Historical Trades'!H8 | ... M8: ='Historical Trades'!M8 | N8: =CLEAN('Historical Trades'!O8) | P8: =IF(G8="sell",M8,-M8) | Q8: =VLOOKUP(N8,'Currency Rates'!$A$3:$C$32,3,0) | R8: =IF(A8="SPUS",0,IF(A8="FWD",0,P8/Q8))
A9: ='Historical Trades'!A9 | B9: ='Historical Trades'!B9 | C9: ='Historical Trades'!C9 | D9: ='Historical Trades'!D9 | E9: ='Historical Trades'!E9 | F9: ='Historical Trades'!F9 | G9: ='Historical Trades'!G9 | H9: ='Historical Trades'!H9 | ... M9: ='Historical Trades'!M9 | N9: =CLEAN('Historical Trades'!O9) | P9: =IF(G9="sell",M9,-M9) | Q9: =VLOOKUP(N9,'Currency Rates'!$A$3:$C$32,3,0) | R9: =IF(A9="SPUS",0,IF(A9="FWD",0,P9/Q9))
A10: ='Historical Trades'!A10 | B10: ='Historical Trades'!B10 | C10: ='Historical Trades'!C10 | D10: ='Historical Trades'!D10 | E10: ='Historical Trades'!E10 | F10: ='Historical Trades'!F10 | G10: ='Historical Trades'!G10 | H10: ='Historical Trades'!H10 | ... M10: ='Historical Trades'!M10 | N10: =CLEAN('Historical Trades'!O10) | P10: =IF(G10="sell",M10,-M10) | Q10: =VLOOKUP(N10,'Currency Rates'!$A$3:$C$32,3,0) | R10: =IF(A10="SPUS",0,IF(A10="FWD",0,P10/Q10))
A11: ='Historical Trades'!A11 | B11: ='Historical Trades'!B11 | C11: ='Historical Trades'!C11 | D11: ='Historical Trades'!D11 | E11: ='Historical Trades'!E11 | F11: ='Historical Trades'!F11 | G11: ='Historical Trades'!G11 | H11: ='Historical Trades'!H11 | ... M11: ='Historical Trades'!M11 | N11: =CLEAN('Historical Trades'!O11) | P11: =IF(G11="sell",M11,-M11) | Q11: =VLOOKUP(N11,'Currency Rates'!$A$3:$C$32,3,0) | R11: =IF(A11="SPUS",0,IF(A11="FWD",0,P11/Q11))
A12: ='Historical Trades'!A12 | B12: ='Historical Trades'!B12 | C12: ='Historical Trades'!C12 | D12: ='Historical Trades'!D12 | E12: ='Historical Trades'!E12 | F12: ='Historical Trades'!F12 | G12: ='Historical Trades'!G12 | H12: ='Historical Trades'!H12 | ... M12: ='Historical Trades'!M12 | N12: =CLEAN('Historical Trades'!O12) | P12: =IF(G12="sell",M12,-M12) | Q12: =VLOOKUP(N12,'Currency Rates'!$A$3:$C$32,3,0) | R12: =IF(A12="SPUS",0,IF(A12="FWD",0,P12/Q12))
A13: ='Historical Trades'!A13 | B13: ='Historical Trades'!B13 | C13: ='Historical Trades'!C13 | D13: ='Historical Trades'!D13 | E13: ='Historical Trades'!E13 | F13: ='Historical Trades'!F13 | G13: ='Historical Trades'!G13 | H13: ='Historical Trades'!H13 | ... M13: ='Historical Trades'!M13 | N13: =CLEAN('Historical Trades'!O13) | P13: =IF(G13="sell",M13,-M13) | Q13: =VLOOKUP(N13,'Currency Rates'!$A$3:$C$32,3,0) | R13: =IF(A13="SPUS",0,IF(A13="FWD",0,P13/Q13))
... A176: ='Historical Trades'!A176 | B176: ='Historical Trades'!B176 | C176: ='Historical Trades'!C176 | D176: ='Historical Trades'!D176 | E176: ='Historical Trades'!E176 | F176: ='Historical Trades'!F176 | G176: ='Historical Trades'!G176 | H176: ='Historical Trades'!H176 | ... M176: ='Historical Trades'!M176 | N176: =CLEAN('Historical Trades'!O176) | P176: =IF(G176="sell",M176,-M176) | Q176: =VLOOKUP(N176,'Currency Rates'!$A$3:$C$32,3,0) | R176: =IF(A176="SPUS",0,IF(A176="FWD",0,P176/Q176))
A177: ='Historical Trades'!A177 | B177: ='Historical Trades'!B177 | C177: ='Historical Trades'!C177 | D177: ='Historical Trades'!D177 | E177: ='Historical Trades'!E177 | F177: ='Historical Trades'!F177 | G177: ='Historical Trades'!G177 | H177: ='Historical Trades'!H177 | ... M177: ='Historical Trades'!M177 | N177: =CLEAN('Historical Trades'!O177) | P177: =IF(G177="sell",M177,-M177) | Q177: =VLOOKUP(N177,'Currency Rates'!$A$3:$C$32,3,0) | R177: =IF(A177="SPUS",0,IF(A177="FWD",0,P177/Q177)) | S177: =L177*50*I177
A178: ='Historical Trades'!A178 | B178: ='Historical Trades'!B178 | C178: ='Historical Trades'!C178 | D178: ='Historical Trades'!D178 | E178: ='Historical Trades'!E178 | F178: ='Historical Trades'!F178 | G178: ='Historical Trades'!G178 | H178: ='Historical Trades'!H178 | ... M178: ='Historical Trades'!M178 | N178: =CLEAN('Historical Trades'!O178) | P178: =IF(G178="sell",M178,-M178) | Q178: =VLOOKUP(N178,'Currency Rates'!$A$3:$C$32,3,0) | R178: =IF(A178="SPUS",0,IF(A178="FWD",0,P178/Q178))
A179: ='Historical Trades'!A179 | B179: ='Historical Trades'!B179 | C179: ='Historical Trades'!C179 | D179: ='Historical Trades'!D179 | E179: ='Historical Trades'!E179 | F179: ='Historical Trades'!F179 | G179: ='Historical Trades'!G179 | H179: ='Historical Trades'!H179 | ... M179: ='Historical Trades'!M179 | N179: =CLEAN('Historical Trades'!O179) | P179: =IF(G179="sell",M179,-M179) | Q179: =VLOOKUP(N179,'Currency Rates'!$A$3:$C$32,3,0) | R179: =IF(A179="SPUS",0,IF(A179="FWD",0,P179/Q179))
A180: ='Historical Trades'!A180 | B180: ='Historical Trades'!B180 | C180: ='Historical Trades'!C180 | D180: ='Historical Trades'!D180 | E180: ='Historical Trades'!E180 | F180: ='Historical Trades'!F180 | G180: ='Historical Trades'!G180 | H180: ='Historical Trades'!H180 | ... M180: ='Historical Trades'!M180 | N180: =CLEAN('Historical Trades'!O180) | P180: =IF(G180="sell",M180,-M180) | Q180: =VLOOKUP(N180,'Currency Rates'!$A$3:$C$32,3,0) | R180: =IF(A180="SPUS",0,IF(A180="FWD",0,P180/Q180))
A181: ='Historical Trades'!A181 | B181: ='Historical Trades'!B181 | C181: ='Historical Trades'!C181 | D181: ='Historical Trades'!D181 | E181: ='Historical Trades'!E181 | F181: ='Historical Trades'!F181 | G181: ='Historical Trades'!G181 | H181: ='Historical Trades'!H181 | ... M181: ='Historical Trades'!M181 | N181: =CLEAN('Historical Trades'!O181) | P181: =IF(G181="sell",M181,-M181) | Q181: =VLOOKUP(N181,'Currency Rates'!$A$3:$C$32,3,0) | R181: =IF(A181="SPUS",0,IF(A181="FWD",0,P181/Q181))
A182: ='Historical Trades'!A182 | B182: ='Historical Trades'!B182 | C182: ='Historical Trades'!C182 | D182: ='Historical Trades'!D182 | E182: ='Historical Trades'!E182 | F182: ='Historical Trades'!F182 | G182: ='Historical Trades'!G182 | H182: ='Historical Trades'!H182 | ... M182: ='Historical Trades'!M182 | N182: =CLEAN('Historical Trades'!O182) | P182: =IF(G182="sell",M182,-M182) | Q182: =VLOOKUP(N182,'Currency Rates'!$A$3:$C$32,3,0) | R182: =IF(A182="SPUS",0,IF(A182="FWD",0,P182/Q182))
A183: ='Historical Trades'!A183 | B183: ='Historical Trades'!B183 | C183: ='Historical Trades'!C183 | D183: ='Historical Trades'!D183 | E183: ='Historical Trades'!E183 | F183: ='Historical Trades'!F183 | G183: ='Historical Trades'!G183 | H183: ='Historical Trades'!H183 | ... M183: ='Historical Trades'!M183 | N183: =CLEAN('Historical Trades'!O183) | P183: =IF(G183="sell",M183,-M183) | Q183: =VLOOKUP(N183,'Currency Rates'!$A$3:$C$32,3,0) | R183: =IF(A183="SPUS",0,IF(A183="FWD",0,P183/Q183))
A184: ='Historical Trades'!A184 | B184: ='Historical Trades'!B184 | C184: ='Historical Trades'!C184 | D184: ='Historical Trades'!D184 | E184: ='Historical Trades'!E184 | F184: ='Historical Trades'!F184 | G184: ='Historical Trades'!G184 | H184: ='Historical Trades'!H184 | ... M184: ='Historical Trades'!M184 | N184: =CLEAN('Historical Trades'!O184) | P184: =IF(G184="sell",M184,-M184) | Q184: =VLOOKUP(N184,'Currency Rates'!$A$3:$C$32,3,0) | R184: =IF(A184="SPUS",0,IF(A184="FWD",0,P184/Q184))
A185: ='Historical Trades'!A185 | B185: ='Historical Trades'!B185 | C185: ='Historical Trades'!C185 | D185: ='Historical Trades'!D185 | E185: ='Historical Trades'!E185 | F185: ='Historical Trades'!F185 | G185: ='Historical Trades'!G185 | H185: ='Historical Trades'!H185 | ... M185: ='Historical Trades'!M185 | N185: =CLEAN('Historical Trades'!O185) | P185: =IF(G185="sell",M185,-M185) | Q185: =VLOOKUP(N185,'Currency Rates'!$A$3:$C$32,3,0) | R185: =IF(A185="SPUS",0,IF(A185="FWD",0,P185/Q185))
A186: ='Historical Trades'!A186 | B186: ='Historical Trades'!B186 | C186: ='Historical Trades'!C186 | D186: ='Historical Trades'!D186 | E186: ='Historical Trades'!E186 | F186: ='Historical Trades'!F186 | G186: ='Historical Trades'!G186 | H186: ='Historical Trades'!H186 | ... M186: ='Historical Trades'!M186 | N186: =CLEAN('Historical Trades'!O186) | P186: =IF(G186="sell",M186,-M186) | Q186: =VLOOKUP(N186,'Currency Rates'!$A$3:$C$32,3,0) | R186: =IF(A186="SPUS",0,IF(A186="FWD",0,P186/Q186))
A187: ='Historical Trades'!A187 | B187: ='Historical Trades'!B187 | C187: ='Historical Trades'!C187 | D187: ='Historical Trades'!D187 | E187: ='Historical Trades'!E187 | F187: ='Historical Trades'!F187 | G187: ='Historical Trades'!G187 | H187: ='Historical Trades'!H187 | ... M187: ='Historical Trades'!M187 | N187: =CLEAN('Historical Trades'!O187) | P187: =IF(G187="sell",M187,-M187) | Q187: =VLOOKUP(N187,'Currency Rates'!$A$3:$C$32,3,0) | R187: =IF(A187="SPUS",0,IF(A187="FWD",0,P187/Q187))
A188: ='Historical Trades'!A188 | B188: ='Historical Trades'!B188 | C188: ='Historical Trades'!C188 | D188: ='Historical Trades'!D188 | E188: ='Historical Trades'!E188 | F188: ='Historical Trades'!F188 | G188: ='Historical Trades'!G188 | H188: ='Historical Trades'!H188 | ... M188: ='Historical Trades'!M188 | N188: =CLEAN('Historical Trades'!O188) | P188: =IF(G188="sell",M188,-M188) | Q188: =VLOOKUP(N188,'Currency Rates'!$A$3:$C$32,3,0) | R188: =IF(A188="SPUS",0,IF(A188="FWD",0,P188/Q188))
A189: ='Historical Trades'!A189 | B189: ='Historical Trades'!B189 | C189: ='Historical Trades'!C189 | D189: ='Historical Trades'!D189 | E189: ='Historical Trades'!E189 | F189: ='Historical Trades'!F189 | G189: ='Historical Trades'!G189 | H189: ='Historical Trades'!H189 | ... M189: ='Historical Trades'!M189 | N189: =CLEAN('Historical Trades'!O189) | P189: =IF(G189="sell",M189,-M189) | Q189: =VLOOKUP(N189,'Currency Rates'!$A$3:$C$32,3,0) | R189: =IF(A189="SPUS",0,IF(A189="FWD",0,P189/Q189))
... A8740: ='Historical Trades'!A8740 | B8740: ='Historical Trades'!B8740 | C8740: ='Historical Trades'!C8740 | D8740: ='Historical Trades'!D8740 | E8740: ='Historical Trades'!E8740 | F8740: ='Historical Trades'!F8740 | G8740: ='Historical Trades'!G8740 | H8740: ='Historical Trades'!H8740 | ... M8740: ='Historical Trades'!M8740 | N8740: =CLEAN('Historical Trades'!O8740) | P8740: =IF(G8740="sell",M8740,-M8740) | Q8740: =VLOOKUP(N8740,'Currency Rates'!$A$3:$C$32,3,0) | R8740: =IF(A8740="SPUS",0,IF(A8740="FWD",0,P8740/Q8740))

Sheet Currency Rates
B1: Pulling in Fixing rates to get USD estimate
A2: Currency | B2: BB London 4:00pm Fixing | C2: Rates for Eze File
A3: AUD | B3: =_xll.BDP(A3&" L160 Curncy","PX_LAST") | C3: =1/B3
A4: BRL | B4: =_xll.BDP(A4&" L160 Curncy","PX_LAST") | C4: =B4
A5: CAD | B5: =_xll.BDP(A5&" L160 Curncy","PX_LAST") | C5: =B5
A6: CHF | B6: =_xll.BDP(A6&" L160 Curncy","PX_LAST") | C6: =B6
A7: CLP | B7: =_xll.BDP(A7&" L160 Curncy","PX_LAST") | C7: =B7
A8: COP | B8: =_xll.BDP(A8&" L160 Curncy","PX_LAST") | C8: =B8
A9: CZK | B9: =_xll.BDP(A9&" L160 Curncy","PX_LAST") | C9: =B9
A10: DKK | B10: =_xll.BDP(A10&" L160 Curncy","PX_LAST") | C10: =B10
A11: EUR | B11: =_xll.BDP(A11&" L160 Curncy","PX_LAST") | C11: =1/B11
A12: GBP | B12: =_xll.BDP(A12&" L160 Curncy","PX_LAST") | C12: =1/B12
A13: HKD | B13: =_xll.BDP(A13&" L160 Curncy","PX_LAST") | C13: =B13
A14: HUF | B14: =_xll.BDP(A14&" L160 Curncy","PX_LAST") | C14: =B14
A15: IDR | B15: =_xll.BDP(A15&" L160 Curncy","PX_LAST") | C15: =B15
A16: ILS | B16: =_xll.BDP(A16&" L160 Curncy","PX_LAST") | C16: =B16
A17: INR | B17: =_xll.BDP(A17&" L160 Curncy","PX_LAST") | C17: =B17
A18: JPY | B18: =_xll.BDP(A18&" L160 Curncy","PX_LAST") | C18: =B18
A19: KRW | B19: =_xll.BDP(A19&" L160 Curncy","PX_LAST") | C19: =B19
A20: MXN | B20: =_xll.BDP(A20&" L160 Curncy","PX_LAST") | C20: =B20
A21: MYR | B21: =_xll.BDP(A21&" L160 Curncy","PX_LAST") | C21: =B21
A22: NOK | B22: =_xll.BDP(A22&" L160 Curncy","PX_LAST") | C22: =B22
A23: NZD | B23: =_xll.BDP(A23&" L160 Curncy","PX_LAST") | C23: =1/B23
A24: PHP | B24: =_xll.BDP(A24&" L160 Curncy","PX_LAST") | C24: =B24
A25: PLN | B25: =_xll.BDP(A25&" L160 Curncy","PX_LAST") | C25: =B25
A26: SEK | B26: =_xll.BDP(A26&" L160 Curncy","PX_LAST") | C26: =B26
A27: SGD | B27: =_xll.BDP(A27&" L160 Curncy","PX_LAST") | C27: =B27
A28: THB | B28: =_xll.BDP(A28&" L160 Curncy","PX_LAST") | C28: =B28
A29: TWD | B29: =_xll.BDP(A29&" L160 Curncy","PX_LAST") | C29: =B29
A30: ZAR | B30: =_xll.BDP(A30&" L160 Curncy","PX_LAST") | C30: =B30
A31: TRY | B31: =_xll.BDP(A31&" L160 Curncy","PX_LAST") | C31: =B31
A32: USD | B32: =_xll.BDP(A32&" L160 Curncy","PX_LAST") | C32: 1

Sheet VP FA Holdings

Sheet VP Proj Cash Statement (8am)

Sheet VP Proj Cash Detail (10am)

Sheet VP Priced Positions

Sheet VP Outstanding Trades
