Workbook
Name ifs: #REF!
Name ifs: 'JP Code_Sheet'!$N$3
Name sumif: #REF!
Name sumif: 'JP Code_Sheet'!$N$3

Sheet JP_POSTED CASH_Detail
A1: Report Name: Posted Cash - Detail | C1: (Sent to passive:RANCIS VARIATION MARGIN CHECK:~7:30am) | D1: Use Second TAB
A2: From Date: 24-Jan-2023 To Date: 24-Jan-2023
A3: Run ID: S-641-061-435
A5: Cash Account Number | B5: Posted Date | C5: Transaction Group Description | D5: Account Number | E5: Security Name | F5: Transaction Number | G5: Transaction Category Description | H5: Transaction Status Description | I5: Account Name | J5: Cash Account Name | K5: Cash Account CCY Code | L5: Linked Custody Account | M5: Location/Nominee Code | N5: Location/Nominee Name | O5: Reg./Sub Acct Code | P5: Reg./Sub Acct Name | Q5: ASDA/CSDA | R5: Collection Status Description | S5: Customer Reference 1 | T5: Customer Reference 2 | U5: Income Reference | V5: Transaction Type Description | W5: Asset Type Description | X5: Asset Category Description | Y5: Security ID | Z5: Coupon Rate | AA5: Maturity Date | AB5: Pool Number | AC5: ISIN | AD5: Ticker | AE5: Units | AF5: Current Face | AG5: Price | AH5: Gross Amount | AI5: Gross Amount CCY Code | AJ5: Principal Amount | AK5: Income Amount | AL5: Commission | AM5: Commission CCY Code | AN5: Other Charges | AO5: UK Withholding Tax | AP5: UK Withholding Tax CCY Code | AQ5: Non UK Withholding Tax | AR5: Non UK Withholding Tax CCY Code | AS5: Source Tax/NRA | AT5: Source Tax/NRA CCY Code | AU5: Net Amount | AV5: Exchange Rate | AW5: Trade Date | AX5: Contractual S/D | AY5: Autosettle Date | AZ5: Ex Date | BA5: Record Date | BB5: Payable Date | BC5: Value Date | BD5: Last Update Date | BE5: Last Update Time | BF5: Dividend/Interest Rate | BG5: UK Withholding Rate | BH5: Non UK Withholding Rate | BI5: Source Tax/NRA Rate | BJ5: Factor | BK5: Previous Factor | BL5: Principal MOF | BM5: Interest MOF | BN5: Trading Broker Number | BO5: Trading Broker Name | BP5: Clearing Broker Number | BQ5: Clearing Broker Name | BR5: Additional Information | BS5: Bank Reference Number | BT5: By Order Of | BU5: Sending/Receiving Bank | BV5: OCC ID | BW5: S and P CUSIP | BX5: NIL Payment/Unknown Rate | BY5: Branch Code | BZ5: Branch Name | CA5: DGSD Eligible

Sheet JP_Cash Projection - Statement
A1: Cash Projections - Statement | B1: INTRADAY (RUN at 9:00)
A2: As Of Date: 14-Jun-2022
A3: Run ID: D-628-797-558
A5: Cash Account CCY Code | B5: Cash Account Number (Balance) | C5: Account Number (Balance) | D5: Account Name (Balance) | E5: Projected Date | F5: Net Opening Cash Balance | G5: Sweep Balance | H5: Total Settled Amount | I5: Total Projected Amount | J5: Projected Ending Balance | K5: Cash Account Name (Balance) | L5: Settled Purchases | M5: Settled Sales | N5: Settled Securities Lending | O5: Settled Dividend Payments | P5: Settled Interest Payments | Q5: Settled Principal Payments | R5: Settled Combined P and I | S5: Settled Maturities/RDM | T5: Settled Corporate Actions | U5: Settled Options/Futures | V5: Settled Miscellaneous | W5: Settled Receipts | X5: Settled Disbursements | Y5: Projected Purchases | Z5: Projected Sales | AA5: Projected Securities Lending | AB5: Projected Dividend Payments | AC5: Projected Interest Payments | AD5: Projected Principal Payments | AE5: Projected Combined P and I | AF5: Projected Maturities/RDM | AG5: Projected Corporate Actions | AH5: Projected Options/Futures | AI5: Projected Miscellaneous | AJ5: Projected Receipts | AK5: Projected Disbursements | AL5: Branch Code | AM5: Branch Name

Sheet JP_Cash Projection - Detail
A1: Cash Projections - Detail | B1: INTRADAY (RUN at 10:00)
A2: As Of Date: 14-Jun-2022
A3: Run ID: D-628-797-558
A5: Cash Account CCY Code | B5: Cash Account Number | C5: Transaction Group Description | D5: Transaction Status Description | E5: Projected Date | F5: Security Name | G5: Transaction Number | H5: Transaction Category Description | I5: Account Number | J5: Account Name | K5: Cash Account Name | L5: Linked Custody Account | M5: Location/Nominee Code | N5: Location/Nominee Name | O5: Reg./Sub Acct Code | P5: Reg./Sub Acct Name | Q5: ASDA/CSDA | R5: Matched | S5: Collection Status Description | T5: Customer Reference 1 | U5: Customer Reference 2 | V5: Income Reference | W5: Transaction Type Description | X5: Asset Type Description | Y5: Asset Category Description | Z5: Security ID | AA5: Coupon Rate | AB5: Maturity Date | AC5: Pool Number | AD5: ISIN | AE5: Ticker | AF5: Units | AG5: Current Face | AH5: Price | AI5: Gross Amount | AJ5: Gross Amount CCY Code | AK5: Principal Amount | AL5: Income Amount | AM5: Commission | AN5: Commission CCY Code | AO5: Other Charges | AP5: UK Withholding Tax | AQ5: UK Withholding Tax CCY Code | AR5: Non UK Withholding Tax | AS5: Non UK Withholding Tax CCY Code | AT5: Source Tax/NRA | AU5: Source Tax/NRA CCY Code | AV5: Net Amount | AW5: Exchange Rate | AX5: Trade Date | AY5: Contractual S/D | AZ5: Posted Date | BA5: Autosettle Date | BB5: Ex Date | BC5: Record Date | BD5: Payable Date | BE5: Value Date | BF5: Last Update Date | BG5: Last Update Time | BH5: Creation Date | BI5: Dividend/Interest Rate | BJ5: UK Withholding Rate | BK5: Non UK Withholding Rate | BL5: Source Tax/NRA Rate | BM5: Factor | BN5: Previous Factor | BO5: Principal MOF | BP5: Interest MOF | BQ5: Trading Broker Number | BR5: Trading Broker Name | BS5: Clearing Broker Number | BT5: Clearing Broker Name | BU5: Additional Information | BV5: Bank Reference Number | BW5: Sending/Receiving Bank | BX5: By Order Of | BY5: OCC ID | BZ5: S and P CUSIP | CA5: NIL Payment/Unknown Rate | CB5: Branch Code | CC5: Branch Name

Sheet JP_Priced Positions_custody
A1: Priced Positions | C1: INTRADAY (RUN at 9:00)
A2: As Of Date: 14-Jun-2022
A3: Run ID: D-628-813-198
A5: Account Number | B5: Cash Account CCY Code | C5: Cash Account Number | D5: Security Name | E5: Location Nominee Code | F5: Reg./Sub Acct Code | G5: Account Name | H5: Linked Custody Account | I5: Cash Account Name | J5: Last Update Date | K5: Asset Type Description | L5: Asset Category Description | M5: Security ID | N5: ISIN | O5: Ticker | P5: Coupon Rate | Q5: Dated Date | R5: Maturity Date | S5: Pool Number | T5: Awaiting Receipt | U5: Awaiting Delivery | V5: In Transit (US) | W5: At Registrar (Glbl) | X5: On Loan | Y5: Pledged (US) | Z5: Available | AA5: Settled Units | AB5: Current Face (Settled) | AC5: Total Units | AD5: Current Face (Total) | AE5: Nominal Value | AF5: Blocked Quantity | AG5: Local Currency | AH5: Market Price | AI5: Price Date | AJ5: Settled Market Value (Local) | AK5: Total Market Value (Local) | AL5: Base Currency | AM5: Exchange Rate | AN5: Settled Market Value (Base) | AO5: Total Market Value (Base) | AP5: Factor | AQ5: Factor Date | AR5: Previous Factor | AS5: Country Code | AT5: Country Description | AU5: Location Nominee Name | AV5: Reg./Sub Acct Name | AW5: Sub Account Type Description | AX5: Location/Nominee Country Code | AY5: Location/Nominee Country Name | AZ5: OCC ID | BA5: S and P CUSIP | BB5: Public CUSIP | BC5: Branch Code | BD5: Branch Name | BE5: DGSD Eligible

Sheet JP_Outstanding Trades
A1: Outstanding Trades
A2: From Date: 17-Jun-2022 To Date: 17-Jun-2022 | B2: INTRA_DAY | C2: Exlcude todays trades
A3: Run ID: D-629-027-467
A5: Account Number | B5: Contractual S/D | C5: Net Amount CCY Code | D5: Transaction Category Description | E5: Transaction Status Description | F5: Account Name | G5: Security ID | H5: ISIN | I5: OCC ID | J5: Security Name | K5: Coupon Rate | L5: Maturity Date | M5: Pool Number | N5: Fail Description | O5: Transaction Type Description | P5: Age (Days) | Q5: Transaction Number | R5: Trading Broker Name | S5: Trade Date | T5: Autosettle Date | U5: Units | V5: Current Face | W5: Net Amount | X5: Elective Event Impact

Sheet Previous Trades Import_OMS Quer
A1: SecType | B1: Portfolio | C1: TradeDate | D1: Trdr | E1: SettleDate | F1: Dest | G1: Side | H1: SecurityDesc | I1: Symbol | J1: AvgPrc | K1: Amount | L1: Done | M1: NetMoney | N1: Note | O1: Currency

Sheet Previous Trade Calc
A1: SecType | B1: Portfolio | C1: TradeDate | D1: Trdr | E1: SettleDate | F1: Dest | G1: Side | H1: SecurityDesc | I1: Symbol | J1: AvgPrc | K1: Amount | L1: Done | M1: NetMoney | N1: Note | O1: Currency | Q1: LOCAL | R1: FX RATE | S1: USD
A2: ='Previous Trades Import_OMS Quer'!A2 -> 0 | B2: ='Previous Trades Import_OMS Quer'!B2 -> 0 | C2: ='Previous Trades Import_OMS Quer'!C2 -> 0 | D2: ='Previous Trades Import_OMS Quer'!D2 -> 0 | E2: ='Previous Trades Import_OMS Quer'!E2 -> 0 | F2: ='Previous Trades Import_OMS Quer'!F2 -> 0 | G2: ='Previous Trades Import_OMS Quer'!G2 -> 0 | H2: ='Previous Trades Import_OMS Quer'!H2 -> 0 | ... N2: ='Previous Trades Import_OMS Quer'!N2 -> 0 | O2: =CLEAN('Previous Trades Import_OMS Quer'!O2) | Q2: =IF(G2="sell",M2,-M2) -> 0 | R2: =VLOOKUP(O2,'Currency Balance'!$O$3:$Q$32,3,0) -> #N/A | S2: =Q2/R2 -> #N/A
A3: ='Previous Trades Import_OMS Quer'!A3 -> 0 | B3: ='Previous Trades Import_OMS Quer'!B3 -> 0 | C3: ='Previous Trades Import_OMS Quer'!C3 -> 0 | D3: ='Previous Trades Import_OMS Quer'!D3 -> 0 | E3: ='Previous Trades Import_OMS Quer'!E3 -> 0 | F3: ='Previous Trades Import_OMS Quer'!F3 -> 0 | G3: ='Previous Trades Import_OMS Quer'!G3 -> 0 | H3: ='Previous Trades Import_OMS Quer'!H3 -> 0 | ... N3: ='Previous Trades Import_OMS Quer'!N3 -> 0 | O3: =CLEAN('Previous Trades Import_OMS Quer'!O3) | Q3: =IF(G3="sell",M3,-M3) -> 0 | R3: =VLOOKUP(O3,'Currency Balance'!$O$3:$Q$32,3,0) -> #N/A | S3: =Q3/R3 -> #N/A
A4: ='Previous Trades Import_OMS Quer'!A4 -> 0 | B4: ='Previous Trades Import_OMS Quer'!B4 -> 0 | C4: ='Previous Trades Import_OMS Quer'!C4 -> 0 | D4: ='Previous Trades Import_OMS Quer'!D4 -> 0 | E4: ='Previous Trades Import_OMS Quer'!E4 -> 0 | F4: ='Previous Trades Import_OMS Quer'!F4 -> 0 | G4: ='Previous Trades Import_OMS Quer'!G4 -> 0 | H4: ='Previous Trades Import_OMS Quer'!H4 -> 0 | ... N4: ='Previous Trades Import_OMS Quer'!N4 -> 0 | O4: =CLEAN('Previous Trades Import_OMS Quer'!O4) | Q4: =IF(G4="sell",M4,-M4) -> 0 | R4: =VLOOKUP(O4,'Currency Balance'!$O$3:$Q$32,3,0) -> #N/A | S4: =Q4/R4 -> #N/A
A5: ='Previous Trades Import_OMS Quer'!A5 -> 0 | B5: ='Previous Trades Import_OMS Quer'!B5 -> 0 | C5: ='Previous Trades Import_OMS Quer'!C5 -> 0 | D5: ='Previous Trades Import_OMS Quer'!D5 -> 0 | E5: ='Previous Trades Import_OMS Quer'!E5 -> 0 | F5: ='Previous Trades Import_OMS Quer'!F5 -> 0 | G5: ='Previous Trades Import_OMS Quer'!G5 -> 0 | H5: ='Previous Trades Import_OMS Quer'!H5 -> 0 | ... N5: ='Previous Trades Import_OMS Quer'!N5 -> 0 | O5: =CLEAN('Previous Trades Import_OMS Quer'!O5) | Q5: =IF(G5="sell",M5,-M5) -> 0 | R5: =VLOOKUP(O5,'Currency Balance'!$O$3:$Q$32,3,0) -> #N/A | S5: =Q5/R5 -> #N/A
A6: ='Previous Trades Import_OMS Quer'!A6 -> 0 | B6: ='Previous Trades Import_OMS Quer'!B6 -> 0 | C6: ='Previous Trades Import_OMS Quer'!C6 -> 0 | D6: ='Previous Trades Import_OMS Quer'!D6 -> 0 | E6: ='Previous Trades Import_OMS Quer'!E6 -> 0 | F6: ='Previous Trades Import_OMS Quer'!F6 -> 0 | G6: ='Previous Trades Import_OMS Quer'!G6 -> 0 | H6: ='Previous Trades Import_OMS Quer'!H6 -> 0 | ... N6: ='Previous Trades Import_OMS Quer'!N6 -> 0 | O6: =CLEAN('Previous Trades Import_OMS Quer'!O6) | Q6: =IF(G6="sell",M6,-M6) -> 0 | R6: =VLOOKUP(O6,'Currency Balance'!$O$3:$Q$32,3,0) -> #N/A | S6: =Q6/R6 -> #N/A
A7: ='Previous Trades Import_OMS Quer'!A7 -> 0 | B7: ='Previous Trades Import_OMS Quer'!B7 -> 0 | C7: ='Previous Trades Import_OMS Quer'!C7 -> 0 | D7: ='Previous Trades Import_OMS Quer'!D7 -> 0 | E7: ='Previous Trades Import_OMS Quer'!E7 -> 0 | F7: ='Previous Trades Import_OMS Quer'!F7 -> 0 | G7: ='Previous Trades Import_OMS Quer'!G7 -> 0 | H7: ='Previous Trades Import_OMS Quer'!H7 -> 0 | ... N7: ='Previous Trades Import_OMS Quer'!N7 -> 0 | O7: =CLEAN('Previous Trades Import_OMS Quer'!O7) | Q7: =IF(G7="sell",M7,-M7) -> 0 | R7: =VLOOKUP(O7,'Currency Balance'!$O$3:$Q$32,3,0) -> #N/A | S7: =Q7/R7 -> #N/A
A8: ='Previous Trades Import_OMS Quer'!A8 -> 0 | B8: ='Previous Trades Import_OMS Quer'!B8 -> 0 | C8: ='Previous Trades Import_OMS Quer'!C8 -> 0 | D8: ='Previous Trades Import_OMS Quer'!D8 -> 0 | E8: ='Previous Trades Import_OMS Quer'!E8 -> 0 | F8: ='Previous Trades Import_OMS Quer'!F8 -> 0 | G8: ='Previous Trades Import_OMS Quer'!G8 -> 0 | H8: ='Previous Trades Import_OMS Quer'!H8 -> 0 | ... N8: ='Previous Trades Import_OMS Quer'!N8 -> 0 | O8: =CLEAN('Previous Trades Import_OMS Quer'!O8) | Q8: =IF(G8="sell",M8,-M8) -> 0 | R8: =VLOOKUP(O8,'Currency Balance'!$O$3:$Q$32,3,0) -> #N/A | S8: =Q8/R8 -> #N/A
A9: ='Previous Trades Import_OMS Quer'!A9 -> 0 | B9: ='Previous Trades Import_OMS Quer'!B9 -> 0 | C9: ='Previous Trades Import_OMS Quer'!C9 -> 0 | D9: ='Previous Trades Import_OMS Quer'!D9 -> 0 | E9: ='Previous Trades Import_OMS Quer'!E9 -> 0 | F9: ='Previous Trades Import_OMS Quer'!F9 -> 0 | G9: ='Previous Trades Import_OMS Quer'!G9 -> 0 | H9: ='Previous Trades Import_OMS Quer'!H9 -> 0 | ... N9: ='Previous Trades Import_OMS Quer'!N9 -> 0 | O9: =CLEAN('Previous Trades Import_OMS Quer'!O9) | Q9: =IF(G9="sell",M9,-M9) -> 0 | R9: =VLOOKUP(O9,'Currency Balance'!$O$3:$Q$32,3,0) -> #N/A | S9: =Q9/R9 -> #N/A
A10: ='Previous Trades Import_OMS Quer'!A10 -> 0 | B10: ='Previous Trades Import_OMS Quer'!B10 -> 0 | C10: ='Previous Trades Import_OMS Quer'!C10 -> 0 | D10: ='Previous Trades Import_OMS Quer'!D10 -> 0 | E10: ='Previous Trades Import_OMS Quer'!E10 -> 0 | F10: ='Previous Trades Import_OMS Quer'!F10 -> 0 | G10: ='Previous Trades Import_OMS Quer'!G10 -> 0 | H10: ='Previous Trades Import_OMS Quer'!H10 -> 0 | ... N10: ='Previous Trades Import_OMS Quer'!N10 -> 0 | O10: =CLEAN('Previous Trades Import_OMS Quer'!O10) | Q10: =IF(G10="sell",M10,-M10) -> 0 | R10: =VLOOKUP(O10,'Currency Balance'!$O$3:$Q$32,3,0) -> #N/A | S10: =Q10/R10 -> #N/A
A11: ='Previous Trades Import_OMS Quer'!A11 -> 0 | B11: ='Previous Trades Import_OMS Quer'!B11 -> 0 | C11: ='Previous Trades Import_OMS Quer'!C11 -> 0 | D11: ='Previous Trades Import_OMS Quer'!D11 -> 0 | E11: ='Previous Trades Import_OMS Quer'!E11 -> 0 | F11: ='Previous Trades Import_OMS Quer'!F11 -> 0 | G11: ='Previous Trades Import_OMS Quer'!G11 -> 0 | H11: ='Previous Trades Import_OMS Quer'!H11 -> 0 | ... N11: ='Previous Trades Import_OMS Quer'!N11 -> 0 | O11: =CLEAN('Previous Trades Import_OMS Quer'!O11) | Q11: =IF(G11="sell",M11,-M11) -> 0 | R11: =VLOOKUP(O11,'Currency Balance'!$O$3:$Q$32,3,0) -> #N/A | S11: =Q11/R11 -> #N/A
A12: ='Previous Trades Import_OMS Quer'!A12 -> 0 | B12: ='Previous Trades Import_OMS Quer'!B12 -> 0 | C12: ='Previous Trades Import_OMS Quer'!C12 -> 0 | D12: ='Previous Trades Import_OMS Quer'!D12 -> 0 | E12: ='Previous Trades Import_OMS Quer'!E12 -> 0 | F12: ='Previous Trades Import_OMS Quer'!F12 -> 0 | G12: ='Previous Trades Import_OMS Quer'!G12 -> 0 | H12: ='Previous Trades Import_OMS Quer'!H12 -> 0 | ... N12: ='Previous Trades Import_OMS Quer'!N12 -> 0 | O12: =CLEAN('Previous Trades Import_OMS Quer'!O12) | Q12: =IF(G12="sell",M12,-M12) -> 0 | R12: =VLOOKUP(O12,'Currency Balance'!$O$3:$Q$32,3,0) -> #N/A | S12: =Q12/R12 -> #N/A
A13: ='Previous Trades Import_OMS Quer'!A13 -> 0 | B13: ='Previous Trades Import_OMS Quer'!B13 -> 0 | C13: ='Previous Trades Import_OMS Quer'!C13 -> 0 | D13: ='Previous Trades Import_OMS Quer'!D13 -> 0 | E13: ='Previous Trades Import_OMS Quer'!E13 -> 0 | F13: ='Previous Trades Import_OMS Quer'!F13 -> 0 | G13: ='Previous Trades Import_OMS Quer'!G13 -> 0 | H13: ='Previous Trades Import_OMS Quer'!H13 -> 0 | ... N13: ='Previous Trades Import_OMS Quer'!N13 -> 0 | O13: =CLEAN('Previous Trades Import_OMS Quer'!O13) | Q13: =IF(G13="sell",M13,-M13) -> 0 | R13: =VLOOKUP(O13,'Currency Balance'!$O$3:$Q$32,3,0) -> #N/A | S13: =Q13/R13 -> #N/A
... A179: ='Previous Trades Import_OMS Quer'!A179 -> 0 | B179: ='Previous Trades Import_OMS Quer'!B179 -> 0 | C179: ='Previous Trades Import_OMS Quer'!C179 -> 0 | D179: ='Previous Trades Import_OMS Quer'!D179 -> 0 | E179: ='Previous Trades Import_OMS Quer'!E179 -> 0 | F179: ='Previous Trades Import_OMS Quer'!F179 -> 0 | G179: ='Previous Trades Import_OMS Quer'!G179 -> 0 | H179: ='Previous Trades Import_OMS Quer'!H179 -> 0 | ... N179: ='Previous Trades Import_OMS Quer'!N179 -> 0 | O179: =CLEAN('Previous Trades Import_OMS Quer'!O179) | Q179: =IF(G179="sell",M179,-M179) -> 0 | R179: =VLOOKUP(O179,'Currency Balance'!$O$3:$Q$32,3,0) -> #N/A | S179: =Q179/R179 -> #N/A
A180: ='Previous Trades Import_OMS Quer'!A180 -> 0 | B180: ='Previous Trades Import_OMS Quer'!B180 -> 0 | C180: ='Previous Trades Import_OMS Quer'!C180 -> 0 | D180: ='Previous Trades Import_OMS Quer'!D180 -> 0 | E180: ='Previous Trades Import_OMS Quer'!E180 -> 0 | F180: ='Previous Trades Import_OMS Quer'!F180 -> 0 | G180: ='Previous Trades Import_OMS Quer'!G180 -> 0 | H180: ='Previous Trades Import_OMS Quer'!H180 -> 0 | ... N180: ='Previous Trades Import_OMS Quer'!N180 -> 0 | O180: =CLEAN('Previous Trades Import_OMS Quer'!O180) | Q180: =IF(G180="sell",M180,-M180) -> 0 | R180: =VLOOKUP(O180,'Currency Balance'!$O$3:$Q$32,3,0) -> #N/A | S180: =Q180/R180 -> #N/A | T180: =L180*50*I180 -> 0
A181: ='Previous Trades Import_OMS Quer'!A181 -> 0 | B181: ='Previous Trades Import_OMS Quer'!B181 -> 0 | C181: ='Previous Trades Import_OMS Quer'!C181 -> 0 | D181: ='Previous Trades Import_OMS Quer'!D181 -> 0 | E181: ='Previous Trades Import_OMS Quer'!E181 -> 0 | F181: ='Previous Trades Import_OMS Quer'!F181 -> 0 | G181: ='Previous Trades Import_OMS Quer'!G181 -> 0 | H181: ='Previous Trades Import_OMS Quer'!H181 -> 0 | ... N181: ='Previous Trades Import_OMS Quer'!N181 -> 0 | O181: =CLEAN('Previous Trades Import_OMS Quer'!O181) | Q181: =IF(G181="sell",M181,-M181) -> 0 | R181: =VLOOKUP(O181,'Currency Balance'!$O$3:$Q$32,3,0) -> #N/A | S181: =Q181/R181 -> #N/A
A182: ='Previous Trades Import_OMS Quer'!A182 -> 0 | B182: ='Previous Trades Import_OMS Quer'!B182 -> 0 | C182: ='Previous Trades Import_OMS Quer'!C182 -> 0 | D182: ='Previous Trades Import_OMS Quer'!D182 -> 0 | E182: ='Previous Trades Import_OMS Quer'!E182 -> 0 | F182: ='Previous Trades Import_OMS Quer'!F182 -> 0 | G182: ='Previous Trades Import_OMS Quer'!G182 -> 0 | H182: ='Previous Trades Import_OMS Quer'!H182 -> 0 | ... N182: ='Previous Trades Import_OMS Quer'!N182 -> 0 | O182: =CLEAN('Previous Trades Import_OMS Quer'!O182) | Q182: =IF(G182="sell",M182,-M182) -> 0 | R182: =VLOOKUP(O182,'Currency Balance'!$O$3:$Q$32,3,0) -> #N/A | S182: =Q182/R182 -> #N/A
A183: ='Previous Trades Import_OMS Quer'!A183 -> 0 | B183: ='Previous Trades Import_OMS Quer'!B183 -> 0 | C183: ='Previous Trades Import_OMS Quer'!C183 -> 0 | D183: ='Previous Trades Import_OMS Quer'!D183 -> 0 | E183: ='Previous Trades Import_OMS Quer'!E183 -> 0 | F183: ='Previous Trades Import_OMS Quer'!F183 -> 0 | G183: ='Previous Trades Import_OMS Quer'!G183 -> 0 | H183: ='Previous Trades Import_OMS Quer'!H183 -> 0 | ... N183: ='Previous Trades Import_OMS Quer'!N183 -> 0 | O183: =CLEAN('Previous Trades Import_OMS Quer'!O183) | Q183: =IF(G183="sell",M183,-M183) -> 0 | R183: =VLOOKUP(O183,'Currency Balance'!$O$3:$Q$32,3,0) -> #N/A | S183: =Q183/R183 -> #N/A
A184: ='Previous Trades Import_OMS Quer'!A184 -> 0 | B184: ='Previous Trades Import_OMS Quer'!B184 -> 0 | C184: ='Previous Trades Import_OMS Quer'!C184 -> 0 | D184: ='Previous Trades Import_OMS Quer'!D184 -> 0 | E184: ='Previous Trades Import_OMS Quer'!E184 -> 0 | F184: ='Previous Trades Import_OMS Quer'!F184 -> 0 | G184: ='Previous Trades Import_OMS Quer'!G184 -> 0 | H184: ='Previous Trades Import_OMS Quer'!H184 -> 0 | ... N184: ='Previous Trades Import_OMS Quer'!N184 -> 0 | O184: =CLEAN('Previous Trades Import_OMS Quer'!O184) | Q184: =IF(G184="sell",M184,-M184) -> 0 | R184: =VLOOKUP(O184,'Currency Balance'!$O$3:$Q$32,3,0) -> #N/A | S184: =Q184/R184 -> #N/A
A185: ='Previous Trades Import_OMS Quer'!A185 -> 0 | B185: ='Previous Trades Import_OMS Quer'!B185 -> 0 | C185: ='Previous Trades Import_OMS Quer'!C185 -> 0 | D185: ='Previous Trades Import_OMS Quer'!D185 -> 0 | E185: ='Previous Trades Import_OMS Quer'!E185 -> 0 | F185: ='Previous Trades Import_OMS Quer'!F185 -> 0 | G185: ='Previous Trades Import_OMS Quer'!G185 -> 0 | H185: ='Previous Trades Import_OMS Quer'!H185 -> 0 | ... N185: ='Previous Trades Import_OMS Quer'!N185 -> 0 | O185: =CLEAN('Previous Trades Import_OMS Quer'!O185) | Q185: =IF(G185="sell",M185,-M185) -> 0 | R185: =VLOOKUP(O185,'Currency Balance'!$O$3:$Q$32,3,0) -> #N/A | S185: =Q185/R185 -> #N/A
A186: ='Previous Trades Import_OMS Quer'!A186 -> 0 | B186: ='Previous Trades Import_OMS Quer'!B186 -> 0 | C186: ='Previous Trades Import_OMS Quer'!C186 -> 0 | D186: ='Previous Trades Import_OMS Quer'!D186 -> 0 | E186: ='Previous Trades Import_OMS Quer'!E186 -> 0 | F186: ='Previous Trades Import_OMS Quer'!F186 -> 0 | G186: ='Previous Trades Import_OMS Quer'!G186 -> 0 | H186: ='Previous Trades Import_OMS Quer'!H186 -> 0 | ... N186: ='Previous Trades Import_OMS Quer'!N186 -> 0 | O186: =CLEAN('Previous Trades Import_OMS Quer'!O186) | Q186: =IF(G186="sell",M186,-M186) -> 0 | R186: =VLOOKUP(O186,'Currency Balance'!$O$3:$Q$32,3,0) -> #N/A | S186: =Q186/R186 -> #N/A
A187: ='Previous Trades Import_OMS Quer'!A187 -> 0 | B187: ='Previous Trades Import_OMS Quer'!B187 -> 0 | C187: ='Previous Trades Import_OMS Quer'!C187 -> 0 | D187: ='Previous Trades Import_OMS Quer'!D187 -> 0 | E187: ='Previous Trades Import_OMS Quer'!E187 -> 0 | F187: ='Previous Trades Import_OMS Quer'!F187 -> 0 | G187: ='Previous Trades Import_OMS Quer'!G187 -> 0 | H187: ='Previous Trades Import_OMS Quer'!H187 -> 0 | ... N187: ='Previous Trades Import_OMS Quer'!N187 -> 0 | O187: =CLEAN('Previous Trades Import_OMS Quer'!O187) | Q187: =IF(G187="sell",M187,-M187) -> 0 | R187: =VLOOKUP(O187,'Currency Balance'!$O$3:$Q$32,3,0) -> #N/A | S187: =Q187/R187 -> #N/A
A188: ='Previous Trades Import_OMS Quer'!A188 -> 0 | B188: ='Previous Trades Import_OMS Quer'!B188 -> 0 | C188: ='Previous Trades Import_OMS Quer'!C188 -> 0 | D188: ='Previous Trades Import_OMS Quer'!D188 -> 0 | E188: ='Previous Trades Import_OMS Quer'!E188 -> 0 | F188: ='Previous Trades Import_OMS Quer'!F188 -> 0 | G188: ='Previous Trades Import_OMS Quer'!G188 -> 0 | H188: ='Previous Trades Import_OMS Quer'!H188 -> 0 | ... N188: ='Previous Trades Import_OMS Quer'!N188 -> 0 | O188: =CLEAN('Previous Trades Import_OMS Quer'!O188) | Q188: =IF(G188="sell",M188,-M188) -> 0 | R188: =VLOOKUP(O188,'Currency Balance'!$O$3:$Q$32,3,0) -> #N/A | S188: =Q188/R188 -> #N/A
A189: ='Previous Trades Import_OMS Quer'!A189 -> 0 | B189: ='Previous Trades Import_OMS Quer'!B189 -> 0 | C189: ='Previous Trades Import_OMS Quer'!C189 -> 0 | D189: ='Previous Trades Import_OMS Quer'!D189 -> 0 | E189: ='Previous Trades Import_OMS Quer'!E189 -> 0 | F189: ='Previous Trades Import_OMS Quer'!F189 -> 0 | G189: ='Previous Trades Import_OMS Quer'!G189 -> 0 | H189: ='Previous Trades Import_OMS Quer'!H189 -> 0 | ... N189: ='Previous Trades Import_OMS Quer'!N189 -> 0 | O189: =CLEAN('Previous Trades Import_OMS Quer'!O189) | Q189: =IF(G189="sell",M189,-M189) -> 0 | R189: =VLOOKUP(O189,'Currency Balance'!$O$3:$Q$32,3,0) -> #N/A | S189: =Q189/R189 -> #N/A
A190: ='Previous Trades Import_OMS Quer'!A190 -> 0 | B190: ='Previous Trades Import_OMS Quer'!B190 -> 0 | C190: ='Previous Trades Import_OMS Quer'!C190 -> 0 | D190: ='Previous Trades Import_OMS Quer'!D190 -> 0 | E190: ='Previous Trades Import_OMS Quer'!E190 -> 0 | F190: ='Previous Trades Import_OMS Quer'!F190 -> 0 | G190: ='Previous Trades Import_OMS Quer'!G190 -> 0 | H190: ='Previous Trades Import_OMS Quer'!H190 -> 0 | ... N190: ='Previous Trades Import_OMS Quer'!N190 -> 0 | O190: =CLEAN('Previous Trades Import_OMS Quer'!O190) | Q190: =IF(G190="sell",M190,-M190) -> 0 | R190: =VLOOKUP(O190,'Currency Balance'!$O$3:$Q$32,3,0) -> #N/A | S190: =Q190/R190 -> #N/A
A191: ='Previous Trades Import_OMS Quer'!A191 -> 0 | B191: ='Previous Trades Import_OMS Quer'!B191 -> 0 | C191: ='Previous Trades Import_OMS Quer'!C191 -> 0 | D191: ='Previous Trades Import_OMS Quer'!D191 -> 0 | E191: ='Previous Trades Import_OMS Quer'!E191 -> 0 | F191: ='Previous Trades Import_OMS Quer'!F191 -> 0 | G191: ='Previous Trades Import_OMS Quer'!G191 -> 0 | H191: ='Previous Trades Import_OMS Quer'!H191 -> 0 | ... N191: ='Previous Trades Import_OMS Quer'!N191 -> 0 | O191: =CLEAN('Previous Trades Import_OMS Quer'!O191) | Q191: =IF(G191="sell",M191,-M191) -> 0 | R191: =VLOOKUP(O191,'Currency Balance'!$O$3:$Q$32,3,0) -> #N/A | S191: =Q191/R191 -> #N/A
A192: ='Previous Trades Import_OMS Quer'!A192 -> 0 | B192: ='Previous Trades Import_OMS Quer'!B192 -> 0 | C192: ='Previous Trades Import_OMS Quer'!C192 -> 0 | D192: ='Previous Trades Import_OMS Quer'!D192 -> 0 | E192: ='Previous Trades Import_OMS Quer'!E192 -> 0 | F192: ='Previous Trades Import_OMS Quer'!F192 -> 0 | G192: ='Previous Trades Import_OMS Quer'!G192 -> 0 | H192: ='Previous Trades Import_OMS Quer'!H192 -> 0 | ... N192: ='Previous Trades Import_OMS Quer'!N192 -> 0 | O192: =CLEAN('Previous Trades Import_OMS Quer'!O192) | Q192: =IF(G192="sell",M192,-M192) -> 0 | R192: =VLOOKUP(O192,'Currency Balance'!$O$3:$Q$32,3,0) -> #N/A | S192: =Q192/R192 -> #N/A
... A8743: ='Previous Trades Import_OMS Quer'!A8743 -> 0 | B8743: ='Previous Trades Import_OMS Quer'!B8743 -> 0 | C8743: ='Previous Trades Import_OMS Quer'!C8743 -> 0 | D8743: ='Previous Trades Import_OMS Quer'!D8743 -> 0 | E8743: ='Previous Trades Import_OMS Quer'!E8743 -> 0 | F8743: ='Previous Trades Import_OMS Quer'!F8743 -> 0 | G8743: ='Previous Trades Import_OMS Quer'!G8743 -> 0 | H8743: ='Previous Trades Import_OMS Quer'!H8743 -> 0 | ... N8743: ='Previous Trades Import_OMS Quer'!N8743 -> 0 | O8743: =CLEAN('Previous Trades Import_OMS Quer'!O8743) | Q8743: =IF(G8743="sell",M8743,-M8743) -> 0 | R8743: =VLOOKUP(O8743,'Currency Balance'!$O$3:$Q$32,3,0) -> #N/A | S8743: =Q8743/R8743 -> #N/A

Sheet JP Code_Sheet
A1: =TODAY() -> 45467 | B1: THIS DATE DRIVES THE ENTIRE SHEET | C1: Removed Sweep purhcase/sales | G1: Use eze for sheet | I1: FLOW | J1: FLOW | K1: CASH DEBIT OTHER DISBURSEMENTS | L1: TOTAL NET FLOW | M1: CASH PROJECTION | N1: MUSXX | O1: PURCHASES | P1: Sales | Q1: JPMORGAN SHORT TERM INVESTMENT FUNDS | T1: REDEMPTION TO FUND | U1: Subscription to fund | V1: FAILING TRADES | W1: OUTSTANDING | X1: Autosettled: already factored in cash | Y1: REVERSAL INTERFUND TRANSFER | Z1: CASH CREDIT FOR OTHER RECEIPTS | AA1: Failing trades (as a result of stock loan) | AB1: Failing trades (as a result of stock loan) | AC1: DISCRETIONARY LENDING SALE FAIL
A2: Custody # | B2: SODCASH | C2: Pending Trades (not using in sheets/uze eze: spot check here) | D2: Income USD | F2: Final sweep | G2: TBILL | H2: Equity | I2: Redemption | J2: Sub | M2: SWEEP | N2: Sweep Priced Positions | O2: Sweep Pending trades | P2: Sweep Pending trades | Q2: Total Sweep Pending | T2: CASH DEBIT OTHER DISBURSEMENTS | V2: PURCHASE | W2: SALE | X2: Net Failing trades | AA2: PURCHASE | AB2: SALE | AC2: Net
A34: Local | B34: LOCAL | D34: LOCAL (div's only appear to hit in USD. Income converted)
A35: AIA40 (USD) | B35: ='Currency Balance'!D33 -> 0 | C35: ='Currency Balance'!H32+'Currency Balance'!J32 -> #NAME?
A36: Base | B36: BASE
A37: G 01305 | C37: =C35+C31 -> #NAME? | D37: =D31+D33 -> 0 | H37: =H31+H33 -> 0
A38: COMBINED (base)
A40: COLUMN | B40: F | C40: L+M+Y+Z | D40: N+O+R+AA+AB+AE (today's date only) | I40: W: REDEMPTION TO FUND :(column AK) | J40: W: Subcription TO FUND :(column AK) | M40: Asset category type(L) | N40: O (ticker= MUSXX)
B41: Cash Projection (SOD):Same Day | C41: Cashprojection (ALL 5 DAYS PROKECTED) | D41: Cash Projection( same Day) | G41: Priced Positions | H41: Priced Positions (DTC for Domestic, diff coding for intl) | I41: Cash Projection Detail | J41: Cash Projection Detail | K41: CASH DEBIT OTHER DISBURSEMENTS | L41: Includes interfund transfers (excluded accounts in Francis tab) | M41: Priced positions | N41: Priced Positions | O41: Cash Projection Detail | P41: Cash Projection Detail | Y41: Cash Projection Detail | Z41: Cash Projection Detail | AA41: JP Outstanding Trades | AB41: JP Outstanding Trades
D42: Detail will show each div (ex and pay) | G42: T+1 accounting | H42: T+1 accounting | Y42: Column W= "Reversal interfund transfer" | Z42: Column W= "CASH CREDIT FOR OTHER RECEIPTS" | AA42: Trades flagged as outstand and DISCRETIONARY LENDING SALE FAIL
C43: Common Stock | D43: Settled Dividend Payments | AA43: *Only picks up trades aged over 2 days | AB43: 2
C44: Preferred Stock | D44: Settled Securities Lending
C45: Mutual Funds & UITS (inlcudes MUSXX) | D45: Settled Combined P and I (interest payments and principal Payments)
D46: Projected Dividend Payments
D47: Projected Combined P and I
B50: *NOTE"
B51: The mutual fund pays a monthy dividend that does not appear to be reflected in projeted cash since it's posted later in the evening.
B52: Run Posted cash later in the evening and filter by "Transaction Category Description", ticker ("MUSXX")
B53: If you see breaks in MAS accounting sheet
A65: BNY REPORTS
A66: Custody # | B66: SODCASH | C66: Pending Trades | D66: Income USD | E66: Cash Flow | F66: Final sweep | G66: TBILL | H66: Equity | I66: Redemption | J66: Sub | M66: SWEEP | N66: Sweep Priced Positions | O66: Sweep Pending trades | P66: Sweep Pending trades | Q66: Total Sweep Pending | T66: CASH DEBIT OTHER DISBURSEMENTS
A72: Reporting | B72: Projected Cash | C72: Projected Cash | D72: Projected Cash | H72: BNY_ Custody Val | V72: Projected Cash | W72: Projected Cash
B73: Consolidate Sweep and Cash | C73: Buy+Sells W/ settled date today and beyond (today date built into code) | D73: Dividends: Income paying today: based off today's date) | H73: Common and mutual funds
B74: Sum opening balance if E in NOT blank | C74: Transaction Amount Reporting Equivalent | D74: Transaction Amount Reporting Equivalent | H74: Posted Basis: All pending trades( prior day cut-off 7:00)
H75: Prior Day | V75: Buy W/ settled date before today (todasy date built into code) | W75: Sells W/ settled date before today

Sheet BNY_Projected Cash Statement
A1: =N2 -> Cash Reporting Date | B1: =BV3 -> 0 | C1: INTRADAY (RUN at 9:00am)
A2: Account Number | B2: Account Name | C2: Cash Account Number | D2: Cash Account Name | E2: Sweep Vehicle Number | F2: Sweep Vehicle Name | G2: Account Group | H2: Reporting Currency Code | I2: Reporting Currency Name | J2: Local Currency Code | K2: Local Currency Name | L2: Location Code | M2: Location Name | N2: Cash Reporting Date | O2: Reference Number | P2: Client Reference Number | Q2: Related Reference | R2: Tax Code | S2: Tax Code Description | T2: Transaction Type Code | U2: Transaction Type | V2: Main Transaction Code | W2: Sub Transaction Code | X2: Detailed Transaction Type Name | Y2: Transaction Description 1 | Z2: Transaction Description 2 | AA2: Transaction Description 3 | AB2: Transaction Description 4 | AC2: Transaction Description 5 | AD2: Transaction Description 6 | AE2: Trade / Ex Date | AF2: Settle / Pay Date | AG2: Actual Settle Date | AH2: Record Date | AI2: Cash Post Date | AJ2: Cash Value Date | AK2: Shares/Par | AL2: Local Price/Rate | AM2: Local Principal Amount | AN2: Local Income Amount | AO2: Gross Amount | AP2: Source Tax Withheld Amount | AQ2: Bank Tax Withheld Amount | AR2: Opening Balance Local | AS2: Transaction Amount Local | AT2: Closing Balance Local | AU2: Opening Balance Reporting Equivalent | AV2: Transaction Amount Reporting Equivalent | AW2: Closing Balance Reporting Equivalent | AX2: Trading Broker Code | AY2: Trading Broker Name | AZ2: Trading BIC Broker Code | BA2: Clearing Broker Code | BB2: Clearing Broker Name | BC2: Clearing BIC Broker Code | BD2: Security Short Description | BE2: Security Description 1 | BF2: Security Description 2 | BG2: Security Description 3 | BH2: Security Description 4 | BI2: Security Description 5 | BJ2: Exchange Rate | BK2: CUSIP/CINS | BL2: TICKER | BM2: ISIN | BN2: SEDOL | BO2: VALOREN | BP2: SICOVAM | BQ2: WPK | BR2: QUICK | BS2: Wire Reference Number | BT2: Begin Date | BU2: End Date | BV2: Report Run Date | BW2: Report Run Time | BX2: Current Factor | BY2: Previous Factor | BZ2: Amortized Units | CA2: Event ID | CB2: Flat Tax % | CC2: Flat Tax Amount | CD2: Solidarity % | CE2: Solidarity Amount | CF2: Flat Tax Currency | CG2: Account - GSP | CH2: Extended Account | CI2: Opening STIF Balance | CJ2: STIF Transaction Amount | CK2: Closing STIF Balance | CL2: Create Date | CM2: Last Updated | CN2: Contractual Indicator Code | CO2: Settlement Policy | CP2: CID | CQ2: IAS Account Number | CR2: IAS Account Name | CS2: IAS Consolidated Account Number | CT2: IAS Consolidated Account Name | CU2: GFC Indicator | CV2: Issue Currency Code | CW2: Accrual Currency Code | CX2: Asset Category

Sheet BONY_Custody Valuation
A1: =AS2 -> As Of Date | B1: =AS3 -> 0 | C1: POSTED (Prior Day)
A2: Account Number | B2: Account Name | C2: Account Group | D2: Reporting Currency Code | E2: Reporting Currency Name | F2: Security Short Description | G2: Security Description 1 | H2: Security Description 2 | I2: Security Description 3 | J2: Security Description 4 | K2: Security Description 5 | L2: Location Code | M2: Location Name | N2: Country of Incorporation Code | O2: Country of Incorporation Name | P2: Local Currency Code | Q2: Local Currency Name | R2: Asset Category Code | S2: Asset Category Name | T2: Asset Type Code | U2: Asset Type Name | V2: Price Date | W2: Maturity Date | X2: Coupon Rate | Y2: Exchange Rate | Z2: Amortized Face | AA2: Units | AB2: Market Value Reporting Currency | AC2: Accrued Interest Reporting Currency | AD2: Accrued Market Value Reporting Currency | AE2: Local Price | AF2: Market Value Local | AG2: Accrued Interest Local | AH2: Accrued Market Value Local | AI2: Cash Investment Vehicle | AJ2: CUSIP CINS | AK2: ISIN | AL2: TICKER | AM2: QUICK | AN2: SEDOL | AO2: VALOREN | AP2: SICOVAM | AQ2: WPK | AR2: Basis | AS2: As Of Date | AT2: Moodys Rating | AU2: S&P Rating | AV2: Report Run Date | AW2: Report Run Time | AX2: Previous Factor Record Date | AY2: Previous Factor Payable Date | AZ2: Previous Factor | BA2: Current Factor Record Date | BB2: Current Factor Payable Date | BC2: Current Factor | BD2: Account Base Currency Code | BE2: Account Base Currency Name | BF2: Accrued Income | BG2: Accrued Interest Currency Code | BH2: Accrued Interest Currency Name | BI2: Issue Currency Code | BJ2: Issue Currency Name | BK2: Issue Date | BL2: Pending Deliver Shares / Par | BM2: Pending Receive Shares / Par | BN2: Price Currency Code | BO2: Price Currency Name | BP2: Principal Amount | BQ2: Principal Currency Code | BR2: Principal Currency Name | BS2: Registration Code | BT2: Registration Name | BU2: Security Status Code | BV2: Security Status Name | BW2: Strike Price | BX2: Traded Shares/Par | BY2: Account - GSP | BZ2: Extended Account | CA2: IAS Account Number | CB2: CID | CC2: IAS Account Name | CD2: IAS Consolidated Account Number | CE2: IAS Consolidated Account Name

Sheet MAS
A1: Custody # | B1: Portfolio | C1: Name of Fund | D1: SOD Cash | E1: Pending Trades +Failing (JP) | F1: Futures Vari | G1: Income | H1: Sweep | I1: Collateral & MD | J1: Total Cash | K1: T-BILL | L1: Equity MV | M1: Total Equity MV | N1: Total Assets | O1: Percent Cash | P1: Cash Flow/Interfund Transfer | Q1: Net Cash | R1: Percent Net Cash | S1: TR Swaps (MTM) | U1: Net Cash (NO Income) | V1: Custody SOD CASH
A2: G 26748 | B2: MCON | C2: MAINSTAY CONSERVATIVE ALLOCATION FUND | D2: =VLOOKUP(A2,'JP Code_Sheet'!$A$2:$E$20,2,0) -> #N/A | E2: =VLOOKUP(A2,'JP Code_Sheet'!$A$3:$C$30,3,0) -> #N/A | G2: =VLOOKUP(A2,'JP Code_Sheet'!$A$2:$E$20,4,0) -> #N/A | H2: =VLOOKUP(A2,'JP Code_Sheet'!$A$3:$F$32,6,0) -> #N/A | J2: =D2+E2+G2+H2+I2 -> #N/A | K2: =VLOOKUP(A2,'JP Code_Sheet'!$A$3:$G$32,7,0) -> #N/A | L2: =VLOOKUP(A2,'JP Code_Sheet'!$A$3:$H$32,8,0) -> #N/A | M2: =K2+L2 -> #N/A | N2: =J2+M2 -> #N/A | O2: =J2/N2 -> #N/A | P2: =VLOOKUP(A2,'JP Code_Sheet'!$A$3:$L$33,12,0) -> #N/A | Q2: =J2+P2 -> #N/A | R2: =Q2/N2 -> #N/A
A3: G 26770 | B3: MODGRO | C3: MAINSTAY GROWTH FUND | D3: =VLOOKUP(A3,'JP Code_Sheet'!$A$2:$E$20,2,0) -> #N/A | E3: =VLOOKUP(A3,'JP Code_Sheet'!$A$3:$C$30,3,0) -> #N/A | G3: =VLOOKUP(A3,'JP Code_Sheet'!$A$2:$E$20,4,0) -> #N/A | H3: =VLOOKUP(A3,'JP Code_Sheet'!$A$3:$F$32,6,0) -> #N/A | J3: =D3+E3+G3+H3+I3 -> #N/A | K3: =VLOOKUP(A3,'JP Code_Sheet'!$A$3:$G$32,7,0) -> #N/A | L3: =VLOOKUP(A3,'JP Code_Sheet'!$A$3:$H$32,8,0) -> #N/A | M3: =K3+L3 -> #N/A | N3: =J3+M3 -> #N/A | O3: =J3/N3 -> #N/A | P3: =VLOOKUP(A3,'JP Code_Sheet'!$A$3:$L$33,12,0) -> #N/A | Q3: =J3+P3 -> #N/A | R3: =Q3/N3 -> #N/A
A4: G 26756 | B4: MGRO | C4: MAINSTAY EQUITY FUND | D4: =VLOOKUP(A4,'JP Code_Sheet'!$A$2:$E$20,2,0) -> #N/A | E4: =VLOOKUP(A4,'JP Code_Sheet'!$A$3:$C$30,3,0) -> #N/A | G4: =VLOOKUP(A4,'JP Code_Sheet'!$A$2:$E$20,4,0) -> #N/A | H4: =VLOOKUP(A4,'JP Code_Sheet'!$A$3:$F$32,6,0) -> #N/A | J4: =D4+E4+G4+H4+I4 -> #N/A | K4: =VLOOKUP(A4,'JP Code_Sheet'!$A$3:$G$32,7,0) -> #N/A | L4: =VLOOKUP(A4,'JP Code_Sheet'!$A$3:$H$32,8,0) -> #N/A | M4: =K4+L4 -> #N/A | N4: =J4+M4 -> #N/A | O4: =J4/N4 -> #N/A | P4: =VLOOKUP(A4,'JP Code_Sheet'!$A$3:$L$33,12,0) -> #N/A | Q4: =J4+P4 -> #N/A | R4: =Q4/N4 -> #N/A
A5: G 26769 | B5: MMOD | C5: MAINSTAY MODERATE ALLOCATION FUND | D5: =VLOOKUP(A5,'JP Code_Sheet'!$A$2:$E$20,2,0) -> #N/A | E5: =VLOOKUP(A5,'JP Code_Sheet'!$A$3:$C$30,3,0) -> #N/A | G5: =VLOOKUP(A5,'JP Code_Sheet'!$A$2:$E$20,4,0) -> #N/A | H5: =VLOOKUP(A5,'JP Code_Sheet'!$A$3:$F$32,6,0) -> #N/A | J5: =D5+E5+G5+H5+I5 -> #N/A | K5: =VLOOKUP(A5,'JP Code_Sheet'!$A$3:$G$32,7,0) -> #N/A | L5: =VLOOKUP(A5,'JP Code_Sheet'!$A$3:$H$32,8,0) -> #N/A | M5: =K5+L5 -> #N/A | N5: =J5+M5 -> #N/A | O5: =J5/N5 -> #N/A | P5: =VLOOKUP(A5,'JP Code_Sheet'!$A$3:$L$33,12,0) -> #N/A | Q5: =J5+P5 -> #N/A | R5: =Q5/N5 -> #N/A
A6: G 26775 | B6: VMCON | C6: MAINSTAY VP CONSERVATIVE ALLOCATION | D6: =VLOOKUP(A6,'JP Code_Sheet'!$A$2:$E$20,2,0) -> #N/A | E6: =VLOOKUP(A6,'JP Code_Sheet'!$A$3:$C$30,3,0) -> #N/A | G6: =VLOOKUP(A6,'JP Code_Sheet'!$A$2:$E$20,4,0) -> #N/A | H6: =VLOOKUP(A6,'JP Code_Sheet'!$A$3:$F$32,6,0) -> #N/A | J6: =D6+E6+G6+H6+I6 -> #N/A | K6: =VLOOKUP(A6,'JP Code_Sheet'!$A$3:$G$32,7,0) -> #N/A | L6: =VLOOKUP(A6,'JP Code_Sheet'!$A$3:$H$32,8,0) -> #N/A | M6: =K6+L6 -> #N/A | N6: =J6+M6 -> #N/A | O6: =J6/N6 -> #N/A | P6: =VLOOKUP(A6,'JP Code_Sheet'!$A$3:$L$33,12,0) -> #N/A | Q6: =J6+P6 -> #N/A | R6: =Q6/N6 -> #N/A
A7: G 26782 | B7: VMGRO | C7: MAINSTAY VP EQUITY ALLOCATION FUND | D7: =VLOOKUP(A7,'JP Code_Sheet'!$A$2:$E$20,2,0) -> #N/A | E7: =VLOOKUP(A7,'JP Code_Sheet'!$A$3:$C$30,3,0) -> #N/A | G7: =VLOOKUP(A7,'JP Code_Sheet'!$A$2:$E$20,4,0) -> #N/A | H7: =VLOOKUP(A7,'JP Code_Sheet'!$A$3:$F$32,6,0) -> #N/A | J7: =D7+E7+G7+H7+I7 -> #N/A | K7: =VLOOKUP(A7,'JP Code_Sheet'!$A$3:$G$32,7,0) -> #N/A | L7: =VLOOKUP(A7,'JP Code_Sheet'!$A$3:$H$32,8,0) -> #N/A | M7: =K7+L7 -> #N/A | N7: =J7+M7 -> #N/A | O7: =J7/N7 -> #N/A | P7: =VLOOKUP(A7,'JP Code_Sheet'!$A$3:$L$33,12,0) -> #N/A | Q7: =J7+P7 -> #N/A | R7: =Q7/N7 -> #N/A
A8: G 26798 | B8: VMMOD | C8: MAINSTAY VP MODERATE ALLOCATION FUND | D8: =VLOOKUP(A8,'JP Code_Sheet'!$A$2:$E$20,2,0) -> #N/A | E8: =VLOOKUP(A8,'JP Code_Sheet'!$A$3:$C$30,3,0) -> #N/A | G8: =VLOOKUP(A8,'JP Code_Sheet'!$A$2:$E$20,4,0) -> #N/A | H8: =VLOOKUP(A8,'JP Code_Sheet'!$A$3:$F$32,6,0) -> #N/A | J8: =D8+E8+G8+H8+I8 -> #N/A | K8: =VLOOKUP(A8,'JP Code_Sheet'!$A$3:$G$32,7,0) -> #N/A | L8: =VLOOKUP(A8,'JP Code_Sheet'!$A$3:$H$32,8,0) -> #N/A | M8: =K8+L8 -> #N/A | N8: =J8+M8 -> #N/A | O8: =J8/N8 -> #N/A | P8: =VLOOKUP(A8,'JP Code_Sheet'!$A$3:$L$33,12,0) -> #N/A | Q8: =J8+P8 -> #N/A | R8: =Q8/N8 -> #N/A
A9: G 26799 | B9: VMMDGR | C9: MAINSTAY VP GROWTH ALLOCATION FUND | D9: =VLOOKUP(A9,'JP Code_Sheet'!$A$2:$E$20,2,0) -> #N/A | E9: =VLOOKUP(A9,'JP Code_Sheet'!$A$3:$C$30,3,0) -> #N/A | G9: =VLOOKUP(A9,'JP Code_Sheet'!$A$2:$E$20,4,0) -> #N/A | H9: =VLOOKUP(A9,'JP Code_Sheet'!$A$3:$F$32,6,0) -> #N/A | J9: =D9+E9+G9+H9+I9 -> #N/A | K9: =VLOOKUP(A9,'JP Code_Sheet'!$A$3:$G$32,7,0) -> #N/A | L9: =VLOOKUP(A9,'JP Code_Sheet'!$A$3:$H$32,8,0) -> #N/A | M9: =K9+L9 -> #N/A | N9: =J9+M9 -> #N/A | O9: =J9/N9 -> #N/A | P9: =VLOOKUP(A9,'JP Code_Sheet'!$A$3:$L$33,12,0) -> #N/A | Q9: =J9+P9 -> #N/A | R9: =Q9/N9 -> #N/A
A10: G 27131 | B10: MODETF | C10: MAINSTAY MODERATE ETF ALLOCATION FUND | D10: =VLOOKUP(A10,'JP Code_Sheet'!$A$2:$E$20,2,0) -> #N/A | E10: =VLOOKUP(B10,$B$31:$H$38,7,0) -> #N/A | G10: =VLOOKUP(A10,'JP Code_Sheet'!$A$2:$E$20,4,0) -> #N/A | H10: =VLOOKUP(A10,'JP Code_Sheet'!$A$3:$F$32,6,0) -> #N/A | J10: =D10+E10+G10+H10+I10 -> #N/A | K10: =VLOOKUP(A10,'JP Code_Sheet'!$A$3:$G$32,7,0) -> #N/A | L10: =VLOOKUP(A10,'JP Code_Sheet'!$A$3:$H$32,8,0) -> #N/A | M10: =K10+L10 -> #N/A | N10: =J10+M10 -> #N/A | O10: =J10/N10 -> #N/A | P10: =VLOOKUP(A10,'JP Code_Sheet'!$A$3:$L$33,12,0) -> #N/A | Q10: =J10+P10 -> #N/A | R10: =Q10/N10 -> #N/A | S10: =B10 -> MODETF | U10: =(D10+E10+H10+I10)+P10 -> #N/A | V10: =D10+E10+H10 -> #N/A
A11: G 27129 | B11: DEFETF | C11: MAINSTAY DEFENSIVE ETF ALLOCATION FUND | D11: =VLOOKUP(A11,'JP Code_Sheet'!$A$2:$E$20,2,0) -> #N/A | E11: =VLOOKUP(B11,$B$31:$H$38,7,0) -> #N/A | G11: =VLOOKUP(A11,'JP Code_Sheet'!$A$2:$E$20,4,0) -> #N/A | H11: =VLOOKUP(A11,'JP Code_Sheet'!$A$3:$F$32,6,0) -> #N/A | J11: =D11+E11+G11+H11+I11 -> #N/A | K11: =VLOOKUP(A11,'JP Code_Sheet'!$A$3:$G$32,7,0) -> #N/A | L11: =VLOOKUP(A11,'JP Code_Sheet'!$A$3:$H$32,8,0) -> #N/A | M11: =K11+L11 -> #N/A | N11: =J11+M11 -> #N/A | O11: =J11/N11 -> #N/A | P11: =VLOOKUP(A11,'JP Code_Sheet'!$A$3:$L$33,12,0) -> #N/A | Q11: =J11+P11 -> #N/A | R11: =Q11/N11 -> #N/A | S11: =B11 -> DEFETF | U11: =(D11+E11+H11+I11)+P11 -> #N/A | V11: =D11+E11+H11 -> #N/A
A12: G 27130 | B12: CONETF | C12: MAINSTAY CONSERVATIVE ETF ALLOCATION | D12: =VLOOKUP(A12,'JP Code_Sheet'!$A$2:$E$20,2,0) -> #N/A | E12: =VLOOKUP(B12,$B$31:$H$38,7,0) -> #N/A | G12: =VLOOKUP(A12,'JP Code_Sheet'!$A$2:$E$20,4,0) -> #N/A | H12: =VLOOKUP(A12,'JP Code_Sheet'!$A$3:$F$32,6,0) -> #N/A | J12: =D12+E12+G12+H12+I12 -> #N/A | K12: =VLOOKUP(A12,'JP Code_Sheet'!$A$3:$G$32,7,0) -> #N/A | L12: =VLOOKUP(A12,'JP Code_Sheet'!$A$3:$H$32,8,0) -> #N/A | M12: =K12+L12 -> #N/A | N12: =J12+M12 -> #N/A | O12: =J12/N12 -> #N/A | P12: =VLOOKUP(A12,'JP Code_Sheet'!$A$3:$L$33,12,0) -> #N/A | Q12: =J12+P12 -> #N/A | R12: =Q12/N12 -> #N/A | S12: =B12 -> CONETF | U12: =(D12+E12+H12+I12)+P12 -> #N/A | V12: =D12+E12+H12 -> #N/A
A13: G 27133 | B13: MGRETF | C13: MAINSTAY GROWTH ETF | D13: =VLOOKUP(A13,'JP Code_Sheet'!$A$2:$E$20,2,0) -> #N/A | E13: =VLOOKUP(B13,$B$31:$H$38,7,0) -> #N/A | G13: =VLOOKUP(A13,'JP Code_Sheet'!$A$2:$E$20,4,0) -> #N/A | H13: =VLOOKUP(A13,'JP Code_Sheet'!$A$3:$F$32,6,0) -> #N/A | J13: =D13+E13+G13+H13+I13 -> #N/A | K13: =VLOOKUP(A13,'JP Code_Sheet'!$A$3:$G$32,7,0) -> #N/A | L13: =VLOOKUP(A13,'JP Code_Sheet'!$A$3:$H$32,8,0) -> #N/A | M13: =K13+L13 -> #N/A | N13: =J13+M13 -> #N/A | O13: =J13/N13 -> #N/A | P13: =VLOOKUP(A13,'JP Code_Sheet'!$A$3:$L$33,12,0) -> #N/A | Q13: =J13+P13 -> #N/A | R13: =Q13/N13 -> #N/A | S13: =B13 -> MGRETF | U13: =(D13+E13+H13+I13)+P13 -> #N/A | V13: =D13+E13+H13 -> #N/A
A14: G 27134 | B14: GRWETF | C14: MAINSTAY EQUITY ETF ALLOCATION FUND | D14: =VLOOKUP(A14,'JP Code_Sheet'!$A$2:$E$20,2,0) -> #N/A | E14: =VLOOKUP(B14,$B$31:$H$38,7,0) -> #N/A | G14: =VLOOKUP(A14,'JP Code_Sheet'!$A$2:$E$20,4,0) -> #N/A | H14: =VLOOKUP(A14,'JP Code_Sheet'!$A$3:$F$32,6,0) -> #N/A | J14: =D14+E14+G14+H14+I14 -> #N/A | K14: =VLOOKUP(A14,'JP Code_Sheet'!$A$3:$G$32,7,0) -> #N/A | L14: =VLOOKUP(A14,'JP Code_Sheet'!$A$3:$H$32,8,0) -> #N/A | M14: =K14+L14 -> #N/A | N14: =J14+M14 -> #N/A | O14: =J14/N14 -> #N/A | P14: =VLOOKUP(A14,'JP Code_Sheet'!$A$3:$L$33,12,0) -> #N/A | Q14: =J14+P14 -> #N/A | R14: =Q14/N14 -> #N/A | S14: =B14 -> GRWETF | U14: =(D14+E14+H14+I14)+P14 -> #N/A | V14: =D14+E14+H14 -> #N/A
A15: G 39869 | B15: ESGETF | C15: MAINSTAY ESG MULTI-ASSET ALLOCATION | D15: =VLOOKUP(A15,'JP Code_Sheet'!$A$2:$E$20,2,0) -> #N/A | E15: =VLOOKUP(B15,$B$31:$H$38,7,0) -> #N/A | G15: =VLOOKUP(A15,'JP Code_Sheet'!$A$2:$E$20,4,0) -> #N/A | H15: =VLOOKUP(A15,'JP Code_Sheet'!$A$3:$F$32,6,0) -> #N/A | J15: =D15+E15+G15+H15+I15 -> #N/A | K15: =VLOOKUP(A15,'JP Code_Sheet'!$A$3:$G$32,7,0) -> #N/A | L15: =VLOOKUP(A15,'JP Code_Sheet'!$A$3:$H$32,8,0) -> #N/A | M15: =K15+L15 -> #N/A | N15: =J15+M15 -> #N/A | O15: =J15/N15 -> #N/A | P15: =VLOOKUP(A15,'JP Code_Sheet'!$A$3:$L$33,12,0) -> #N/A | Q15: =J15+P15 -> #N/A | R15: =Q15/N15 -> #N/A | S15: =B15 -> ESGETF | U15: =(D15+E15+H15+I15)+P15 -> #N/A | V15: =D15+E15+H15 -> #N/A
A16: G 26821 | B16: BALETF | C16: MAINSTAY ETF ACCOUNT | D16: =VLOOKUP(A16,'JP Code_Sheet'!$A$2:$E$20,2,0) -> #N/A | E16: =VLOOKUP(B16,$B$31:$H$38,7,0) -> #N/A | G16: =VLOOKUP(A16,'JP Code_Sheet'!$A$2:$E$20,4,0) -> #N/A | H16: =VLOOKUP(A16,'JP Code_Sheet'!$A$3:$F$32,6,0) -> #N/A | J16: =D16+E16+G16+H16+I16 -> #N/A | K16: =VLOOKUP(A16,'JP Code_Sheet'!$A$3:$G$32,7,0) -> #N/A | L16: =VLOOKUP(A16,'JP Code_Sheet'!$A$3:$H$32,8,0) -> #N/A | M16: =K16+L16 -> #N/A | N16: =J16+M16 -> #N/A | O16: =J16/N16 -> #N/A | P16: =VLOOKUP(A16,'JP Code_Sheet'!$A$3:$L$33,12,0) -> #N/A | Q16: =J16+P16 -> #N/A | R16: =Q16/N16 -> #N/A | S16: =B16 -> BALETF | U16: =(D16+E16+H16+I16)+P16 -> #N/A | V16: =D16+E16+H16 -> #N/A
A17: G 26824 | B17: VPBALETF | C17: MAINSTAY VP ETF ACCOUNT | D17: =VLOOKUP(A17,'JP Code_Sheet'!$A$2:$E$20,2,0) -> #N/A | E17: =VLOOKUP(B17,$B$31:$H$38,7,0) -> #N/A | G17: =VLOOKUP(A17,'JP Code_Sheet'!$A$2:$E$20,4,0) -> #N/A | H17: =VLOOKUP(A17,'JP Code_Sheet'!$A$3:$F$32,6,0) -> #N/A | J17: =D17+E17+G17+H17+I17 -> #N/A | K17: =VLOOKUP(A17,'JP Code_Sheet'!$A$3:$G$32,7,0) -> #N/A | L17: =VLOOKUP(A17,'JP Code_Sheet'!$A$3:$H$32,8,0) -> #N/A | M17: =K17+L17 -> #N/A | N17: =J17+M17 -> #N/A | O17: =J17/N17 -> #N/A | P17: =VLOOKUP(A17,'JP Code_Sheet'!$A$3:$L$33,12,0) -> #N/A | Q17: =J17+P17 -> #N/A | R17: =Q17/N17 -> #N/A | S17: =B17 -> VPBALETF | U17: =(D17+E17+H17+I17)+P17 -> #N/A | V17: =D17+E17+H17 -> #N/A
N18: NOT EZE PLUG | U18: PLUG INTO EZE | V18: Input to Rec Sheet
A19: T-0 | C19: EZE | Q19: Check for late flows
A20: =D20-1 -> 45466 | B20: S/D | D20: ='JP Code_Sheet'!A1 -> 45467 | E20: =D20+1 -> 45468 | F20: =E20+1 -> 45469 | G20: =F20+1 -> 45470 | H20: =G20+1 -> 45471 | I20: =H20+1 -> 45472 | J20: =I20+1 -> 45473 | K20: =J20+1 -> 45474 | L20: =K20+1 -> 45475 | M20: Total Pending
A21: =SUMIFS('Previous Trade Calc'!$Q:$Q,'Previous Trade Calc'!$B:$B,MAS!$B$21,'Previous Trade Calc'!$E:$E,$A$20) -> 0 | B21: MODETF | D21: =SUMIFS('Previous Trade Calc'!$Q:$Q,'Previous Trade Calc'!$B:$B,MAS!$B$21,'Previous Trade Calc'!$E:$E,D20) -> 0 | E21: =SUMIFS('Previous Trade Calc'!$Q:$Q,'Previous Trade Calc'!$B:$B,MAS!$B$21,'Previous Trade Calc'!$E:$E,E20) -> 0 | F21: =SUMIFS('Previous Trade Calc'!$Q:$Q,'Previous Trade Calc'!$B:$B,MAS!$B$21,'Previous Trade Calc'!$E:$E,F20) -> 0 | G21: =SUMIFS('Previous Trade Calc'!$Q:$Q,'Previous Trade Calc'!$B:$B,MAS!$B$21,'Previous Trade Calc'!$E:$E,G20) -> 0 | H21: =SUMIFS('Previous Trade Calc'!$Q:$Q,'Previous Trade Calc'!$B:$B,MAS!$B$21,'Previous Trade Calc'!$E:$E,H20) -> 0 | I21: =SUMIFS('Previous Trade Calc'!$Q:$Q,'Previous Trade Calc'!$B:$B,MAS!$B$21,'Previous Trade Calc'!$E:$E,I20) -> 0 | J21: =SUMIFS('Previous Trade Calc'!$Q:$Q,'Previous Trade Calc'!$B:$B,MAS!$B$21,'Previous Trade Calc'!$E:$E,J20) -> 0 | K21: =SUMIFS('Previous Trade Calc'!$Q:$Q,'Previous Trade Calc'!$B:$B,MAS!$B$21,'Previous Trade Calc'!$E:$E,K20) -> 0 | L21: =SUMIFS('Previous Trade Calc'!$Q:$Q,'Previous Trade Calc'!$B:$B,MAS!$B$21,'Previous Trade Calc'!$E:$E,L20) -> 0 | M21: =SUM(D21:L21) -> 0 | U21: @CASHUSD
A22: =SUMIFS('Previous Trade Calc'!$Q:$Q,'Previous Trade Calc'!$B:$B,MAS!$B$22,'Previous Trade Calc'!$E:$E,$A$20) -> 0 | B22: DEFETF | D22: =SUMIFS('Previous Trade Calc'!$Q:$Q,'Previous Trade Calc'!$B:$B,MAS!$B$22,'Previous Trade Calc'!$E:$E,D20) -> 0 | E22: =SUMIFS('Previous Trade Calc'!$Q:$Q,'Previous Trade Calc'!$B:$B,MAS!$B$22,'Previous Trade Calc'!$E:$E,E20) -> 0 | F22: =SUMIFS('Previous Trade Calc'!$Q:$Q,'Previous Trade Calc'!$B:$B,MAS!$B$22,'Previous Trade Calc'!$E:$E,F20) -> 0 | G22: =SUMIFS('Previous Trade Calc'!$Q:$Q,'Previous Trade Calc'!$B:$B,MAS!$B$22,'Previous Trade Calc'!$E:$E,G20) -> 0 | H22: =SUMIFS('Previous Trade Calc'!$Q:$Q,'Previous Trade Calc'!$B:$B,MAS!$B$22,'Previous Trade Calc'!$E:$E,H20) -> 0 | I22: =SUMIFS('Previous Trade Calc'!$Q:$Q,'Previous Trade Calc'!$B:$B,MAS!$B$22,'Previous Trade Calc'!$E:$E,I20) -> 0 | J22: =SUMIFS('Previous Trade Calc'!$Q:$Q,'Previous Trade Calc'!$B:$B,MAS!$B$22,'Previous Trade Calc'!$E:$E,J20) -> 0 | K22: =SUMIFS('Previous Trade Calc'!$Q:$Q,'Previous Trade Calc'!$B:$B,MAS!$B$22,'Previous Trade Calc'!$E:$E,K20) -> 0 | L22: =SUMIFS('Previous Trade Calc'!$Q:$Q,'Previous Trade Calc'!$B:$B,MAS!$B$22,'Previous Trade Calc'!$E:$E,L20) -> 0 | M22: =SUM(D22:L22) -> 0
A23: =SUMIFS('Previous Trade Calc'!$Q:$Q,'Previous Trade Calc'!$B:$B,MAS!$B$23,'Previous Trade Calc'!$E:$E,$A$20) -> 0 | B23: CONETF | D23: =SUMIFS('Previous Trade Calc'!$Q:$Q,'Previous Trade Calc'!$B:$B,MAS!$B$23,'Previous Trade Calc'!$E:$E,D20) -> 0 | E23: =SUMIFS('Previous Trade Calc'!$Q:$Q,'Previous Trade Calc'!$B:$B,MAS!$B$23,'Previous Trade Calc'!$E:$E,E20) -> 0 | F23: =SUMIFS('Previous Trade Calc'!$Q:$Q,'Previous Trade Calc'!$B:$B,MAS!$B$23,'Previous Trade Calc'!$E:$E,F20) -> 0 | G23: =SUMIFS('Previous Trade Calc'!$Q:$Q,'Previous Trade Calc'!$B:$B,MAS!$B$23,'Previous Trade Calc'!$E:$E,G20) -> 0 | H23: =SUMIFS('Previous Trade Calc'!$Q:$Q,'Previous Trade Calc'!$B:$B,MAS!$B$23,'Previous Trade Calc'!$E:$E,H20) -> 0 | I23: =SUMIFS('Previous Trade Calc'!$Q:$Q,'Previous Trade Calc'!$B:$B,MAS!$B$23,'Previous Trade Calc'!$E:$E,I20) -> 0 | J23: =SUMIFS('Previous Trade Calc'!$Q:$Q,'Previous Trade Calc'!$B:$B,MAS!$B$23,'Previous Trade Calc'!$E:$E,J20) -> 0 | K23: =SUMIFS('Previous Trade Calc'!$Q:$Q,'Previous Trade Calc'!$B:$B,MAS!$B$23,'Previous Trade Calc'!$E:$E,K20) -> 0 | L23: =SUMIFS('Previous Trade Calc'!$Q:$Q,'Previous Trade Calc'!$B:$B,MAS!$B$23,'Previous Trade Calc'!$E:$E,L20) -> 0 | M23: =SUM(D23:L23) -> 0
A24: =SUMIFS('Previous Trade Calc'!$Q:$Q,'Previous Trade Calc'!$B:$B,MAS!$B$24,'Previous Trade Calc'!$E:$E,$A$20) -> 0 | B24: MGRETF | D24: =SUMIFS('Previous Trade Calc'!$Q:$Q,'Previous Trade Calc'!$B:$B,MAS!$B$24,'Previous Trade Calc'!$E:$E,D20) -> 0 | E24: =SUMIFS('Previous Trade Calc'!$Q:$Q,'Previous Trade Calc'!$B:$B,MAS!$B$24,'Previous Trade Calc'!$E:$E,E20) -> 0 | F24: =SUMIFS('Previous Trade Calc'!$Q:$Q,'Previous Trade Calc'!$B:$B,MAS!$B$24,'Previous Trade Calc'!$E:$E,F20) -> 0 | G24: =SUMIFS('Previous Trade Calc'!$Q:$Q,'Previous Trade Calc'!$B:$B,MAS!$B$24,'Previous Trade Calc'!$E:$E,G20) -> 0 | H24: =SUMIFS('Previous Trade Calc'!$Q:$Q,'Previous Trade Calc'!$B:$B,MAS!$B$24,'Previous Trade Calc'!$E:$E,H20) -> 0 | I24: =SUMIFS('Previous Trade Calc'!$Q:$Q,'Previous Trade Calc'!$B:$B,MAS!$B$24,'Previous Trade Calc'!$E:$E,I20) -> 0 | J24: =SUMIFS('Previous Trade Calc'!$Q:$Q,'Previous Trade Calc'!$B:$B,MAS!$B$24,'Previous Trade Calc'!$E:$E,J20) -> 0 | K24: =SUMIFS('Previous Trade Calc'!$Q:$Q,'Previous Trade Calc'!$B:$B,MAS!$B$24,'Previous Trade Calc'!$E:$E,K20) -> 0 | L24: =SUMIFS('Previous Trade Calc'!$Q:$Q,'Previous Trade Calc'!$B:$B,MAS!$B$24,'Previous Trade Calc'!$E:$E,L20) -> 0 | M24: =SUM(D24:L24) -> 0
A25: =SUMIFS('Previous Trade Calc'!$Q:$Q,'Previous Trade Calc'!$B:$B,MAS!$B$25,'Previous Trade Calc'!$E:$E,$A$20) -> 0 | B25: GRWETF | D25: =SUMIFS('Previous Trade Calc'!$Q:$Q,'Previous Trade Calc'!$B:$B,MAS!$B$25,'Previous Trade Calc'!$E:$E,D20) -> 0 | E25: =SUMIFS('Previous Trade Calc'!$Q:$Q,'Previous Trade Calc'!$B:$B,MAS!$B$25,'Previous Trade Calc'!$E:$E,E20) -> 0 | F25: =SUMIFS('Previous Trade Calc'!$Q:$Q,'Previous Trade Calc'!$B:$B,MAS!$B$25,'Previous Trade Calc'!$E:$E,F20) -> 0 | G25: =SUMIFS('Previous Trade Calc'!$Q:$Q,'Previous Trade Calc'!$B:$B,MAS!$B$25,'Previous Trade Calc'!$E:$E,G20) -> 0 | H25: =SUMIFS('Previous Trade Calc'!$Q:$Q,'Previous Trade Calc'!$B:$B,MAS!$B$25,'Previous Trade Calc'!$E:$E,H20) -> 0 | I25: =SUMIFS('Previous Trade Calc'!$Q:$Q,'Previous Trade Calc'!$B:$B,MAS!$B$25,'Previous Trade Calc'!$E:$E,I20) -> 0 | J25: =SUMIFS('Previous Trade Calc'!$Q:$Q,'Previous Trade Calc'!$B:$B,MAS!$B$25,'Previous Trade Calc'!$E:$E,J20) -> 0 | K25: =SUMIFS('Previous Trade Calc'!$Q:$Q,'Previous Trade Calc'!$B:$B,MAS!$B$25,'Previous Trade Calc'!$E:$E,K20) -> 0 | L25: =SUMIFS('Previous Trade Calc'!$Q:$Q,'Previous Trade Calc'!$B:$B,MAS!$B$25,'Previous Trade Calc'!$E:$E,L20) -> 0 | M25: =SUM(D25:L25) -> 0
A26: =SUMIFS('Previous Trade Calc'!$Q:$Q,'Previous Trade Calc'!$B:$B,MAS!$B$26,'Previous Trade Calc'!$E:$E,$A$20) -> 0 | B26: ESGETF | D26: =SUMIFS('Previous Trade Calc'!$Q:$Q,'Previous Trade Calc'!$B:$B,MAS!$B$26,'Previous Trade Calc'!$E:$E,D20) -> 0 | E26: =SUMIFS('Previous Trade Calc'!$Q:$Q,'Previous Trade Calc'!$B:$B,MAS!$B$26,'Previous Trade Calc'!$E:$E,E20) -> 0 | F26: =SUMIFS('Previous Trade Calc'!$Q:$Q,'Previous Trade Calc'!$B:$B,MAS!$B$26,'Previous Trade Calc'!$E:$E,F20) -> 0 | G26: =SUMIFS('Previous Trade Calc'!$Q:$Q,'Previous Trade Calc'!$B:$B,MAS!$B$26,'Previous Trade Calc'!$E:$E,G20) -> 0 | H26: =SUMIFS('Previous Trade Calc'!$Q:$Q,'Previous Trade Calc'!$B:$B,MAS!$B$26,'Previous Trade Calc'!$E:$E,H20) -> 0 | I26: =SUMIFS('Previous Trade Calc'!$Q:$Q,'Previous Trade Calc'!$B:$B,MAS!$B$26,'Previous Trade Calc'!$E:$E,I20) -> 0 | J26: =SUMIFS('Previous Trade Calc'!$Q:$Q,'Previous Trade Calc'!$B:$B,MAS!$B$26,'Previous Trade Calc'!$E:$E,J20) -> 0 | K26: =SUMIFS('Previous Trade Calc'!$Q:$Q,'Previous Trade Calc'!$B:$B,MAS!$B$26,'Previous Trade Calc'!$E:$E,K20) -> 0 | L26: =SUMIFS('Previous Trade Calc'!$Q:$Q,'Previous Trade Calc'!$B:$B,MAS!$B$26,'Previous Trade Calc'!$E:$E,L20) -> 0 | M26: =SUM(D26:L26) -> 0
A27: =SUMIFS('Previous Trade Calc'!$Q:$Q,'Previous Trade Calc'!$B:$B,MAS!$B$27,'Previous Trade Calc'!$E:$E,$A$20) -> 0 | B27: BALETF | D27: =SUMIFS('Previous Trade Calc'!$Q:$Q,'Previous Trade Calc'!$B:$B,MAS!$B$27,'Previous Trade Calc'!$E:$E,D20) -> 0 | E27: =SUMIFS('Previous Trade Calc'!$Q:$Q,'Previous Trade Calc'!$B:$B,MAS!$B$27,'Previous Trade Calc'!$E:$E,E20) -> 0 | F27: =SUMIFS('Previous Trade Calc'!$Q:$Q,'Previous Trade Calc'!$B:$B,MAS!$B$27,'Previous Trade Calc'!$E:$E,F20) -> 0 | G27: =SUMIFS('Previous Trade Calc'!$Q:$Q,'Previous Trade Calc'!$B:$B,MAS!$B$27,'Previous Trade Calc'!$E:$E,G20) -> 0 | H27: =SUMIFS('Previous Trade Calc'!$Q:$Q,'Previous Trade Calc'!$B:$B,MAS!$B$27,'Previous Trade Calc'!$E:$E,H20) -> 0 | I27: =SUMIFS('Previous Trade Calc'!$Q:$Q,'Previous Trade Calc'!$B:$B,MAS!$B$27,'Previous Trade Calc'!$E:$E,I20) -> 0 | J27: =SUMIFS('Previous Trade Calc'!$Q:$Q,'Previous Trade Calc'!$B:$B,MAS!$B$27,'Previous Trade Calc'!$E:$E,J20) -> 0 | K27: =SUMIFS('Previous Trade Calc'!$Q:$Q,'Previous Trade Calc'!$B:$B,MAS!$B$27,'Previous Trade Calc'!$E:$E,K20) -> 0 | L27: =SUMIFS('Previous Trade Calc'!$Q:$Q,'Previous Trade Calc'!$B:$B,MAS!$B$27,'Previous Trade Calc'!$E:$E,L20) -> 0 | M27: =SUM(D27:L27) -> 0
A28: =SUMIFS('Previous Trade Calc'!$Q:$Q,'Previous Trade Calc'!$B:$B,MAS!$B$28,'Previous Trade Calc'!$E:$E,$A$20) -> 0 | B28: VPBALETF | D28: =SUMIFS('Previous Trade Calc'!$Q:$Q,'Previous Trade Calc'!$B:$B,MAS!$B$28,'Previous Trade Calc'!$E:$E,D20) -> 0 | E28: =SUMIFS('Previous Trade Calc'!$Q:$Q,'Previous Trade Calc'!$B:$B,MAS!$B$28,'Previous Trade Calc'!$E:$E,E20) -> 0 | F28: =SUMIFS('Previous Trade Calc'!$Q:$Q,'Previous Trade Calc'!$B:$B,MAS!$B$28,'Previous Trade Calc'!$E:$E,F20) -> 0 | G28: =SUMIFS('Previous Trade Calc'!$Q:$Q,'Previous Trade Calc'!$B:$B,MAS!$B$28,'Previous Trade Calc'!$E:$E,G20) -> 0 | H28: =SUMIFS('Previous Trade Calc'!$Q:$Q,'Previous Trade Calc'!$B:$B,MAS!$B$28,'Previous Trade Calc'!$E:$E,H20) -> 0 | I28: =SUMIFS('Previous Trade Calc'!$Q:$Q,'Previous Trade Calc'!$B:$B,MAS!$B$28,'Previous Trade Calc'!$E:$E,I20) -> 0 | J28: =SUMIFS('Previous Trade Calc'!$Q:$Q,'Previous Trade Calc'!$B:$B,MAS!$B$28,'Previous Trade Calc'!$E:$E,J20) -> 0 | K28: =SUMIFS('Previous Trade Calc'!$Q:$Q,'Previous Trade Calc'!$B:$B,MAS!$B$28,'Previous Trade Calc'!$E:$E,K20) -> 0 | L28: =SUMIFS('Previous Trade Calc'!$Q:$Q,'Previous Trade Calc'!$B:$B,MAS!$B$28,'Previous Trade Calc'!$E:$E,L20) -> 0 | M28: =SUM(D28:L28) -> 0
C30: JP Reports Pending Trades | E30: Diff | F30: Failing trades (from stock loan) | G30: Failing Trades | H30: Total
A31: G 27131 | B31: MODETF | C31: =VLOOKUP(A31,'JP Code_Sheet'!$A$2:$E$20,3,0) -> #N/A | E31: =M21-C31 -> #N/A | F31: =VLOOKUP(A31,'JP Code_Sheet'!$A$3:$AC$33,29,0) -> #N/A | G31: =VLOOKUP(A31,'JP Code_Sheet'!$A$3:$X$33,24,0) -> #N/A | H31: =(C31+G31)-F31 -> #N/A
A32: G 27129 | B32: DEFETF | C32: =VLOOKUP(A32,'JP Code_Sheet'!$A$2:$E$20,3,0) -> #N/A | E32: =M22-C32 -> #N/A | F32: =VLOOKUP(A32,'JP Code_Sheet'!$A$3:$AC$33,29,0) -> #N/A | G32: =VLOOKUP(A32,'JP Code_Sheet'!$A$3:$X$33,24,0) -> #N/A | H32: =(C32+G32)-F32 -> #N/A
A33: G 27130 | B33: CONETF | C33: =VLOOKUP(A33,'JP Code_Sheet'!$A$2:$E$20,3,0) -> #N/A | E33: =M23-C33 -> #N/A | F33: =VLOOKUP(A33,'JP Code_Sheet'!$A$3:$AC$33,29,0) -> #N/A | G33: =VLOOKUP(A33,'JP Code_Sheet'!$A$3:$X$33,24,0) -> #N/A | H33: =(C33+G33)-F33 -> #N/A
A34: G 27133 | B34: MGRETF | C34: =VLOOKUP(A34,'JP Code_Sheet'!$A$2:$E$20,3,0) -> #N/A | E34: =M24-C34 -> #N/A | F34: =VLOOKUP(A34,'JP Code_Sheet'!$A$3:$AC$33,29,0) -> #N/A | G34: =VLOOKUP(A34,'JP Code_Sheet'!$A$3:$X$33,24,0) -> #N/A | H34: =(C34+G34)-F34 -> #N/A
A35: G 27134 | B35: GRWETF | C35: =VLOOKUP(A35,'JP Code_Sheet'!$A$2:$E$20,3,0) -> #N/A | E35: =M25-C35 -> #N/A | F35: =VLOOKUP(A35,'JP Code_Sheet'!$A$3:$AC$33,29,0) -> #N/A | G35: =VLOOKUP(A35,'JP Code_Sheet'!$A$3:$X$33,24,0) -> #N/A | H35: =(C35+G35)-F35 -> #N/A
A36: G 39869 | B36: ESGETF | C36: =VLOOKUP(A36,'JP Code_Sheet'!$A$2:$E$20,3,0) -> #N/A | E36: =M26-C36 -> #N/A | F36: =VLOOKUP(A36,'JP Code_Sheet'!$A$3:$AC$33,29,0) -> #N/A | G36: =VLOOKUP(A36,'JP Code_Sheet'!$A$3:$X$33,24,0) -> #N/A | H36: =(C36+G36)-F36 -> #N/A
A37: G 26821 | B37: BALETF | C37: =VLOOKUP(A37,'JP Code_Sheet'!$A$2:$E$20,3,0) -> #N/A | E37: =M27-C37 -> #N/A | F37: =VLOOKUP(A37,'JP Code_Sheet'!$A$3:$AC$33,29,0) -> #N/A | G37: =VLOOKUP(A37,'JP Code_Sheet'!$A$3:$X$33,24,0) -> #N/A | H37: =(C37+G37)-F37 -> #N/A
A38: G 26824 | B38: VPBALETF | C38: =VLOOKUP(A38,'JP Code_Sheet'!$A$2:$E$20,3,0) -> #N/A | E38: =M28-C38 -> #N/A | F38: =VLOOKUP(A38,'JP Code_Sheet'!$A$3:$AC$33,29,0) -> #N/A | G38: =VLOOKUP(A38,'JP Code_Sheet'!$A$3:$X$33,24,0) -> #N/A | H38: =(C38+G38)-F38 -> #N/A
F39: *JP Loans cash from failing trades.
F40: *Deducted from failing trades to avoid cash duplication
F41: *Failing Trades due to stock loan are only front cash past T+2 settlement (even on T+1 trades) (Coded in sheet)
A51: Accounting
C52: MODETF | K52: DEFETF | S52: CONETF | AA52: MGRETF | AI52: GRWETF | AQ52: ESGETF | AY52: BALETF | BG52: VPBALETF
C53: SOD Cash(USD: cash projections) | D53: Sweep (priced positions) | E53: Pending fails | F53: SOD Cash (sheet) | G53: Income | H53: Sub/Red | I53: Trades | J53: CASH EOD (SOD Next day) | K53: SOD Cash(USD: cash projections) | L53: Sweep (priced positions) | M53: Pending fails | N53: SOD Cash (sheet) | O53: Income | P53: Sub/Red | Q53: Trades | R53: CASH EOD (SOD Next day) | S53: SOD Cash(USD: cash projections) | T53: Sweep (priced positions) | U53: Pending fails | V53: SOD Cash (sheet) | W53: Income | X53: Sub/Red | Y53: Trades | Z53: CASH EOD (SOD Next day) | AA53: SOD Cash(USD: cash projections) | AB53: Sweep (priced positions) | AC53: Pending fails | AD53: SOD Cash (sheet) | AE53: Income | AF53: Sub/Red | AG53: Trades | AH53: CASH EOD (SOD Next day) | AI53: SOD Cash(USD: cash projections) | AJ53: Sweep (priced positions) | AK53: Pending fails | AL53: SOD Cash (sheet) | AM53: Income | AN53: Sub/Red | AO53: Trades | AP53: CASH EOD (SOD Next day) | AQ53: SOD Cash(USD: cash projections) | AR53: Sweep (priced positions) | AS53: Pending fails | AT53: SOD Cash (sheet) | AU53: Income | AV53: Sub/Red | AW53: Trades | AX53: CASH EOD (SOD Next day) | AY53: SOD Cash(USD: cash projections) | AZ53: Sweep (priced positions) | BA53: Pending fails | BB53: SOD Cash (sheet) | BC53: Income | BD53: Sub/Red | BE53: Trades | BF53: CASH EOD (SOD Next day) | BG53: SOD Cash(USD: cash projections) | BH53: Sweep (priced positions) | BI53: Pending fails | BJ53: SOD Cash (sheet) | BK53: Income | BL53: Sub/Red | BM53: Trades | BN53: CASH EOD (SOD Next day)
A54: =TODAY() -> 45467 | C54: =D10 -> #N/A | D54: =H10 -> #N/A | E54: =E10 -> #N/A | F54: =C54+D54+E54 -> #N/A | G54: =G10 -> #N/A | H54: =P10 -> #N/A | J54: =F54+G54+H54 -> #N/A | K54: =D11 -> #N/A | L54: =H11 -> #N/A | M54: =E11 -> #N/A | N54: =K54+L54+M54 -> #N/A | O54: =G11 -> #N/A | P54: =P11 -> #N/A | R54: =N54+O54+P54 -> #N/A | S54: =D12 -> #N/A | T54: =H12 -> #N/A | U54: =E12 -> #N/A | V54: =S54+T54+U54 -> #N/A | W54: =G12 -> #N/A | X54: =P12 -> #N/A | Z54: =V54+W54+X54 -> #N/A | AA54: =D13 -> #N/A | AB54: =H13 -> #N/A | AC54: =E13 -> #N/A | AD54: =AA54+AB54+AC54 -> #N/A | AE54: =G13 -> #N/A | AF54: =P13 -> #N/A | AH54: =AD54+AE54+AF54 -> #N/A | AI54: =D14 -> #N/A | AJ54: =H14 -> #N/A | AK54: =E14 -> #N/A | AL54: =AI54+AJ54+AK54 -> #N/A | AM54: =G14 -> #N/A | AN54: =P14 -> #N/A | AP54: =AL54+AM54+AN54 -> #N/A | AQ54: =D15 -> #N/A | AR54: =H15 -> #N/A | AS54: =E15 -> #N/A | AT54: =AQ54+AR54+AS54 -> #N/A | AU54: =G15 -> #N/A | AV54: =P15 -> #N/A | AX54: =AT54+AU54+AV54 -> #N/A | AY54: =D16 -> #N/A | AZ54: =H16 -> #N/A | BA54: =E16 -> #N/A | BB54: =AY54+AZ54+BA54 -> #N/A | BC54: =G16 -> #N/A | BD54: =P16 -> #N/A | BF54: =BB54+BC54+BD54 -> #N/A | BG54: =D17 -> #N/A | BH54: =H17 -> #N/A | BI54: =E17 -> #N/A | BJ54: =BG54+BH54+BI54 -> #N/A | BK54: =G17 -> #N/A | BL54: =P17 -> #N/A | BN54: =BJ54+BK54+BL54 -> #N/A

Sheet Francis
A1: Custody # | B1: Portfolio | C1: Name of Fund | D1: Trade Check | E1: SOD Cash(USD: cash projections) | F1: SOD Cash FX (base) | G1: Pending Trades +Failing (JP/BNY) | H1: Futures Vari (as of previous day: detailed net asset val) | I1: Income (projections) | J1: Sweep (priced positions) | K1: Collateral & MD | L1: Total Cash | M1: T-BILL (priced positions) | N1: Equity MV (priced positions) | P1: Total Assets | Q1: Percent Cash | R1: Cash Flow (cash projection) | S1: Net Cash | T1: Percent Net Cash | U1: FUTURE Yest Close | V1: FUTURE Yest Close -2 | W1: VARIATION MARGIN | X1: FUTURES | Y1: FUTURE/ETF PRICE | Z1: NET CASH + TBILLS + VARIATION MARGIN | AA1: FUTURE MV | AB1: INVESTABLE | AC1: FUTURE/ETF CONTRACTS | AD1: PORTFOLIO | AH1: Drives Entire sheet | AJ1: SETTLE T0 | AK1: SETTLE T1 | AL1: SETTLE T2 | AM1: PORTFOLIO | AS1: TBILLS | AT1: TBILLS | AX1: Drives Entire sheet | AZ1: INTRADAY PENDING TRADES T0 | BA1: INTRADAY PENDING TRADES T1 | BB1: INTRADAY PENDING TRADES T2 | BC1: FUTURES + INTRADAY FUTURES | BD1: FUTURE/ETF PRICE | BE1: NET CASH + TBILLS + VARIATION MARGIN + PENDING TRADES | BF1: FUTURE MV | BI1: INVESTABLE | BJ1: FUTURE/ETF CONTRACTS | BK1: PORTFOLIO | BQ1: SETTLE T0 | BR1: SETTLE T1 | BS1: SETTLE T2 | BT1: PORTFOLIO | BZ1: MOC PENDING TRADES + SUB/RED MOC T1 | CA1: MOC PENDING TRADES + SUB/RED MOC T2 | CB1: FUTURES + INTRADAY FUTURES | CC1: FUTURE/ETF PRICE | CD1: NET CASH + TBILLS + VARIATION MARGIN + PENDING TRADES | CE1: FUTURE MV | CH1: INVESTABLE | CI1: FUTURE/ETF CONTRACTS | CJ1: PORTFOLIO | CP1: SETTLE T0 | CQ1: SETTLE T1 | CR1: SETTLE T2 | CS1: PORTFOLIO
A2: G 26763 | B2: MAINSP | C2: MainStay S&P 500 Index Fund | D2: =IF(P24>10000,"Don't Trade (Check Variation)","Trade (Variation Good)") -> #NAME? | E2: =VLOOKUP(A2,'JP Code_Sheet'!$A$2:$E$20,2,0) -> #N/A | G2: =VLOOKUP(A2,$A$23:$G$27,7,0) -> #N/A | I2: =VLOOKUP(A2,'JP Code_Sheet'!$A$2:$E$20,4,0) -> #N/A | J2: =VLOOKUP(A2,'JP Code_Sheet'!$A$3:$F$32,6,0) -> #N/A | L2: =E2+G2+I2+J2+K2+F2 -> #N/A | M2: =Equitizer_Mainsp_CALC!H17 -> 0 | N2: =SUMIFS('Eze Export_equitizer_MAINSP'!H:H,'Eze Export_equitizer_MAINSP'!B:B,"CSUS") -> 0 | P2: =L2+D23+N2 -> #N/A | Q2: =L2/P2 -> #N/A | R2: =VLOOKUP(A2,'JP Code_Sheet'!$A$3:$L$33,12,0) -> #N/A | S2: =L2+R2 -> #N/A | T2: =S2/P2 -> #N/A | U2: =_xll.BDP(AH2&" INDEX","px_close_1d") -> #NAME? | V2: {=_xll.BDP(AH2&" INDEX","px_close_2d")} -> #NAME? | W2: =(U2-V2)*50*X2 -> #NAME? | X2: =Equitizer_Mainsp_CALC!F5 -> 0 | Y2: {=_xll.BDP(AH2&" index","px_last")} -> #NAME? | Z2: =S2+M2+W2 -> #N/A | AA2: =X2*U2*50 -> #NAME? | AB2: =Z2-AA2 -> #N/A | AC2: =IF(AB2>0,ROUNDDOWN(AB2/(Y2*50),0),ROUNDUP(AB2/(Y2*50),0)) -> #N/A | AD2: =B2 -> MAINSP | AE2: =TODAY() -> 45467 | AF2: =TODAY() -> 45467 | AG2: =IF(AC2=0,"",IF(AC2>0,"BUY","SELL")) -> #N/A | AI2: =IF(AG2="SELL",IF(ABS(AC2)>X2,"CHECK",ABS(AC2)),ABS(AC2)) -> #N/A | AM2: =AD2 -> MAINSP | AS2: =S2+W2-G14-F14-E14 -> #N/A | AT2: =IF(AS2>0,ROUNDDOWN(AS2,-5),ROUNDUP(AS2,-5)) -> #N/A | AU2: =TODAY() -> 45467 | AV2: =TODAY() -> 45467 | AW2: =IF(AT2>=0,IF((ABS(AT2))>=100000,"BUY",""),"SELL") -> #N/A | AY2: =IF(AW2="SELL",IF(ABS(AT2)>Equitizer_Mainsp_CALC!H17,"CHECK",IF(AT2>0,IF((AT2)>=100000,ABS(AT2),""),-AT2)),IF(AT2>0,IF((AT2)>=100000,ABS(AT2),""),-AT2)) -> #N/A | AZ2: 0 | BC2: =X2+AC2 -> #N/A | BD2: {=_xll.BDP(AH2&" index","px_last")} -> #NAME? | BE2: =Z2+AZ2+BA2+BB2 -> #N/A | BF2: =BC2*BD2*50 -> #N/A | BI2: =BE2-BF2 -> #N/A | BJ2: =IF(BI2>0,ROUNDDOWN(BI2/(BD2*50),0),ROUNDUP(BI2/(BD2*50),0)) -> #N/A | BK2: =AD2 -> MAINSP | BL2: =AE2 -> 45467 | BM2: =AF2 -> 45467 | BN2: =IF(BJ2=0,"",IF(BJ2>0,"Buy","Sell")) -> #N/A | BO2: =AH2 -> 0 | BP2: =ABS(BJ2) -> #N/A | BT2: =BK2 -> MAINSP | BZ2: 0 | CA2: 0 | CB2: =BC2+BJ2 -> #N/A | CC2: {=_xll.BDP(AH2&" index","px_last")} -> #NAME? | CD2: =BE2+BZ2+CA2 -> #N/A | CE2: =CB2*CC2*50 -> #N/A | CH2: =CD2-CE2 -> #N/A | CI2: =IF(CH2>0,ROUNDDOWN(CH2/(CC2*50),0),ROUNDUP(CH2/(CC2*50),0)) -> #N/A | CJ2: =BK2 -> MAINSP | CK2: =BL2 -> 45467 | CL2: =BM2 -> 45467 | CM2: =IF(CI2=0,"",IF(CI2>0,"Buy","Sell")) -> #N/A | CN2: =AH2 -> 0 | CO2: =ABS(CI2) -> #N/A | CS2: =CJ2 -> MAINSP
A3: G 26794 | B3: VPIE | C3: MainStay VP S&P 500 Index Portfolio | D3: =IF(P25>10000,"Don't Trade (Check Variation)","Trade (Variation Good)") -> #NAME? | E3: =VLOOKUP(A3,'JP Code_Sheet'!$A$2:$E$32,2,0) -> #N/A | G3: =VLOOKUP(A3,$A$23:$G$27,7,0) -> #N/A | I3: =VLOOKUP(A3,'JP Code_Sheet'!$A$2:$E$32,4,0) -> #N/A | J3: =VLOOKUP(A3,'JP Code_Sheet'!$A$3:$F$32,6,0) -> #N/A | L3: =E3+G3+I3+J3+K3+F3 -> #N/A | M3: =Equitizer_VPIE_CALC!H17 -> 0 | N3: =SUMIFS('Eze Export_equitizer_VPIE'!H:H,'Eze Export_equitizer_VPIE'!B:B,"CSUS") -> 0 | P3: =L3+D24+N3 -> #N/A | Q3: =L3/P3 -> #N/A | R3: =VLOOKUP(A3,'JP Code_Sheet'!$A$3:$L$33,12,0) -> #N/A | S3: =L3+R3 -> #N/A | T3: =S3/P3 -> #N/A | U3: =_xll.BDP(AH3&" INDEX","px_close_1d") -> #NAME? | V3: {=_xll.BDP(AH3&" INDEX","px_close_2d")} -> #NAME? | W3: =(U3-V3)*50*X3 -> #NAME? | X3: =Equitizer_VPIE_CALC!F5 -> 0 | Y3: {=_xll.BDP(AH3&" index","px_last")} -> #NAME? | Z3: =S3+M3+W3 -> #N/A | AA3: =X3*U3*50 -> #NAME? | AB3: =Z3-AA3 -> #N/A | AC3: =IF(AB3>0,ROUNDDOWN(AB3/(Y3*50),0),ROUNDUP(AB3/(Y3*50),0)) -> #N/A | AD3: =B3 -> VPIE | AE3: =TODAY() -> 45467 | AF3: =TODAY() -> 45467 | AG3: =IF(AC3=0,"",IF(AC3>0,"BUY","SELL")) -> #N/A | AI3: =IF(AG3="SELL",IF(ABS(AC3)>X3,"CHECK",ABS(AC3)),ABS(AC3)) -> #N/A | AM3: =AD3 -> VPIE | AS3: =S3+W3-G15-F15-E15 -> #N/A | AT3: =IF(AS3>0,ROUNDDOWN(AS3,-5),ROUNDUP(AS3,-5)) -> #N/A | AU3: =TODAY() -> 45467 | AV3: =TODAY() -> 45467 | AW3: =IF(AT3>=0,IF((ABS(AT3))>=100000,"BUY",""),"SELL") -> #N/A | AY3: =IF(AW3="SELL",IF(ABS(AT3)>Equitizer_VPIE_CALC!H17,"CHECK",IF(AT3>0,IF((AT3)>=100000,ABS(AT3),""),-AT3)),IF(AT3>0,IF((AT3)>=100000,ABS(AT3),""),-AT3)) -> #N/A | AZ3: 0 | BC3: =X3+AC3 -> #N/A | BD3: {=_xll.BDP(AH3&" index","px_last")} -> #NAME? | BE3: =Z3+AZ3+BA3+BB3 -> #N/A | BF3: =BC3*BD3*50 -> #N/A | BI3: =BE3-BF3 -> #N/A | BJ3: =IF(BI3>0,ROUNDDOWN(BI3/(BD3*50),0),ROUNDUP(BI3/(BD3*50),0)) -> #N/A | BK3: =AD3 -> VPIE | BL3: =AE3 -> 45467 | BM3: =AF3 -> 45467 | BN3: =IF(BJ3=0,"",IF(BJ3>0,"Buy","Sell")) -> #N/A | BO3: =AH3 -> 0 | BP3: =ABS(BJ3) -> #N/A | BT3: =BK3 -> VPIE | BZ3: 0 | CA3: 0 | CB3: =BC3+BJ3 -> #N/A | CC3: {=_xll.BDP(AH3&" index","px_last")} -> #NAME? | CD3: =BE3+BZ3+CA3 -> #N/A | CE3: =CB3*CC3*50 -> #N/A | CH3: =CD3-CE3 -> #N/A | CI3: =IF(CH3>0,ROUNDDOWN(CH3/(CC3*50),0),ROUNDUP(CH3/(CC3*50),0)) -> #N/A | CJ3: =BK3 -> VPIE | CK3: =BL3 -> 45467 | CL3: =BM3 -> 45467 | CM3: =IF(CI3=0,"",IF(CI3>0,"Buy","Sell")) -> #N/A | CN3: =AH3 -> 0 | CO3: =ABS(CI3) -> #N/A | CS3: =CJ3 -> VPIE
A4: G 09047 | B4: NYLPIE | C4: NYL SEP ACCT 10A | E4: =VLOOKUP(A4,'JP Code_Sheet'!$A$2:$E$32,2,0) -> #N/A | G4: =VLOOKUP(A4,$A$23:$G$27,7,0) -> #N/A | I4: =VLOOKUP(A4,'JP Code_Sheet'!$A$2:$E$32,4,0) -> #N/A | J4: =VLOOKUP(A4,'JP Code_Sheet'!$A$3:$F$32,6,0) -> #N/A | L4: =E4+G4+I4+J4+K4+F4 -> #N/A | N4: =VLOOKUP(A4,'JP Code_Sheet'!$A$3:$H$32,8,0) -> #N/A | P4: =L4+M4+N4 -> #N/A | Q4: =L4/P4 -> #N/A | R4: =VLOOKUP(A4,'JP Code_Sheet'!$A$3:$L$33,12,0) -> #N/A | S4: =L4+R4 -> #N/A | T4: =S4/P4 -> #N/A | Y4: {=_xll.BDP("VOO EQUITY","px_last")} -> #NAME? | AB4: =S4-(P4*0.00002) -> #N/A | AC4: =IF(S4>0,IF(ABS(T4)>0.0001,ROUND(AB4/Y4,0),0),ROUNDUP(S4/Y4,-1)) -> #N/A | AD4: =B4 -> NYLPIE | AJ4: =$S4+(D16-G4) -> #N/A | AK4: =$S4+(D16+E16-G4) -> #N/A | AL4: =$S4+(D16+E16+F16-G4) -> #N/A | AM4: =AD4 -> NYLPIE | AN4: =TODAY() -> 45467 | AO4: =IF(AJ4<0,AN4,IF(AK4<0,WORKDAY(AN4,1),WORKDAY(AN4,1))) -> #N/A | AP4: =IF(AC4=0,"",IF(AC4>0,"Buy","Sell")) -> #N/A | AQ4: VOO | AR4: =ABS(AC4) -> #N/A | AZ4: 0 | BA4: 0 | BB4: 0 | BD4: {=_xll.BDP("VOO EQUITY","px_last")} -> #NAME? | BG4: =S4+AZ4+BA4+BB4+(-AC4*BD4) -> #N/A | BH4: =BG4/P4 -> #N/A | BI4: =BG4-(P4*0.00002) -> #N/A | BJ4: =IF(BI4>0,IF(ABS(BH4)>0.0001,ROUND(BI4/BD4,0),0),ROUNDUP(BI4/BD4,-1)) -> #N/A | BK4: =AD4 -> NYLPIE | BQ4: =AJ4+IF((NETWORKDAYS($AN4,$AO4,0)=1),-$AC4*$BD4,0)+AZ4 -> #N/A | BR4: =BQ4+IF((NETWORKDAYS($AN4,$AO4,0)=2),-$AC4*$BD4,0)+BA4 -> #N/A | BS4: =BR4+IF((NETWORKDAYS($AN4,$AO4,0)=3),-$AC4*$BD4,0)+BB4 -> #N/A | BT4: =BK4 -> NYLPIE | BU4: =TODAY() -> 45467 | BV4: =IF(BQ4<0,BU4,IF(BR4<0,WORKDAY(BU4,1),WORKDAY(BU4,1))) -> #N/A | BW4: =IF(BJ4=0,"",IF(BJ4>0,"Buy","Sell")) -> #N/A | BX4: VOO | BY4: =ABS(BJ4) -> #N/A | BZ4: 0 | CA4: 0 | CC4: {=_xll.BDP("VOO EQUITY","px_last")} -> #NAME? | CF4: =BG4+BZ4+CA4+(-BJ4*CC4) -> #N/A | CG4: =CF4/P4 -> #N/A | CH4: =CF4-(AO4*0.00002) -> #N/A | CI4: =IF(CH4>0,IF(ABS(CG4)>0.0001,ROUND(CH4/CC4,0),0),ROUNDUP(CH4/CC4,-1)) -> #N/A | CJ4: =BK4 -> NYLPIE | CP4: =BQ4+IF((NETWORKDAYS($BU4,$BV4,0)=1),-$BJ4*$BD4,0) -> #N/A | CQ4: =CP4+IF((NETWORKDAYS($BU4,$BV4,0)=2),-$BJ4*$BD4,0)+BZ4 -> #N/A | CR4: =CQ4+IF((NETWORKDAYS($BU4,$BV4,0)=3),-$BJ4*$BD4,0)+CA4 -> #N/A | CS4: =CJ4 -> NYLPIE | CT4: =TODAY() -> 45467 | CU4: =IF(CP4<0,CT4+1,IF(CQ4<0,WORKDAY(CT4,1),WORKDAY(CT4,1))) -> #N/A | CV4: =IF(CI4=0,"",IF(CI4>0,"Buy","Sell")) -> #N/A | CW4: VOO | CX4: =ABS(CI4) -> #N/A | CY4: MOC
A5: G 01324 | B5: FOUNDLCE | C5: NEW YORK LIFE FOUN | E5: =VLOOKUP(A5,'JP Code_Sheet'!$A$2:$E$32,2,0) -> #N/A | G5: =VLOOKUP(A5,$A$23:$G$27,7,0) -> #N/A | I5: =VLOOKUP(A5,'JP Code_Sheet'!$A$2:$E$32,4,0) -> #N/A | J5: =VLOOKUP(A5,'JP Code_Sheet'!$A$3:$F$32,6,0) -> #N/A | L5: =E5+G5+I5+J5+K5+F5 -> #N/A | N5: =VLOOKUP(A5,'JP Code_Sheet'!$A$3:$H$32,8,0) -> #N/A | P5: =L5+M5+N5 -> #N/A | Q5: =L5/P5 -> #N/A | R5: =VLOOKUP(A5,'JP Code_Sheet'!$A$3:$L$33,12,0) -> #N/A | S5: =L5+R5 -> #N/A | T5: =S5/P5 -> #N/A | Y5: {=_xll.BDP("VOO EQUITY","px_last")} -> #NAME? | AB5: =S5-(P5*0.00002) -> #N/A | AC5: =IF(S5>0,IF(ABS(T5)>0.00015,ROUND(AB5/Y5,0),0),ROUNDUP(S5/Y5,0)) -> #N/A | AD5: =B5 -> FOUNDLCE | AJ5: =$S5+(D17-G5) -> #N/A | AK5: =$S5+(D17+E17-G5) -> #N/A | AL5: =$S5+(D17+E17+F17-G5) -> #N/A | AM5: =AD5 -> FOUNDLCE | AN5: =TODAY() -> 45467 | AO5: =IF(AJ5<0,AN5,IF(AK5<0,WORKDAY(AN5,1),WORKDAY(AN5,1))) -> #N/A | AP5: =IF(AC5=0,"",IF(AC5>0,"Buy","Sell")) -> #N/A | AQ5: VOO | AR5: =ABS(AC5) -> #N/A | AZ5: 0 | BA5: 0 | BB5: 0 | BD5: {=_xll.BDP("VOO EQUITY","px_last")} -> #NAME? | BG5: =S5+AZ5+BA5+BB5+(-AC5*BD5) -> #N/A | BH5: =BG5/P5 -> #N/A | BI5: =BG5-(P5*0.00002) -> #N/A | BJ5: =IF(BI5>0,IF(ABS(BH5)>0.0001,ROUND(BI5/BD5,0),0),ROUNDUP(BI5/BD5,-1)) -> #N/A | BK5: =AD5 -> FOUNDLCE | BQ5: =AJ5+IF((NETWORKDAYS($AN5,$AO5,0)=1),-$AC5*$BD5,0)+AZ5 -> #N/A | BR5: =BQ5+IF((NETWORKDAYS($AN5,$AO5,0)=2),-$AC5*$BD5,0)+BA5 -> #N/A | BS5: =BR5+IF((NETWORKDAYS($AN5,$AO5,0)=3),-$AC5*$BD5,0)+BB5 -> #N/A | BT5: =BK5 -> FOUNDLCE | BU5: =TODAY() -> 45467 | BV5: =IF(BQ5<0,BU5,IF(BR5<0,WORKDAY(BU5,1),WORKDAY(BU5,1))) -> #N/A | BW5: =IF(BJ5=0,"",IF(BJ5>0,"Buy","Sell")) -> #N/A | BX5: VOO | BY5: =ABS(BJ5) -> #N/A | BZ5: 0 | CA5: 0 | CC5: {=_xll.BDP("VOO EQUITY","px_last")} -> #NAME? | CF5: =BG5+BZ5+CA5+(-BJ5*CC5) -> #N/A | CG5: =CF5/P5 -> #N/A | CH5: =CF5-(AO5*0.00002) -> #N/A | CI5: =IF(CH5>0,IF(ABS(CG5)>0.0001,ROUND(CH5/CC5,0),0),ROUNDUP(CH5/CC5,-1)) -> #N/A | CJ5: =BK5 -> FOUNDLCE | CP5: =BQ5+IF((NETWORKDAYS($BU5,$BV5,0)=1),-$BJ5*$BD5,0) -> #N/A | CQ5: =CP5+IF((NETWORKDAYS($BU5,$BV5,0)=2),-$BJ5*$BD5,0)+BZ5 -> #N/A | CR5: =CQ5+IF((NETWORKDAYS($BU5,$BV5,0)=3),-$BJ5*$BD5,0)+CA5 -> #N/A | CS5: =CJ5 -> FOUNDLCE | CT5: =TODAY() -> 45467 | CU5: =IF(CP5<0,WORKDAY(CT5,1),IF(CQ5<0,WORKDAY(CT5,1),WORKDAY(CT5,1))) -> #N/A | CV5: =IF(CI5=0,"",IF(CI5>0,"Buy","Sell")) -> #N/A | CW5: VOO | CX5: =ABS(CI5) -> #N/A | CY5: MOC
A6: G 01305 | B6: GIAACWIP | C6: NYLIAC - GIA ACWI | E6: =VLOOKUP(A6,'JP Code_Sheet'!$A$2:$E$32,2,0) -> #N/A | G6: =VLOOKUP(A6,$A$23:$G$27,7,0) -> #NAME? | I6: ='JP Code_Sheet'!D37 -> 0 | J6: =VLOOKUP(A6,'JP Code_Sheet'!$A$3:$F$32,6,0) -> #N/A | L6: =E6+G6+I6+J6+K6+F6 -> #N/A | N6: ='JP Code_Sheet'!H37 -> 0 | P6: =L6+M6+N6 -> #N/A | Q6: =L6/P6 -> #N/A | R6: =VLOOKUP(A6,'JP Code_Sheet'!$A$3:$L$33,12,0) -> #N/A | S6: =L6+R6 -> #N/A | T6: =S6/P6 -> #N/A | Y6: {=_xll.BDP("ACWI EQUITY","px_last")} -> #NAME? | AB6: =S6-(P6*0.00002) -> #N/A | AC6: =IF(S6>0,IF(ABS(T6)>0.0001,ROUND(AB6/Y6,0),0),ROUNDUP(S6/Y6,-1)) -> #N/A | AD6: =B6 -> GIAACWIP | AJ6: =$S6+(D18-G6) -> #N/A | AK6: =$S6+(D18+E18-G6) -> #N/A | AL6: =$S6+(D18+E18+F18-G6) -> #N/A | AM6: =AD6 -> GIAACWIP | AN6: =TODAY() -> 45467 | AO6: =IF(AJ6<0,AN6,IF(AK6<0,WORKDAY(AN6,1),WORKDAY(AN6,1))) -> #N/A | AP6: =IF(AC6=0,"",IF(AC6>0,"Buy","Sell")) -> #N/A | AQ6: ACWI | AR6: =ABS(AC6) -> #N/A | AZ6: 0 | BA6: 0 | BB6: 0 | BD6: {=_xll.BDP("ACWI EQUITY","px_last")} -> #NAME? | BG6: =S6+AZ6+BA6+BB6+(-AC6*BD6) -> #N/A | BH6: =BG6/P6 -> #N/A | BI6: =BG6-(P6*0.00002) -> #N/A | BJ6: =IF(BI6>0,IF(ABS(BH6)>0.0001,ROUND(BI6/BD6,0),0),ROUNDUP(BI6/BD6,-1)) -> #N/A | BK6: =AD6 -> GIAACWIP | BQ6: =AJ6+IF((NETWORKDAYS($AN6,$AO6,0)=1),-$AC6*$BD6,0)+AZ6 -> #N/A | BR6: =BQ6+IF((NETWORKDAYS($AN6,$AO6,0)=2),-$AC6*$BD6,0)+BA6 -> #N/A | BS6: =BR6+IF((NETWORKDAYS($AN6,$AO6,0)=3),-$AC6*$BD6,0)+BB6 -> #N/A | BT6: =BK6 -> GIAACWIP | BU6: =TODAY() -> 45467 | BV6: =IF(BQ6<0,BU6,IF(BR6<0,WORKDAY(BU6,1),WORKDAY(BU6,1))) -> #N/A | BW6: =IF(BJ6=0,"",IF(BJ6>0,"Buy","Sell")) -> #N/A | BX6: ACWI | BY6: =ABS(BJ6) -> #N/A | BZ6: 0 | CA6: 0 | CC6: {=_xll.BDP("ACWI EQUITY","px_last")} -> #NAME? | CF6: =BG6+BZ6+CA6+(-BJ6*CC6) -> #N/A | CG6: =CF6/P6 -> #N/A | CH6: =CF6-(AO6*0.00002) -> #N/A | CI6: =IF(CH6>0,IF(ABS(CG6)>0.0001,ROUND(CH6/CC6,0),0),ROUNDUP(CH6/CC6,-1)) -> #N/A | CJ6: =BK6 -> GIAACWIP | CP6: =BQ6+IF((NETWORKDAYS($BU6,$BV6,0)=1),-$BJ6*$BD6,0) -> #N/A | CQ6: =CP6+IF((NETWORKDAYS($BU6,$BV6,0)=2),-$BJ6*$BD6,0)+BZ6 -> #N/A | CR6: =CQ6+IF((NETWORKDAYS($BU6,$BV6,0)=3),-$BJ6*$BD6,0)+CA6 -> #N/A | CS6: =CJ6 -> GIAACWIP | CT6: =TODAY() -> 45467 | CU6: =IF(CP6<0,WORKDAY(CT6,1),IF(CQ6<0,WORKDAY(CT6,1),WORKDAY(CT6,1))) -> #N/A | CV6: =IF(CI6=0,"",IF(CI6>0,"Buy","Sell")) -> #N/A | CW6: ACWI | CX6: =ABS(CI6) -> #N/A | CY6: MOC
A7: 353109 | B7: GIA1902 | C7: NYLIAC GENERAL (GIA), 190 | E7: =VLOOKUP(A7,'JP Code_Sheet'!$A$67:$B$71,2,0) -> #N/A | G7: =VLOOKUP(A7,$A$29:$G$29,7,0) -> #N/A | I7: =VLOOKUP(A7,'JP Code_Sheet'!$A$67:$D$71,4,0) -> #N/A | L7: =E7+G7+I7+J7+K7+F7 -> #N/A | N7: =VLOOKUP(A7,'JP Code_Sheet'!$A$67:$H$71,8,0) -> #N/A | P7: =L7+M7+N7 -> #N/A | Q7: =L7/P7 -> #N/A | S7: =L7+R7 -> #N/A | T7: =S7/P7 -> #N/A | Y7: {=_xll.BDP("VOO EQUITY","px_last")} -> #NAME? | AB7: =S7-(P7*0.00002) -> #N/A | AC7: =IF(S7>0,IF(ABS(T7)>0.0001,ROUND(AB7/Y7,0),0),ROUNDUP(S7/Y7,-1)) -> #N/A | AD7: =B7 -> GIA1902 | AJ7: =$S7+(D19-G7) -> #N/A | AK7: =$S7+(D19+E19-G7) -> #N/A | AL7: =$S7+(D19+E19+F19-G7) -> #N/A | AM7: =AD7 -> GIA1902 | AN7: =TODAY() -> 45467 | AO7: =IF(AJ7<0,AN7,IF(AK7<0,WORKDAY(AN7,1),WORKDAY(AN7,1))) -> #N/A | AP7: =IF(AC7=0,"",IF(AC7>0,"Buy","Sell")) -> #N/A | AQ7: VOO | AR7: =ABS(AC7) -> #N/A | AZ7: 0 | BA7: 0 | BB7: 0 | BD7: {=_xll.BDP("VOO EQUITY","px_last")} -> #NAME? | BG7: =S7+AZ7+BA7+BB7+(-AC7*BD7) -> #N/A | BH7: =BG7/P7 -> #N/A | BI7: =BG7-(P7*0.00002) -> #N/A | BJ7: =IF(BI7>0,IF(ABS(BH7)>0.0001,ROUND(BI7/BD7,0),0),ROUNDUP(BI7/BD7,-1)) -> #N/A | BK7: =AD7 -> GIA1902 | BQ7: =AJ7+IF((NETWORKDAYS($AN7,$AO7,0)=1),-$AC7*$BD7,0)+AZ7 -> #N/A | BR7: =BQ7+IF((NETWORKDAYS($AN7,$AO7,0)=2),-$AC7*$BD7,0)+BA7 -> #N/A | BS7: =BR7+IF((NETWORKDAYS($AN7,$AO7,0)=3),-$AC7*$BD7,0)+BB7 -> #N/A | BT7: =BK7 -> GIA1902 | BU7: =TODAY() -> 45467 | BV7: =IF(BQ7<0,BU7,IF(BR7<0,WORKDAY(BU7,1),WORKDAY(BU7,1))) -> #N/A | BW7: =IF(BJ7=0,"",IF(BJ7>0,"Buy","Sell")) -> #N/A | BX7: VOO | BY7: =ABS(BJ7) -> #N/A | BZ7: 0 | CA7: =BA7 -> 0 | CC7: {=_xll.BDP("VOO EQUITY","px_last")} -> #NAME? | CF7: =BG7+BZ7+CA7+(-BJ7*CC7) -> #N/A | CG7: =CF7/P7 -> #N/A | CH7: =CF7-(AO7*0.00002) -> #N/A | CI7: =IF(CH7>0,IF(ABS(CG7)>0.0001,ROUND(CH7/CC7,0),0),ROUNDUP(CH7/CC7,-1)) -> #N/A | CJ7: =BK7 -> GIA1902 | CP7: =BQ7+IF((NETWORKDAYS($BU7,$BV7,0)=1),-$BJ7*$BD7,0) -> #N/A | CQ7: =CP7+IF((NETWORKDAYS($BU7,$BV7,0)=2),-$BJ7*$BD7,0)+BZ7 -> #N/A | CR7: =CQ7+IF((NETWORKDAYS($BU7,$BV7,0)=3),-$BJ7*$BD7,0)+CA7 -> #N/A | CS7: =CJ7 -> GIA1902 | CT7: =TODAY() -> 45467 | CU7: =IF(CP7<0,WORKDAY(CT7,1),IF(CQ7<0,WORKDAY(CT7,1),WORKDAY(CT7,1))) -> #N/A | CV7: =IF(CI7=0,"",IF(CI7>0,"Buy","Sell")) -> #N/A | CW7: VOO | CX7: =ABS(CI7) -> #N/A | CY7: MOC
M8: Could be off T+1 accounting | N8: Could be off T+1 accounting | AZ8: FROM LOADED TRADES - TRITON OR EZE | BK8: COPY TO PE TRADE FILE FOR EZE UPLOAD | BT8: COPY TO PE TRADE FILE FOR EZE UPLOAD | CJ8: COPY TO PE TRADE FILE FOR EZE UPLOAD | CS8: COPY TO PE TRADE FILE FOR EZE UPLOAD
E9: GIAACWIP | F9: ='JP Code_Sheet'!B35 -> 0 | N9: Posted Custidy report | Q9: =B2 -> MAINSP | U9: REFRESH BLOOMBERG | X9: REFRESH FUTURES HOLDING | AD9: MORNING CASH | AF9: COPY TO DAILY EZE UPLOAD | AM9: MORNING CASH | AO9: COPY TO DAILY EZE UPLOAD | AU9: MORNING CASH | AW9: COPY TO DAILY EZE UPLOAD
F10: Local CCY bal coverted to USD | Q10: SUBSCRIPTION TO FUND | R10: =SUMIFS('JP_Cash Projection - Detail'!AV:AV,'JP_Cash Projection - Detail'!I:I,A2,'JP_Cash Projection - Detail'!W:W,Francis!Q10) -> 0 | AD10: FUTURES | AM10: ETFS | AU10: TBILLS
F11: Not factored in Daily Trade Calc | Q11: REDEMPTION TO FUND | R11: =SUMIFS('JP_Cash Projection - Detail'!AV:AV,'JP_Cash Projection - Detail'!I:I,A2,'JP_Cash Projection - Detail'!W:W,Francis!Q11) -> 0
A12: T-0 | C12: EZE | R12: =SUM(R10:R11) -> 0 | AE12: Account | AF12: BBSYMBOL | AG12: Country | AH12: Side | AI12: Target Size | AO12: Trade Cusip | AP12: Current Eze TBill Position | AQ12: Tbill Position after Trade | AR12: Trade Month | AS12: Trade Check | AU12: TS | AV12: Side | AW12: Qty(M) | AX12: Settle Date | AY12: Account | CJ12: MOC | CS12: MOC
A13: =D13-1 -> 45466 | B13: S/D | D13: ='JP Code_Sheet'!A1 -> 45467 | E13: =D13+1 -> 45468 | F13: =E13+1 -> 45469 | G13: =F13+1 -> 45470 | H13: =G13+1 -> 45471 | I13: =H13+1 -> 45472 | J13: =I13+1 -> 45473 | K13: =J13+1 -> 45474 | L13: Total Pending | Q13: =B3 -> VPIE | U13: Net Cash | AE13: 00102703 | AF13: =AH2&" Index" -> Index | AG13: USA | AH13: =IF(AG2="SELL","S","B") -> #N/A | AI13: =AI2 -> #N/A | AO13: =_xll.BDP(AU13&" isin","ID_CUSIP_REAL") -> #NAME? | AP13: =IFERROR(VLOOKUP(AO13,'Eze Export_equitizer_MAINSP'!$C$3:$G$515,5,0),0) -> 0 | AQ13: =IF(AV13="s",AP13-AW13,0) -> #N/A | AR13: =_xll.BDP(AU13&" isin","security name") -> #NAME? | AS13: =IF(AQ13>0,"Continue with TBill Trade","Check TBill ISIN") -> #N/A | AU13: =AX2 -> 0 | AV13: =IF(AW2="SELL","S","B") -> #N/A | AW13: =AY2/1000 -> #N/A | AX13: =AV2 -> 45467 | AY13: MAINSP | CJ13: INSTRUCT SETTLE DATE | CS13: INSTUCT SETTLE DATE
A14: =SUMIFS('Previous Trade Calc'!$Q:$Q,'Previous Trade Calc'!$B:$B,$B$14,'Previous Trade Calc'!$E:$E,A13) -> 0 | B14: MAINSP | D14: =SUMIFS('Previous Trade Calc'!$Q:$Q,'Previous Trade Calc'!$B:$B,$B$14,'Previous Trade Calc'!$E:$E,D13) -> 0 | E14: =SUMIFS('Previous Trade Calc'!$Q:$Q,'Previous Trade Calc'!$B:$B,$B$14,'Previous Trade Calc'!$E:$E,E13) -> 0 | F14: =SUMIFS('Previous Trade Calc'!$Q:$Q,'Previous Trade Calc'!$B:$B,$B$14,'Previous Trade Calc'!$E:$E,F13) -> 0 | G14: =SUMIFS('Previous Trade Calc'!$Q:$Q,'Previous Trade Calc'!$B:$B,$B$14,'Previous Trade Calc'!$E:$E,G13) -> 0 | H14: =SUMIFS('Previous Trade Calc'!$Q:$Q,'Previous Trade Calc'!$B:$B,$B$14,'Previous Trade Calc'!$E:$E,H13) -> 0 | I14: =SUMIFS('Previous Trade Calc'!$Q:$Q,'Previous Trade Calc'!$B:$B,$B$14,'Previous Trade Calc'!$E:$E,I13) -> 0 | J14: =SUMIFS('Previous Trade Calc'!$Q:$Q,'Previous Trade Calc'!$B:$B,$B$14,'Previous Trade Calc'!$E:$E,J13) -> 0 | K14: =SUMIFS('Previous Trade Calc'!$Q:$Q,'Previous Trade Calc'!$B:$B,$B$14,'Previous Trade Calc'!$E:$E,K13) -> 0 | L14: =SUM(D14:K14) -> 0 | Q14: SUBSCRIPTION TO FUND | R14: =SUMIFS('JP_Cash Projection - Detail'!AV:AV,'JP_Cash Projection - Detail'!I:I,A3,'JP_Cash Projection - Detail'!W:W,Francis!Q14) -> 0 | U14: SOD Cash(USD: cash projections) | AE14: 00102702 | AF14: =AH3&" Index" -> Index | AG14: USA | AH14: =IF(AG3="SELL","S","B") -> #N/A | AI14: =AI3 -> #N/A | AO14: =_xll.BDP(AU14&" isin","ID_CUSIP_REAL") -> #NAME? | AP14: =VLOOKUP(AO14,'Eze Export_equitizer_VPIE'!$C$3:$G$523,5,0) -> #NAME? | AQ14: =IF(AV14="s",AP14-AW14,0) -> #N/A | AR14: =_xll.BDP(AU14&" isin","security name") -> #NAME? | AS14: =IF(AQ14>0,"Continue with TBill Trade","Check TBill ISIN") -> #N/A | AU14: =AX3 -> 0 | AV14: =IF(AW3="SELL","S","B") -> #N/A | AW14: =AY3/1000 -> #N/A | AX14: =AV3 -> 45467 | AY14: VPIE
A15: =SUMIFS('Previous Trade Calc'!$Q:$Q,'Previous Trade Calc'!$B:$B,$B$15,'Previous Trade Calc'!$E:$E,A13) -> 0 | B15: VPIE | D15: =SUMIFS('Previous Trade Calc'!$Q:$Q,'Previous Trade Calc'!$B:$B,$B$15,'Previous Trade Calc'!$E:$E,D13) -> 0 | E15: =SUMIFS('Previous Trade Calc'!$Q:$Q,'Previous Trade Calc'!$B:$B,$B$15,'Previous Trade Calc'!$E:$E,E13) -> 0 | F15: =SUMIFS('Previous Trade Calc'!$Q:$Q,'Previous Trade Calc'!$B:$B,$B$15,'Previous Trade Calc'!$E:$E,F13) -> 0 | G15: =SUMIFS('Previous Trade Calc'!$Q:$Q,'Previous Trade Calc'!$B:$B,$B$15,'Previous Trade Calc'!$E:$E,G13) -> 0 | H15: =SUMIFS('Previous Trade Calc'!$Q:$Q,'Previous Trade Calc'!$B:$B,$B$15,'Previous Trade Calc'!$E:$E,H13) -> 0 | I15: =SUMIFS('Previous Trade Calc'!$Q:$Q,'Previous Trade Calc'!$B:$B,$B$15,'Previous Trade Calc'!$E:$E,I13) -> 0 | J15: =SUMIFS('Previous Trade Calc'!$Q:$Q,'Previous Trade Calc'!$B:$B,$B$15,'Previous Trade Calc'!$E:$E,J13) -> 0 | K15: =SUMIFS('Previous Trade Calc'!$Q:$Q,'Previous Trade Calc'!$B:$B,$B$15,'Previous Trade Calc'!$E:$E,K13) -> 0 | L15: =SUM(D15:K15) -> 0 | Q15: REDEMPTION TO FUND | R15: =SUMIFS('JP_Cash Projection - Detail'!AV:AV,'JP_Cash Projection - Detail'!I:I,A3,'JP_Cash Projection - Detail'!W:W,Francis!Q15) -> 0 | U15: SOD Cash FX (base)
A16: =SUMIFS('Previous Trade Calc'!$Q:$Q,'Previous Trade Calc'!$B:$B,$B$16,'Previous Trade Calc'!$E:$E,A13) -> 0 | B16: NYLPIE | D16: =SUMIFS('Previous Trade Calc'!$Q:$Q,'Previous Trade Calc'!$B:$B,$B$16,'Previous Trade Calc'!$E:$E,D13) -> 0 | E16: =SUMIFS('Previous Trade Calc'!$Q:$Q,'Previous Trade Calc'!$B:$B,$B$16,'Previous Trade Calc'!$E:$E,E13) -> 0 | F16: =SUMIFS('Previous Trade Calc'!$Q:$Q,'Previous Trade Calc'!$B:$B,$B$16,'Previous Trade Calc'!$E:$E,F13) -> 0 | G16: =SUMIFS('Previous Trade Calc'!$Q:$Q,'Previous Trade Calc'!$B:$B,$B$16,'Previous Trade Calc'!$E:$E,G13) -> 0 | H16: =SUMIFS('Previous Trade Calc'!$Q:$Q,'Previous Trade Calc'!$B:$B,$B$16,'Previous Trade Calc'!$E:$E,H13) -> 0 | I16: =SUMIFS('Previous Trade Calc'!$Q:$Q,'Previous Trade Calc'!$B:$B,$B$16,'Previous Trade Calc'!$E:$E,I13) -> 0 | J16: =SUMIFS('Previous Trade Calc'!$Q:$Q,'Previous Trade Calc'!$B:$B,$B$16,'Previous Trade Calc'!$E:$E,J13) -> 0 | K16: =SUMIFS('Previous Trade Calc'!$Q:$Q,'Previous Trade Calc'!$B:$B,$B$16,'Previous Trade Calc'!$E:$E,K13) -> 0 | L16: =SUM(D16:K16) -> 0 | R16: =SUM(R14:R15) -> 0 | U16: Pending Trade (Base_Eze) | AG16: Copy & Paste Special Value Below | AX16: Copy & Paste Special Value Below
A17: =SUMIFS('Previous Trade Calc'!$Q:$Q,'Previous Trade Calc'!$B:$B,$B$17,'Previous Trade Calc'!$E:$E,A13) -> 0 | B17: FOUNDLCE | D17: =SUMIFS('Previous Trade Calc'!$Q:$Q,'Previous Trade Calc'!$B:$B,$B$17,'Previous Trade Calc'!$E:$E,D13) -> 0 | E17: =SUMIFS('Previous Trade Calc'!$Q:$Q,'Previous Trade Calc'!$B:$B,$B$17,'Previous Trade Calc'!$E:$E,E13) -> 0 | F17: =SUMIFS('Previous Trade Calc'!$Q:$Q,'Previous Trade Calc'!$B:$B,$B$17,'Previous Trade Calc'!$E:$E,F13) -> 0 | G17: =SUMIFS('Previous Trade Calc'!$Q:$Q,'Previous Trade Calc'!$B:$B,$B$17,'Previous Trade Calc'!$E:$E,G13) -> 0 | H17: =SUMIFS('Previous Trade Calc'!$Q:$Q,'Previous Trade Calc'!$B:$B,$B$17,'Previous Trade Calc'!$E:$E,H13) -> 0 | I17: =SUMIFS('Previous Trade Calc'!$Q:$Q,'Previous Trade Calc'!$B:$B,$B$17,'Previous Trade Calc'!$E:$E,I13) -> 0 | J17: =SUMIFS('Previous Trade Calc'!$Q:$Q,'Previous Trade Calc'!$B:$B,$B$17,'Previous Trade Calc'!$E:$E,J13) -> 0 | K17: =SUMIFS('Previous Trade Calc'!$Q:$Q,'Previous Trade Calc'!$B:$B,$B$17,'Previous Trade Calc'!$E:$E,K13) -> 0 | L17: =SUM(D17:K17) -> 0 | U17: Income (projections)
A18: =SUMIFS('Previous Trade Calc'!$Q:$Q,'Previous Trade Calc'!$B:$B,$B$18,'Previous Trade Calc'!$E:$E,A13) -> 0 | B18: GIAACWIP | D18: =SUMIFS('Previous Trade Calc'!$S:$S,'Previous Trade Calc'!$B:$B,$B$18,'Previous Trade Calc'!$E:$E,D13) -> 0 | E18: =SUMIFS('Previous Trade Calc'!$S:$S,'Previous Trade Calc'!$B:$B,$B$18,'Previous Trade Calc'!$E:$E,E13) -> 0 | F18: =SUMIFS('Previous Trade Calc'!$S:$S,'Previous Trade Calc'!$B:$B,$B$18,'Previous Trade Calc'!$E:$E,F13) -> 0 | G18: =SUMIFS('Previous Trade Calc'!$S:$S,'Previous Trade Calc'!$B:$B,$B$18,'Previous Trade Calc'!$E:$E,G13) -> 0 | H18: =SUMIFS('Previous Trade Calc'!$S:$S,'Previous Trade Calc'!$B:$B,$B$18,'Previous Trade Calc'!$E:$E,H13) -> 0 | I18: =SUMIFS('Previous Trade Calc'!$S:$S,'Previous Trade Calc'!$B:$B,$B$18,'Previous Trade Calc'!$E:$E,I13) -> 0 | J18: =SUMIFS('Previous Trade Calc'!$S:$S,'Previous Trade Calc'!$B:$B,$B$18,'Previous Trade Calc'!$E:$E,J13) -> 0 | K18: =SUMIFS('Previous Trade Calc'!$S:$S,'Previous Trade Calc'!$B:$B,$B$18,'Previous Trade Calc'!$E:$E,K13) -> 0 | L18: =SUM(D18:K18) -> 0 | U18: Sweep (priced positions) | AE18: AB2 & AB3 SHOULD APPROX = CASHFLOW + INCOME | AU18: if same way combine then allocate
A19: =SUMIFS('Previous Trade Calc'!$Q:$Q,'Previous Trade Calc'!$B:$B,$B$19,'Previous Trade Calc'!$E:$E,A13) -> 0 | B19: GIA1902 | D19: =SUMIFS('Previous Trade Calc'!$S:$S,'Previous Trade Calc'!$B:$B,$B$19,'Previous Trade Calc'!$E:$E,D13) -> 0 | E19: =SUMIFS('Previous Trade Calc'!$S:$S,'Previous Trade Calc'!$B:$B,$B$19,'Previous Trade Calc'!$E:$E,E13) -> 0 | F19: =SUMIFS('Previous Trade Calc'!$S:$S,'Previous Trade Calc'!$B:$B,$B$19,'Previous Trade Calc'!$E:$E,F13) -> 0 | G19: =SUMIFS('Previous Trade Calc'!$S:$S,'Previous Trade Calc'!$B:$B,$B$19,'Previous Trade Calc'!$E:$E,G13) -> 0 | H19: =SUMIFS('Previous Trade Calc'!$S:$S,'Previous Trade Calc'!$B:$B,$B$19,'Previous Trade Calc'!$E:$E,H13) -> 0 | I19: =SUMIFS('Previous Trade Calc'!$S:$S,'Previous Trade Calc'!$B:$B,$B$19,'Previous Trade Calc'!$E:$E,I13) -> 0 | J19: =SUMIFS('Previous Trade Calc'!$S:$S,'Previous Trade Calc'!$B:$B,$B$19,'Previous Trade Calc'!$E:$E,J13) -> 0 | K19: =SUMIFS('Previous Trade Calc'!$S:$S,'Previous Trade Calc'!$B:$B,$B$19,'Previous Trade Calc'!$E:$E,K13) -> 0 | L19: =SUM(D19:K19) -> 0 | U19: Collateral & MD | AM19: AB3 - AB6 SHOULD APPROX = CASHFLOW + INCOME | AU19: =AX2 -> 0 | AV19: =IF(AV13=AV14,AV13,"") -> #N/A | AW19: =IF(AV13=AV14,AW13+AW14,0) -> #N/A | AX19: =AX13 -> 45467
U20: Cash Flow (cash projection)
AU21: TBILL TRADES SHOULD APPROX = CASHFLOW + INCOME
C22: JP Reports Pending Trades | E22: Diff | F22: Failing Trades | G22: Total | I22: *Refresh Bloomberg Codes | L22: REALIZED G/L FUTURFUTURES CONTRACTS | Q22: Manually update using yest postions (prior to trades) | U22: pending trades total | AN22: FINAL TRADES
A23: G 26763 | B23: MAINSP | C23: =VLOOKUP(A23,'JP Code_Sheet'!$A$3:$C$37,3,0) -> #N/A | E23: =C23-L14 -> #N/A | F23: =VLOOKUP(A23,'JP Code_Sheet'!$A$3:$X$33,24,0) -> #N/A | G23: =C23+F23 -> #N/A | I23: Yesterday Variation | J23: Prior Day Variation | K23: JP Movement | L23: Variation Diff | M23: -2 Day Price | N23: -3 Day Price | Q23: Yest Positions | AE23: Account | AF23: BBSYMBOL | AG23: Country | AH23: Side | AI23: Target Size | AU23: TS | AV23: Side | AW23: Qty(M) | AX23: Settle Date | AY23: Account
A24: G 26794 | B24: VPIE | C24: =VLOOKUP(A24,'JP Code_Sheet'!$A$3:$C$37,3,0) -> #N/A | E24: =C24-L15 -> #N/A | F24: =VLOOKUP(A24,'JP Code_Sheet'!$A$3:$X$33,24,0) -> #N/A | G24: =C24+F24 -> #N/A | I24: MAINSP | J24: =(M24-N24)*50*Q24 -> #NAME? | K24: =SUMIFS('JP_POSTED CASH_Detail'!AU:AU,'JP_POSTED CASH_Detail'!D:D,$O$24,'JP_POSTED CASH_Detail'!E:E,$L$22) -> 0 | L24: =K24-J24 -> #NAME? | M24: =_xll.BDP(AH3&" INDEX","px_close_2d") -> #NAME? | N24: =_xll.BDP(AH2&" INDEX","px_close_3d") -> #NAME? | O24: G 26763 | P24: =ABS(L24) -> #NAME? | U24: variation margin
A25: G 09047 | B25: NYLPIE | C25: =VLOOKUP(A25,'JP Code_Sheet'!$A$3:$C$37,3,0) -> #N/A | E25: =C25-L16 -> #N/A | F25: =VLOOKUP(A25,'JP Code_Sheet'!$A$3:$X$33,24,0) -> #N/A | G25: =C25+F25 -> #N/A | I25: VPIE | J25: =(M25-N25)*50*Q25 -> #NAME? | K25: =SUMIFS('JP_POSTED CASH_Detail'!AU:AU,'JP_POSTED CASH_Detail'!D:D,$O$25,'JP_POSTED CASH_Detail'!E:E,$L$22) -> 0 | L25: =K25-J25 -> #NAME? | M25: =_xll.BDP(AH3&" INDEX","px_close_2d") -> #NAME? | N25: =_xll.BDP(AH3&" INDEX","px_close_3d") -> #NAME? | O25: G 26794 | P25: =ABS(L25) -> #NAME? | U25: included in morning cash or no
A26: G 01324 | B26: FOUNDLCE | C26: =VLOOKUP(A26,'JP Code_Sheet'!$A$3:$C$37,3,0) -> #N/A | E26: =C26-L17 -> #N/A | F26: =VLOOKUP(A26,'JP Code_Sheet'!$A$3:$X$33,24,0) -> #N/A | G26: =C26+F26 -> #N/A
A27: G 01305 | B27: GIAACWIP | C27: =VLOOKUP(A27,'JP Code_Sheet'!$A$3:$C$37,3,0) -> #NAME? | E27: =C27-L18 -> #NAME? | F27: =VLOOKUP(A27,'JP Code_Sheet'!$A$3:$X$33,24,0) -> #N/A | G27: =C27+F27 -> #NAME? | U27: MIDDAY SUB/RED | AH27: *Copy and paste into triton (include headers) | AX27: *Drag and drop into TSOX
C28: BNY Reports Pending Trades | F28: Failing Trades | G28: Total | U28: SCHEDULED MOC | AH28: *FINAL TRADES | AX28: *FINAL TRADES
A29: 353109 | B29: GIA1902 | C29: =VLOOKUP(A29,'JP Code_Sheet'!$A$67:$C$71,3,0) -> #N/A | E29: =C29-L19 -> #N/A | F29: =VLOOKUP(A29,'JP Code_Sheet'!$A$67:$X$72,24,0) -> #N/A | G29: =C29+F29 -> #N/A
U30: ask pending on dates that are beyond settle | AI30: *GS_FUTALGO_GD | AY30: *TSOX RFQ (BAC, CG, Citadel)
AI31: *Type: MKT | AY31: *Comm: None
E32: GIAACWIP (NET CASH) | F32: =S6 -> #N/A | AI32: *POV: 5% | AY32: *Trade diff direction separately (complete one first)
E33: GIAACWIP (AIA40) | AI33: *Trade diff direction separately (complete one first) | AY33: *Aloc Trades in BLOT
A34: G23630 / GTI 85756 | E34: Foreign Cash (USD) | F34: =F9 -> 0 | AI34: *Comm: $2.15
A35: G09047/32296 | B35: NYLPIE | E35: Pending Foreign Trades NET (USD) | F35: ='Currency Balance'!J33 -> #NAME? | AJ35: Trader | AK35: Cust | AL35: Prt | AM35: TradeDate | AN35: SettleDate | AO35: Side | AP35: Security | AQ35: Amount | AR35: Done | AS35: Price | AT35: COMM | AU35: Broker | AV35: Note
A36: G01305/AIA40 | B36: GIAACWIP | E36: Failed Foreign Trades NET (USD) | F36: ='Currency Balance'!H73 -> #NAME? | AJ36: FO | AK36: BONY | AL36: =AM4 -> NYLPIE | AM36: =AN4 -> 45467 | AN36: =AO4 -> #N/A | AO36: =AP4 -> #N/A | AP36: =AQ4 -> VOO | AQ36: =AR4 -> #N/A | AV36: Cash1
AJ37: FO | AK37: BONY | AL37: =AM5 -> FOUNDLCE | AM37: =AN5 -> 45467 | AN37: =AO5 -> #N/A | AO37: =AP5 -> #N/A | AP37: =AQ5 -> VOO | AQ37: =AR5 -> #N/A | AV37: Cash1
E38: Net Estimated Cash | F38: =SUM(F32:F36) -> #N/A | AJ38: FO | AK38: BONY | AL38: =AM6 -> GIAACWIP | AM38: =AN6 -> 45467 | AN38: =AO6 -> #N/A | AO38: =AP6 -> #N/A | AP38: =AQ6 -> ACWI | AQ38: =AR6 -> #N/A | AV38: Cash1
AJ39: FO | AK39: BONY | AL39: =AM7 -> GIA1902 | AM39: =AN7 -> 45467 | AN39: =AO7 -> #N/A | AO39: =AP7 -> #N/A | AP39: =AQ7 -> VOO | AQ39: =AR7 -> #N/A | AV39: Cash1
AS40: *comm: EI (code) for VOO | AT40: *comm: RI (code) for ACWI
AS41: *Jeff Algo | AT41: *Copy Paste Special Value
AS42: *POV: 5% | AT42: *FINAL TRADES
AS43: *Trade diff direction separately, diff brokers (complete one first) | AT43: *Create Import for Eze
AH45: Broker | AI45: Strategy Type | AJ45: S/D | AL45: MAS Trades | AM45: Confirm Settlment date (T+1)
AH46: CITI Algo | AI46: TWAP | AJ46: Broker Deaults to T+1 | AL46: TRITON | AM46: IF 2SIDED TRADE
AH47: VIRTU Algo | AI47: Special | AJ47: Broker Deaults to T+1 | AL47: TRITON | AM47: CHECK FOR LIQUIDITY - IF OVER 3% - TRADE ON TRADEWEB
AH48: CITI Algo | AI48: POV (cross trades- smaller) | AJ48: Confirm w/ broker | AL48: TRITON | AM48: CROSSMERGE - LOOK FOR SAS LIST - CLICK CROSSMERGE - IF ALL ONE SIDED - IGNORE THIS STEP
G49: REDEMPTION TO FUND | AH49: VIRTU Algo | AI49: POV (cross trades- smaller) | AJ49: Confirm w/ broker | AL49: TRITON | AM49: COLUMN CROSS/MERGE IF CROSS IS FLAGGED IN CELL - THAT MEANS THERE ARE SAME TICKER WITH BUY & SELL
G50: Subscription to fund | AL50: TRITON | AM50: CHOOSE ALL NON CROSS TRADES PLUS LARGER OF CROSS TRADES
A51: Accounting | AL51: TRITON | AM51: SEND LARGE CROSS PLUS NON-CROSS TRADES TO HIGHLIGHT THE TRADES
AL52: TRITON | AM52: CLICK DEST - CITI OR VIRTU TWAP ALGO
C53: =E1 -> SOD Cash(USD: cash projections) | D53: =J1 -> Sweep (priced positions) | E53: Pending fails | F53: SOD Cash (sheet) | G53: Income | H53: Sub/Red (ONLY) | I53: Variation (today) | J53: Trades (Tbills) | K53: CASH EOD (SOD Next day) | N53: SOD Cash(USD: cash projections) | O53: Sweep (priced positions) | P53: Pending fails | Q53: SOD Cash (sheet) | R53: Income | S53: Sub/Red (ONLY) | T53: Variation (today) | U53: Trades (Tbills) | V53: CASH EOD (SOD Next day) | AN53: TRITON | AO53: ONCE DEST ALGO IS IN THE DEST AND FULL SHARES ARE IN SIZE - CLICK EXECUTE
A54: =TODAY() -> 45467 | B54: =B2 -> MAINSP | C54: =E2 -> #N/A | D54: =J2 -> #N/A | E54: =G2 -> #N/A | F54: =C54+D54+E54 -> #N/A | G54: =I2 -> #N/A | H54: =R12 -> 0 | I54: =W2 -> #NAME? | J54: =IF(AV13="S",AW13*1000,-AW13*1000) -> #N/A | K54: =F54+H54+I54+J54+G54 -> #N/A | M54: =B3 -> VPIE | N54: =E3 -> #N/A | O54: =J3 -> #N/A | P54: =G3 -> #N/A | Q54: =N54+O54+P54 -> #N/A | R54: =I3 -> #N/A | S54: =R16 -> 0 | T54: =W3 -> #NAME? | U54: =IF(AV14="S",AW14*1000,-AW14*1000) -> #N/A | V54: =Q54+S54+T54+U54+R54 -> #N/A | AN54: TRITON | AO54: FOR CROSS TRADES - CLICK DEST - CITI/VIRTU ALGO US - CHOOSE POV STRATEGY; % PARTICIPATION 5%; TIME START 9:40:01 OR WHEN TWAP TRADE ENDS PLUS 1 SECOND
AL55: TRITON | AM55: VERIFY SHARES ARE COMPLETE IN 10 OR 15MINUTES
AL56: TRITON | AM56: IF 1SIDED TRADED
AL57: TRITON | AM57: CHECK FOR LIQUIDITY - IF OVER 3% - TRADE ON TRADEWEB
AL58: TRITON | AM58: HIGHLIGHT THE TRADES - CLICK DEST - CITI OR VIRTU ALGO US
AL59: TRITON | AM59: CHOOSE SPECIAL STRATEGY OR TWAP; ENTER START TIME 930AM; END TIME 940AM
AL60: BCHAT | AM60: IF TRADING USING POV/PARTICIPATION - PLEASE LET CITI/VIRTU KNOW T1 SETTLE
AL61: EZE ALGO | AM61: IF ALGOS - COMM CODE - RO IF OPEN - RI IF MIDDLE OF DAY - RM IF FOR CLOSE
AL62: EZE TWEB | AM62: IF TRADEWEB - COMM CODE - PO IF OPEN - PI IF MIDDLE OF DAY - PM IF FOR CLOSE

Sheet NYLIC_JP_
A1: Custody # | B1: Portfolio | C1: Name of Fund | E1: SOD Cash(USD: cash projections) | F1: SOD Cash FX (base) | G1: Pending Trades +Failing (JP) | I1: Income (projections) | J1: Sweep (priced positions) | K1: Collateral & MD | L1: Total Cash | M1: T-BILL (priced positions) | N1: Equity MV (priced positions) | P1: Total Assets | Q1: Percent Cash | R1: Cash Flow (cash projection) | S1: Net Cash | T1: Percent Net Cash | U1: Updated Cash
A2: G 04143 | B2: IQSMAETF | C2: NYLIC INDEX IQ ETF (SMA) 1872 | D2: S&P 500 IND FD | E2: =VLOOKUP(A2,'JP Code_Sheet'!$A$2:$E$32,2,0) -> #N/A | G2: =VLOOKUP(A2,$A$29:$H$35,8,0) -> #N/A | I2: =VLOOKUP(A2,'JP Code_Sheet'!$A$2:$E$32,4,0) -> #N/A | J2: =VLOOKUP(A2,'JP Code_Sheet'!$A$3:$F$32,6,0) -> #N/A | L2: =E2+G2+I2+J2+K2+F2 -> #N/A | M2: =VLOOKUP(A2,'JP Code_Sheet'!$A$3:$G$32,7,0) -> #N/A | N2: =VLOOKUP(A2,'JP Code_Sheet'!$A$3:$H$32,8,0) -> #N/A | P2: =L2+M2+N2 -> #N/A | Q2: =L2/P2 -> #N/A | R2: =VLOOKUP(A2,'JP Code_Sheet'!$A$3:$L$33,12,0) -> #N/A | S2: =L2+R2 -> #N/A | T2: =S2/P2 -> #N/A
A3: G 22738 | B3: NYLIC 1940 | C3: NYLIC GENL ETF STRATEGY (PAPC) 1940 | D3: VP S&P 500 FD | E3: =VLOOKUP(A3,'JP Code_Sheet'!$A$2:$E$32,2,0) -> #N/A | G3: =VLOOKUP(A3,$A$29:$H$35,8,0) -> #N/A | I3: =VLOOKUP(A3,'JP Code_Sheet'!$A$2:$E$32,4,0) -> #N/A | J3: =VLOOKUP(A3,'JP Code_Sheet'!$A$3:$F$32,6,0) -> #N/A | L3: =E3+G3+I3+J3+K3+F3 -> #N/A | M3: =VLOOKUP(A3,'JP Code_Sheet'!$A$3:$G$32,7,0) -> #N/A | N3: =VLOOKUP(A3,'JP Code_Sheet'!$A$3:$H$32,8,0) -> #N/A | P3: =L3+M3+N3 -> #N/A | Q3: =L3/P3 -> #N/A | R3: =VLOOKUP(A3,'JP Code_Sheet'!$A$3:$L$33,12,0) -> #N/A | S3: =L3+R3 -> #N/A | T3: =S3/P3 -> #N/A
A4: G 26059 | B4: NYLIC1976 | C4: NYLIC GENERAL EQUITY ETF STRATEGY (SP), 1976 | E4: =VLOOKUP(A4,'JP Code_Sheet'!$A$2:$E$32,2,0) -> #N/A | G4: =VLOOKUP(A4,$A$29:$H$35,8,0) -> #N/A | I4: =VLOOKUP(A4,'JP Code_Sheet'!$A$2:$E$32,4,0) -> #N/A | J4: =VLOOKUP(A4,'JP Code_Sheet'!$A$3:$F$32,6,0) -> #N/A | L4: =E4+G4+I4+J4+K4+F4 -> #N/A | M4: =VLOOKUP(A4,'JP Code_Sheet'!$A$3:$G$32,7,0) -> #N/A | N4: =VLOOKUP(A4,'JP Code_Sheet'!$A$3:$H$32,8,0) -> #N/A | P4: =L4+M4+N4 -> #N/A | Q4: =L4/P4 -> #N/A | R4: =VLOOKUP(A4,'JP Code_Sheet'!$A$3:$L$33,12,0) -> #N/A | S4: =L4+R4 -> #N/A | T4: =S4/P4 -> #N/A
A5: G 23630 | B5: NYLINT | C5: NYLIC GENERAL INTERNATIONAL EQUITY (POST) 1682 | E5: =VLOOKUP(A5,'JP Code_Sheet'!$A$2:$E$32,2,0) -> #N/A | G5: =VLOOKUP(A5,$A$29:$H$35,8,0) -> #N/A | I5: =VLOOKUP(A5,'JP Code_Sheet'!$A$2:$E$32,4,0) -> #N/A | J5: =VLOOKUP(A5,'JP Code_Sheet'!$A$3:$F$32,6,0) -> #N/A | L5: =E5+G5+I5+J5+K5+F5 -> #N/A | M5: =VLOOKUP(A5,'JP Code_Sheet'!$A$3:$G$32,7,0) -> #N/A | N5: =VLOOKUP(A5,'JP Code_Sheet'!$A$3:$H$32,8,0) -> #N/A | P5: =L5+M5+N5 -> #N/A | Q5: =L5/P5 -> #N/A | R5: =VLOOKUP(A5,'JP Code_Sheet'!$A$3:$L$33,12,0) -> #N/A | S5: =L5+R5 -> #N/A | T5: =S5/P5 -> #N/A
A6: G 01894 | B6: NYLIQETF | C6: NYLIC INDEXIQ ETF (LTC), 1855 | E6: =VLOOKUP(A6,'JP Code_Sheet'!$A$2:$E$32,2,0) -> #N/A | G6: =VLOOKUP(A6,$A$29:$H$35,8,0) -> #N/A | I6: =VLOOKUP(A6,'JP Code_Sheet'!$A$2:$E$32,4,0) -> #N/A | J6: =VLOOKUP(A6,'JP Code_Sheet'!$A$3:$F$32,6,0) -> #N/A | L6: =E6+G6+I6+J6+K6+F6 -> #N/A | M6: =VLOOKUP(A6,'JP Code_Sheet'!$A$3:$G$32,7,0) -> #N/A | N6: =VLOOKUP(A6,'JP Code_Sheet'!$A$3:$H$32,8,0) -> #N/A | P6: =L6+M6+N6 -> #N/A | Q6: =L6/P6 -> #N/A | R6: =VLOOKUP(A6,'JP Code_Sheet'!$A$3:$L$33,12,0) -> #N/A | S6: =L6+R6 -> #N/A | T6: =S6/P6 -> #N/A
A7: G 21866 | B7: SSC1901 | C7: NYLIC GENERAL (SSC), 1901 | E7: =VLOOKUP(A7,'JP Code_Sheet'!$A$2:$E$32,2,0) -> #N/A | G7: =VLOOKUP(A7,$A$29:$H$35,8,0) -> #N/A | I7: =VLOOKUP(A7,'JP Code_Sheet'!$A$2:$E$32,4,0) -> #N/A | J7: =VLOOKUP(A7,'JP Code_Sheet'!$A$3:$F$32,6,0) -> #N/A | L7: =E7+G7+I7+J7+K7+F7 -> #N/A | M7: =VLOOKUP(A7,'JP Code_Sheet'!$A$3:$G$32,7,0) -> #N/A | N7: =VLOOKUP(A7,'JP Code_Sheet'!$A$3:$H$32,8,0) -> #N/A | P7: =L7+M7+N7 -> #N/A | Q7: =L7/P7 -> #N/A | R7: =VLOOKUP(A7,'JP Code_Sheet'!$A$3:$L$33,12,0) -> #N/A | S7: =L7+R7 -> #N/A | T7: =S7/P7 -> #N/A
A8: S 17736 | B8: LINAETF | C8: LIFE INSURANCE COMPANY OF NORTH AMERICA LINA MacKay Service Accounts (SMA) 2255 | E8: =VLOOKUP(A8,'JP Code_Sheet'!$A$2:$E$32,2,0) -> #N/A | G8: =VLOOKUP(A8,$A$29:$H$35,8,0) -> #N/A | I8: =VLOOKUP(A8,'JP Code_Sheet'!$A$2:$E$32,4,0) -> #N/A | J8: =VLOOKUP(A8,'JP Code_Sheet'!$A$3:$F$32,6,0) -> #N/A | L8: =E8+G8+I8+J8+K8+F8 -> #N/A | M8: =VLOOKUP(A8,'JP Code_Sheet'!$A$3:$G$32,7,0) -> #N/A | N8: =VLOOKUP(A8,'JP Code_Sheet'!$A$3:$H$32,8,0) -> #N/A | P8: =L8+M8+N8 -> #N/A | Q8: =L8/P8 -> #N/A | R8: =VLOOKUP(A8,'JP Code_Sheet'!$A$3:$L$33,12,0) -> #N/A | S8: =L8+R8 -> #N/A | T8: =S8/P8 -> #N/A
A9: S 19661 | B9: LTCIIP2299 | C9: NYLIC General Equity ETF Strategy (LTC IIP), 2299 | E9: =VLOOKUP(A9,'JP Code_Sheet'!$A$2:$E$35,2,0) -> #N/A | G9: =VLOOKUP(A9,$A$31:$H$38,8,0) -> #N/A | I9: =VLOOKUP(A9,'JP Code_Sheet'!$A$2:$E$35,4,0) -> #N/A | J9: =VLOOKUP(A9,'JP Code_Sheet'!$A$3:$F$35,6,0) -> #N/A | L9: =E9+G9+I9+J9+K9+F9 -> #N/A | M9: =VLOOKUP(A9,'JP Code_Sheet'!$A$3:$G$35,7,0) -> #N/A | N9: =VLOOKUP(A9,'JP Code_Sheet'!$A$3:$H$35,8,0) -> #N/A | P9: =L9+M9+N9 -> #N/A | Q9: =L9/P9 -> #N/A | R9: =VLOOKUP(A9,'JP Code_Sheet'!$A$3:$L$35,12,0) -> #N/A | S9: =L9+R9 -> #N/A | T9: =S9/P9 -> #N/A
M11: Could be off T+1 accounting | N11: Could be off T+1 accounting
A12: DTC/Act
A13: G23630 / GTI 85756
A16: T-0 | B16: EZE
A17: =C17-1 -> 45466 | B17: S/D | C17: ='JP Code_Sheet'!A1 -> 45467 | E17: =C17+1 -> 45468 | F17: =E17+1 -> 45469 | G17: =F17+1 -> 45470 | H17: =G17+1 -> 45471 | I17: =H17+1 -> 45472 | J17: =I17+1 -> 45473 | K17: =J17+1 -> 45474 | L17: =K17+1 -> 45475 | M17: Total Pending
A18: =SUMIFS('Previous Trade Calc'!$Q:$Q,'Previous Trade Calc'!$B:$B,$B$18,'Previous Trade Calc'!$E:$E,A17) -> 0 | B18: IQSMAETF | C18: =SUMIFS('Previous Trade Calc'!$Q:$Q,'Previous Trade Calc'!$B:$B,$B$18,'Previous Trade Calc'!$E:$E,C17) -> 0 | E18: =SUMIFS('Previous Trade Calc'!$Q:$Q,'Previous Trade Calc'!$B:$B,$B$18,'Previous Trade Calc'!$E:$E,E17) -> 0 | F18: =SUMIFS('Previous Trade Calc'!$Q:$Q,'Previous Trade Calc'!$B:$B,$B$18,'Previous Trade Calc'!$E:$E,F17) -> 0 | G18: =SUMIFS('Previous Trade Calc'!$Q:$Q,'Previous Trade Calc'!$B:$B,$B$18,'Previous Trade Calc'!$E:$E,G17) -> 0 | H18: =SUMIFS('Previous Trade Calc'!$Q:$Q,'Previous Trade Calc'!$B:$B,$B$18,'Previous Trade Calc'!$E:$E,H17) -> 0 | I18: =SUMIFS('Previous Trade Calc'!$Q:$Q,'Previous Trade Calc'!$B:$B,$B$18,'Previous Trade Calc'!$E:$E,I17) -> 0 | J18: =SUMIFS('Previous Trade Calc'!$Q:$Q,'Previous Trade Calc'!$B:$B,$B$18,'Previous Trade Calc'!$E:$E,J17) -> 0 | K18: =SUMIFS('Previous Trade Calc'!$Q:$Q,'Previous Trade Calc'!$B:$B,$B$18,'Previous Trade Calc'!$E:$E,K17) -> 0 | L18: =SUMIFS('Previous Trade Calc'!$Q:$Q,'Previous Trade Calc'!$B:$B,$B$18,'Previous Trade Calc'!$E:$E,L17) -> 0 | M18: =SUM(C18:L18) -> 0
A19: =SUMIFS('Previous Trade Calc'!$Q:$Q,'Previous Trade Calc'!$B:$B,$B$19,'Previous Trade Calc'!$E:$E,A17) -> 0 | B19: NYLIC 1940 | C19: =SUMIFS('Previous Trade Calc'!$Q:$Q,'Previous Trade Calc'!$B:$B,$B$19,'Previous Trade Calc'!$E:$E,C17) -> 0 | E19: =SUMIFS('Previous Trade Calc'!$Q:$Q,'Previous Trade Calc'!$B:$B,$B$19,'Previous Trade Calc'!$E:$E,E17) -> 0 | F19: =SUMIFS('Previous Trade Calc'!$Q:$Q,'Previous Trade Calc'!$B:$B,$B$19,'Previous Trade Calc'!$E:$E,F17) -> 0 | G19: =SUMIFS('Previous Trade Calc'!$Q:$Q,'Previous Trade Calc'!$B:$B,$B$19,'Previous Trade Calc'!$E:$E,G17) -> 0 | H19: =SUMIFS('Previous Trade Calc'!$Q:$Q,'Previous Trade Calc'!$B:$B,$B$19,'Previous Trade Calc'!$E:$E,H17) -> 0 | I19: =SUMIFS('Previous Trade Calc'!$Q:$Q,'Previous Trade Calc'!$B:$B,$B$19,'Previous Trade Calc'!$E:$E,I17) -> 0 | J19: =SUMIFS('Previous Trade Calc'!$Q:$Q,'Previous Trade Calc'!$B:$B,$B$19,'Previous Trade Calc'!$E:$E,J17) -> 0 | K19: =SUMIFS('Previous Trade Calc'!$Q:$Q,'Previous Trade Calc'!$B:$B,$B$19,'Previous Trade Calc'!$E:$E,K17) -> 0 | L19: =SUMIFS('Previous Trade Calc'!$Q:$Q,'Previous Trade Calc'!$B:$B,$B$19,'Previous Trade Calc'!$E:$E,L17) -> 0 | M19: =SUM(C19:L19) -> 0
A20: =SUMIFS('Previous Trade Calc'!$Q:$Q,'Previous Trade Calc'!$B:$B,$B$20,'Previous Trade Calc'!$E:$E,A17) -> 0 | B20: NYLIC1976 | C20: =SUMIFS('Previous Trade Calc'!$Q:$Q,'Previous Trade Calc'!$B:$B,$B$20,'Previous Trade Calc'!$E:$E,C17) -> 0 | E20: =SUMIFS('Previous Trade Calc'!$Q:$Q,'Previous Trade Calc'!$B:$B,$B$20,'Previous Trade Calc'!$E:$E,E17) -> 0 | F20: =SUMIFS('Previous Trade Calc'!$Q:$Q,'Previous Trade Calc'!$B:$B,$B$20,'Previous Trade Calc'!$E:$E,F17) -> 0 | G20: =SUMIFS('Previous Trade Calc'!$Q:$Q,'Previous Trade Calc'!$B:$B,$B$20,'Previous Trade Calc'!$E:$E,G17) -> 0 | H20: =SUMIFS('Previous Trade Calc'!$Q:$Q,'Previous Trade Calc'!$B:$B,$B$20,'Previous Trade Calc'!$E:$E,H17) -> 0 | I20: =SUMIFS('Previous Trade Calc'!$Q:$Q,'Previous Trade Calc'!$B:$B,$B$20,'Previous Trade Calc'!$E:$E,I17) -> 0 | J20: =SUMIFS('Previous Trade Calc'!$Q:$Q,'Previous Trade Calc'!$B:$B,$B$20,'Previous Trade Calc'!$E:$E,J17) -> 0 | K20: =SUMIFS('Previous Trade Calc'!$Q:$Q,'Previous Trade Calc'!$B:$B,$B$20,'Previous Trade Calc'!$E:$E,K17) -> 0 | L20: =SUMIFS('Previous Trade Calc'!$Q:$Q,'Previous Trade Calc'!$B:$B,$B$20,'Previous Trade Calc'!$E:$E,L17) -> 0 | M20: =SUM(C20:L20) -> 0
A21: =SUMIFS('Previous Trade Calc'!$Q:$Q,'Previous Trade Calc'!$B:$B,$B$21,'Previous Trade Calc'!$E:$E,A17) -> 0 | B21: NYLINT | C21: =SUMIFS('Previous Trade Calc'!$Q:$Q,'Previous Trade Calc'!$B:$B,$B$21,'Previous Trade Calc'!$E:$E,C17) -> 0 | E21: =SUMIFS('Previous Trade Calc'!$Q:$Q,'Previous Trade Calc'!$B:$B,$B$21,'Previous Trade Calc'!$E:$E,E17) -> 0 | F21: =SUMIFS('Previous Trade Calc'!$Q:$Q,'Previous Trade Calc'!$B:$B,$B$21,'Previous Trade Calc'!$E:$E,F17) -> 0 | G21: =SUMIFS('Previous Trade Calc'!$Q:$Q,'Previous Trade Calc'!$B:$B,$B$21,'Previous Trade Calc'!$E:$E,G17) -> 0 | H21: =SUMIFS('Previous Trade Calc'!$Q:$Q,'Previous Trade Calc'!$B:$B,$B$21,'Previous Trade Calc'!$E:$E,H17) -> 0 | I21: =SUMIFS('Previous Trade Calc'!$Q:$Q,'Previous Trade Calc'!$B:$B,$B$21,'Previous Trade Calc'!$E:$E,I17) -> 0 | J21: =SUMIFS('Previous Trade Calc'!$Q:$Q,'Previous Trade Calc'!$B:$B,$B$21,'Previous Trade Calc'!$E:$E,J17) -> 0 | K21: =SUMIFS('Previous Trade Calc'!$Q:$Q,'Previous Trade Calc'!$B:$B,$B$21,'Previous Trade Calc'!$E:$E,K17) -> 0 | L21: =SUMIFS('Previous Trade Calc'!$Q:$Q,'Previous Trade Calc'!$B:$B,$B$21,'Previous Trade Calc'!$E:$E,L17) -> 0 | M21: =SUM(C21:L21) -> 0
A22: =SUMIFS('Previous Trade Calc'!$Q:$Q,'Previous Trade Calc'!$B:$B,$B$22,'Previous Trade Calc'!$E:$E,A17) -> 0 | B22: NYLIQETF | C22: =SUMIFS('Previous Trade Calc'!$S:$S,'Previous Trade Calc'!$B:$B,$B$22,'Previous Trade Calc'!$E:$E,C17) -> 0 | E22: =SUMIFS('Previous Trade Calc'!$S:$S,'Previous Trade Calc'!$B:$B,$B$22,'Previous Trade Calc'!$E:$E,E17) -> 0 | F22: =SUMIFS('Previous Trade Calc'!$S:$S,'Previous Trade Calc'!$B:$B,$B$22,'Previous Trade Calc'!$E:$E,F17) -> 0 | G22: =SUMIFS('Previous Trade Calc'!$S:$S,'Previous Trade Calc'!$B:$B,$B$22,'Previous Trade Calc'!$E:$E,G17) -> 0 | H22: =SUMIFS('Previous Trade Calc'!$S:$S,'Previous Trade Calc'!$B:$B,$B$22,'Previous Trade Calc'!$E:$E,H17) -> 0 | I22: =SUMIFS('Previous Trade Calc'!$S:$S,'Previous Trade Calc'!$B:$B,$B$22,'Previous Trade Calc'!$E:$E,I17) -> 0 | J22: =SUMIFS('Previous Trade Calc'!$S:$S,'Previous Trade Calc'!$B:$B,$B$22,'Previous Trade Calc'!$E:$E,J17) -> 0 | K22: =SUMIFS('Previous Trade Calc'!$S:$S,'Previous Trade Calc'!$B:$B,$B$22,'Previous Trade Calc'!$E:$E,K17) -> 0 | L22: =SUMIFS('Previous Trade Calc'!$S:$S,'Previous Trade Calc'!$B:$B,$B$22,'Previous Trade Calc'!$E:$E,L17) -> 0 | M22: =SUM(C22:L22) -> 0
A23: =SUMIFS('Previous Trade Calc'!$Q:$Q,'Previous Trade Calc'!$B:$B,$B$23,'Previous Trade Calc'!$E:$E,A17) -> 0 | B23: SSC1901 | C23: =SUMIFS('Previous Trade Calc'!$S:$S,'Previous Trade Calc'!$B:$B,$B$23,'Previous Trade Calc'!$E:$E,C17) -> 0 | D23: =SUMIFS('Previous Trade Calc'!$S:$S,'Previous Trade Calc'!$B:$B,$B$23,'Previous Trade Calc'!$E:$E,D17) -> 0 | E23: =SUMIFS('Previous Trade Calc'!$S:$S,'Previous Trade Calc'!$B:$B,$B$23,'Previous Trade Calc'!$E:$E,E17) -> 0 | F23: =SUMIFS('Previous Trade Calc'!$S:$S,'Previous Trade Calc'!$B:$B,$B$23,'Previous Trade Calc'!$E:$E,F17) -> 0 | G23: =SUMIFS('Previous Trade Calc'!$S:$S,'Previous Trade Calc'!$B:$B,$B$23,'Previous Trade Calc'!$E:$E,G17) -> 0 | H23: =SUMIFS('Previous Trade Calc'!$S:$S,'Previous Trade Calc'!$B:$B,$B$23,'Previous Trade Calc'!$E:$E,H17) -> 0 | I23: =SUMIFS('Previous Trade Calc'!$S:$S,'Previous Trade Calc'!$B:$B,$B$23,'Previous Trade Calc'!$E:$E,I17) -> 0 | J23: =SUMIFS('Previous Trade Calc'!$S:$S,'Previous Trade Calc'!$B:$B,$B$23,'Previous Trade Calc'!$E:$E,J17) -> 0 | ... L23: =SUMIFS('Previous Trade Calc'!$S:$S,'Previous Trade Calc'!$B:$B,$B$23,'Previous Trade Calc'!$E:$E,L17) -> 0 | M23: =SUM(C23:L23) -> 0
A24: =SUMIFS('Previous Trade Calc'!$Q:$Q,'Previous Trade Calc'!$B:$B,$B$24,'Previous Trade Calc'!$E:$E,A17) -> 0 | B24: LINAETF | C24: =SUMIFS('Previous Trade Calc'!$S:$S,'Previous Trade Calc'!$B:$B,$B$24,'Previous Trade Calc'!$E:$E,C17) -> 0 | D24: =SUMIFS('Previous Trade Calc'!$S:$S,'Previous Trade Calc'!$B:$B,$B$24,'Previous Trade Calc'!$E:$E,D17) -> 0 | E24: =SUMIFS('Previous Trade Calc'!$S:$S,'Previous Trade Calc'!$B:$B,$B$24,'Previous Trade Calc'!$E:$E,E17) -> 0 | F24: =SUMIFS('Previous Trade Calc'!$S:$S,'Previous Trade Calc'!$B:$B,$B$24,'Previous Trade Calc'!$E:$E,F17) -> 0 | G24: =SUMIFS('Previous Trade Calc'!$S:$S,'Previous Trade Calc'!$B:$B,$B$24,'Previous Trade Calc'!$E:$E,G17) -> 0 | H24: =SUMIFS('Previous Trade Calc'!$S:$S,'Previous Trade Calc'!$B:$B,$B$24,'Previous Trade Calc'!$E:$E,H17) -> 0 | I24: =SUMIFS('Previous Trade Calc'!$S:$S,'Previous Trade Calc'!$B:$B,$B$24,'Previous Trade Calc'!$E:$E,I17) -> 0 | J24: =SUMIFS('Previous Trade Calc'!$S:$S,'Previous Trade Calc'!$B:$B,$B$24,'Previous Trade Calc'!$E:$E,J17) -> 0 | ... L24: =SUMIFS('Previous Trade Calc'!$S:$S,'Previous Trade Calc'!$B:$B,$B$24,'Previous Trade Calc'!$E:$E,L17) -> 0 | M24: =SUM(C24:L24) -> 0
A25: =SUMIFS('Previous Trade Calc'!$Q:$Q,'Previous Trade Calc'!$B:$B,$B$25,'Previous Trade Calc'!$E:$E,A17) -> 0 | B25: LTCIIP2299 | C25: =SUMIFS('Previous Trade Calc'!$S:$S,'Previous Trade Calc'!$B:$B,$B$25,'Previous Trade Calc'!$E:$E,C17) -> 0 | D25: =SUMIFS('Previous Trade Calc'!$S:$S,'Previous Trade Calc'!$B:$B,$B$24,'Previous Trade Calc'!$E:$E,D18) -> 0 | E25: =SUMIFS('Previous Trade Calc'!$S:$S,'Previous Trade Calc'!$B:$B,$B$25,'Previous Trade Calc'!$E:$E,E17) -> 0 | F25: =SUMIFS('Previous Trade Calc'!$S:$S,'Previous Trade Calc'!$B:$B,$B$25,'Previous Trade Calc'!$E:$E,F17) -> 0 | G25: =SUMIFS('Previous Trade Calc'!$S:$S,'Previous Trade Calc'!$B:$B,$B$25,'Previous Trade Calc'!$E:$E,G17) -> 0 | H25: =SUMIFS('Previous Trade Calc'!$S:$S,'Previous Trade Calc'!$B:$B,$B$25,'Previous Trade Calc'!$E:$E,H17) -> 0 | I25: =SUMIFS('Previous Trade Calc'!$S:$S,'Previous Trade Calc'!$B:$B,$B$25,'Previous Trade Calc'!$E:$E,I17) -> 0 | J25: =SUMIFS('Previous Trade Calc'!$S:$S,'Previous Trade Calc'!$B:$B,$B$25,'Previous Trade Calc'!$E:$E,J17) -> 0 | K25: =SUMIFS('Previous Trade Calc'!$S:$S,'Previous Trade Calc'!$B:$B,$B$25,'Previous Trade Calc'!$E:$E,K17) -> 0 | L25: =SUMIFS('Previous Trade Calc'!$S:$S,'Previous Trade Calc'!$B:$B,$B$25,'Previous Trade Calc'!$E:$E,L17) -> 0 | M25: =SUM(C25:L25) -> 0
C28: JP Reports Pending Trades | F28: Diff | G28: Failing Trades | H28: Total
A29: G 04143 | B29: IQSMAETF | C29: =VLOOKUP(A29,'JP Code_Sheet'!$A$3:$C$33,3,0) -> #N/A | F29: =M18-C29 -> #N/A | G29: =VLOOKUP(A29,'JP Code_Sheet'!$A$3:$X$33,24,0) -> #N/A | H29: =C29+G29 -> #N/A
A30: G 22738 | B30: NYLIC 1940 | C30: =VLOOKUP(A30,'JP Code_Sheet'!$A$3:$C$33,3,0) -> #N/A | F30: =M19-C30 -> #N/A | G30: =VLOOKUP(A30,'JP Code_Sheet'!$A$3:$X$33,24,0) -> #N/A | H30: =C30+G30 -> #N/A
A31: G 26059 | B31: NYLIC1976 | C31: =VLOOKUP(A31,'JP Code_Sheet'!$A$3:$C$33,3,0) -> #N/A | F31: =M20-C31 -> #N/A | G31: =VLOOKUP(A31,'JP Code_Sheet'!$A$3:$X$33,24,0) -> #N/A | H31: =C31+G31 -> #N/A
A32: G 23630 | B32: NYLINT | C32: =VLOOKUP(A32,'JP Code_Sheet'!$A$3:$C$33,3,0) -> #N/A | F32: =M21-C32 -> #N/A | G32: =VLOOKUP(A32,'JP Code_Sheet'!$A$3:$X$33,24,0) -> #N/A | H32: =C32+G32 -> #N/A
A33: G 01894 | B33: NYLIQETF | C33: =VLOOKUP(A33,'JP Code_Sheet'!$A$3:$C$33,3,0) -> #N/A | F33: =M22-C33 -> #N/A | G33: =VLOOKUP(A33,'JP Code_Sheet'!$A$3:$X$33,24,0) -> #N/A | H33: =C33+G33 -> #N/A
A34: G 21866 | B34: SSC1901 | C34: =VLOOKUP(A34,'JP Code_Sheet'!$A$3:$C$33,3,0) -> #N/A | F34: =M23-C34 -> #N/A | G34: =VLOOKUP(A34,'JP Code_Sheet'!$A$3:$X$33,24,0) -> #N/A | H34: =C34+G34 -> #N/A
A35: S 17736 | B35: LINAETF | C35: =VLOOKUP(A35,'JP Code_Sheet'!$A$3:$C$33,3,0) -> #N/A | F35: =M24-C35 -> #N/A | G35: =VLOOKUP(A35,'JP Code_Sheet'!$A$3:$X$33,24,0) -> #N/A | H35: =C35+G35 -> #N/A
A36: S 19661 | B36: LTCIIP2299 | C36: =VLOOKUP(A36,'JP Code_Sheet'!$A$3:$C$35,3,0) -> #N/A | F36: =M25-C36 -> #N/A | G36: =VLOOKUP(A36,'JP Code_Sheet'!$A$3:$X$35,24,0) -> #N/A | H36: =C36+G36 -> #N/A

Sheet NYLIC_BNY
A1: Custody # | B1: Portfolio | C1: Name of Fund | E1: SOD Cash(USD: settled cash balances) | G1: Pending Trades +Failing (BNY) | H1: Futures Vari (as of previous day: detailed net asset val) | I1: Income (projections) | J1: Sweep (priced positions) | L1: Total Cash | N1: Equity MV (BNY custody_ Posted positions) | P1: Total Assets | Q1: Percent Cash | R1: Cash Flow (cash projection) | S1: Net Cash | T1: Percent Net Cash | U1: Updated Cash
A2: 353109 | B2: GIA1902 | C2: NYLIAC GENERAL (GIA), 190 | D2: S&P 500 IND FD | E2: =VLOOKUP(A2,'JP Code_Sheet'!$A$67:$B$71,2,0) -> #N/A | G2: =VLOOKUP(A2,$A$26:$G$30,7,0) -> #N/A | I2: =VLOOKUP(A2,'JP Code_Sheet'!$A$67:$D$71,4,0) -> #N/A | L2: =E2+G2+I2+J2+K2+F2 -> #N/A | N2: =VLOOKUP(A2,'JP Code_Sheet'!$A$67:$H$71,8,0) -> #N/A | P2: =L2+M2+N2 -> #N/A | Q2: =L2/P2 -> #N/A | S2: =L2+R2 -> #N/A | T2: =S2/P2 -> #N/A
A3: 676966 | B3: IQ50ETF | C3: NYLIAC INDEX IQ ETF SMA 1839 | D3: VP S&P 500 FD | E3: =VLOOKUP(A3,'JP Code_Sheet'!$A$67:$B$71,2,0) -> #N/A | G3: =VLOOKUP(A3,$A$26:$G$30,7,0) -> #N/A | I3: =VLOOKUP(A3,'JP Code_Sheet'!$A$67:$D$71,4,0) -> #N/A | L3: =E3+G3+I3+J3+K3+F3 -> #N/A | N3: =VLOOKUP(A3,'JP Code_Sheet'!$A$67:$H$71,8,0) -> #N/A | P3: =L3+M3+N3 -> #N/A | Q3: =L3/P3 -> #N/A | S3: =L3+R3 -> #N/A | T3: =S3/P3 -> #N/A
A4: 666129 | B4: GIALCEP | C4: NYLIAC LARGE CAP ENHANCED (GIA), 1827 | E4: =VLOOKUP(A4,'JP Code_Sheet'!$A$67:$B$71,2,0) -> #N/A | G4: =VLOOKUP(A4,$A$26:$G$30,7,0) -> #N/A | I4: =VLOOKUP(A4,'JP Code_Sheet'!$A$67:$D$71,4,0) -> #N/A | L4: =E4+G4+I4+J4+K4+F4 -> #N/A | N4: =VLOOKUP(A4,'JP Code_Sheet'!$A$67:$H$71,8,0) -> #N/A | P4: =L4+M4+N4 -> #N/A | Q4: =L4/P4 -> #N/A | S4: =L4+R4 -> #N/A | T4: =S4/P4 -> #N/A
A5: 157506 | B5: NYLIM225 | C5: NYLIM LLC INDEXIQ ETF 2252/Life Pre-82 NYL Ventures Equity | E5: =VLOOKUP(A5,'JP Code_Sheet'!$A$67:$B$71,2,0) -> #N/A | G5: =VLOOKUP(A5,$A$26:$G$30,7,0) -> #N/A | I5: =VLOOKUP(A5,'JP Code_Sheet'!$A$67:$D$71,4,0) -> #N/A | L5: =E5+G5+I5+J5+K5+F5 -> #N/A | N5: =VLOOKUP(A5,'JP Code_Sheet'!$A$67:$H$71,8,0) -> #N/A | P5: =L5+M5+N5 -> #N/A | Q5: =L5/P5 -> #N/A | S5: =L5+R5 -> #N/A | T5: =S5/P5 -> #N/A
A6: 776443 | B6: FDAClear2300 | C6: NYLIAC General Equity ETF Strategy (FDA Clear), 2300 | E6: =VLOOKUP(A6,'JP Code_Sheet'!$A$69:$B$75,2,0) -> #N/A | G6: =VLOOKUP(A6,$A$28:$G$34,7,0) -> #N/A | I6: =VLOOKUP(A6,'JP Code_Sheet'!$A$69:$D$75,4,0) -> #N/A | L6: =E6+G6+I6+J6+K6+F6 -> #N/A | N6: =VLOOKUP(A6,'JP Code_Sheet'!$A$69:$H$75,8,0) -> #N/A | P6: =L6+M6+N6 -> #N/A | Q6: =L6/P6 -> #N/A | S6: =L6+R6 -> #N/A | T6: =S6/P6 -> #N/A
E7: (Includes Sweep+cash) | J7: Included in SOD
A16: T-0 | B16: EZE
A17: =C17-1 -> 45466 | B17: S/D | C17: ='JP Code_Sheet'!A1 -> 45467 | E17: =C17+1 -> 45468 | F17: =E17+1 -> 45469 | G17: =F17+1 -> 45470 | H17: =G17+1 -> 45471 | I17: =H17+1 -> 45472 | J17: =I17+1 -> 45473 | K17: =J17+1 -> 45474 | L17: =K17+1 -> 45475 | M17: Total Pending
A18: =SUMIFS('Previous Trade Calc'!$Q:$Q,'Previous Trade Calc'!$B:$B,$B$18,'Previous Trade Calc'!$E:$E,A17) -> 0 | B18: GIA1902 | C18: =SUMIFS('Previous Trade Calc'!$Q:$Q,'Previous Trade Calc'!$B:$B,$B$18,'Previous Trade Calc'!$E:$E,C17) -> 0 | E18: =SUMIFS('Previous Trade Calc'!$Q:$Q,'Previous Trade Calc'!$B:$B,$B$18,'Previous Trade Calc'!$E:$E,E17) -> 0 | F18: =SUMIFS('Previous Trade Calc'!$Q:$Q,'Previous Trade Calc'!$B:$B,$B$18,'Previous Trade Calc'!$E:$E,F17) -> 0 | G18: =SUMIFS('Previous Trade Calc'!$Q:$Q,'Previous Trade Calc'!$B:$B,$B$18,'Previous Trade Calc'!$E:$E,G17) -> 0 | H18: =SUMIFS('Previous Trade Calc'!$Q:$Q,'Previous Trade Calc'!$B:$B,$B$18,'Previous Trade Calc'!$E:$E,H17) -> 0 | I18: =SUMIFS('Previous Trade Calc'!$Q:$Q,'Previous Trade Calc'!$B:$B,$B$18,'Previous Trade Calc'!$E:$E,I17) -> 0 | J18: =SUMIFS('Previous Trade Calc'!$Q:$Q,'Previous Trade Calc'!$B:$B,$B$18,'Previous Trade Calc'!$E:$E,J17) -> 0 | K18: =SUMIFS('Previous Trade Calc'!$Q:$Q,'Previous Trade Calc'!$B:$B,$B$18,'Previous Trade Calc'!$E:$E,K17) -> 0 | L18: =SUMIFS('Previous Trade Calc'!$Q:$Q,'Previous Trade Calc'!$B:$B,$B$18,'Previous Trade Calc'!$E:$E,L17) -> 0 | M18: =SUM(C18:L18) -> 0
A19: =SUMIFS('Previous Trade Calc'!$Q:$Q,'Previous Trade Calc'!$B:$B,$B$19,'Previous Trade Calc'!$E:$E,A17) -> 0 | B19: IQ50ETF | C19: =SUMIFS('Previous Trade Calc'!$Q:$Q,'Previous Trade Calc'!$B:$B,$B$19,'Previous Trade Calc'!$E:$E,C17) -> 0 | E19: =SUMIFS('Previous Trade Calc'!$Q:$Q,'Previous Trade Calc'!$B:$B,$B$19,'Previous Trade Calc'!$E:$E,E17) -> 0 | F19: =SUMIFS('Previous Trade Calc'!$Q:$Q,'Previous Trade Calc'!$B:$B,$B$19,'Previous Trade Calc'!$E:$E,F17) -> 0 | G19: =SUMIFS('Previous Trade Calc'!$Q:$Q,'Previous Trade Calc'!$B:$B,$B$19,'Previous Trade Calc'!$E:$E,G17) -> 0 | H19: =SUMIFS('Previous Trade Calc'!$Q:$Q,'Previous Trade Calc'!$B:$B,$B$19,'Previous Trade Calc'!$E:$E,H17) -> 0 | I19: =SUMIFS('Previous Trade Calc'!$Q:$Q,'Previous Trade Calc'!$B:$B,$B$19,'Previous Trade Calc'!$E:$E,I17) -> 0 | J19: =SUMIFS('Previous Trade Calc'!$Q:$Q,'Previous Trade Calc'!$B:$B,$B$19,'Previous Trade Calc'!$E:$E,J17) -> 0 | K19: =SUMIFS('Previous Trade Calc'!$Q:$Q,'Previous Trade Calc'!$B:$B,$B$19,'Previous Trade Calc'!$E:$E,K17) -> 0 | L19: =SUMIFS('Previous Trade Calc'!$Q:$Q,'Previous Trade Calc'!$B:$B,$B$19,'Previous Trade Calc'!$E:$E,L17) -> 0 | M19: =SUM(C19:L19) -> 0
A20: =SUMIFS('Previous Trade Calc'!$Q:$Q,'Previous Trade Calc'!$B:$B,$B$20,'Previous Trade Calc'!$E:$E,A17) -> 0 | B20: GIALCEP | C20: =SUMIFS('Previous Trade Calc'!$Q:$Q,'Previous Trade Calc'!$B:$B,$B$20,'Previous Trade Calc'!$E:$E,C17) -> 0 | E20: =SUMIFS('Previous Trade Calc'!$Q:$Q,'Previous Trade Calc'!$B:$B,$B$20,'Previous Trade Calc'!$E:$E,E17) -> 0 | F20: =SUMIFS('Previous Trade Calc'!$Q:$Q,'Previous Trade Calc'!$B:$B,$B$20,'Previous Trade Calc'!$E:$E,F17) -> 0 | G20: =SUMIFS('Previous Trade Calc'!$Q:$Q,'Previous Trade Calc'!$B:$B,$B$20,'Previous Trade Calc'!$E:$E,G17) -> 0 | H20: =SUMIFS('Previous Trade Calc'!$Q:$Q,'Previous Trade Calc'!$B:$B,$B$20,'Previous Trade Calc'!$E:$E,H17) -> 0 | I20: =SUMIFS('Previous Trade Calc'!$Q:$Q,'Previous Trade Calc'!$B:$B,$B$20,'Previous Trade Calc'!$E:$E,I17) -> 0 | J20: =SUMIFS('Previous Trade Calc'!$Q:$Q,'Previous Trade Calc'!$B:$B,$B$20,'Previous Trade Calc'!$E:$E,J17) -> 0 | K20: =SUMIFS('Previous Trade Calc'!$Q:$Q,'Previous Trade Calc'!$B:$B,$B$20,'Previous Trade Calc'!$E:$E,K17) -> 0 | L20: =SUMIFS('Previous Trade Calc'!$Q:$Q,'Previous Trade Calc'!$B:$B,$B$20,'Previous Trade Calc'!$E:$E,L17) -> 0 | M20: =SUM(C20:L20) -> 0
A21: =SUMIFS('Previous Trade Calc'!$Q:$Q,'Previous Trade Calc'!$B:$B,$B$21,'Previous Trade Calc'!$E:$E,A17) -> 0 | B21: FDAClear2300 | C21: =SUMIFS('Previous Trade Calc'!$Q:$Q,'Previous Trade Calc'!$B:$B,$B$21,'Previous Trade Calc'!$E:$E,C17) -> 0 | D21: =SUMIFS('Previous Trade Calc'!$Q:$Q,'Previous Trade Calc'!$B:$B,$B$21,'Previous Trade Calc'!$E:$E,D18) -> 0 | E21: =SUMIFS('Previous Trade Calc'!$Q:$Q,'Previous Trade Calc'!$B:$B,$B$21,'Previous Trade Calc'!$E:$E,E17) -> 0 | F21: =SUMIFS('Previous Trade Calc'!$Q:$Q,'Previous Trade Calc'!$B:$B,$B$21,'Previous Trade Calc'!$E:$E,F17) -> 0 | G21: =SUMIFS('Previous Trade Calc'!$Q:$Q,'Previous Trade Calc'!$B:$B,$B$21,'Previous Trade Calc'!$E:$E,G17) -> 0 | H21: =SUMIFS('Previous Trade Calc'!$Q:$Q,'Previous Trade Calc'!$B:$B,$B$21,'Previous Trade Calc'!$E:$E,H17) -> 0 | I21: =SUMIFS('Previous Trade Calc'!$Q:$Q,'Previous Trade Calc'!$B:$B,$B$21,'Previous Trade Calc'!$E:$E,I17) -> 0 | J21: =SUMIFS('Previous Trade Calc'!$Q:$Q,'Previous Trade Calc'!$B:$B,$B$21,'Previous Trade Calc'!$E:$E,J17) -> 0 | K21: =SUMIFS('Previous Trade Calc'!$Q:$Q,'Previous Trade Calc'!$B:$B,$B$21,'Previous Trade Calc'!$E:$E,K17) -> 0 | L21: =SUMIFS('Previous Trade Calc'!$Q:$Q,'Previous Trade Calc'!$B:$B,$B$21,'Previous Trade Calc'!$E:$E,L17) -> 0 | M21: =SUMIFS('Previous Trade Calc'!$Q:$Q,'Previous Trade Calc'!$B:$B,$B$21,'Previous Trade Calc'!$E:$E,M17) -> 0
A22: =SUMIFS('Previous Trade Calc'!$Q:$Q,'Previous Trade Calc'!$B:$B,$B$22,'Previous Trade Calc'!$E:$E,A17) -> 0 | B22: NYLIM225 | C22: =SUMIFS('Previous Trade Calc'!$Q:$Q,'Previous Trade Calc'!$B:$B,$B$22,'Previous Trade Calc'!$E:$E,C17) -> 0 | E22: =SUMIFS('Previous Trade Calc'!$Q:$Q,'Previous Trade Calc'!$B:$B,$B$22,'Previous Trade Calc'!$E:$E,E17) -> 0 | F22: =SUMIFS('Previous Trade Calc'!$Q:$Q,'Previous Trade Calc'!$B:$B,$B$22,'Previous Trade Calc'!$E:$E,F17) -> 0 | G22: =SUMIFS('Previous Trade Calc'!$Q:$Q,'Previous Trade Calc'!$B:$B,$B$22,'Previous Trade Calc'!$E:$E,G17) -> 0 | H22: =SUMIFS('Previous Trade Calc'!$Q:$Q,'Previous Trade Calc'!$B:$B,$B$22,'Previous Trade Calc'!$E:$E,H17) -> 0 | I22: =SUMIFS('Previous Trade Calc'!$Q:$Q,'Previous Trade Calc'!$B:$B,$B$22,'Previous Trade Calc'!$E:$E,I17) -> 0 | J22: =SUMIFS('Previous Trade Calc'!$Q:$Q,'Previous Trade Calc'!$B:$B,$B$22,'Previous Trade Calc'!$E:$E,J17) -> 0 | K22: =SUMIFS('Previous Trade Calc'!$Q:$Q,'Previous Trade Calc'!$B:$B,$B$22,'Previous Trade Calc'!$E:$E,K17) -> 0 | L22: =SUMIFS('Previous Trade Calc'!$Q:$Q,'Previous Trade Calc'!$B:$B,$B$22,'Previous Trade Calc'!$E:$E,L17) -> 0 | M22: =SUM(C22:L22) -> 0
C25: BNY Reports Pending Trades | E25: Diff | F25: Failing Trades | G25: Total
A26: 353109 | B26: GIA1902 | C26: =VLOOKUP(A26,'JP Code_Sheet'!$A$67:$C$71,3,0) -> #N/A | E26: =C26-M18 -> #N/A | F26: =VLOOKUP(A26,'JP Code_Sheet'!$A$67:$X$71,24,0) -> #N/A | G26: =C26+F26 -> #N/A
A27: 676966 | B27: IQ50ETF | C27: =VLOOKUP(A27,'JP Code_Sheet'!$A$67:$C$71,3,0) -> #N/A | E27: =C27-M19 -> #N/A | F27: =VLOOKUP(A27,'JP Code_Sheet'!$A$67:$X$71,24,0) -> #N/A | G27: =C27+F27 -> #N/A
A28: 666129 | B28: GIALCEP | C28: =VLOOKUP(A28,'JP Code_Sheet'!$A$67:$C$71,3,0) -> #N/A | E28: =C28-M20 -> #N/A | F28: =VLOOKUP(A28,'JP Code_Sheet'!$A$67:$X$71,24,0) -> #N/A | G28: =C28+F28 -> #N/A
A29: 776443 | B29: FDAClear2300 | C29: =VLOOKUP(A29,'JP Code_Sheet'!$A$69:$C$75,3,0) -> #N/A | E29: =C29-M21 -> #N/A | F29: =VLOOKUP(A29,'JP Code_Sheet'!$A$69:$X$75,24,0) -> #N/A | G29: =C29+F29 -> #N/A
A30: 157506 | B30: NYLIM225 | C30: =VLOOKUP(A30,'JP Code_Sheet'!$A$67:$C$71,3,0) -> #N/A | E30: =C30-M22 -> #N/A | F30: =VLOOKUP(A30,'JP Code_Sheet'!$A$67:$X$71,24,0) -> #N/A | G30: =C30+F30 -> #N/A

Sheet Currency Balance
A1: ='JP Code_Sheet'!A1 -> 45467 | E1: SI on for all Div's | G1: Purchases (LOCAL) | H1: Purchases (BASE) | I1: Sale (LOCAL) | J1: Sale (BASE) | P1: Pulling in Fixing rates to get USD estimate
A2: AIA40 | C2: Local Balance | D2: USD Bal | E2: Income Local | G2: Pending Equity Trades | H2: Pending Equity Trades | I2: Pending Equity Trades | J2: Pending Equity Trades | O2: Currency | P2: BB London 4:00pm Fixing | Q2: Rates for Eze File
B3: AUD | C3: =SUMIFS('JP_Priced Positions_custody'!AK:AK,'JP_Priced Positions_custody'!AG:AG,B3,'JP_Priced Positions_custody'!A:A,$A$2,'JP_Priced Positions_custody'!L:L,"CASH") -> 0 | D3: =SUMIFS('JP_Priced Positions_custody'!AO:AO,'JP_Priced Positions_custody'!AG:AG,B3,'JP_Priced Positions_custody'!A:A,$A$2,'JP_Priced Positions_custody'!L:L,"CASH") -> 0 | E3: =SUMIFS('JP_Cash Projection - Statement'!N:N,'JP_Cash Projection - Statement'!E:E,'JP Code_Sheet'!$A$1,'JP_Cash Projection - Statement'!C:C,'JP Code_Sheet'!$A$33,'JP_Cash Projection - Statement'!A:A,'Currency Balance'!B3)+SUMIFS('JP_Cash Projection - Statement'!O:O,'JP_Cash Projection - Statement'!E:E,'JP Code_Sheet'!$A$1,'JP_Cash Projection - Statement'!C:C,'JP Code_Sheet'!$A$33,'JP_Cash Projection - Statement'!A:A,'Currency Balance'!B3)+SUMIFS('JP_Cash Projection - Statement'!R:R,'JP_Cash Projection - Statement'!E:E,'JP Code_Sheet'!$A$1,'JP_Cash Projection - Statement'!C:C,'JP Code_Sheet'!$A$33,'JP_Cash Projection - Statement'!A:A,'Currency Balance'!B3)+SUMIFS('JP_Cash Projection - Statement'!AA:AA,'JP_Cash Projection - Statement'!E:E,'JP Code_Sheet'!$A$1,'JP_Cash Projection - Statement'!C:C,'JP Code_Sheet'!$A$33,'JP_Cash Projection - Statement'!A:A,'Currency Balance'!B3)+SUMIFS('JP_Cash Projection - Statement'!AB:AB,'JP_Cash Projection - Statement'!E:E,'JP Code_Sheet'!$A$1,'JP_Cash Projection - Statement'!C:C,'JP Code_Sheet'!$A$33,'JP_Cash Projection - Statement'!A:A,'Currency Balance'!B3)+SUMIFS('JP_Cash Projection - Statement'!AE:AE,'JP_Cash Projection - Statement'!E:E,'JP Code_Sheet'!$A$1,'JP_Cash Projection - Statement'!C:C,'JP Code_Sheet'!$A$33,'JP_Cash Projection - Statement'!A:A,'Currency Balance'!B3) -> 0 | G3: =SUMIFS('JP_Cash Projection - Detail'!AV:AV,'JP_Cash Projection - Detail'!I:I,$A$2,'JP_Cash Projection - Detail'!K:K,B3,'JP_Cash Projection - Detail'!H:H,"PURCHASE") -> 0 | H3: =G3/Q3 -> #NAME? | I3: =SUMIFS('JP_Cash Projection - Detail'!AV:AV,'JP_Cash Projection - Detail'!I:I,$A$2,'JP_Cash Projection - Detail'!K:K,B3,'JP_Cash Projection - Detail'!H:H,"SALE") -> 0 | J3: =I3/Q3 -> #NAME? | O3: AUD | P3: =_xll.BDP(O3&" L160 Curncy","PX_LAST") -> #NAME? | Q3: =1/P3 -> #NAME?
B4: BRL | C4: =SUMIFS('JP_Priced Positions_custody'!AK:AK,'JP_Priced Positions_custody'!AG:AG,B4,'JP_Priced Positions_custody'!A:A,$A$2,'JP_Priced Positions_custody'!L:L,"CASH") -> 0 | D4: =SUMIFS('JP_Priced Positions_custody'!AO:AO,'JP_Priced Positions_custody'!AG:AG,B4,'JP_Priced Positions_custody'!A:A,$A$2,'JP_Priced Positions_custody'!L:L,"CASH") -> 0 | E4: =SUMIFS('JP_Cash Projection - Statement'!N:N,'JP_Cash Projection - Statement'!E:E,'JP Code_Sheet'!$A$1,'JP_Cash Projection - Statement'!C:C,'JP Code_Sheet'!$A$33,'JP_Cash Projection - Statement'!A:A,'Currency Balance'!B4)+SUMIFS('JP_Cash Projection - Statement'!O:O,'JP_Cash Projection - Statement'!E:E,'JP Code_Sheet'!$A$1,'JP_Cash Projection - Statement'!C:C,'JP Code_Sheet'!$A$33,'JP_Cash Projection - Statement'!A:A,'Currency Balance'!B4)+SUMIFS('JP_Cash Projection - Statement'!R:R,'JP_Cash Projection - Statement'!E:E,'JP Code_Sheet'!$A$1,'JP_Cash Projection - Statement'!C:C,'JP Code_Sheet'!$A$33,'JP_Cash Projection - Statement'!A:A,'Currency Balance'!B4)+SUMIFS('JP_Cash Projection - Statement'!AA:AA,'JP_Cash Projection - Statement'!E:E,'JP Code_Sheet'!$A$1,'JP_Cash Projection - Statement'!C:C,'JP Code_Sheet'!$A$33,'JP_Cash Projection - Statement'!A:A,'Currency Balance'!B4)+SUMIFS('JP_Cash Projection - Statement'!AB:AB,'JP_Cash Projection - Statement'!E:E,'JP Code_Sheet'!$A$1,'JP_Cash Projection - Statement'!C:C,'JP Code_Sheet'!$A$33,'JP_Cash Projection - Statement'!A:A,'Currency Balance'!B4)+SUMIFS('JP_Cash Projection - Statement'!AE:AE,'JP_Cash Projection - Statement'!E:E,'JP Code_Sheet'!$A$1,'JP_Cash Projection - Statement'!C:C,'JP Code_Sheet'!$A$33,'JP_Cash Projection - Statement'!A:A,'Currency Balance'!B4) -> 0 | G4: =SUMIFS('JP_Cash Projection - Detail'!AV:AV,'JP_Cash Projection - Detail'!I:I,$A$2,'JP_Cash Projection - Detail'!K:K,B4,'JP_Cash Projection - Detail'!H:H,"PURCHASE") -> 0 | H4: =G4/Q4 -> #NAME? | I4: =SUMIFS('JP_Cash Projection - Detail'!AV:AV,'JP_Cash Projection - Detail'!I:I,$A$2,'JP_Cash Projection - Detail'!K:K,B4,'JP_Cash Projection - Detail'!H:H,"SALE") -> 0 | J4: =I4/Q4 -> #NAME? | O4: BRL | P4: =_xll.BDP(O4&" L160 Curncy","PX_LAST") -> #NAME? | Q4: =P4 -> #NAME?
B5: CAD | C5: =SUMIFS('JP_Priced Positions_custody'!AK:AK,'JP_Priced Positions_custody'!AG:AG,B5,'JP_Priced Positions_custody'!A:A,$A$2,'JP_Priced Positions_custody'!L:L,"CASH") -> 0 | D5: =SUMIFS('JP_Priced Positions_custody'!AO:AO,'JP_Priced Positions_custody'!AG:AG,B5,'JP_Priced Positions_custody'!A:A,$A$2,'JP_Priced Positions_custody'!L:L,"CASH") -> 0 | E5: =SUMIFS('JP_Cash Projection - Statement'!N:N,'JP_Cash Projection - Statement'!E:E,'JP Code_Sheet'!$A$1,'JP_Cash Projection - Statement'!C:C,'JP Code_Sheet'!$A$33,'JP_Cash Projection - Statement'!A:A,'Currency Balance'!B5)+SUMIFS('JP_Cash Projection - Statement'!O:O,'JP_Cash Projection - Statement'!E:E,'JP Code_Sheet'!$A$1,'JP_Cash Projection - Statement'!C:C,'JP Code_Sheet'!$A$33,'JP_Cash Projection - Statement'!A:A,'Currency Balance'!B5)+SUMIFS('JP_Cash Projection - Statement'!R:R,'JP_Cash Projection - Statement'!E:E,'JP Code_Sheet'!$A$1,'JP_Cash Projection - Statement'!C:C,'JP Code_Sheet'!$A$33,'JP_Cash Projection - Statement'!A:A,'Currency Balance'!B5)+SUMIFS('JP_Cash Projection - Statement'!AA:AA,'JP_Cash Projection - Statement'!E:E,'JP Code_Sheet'!$A$1,'JP_Cash Projection - Statement'!C:C,'JP Code_Sheet'!$A$33,'JP_Cash Projection - Statement'!A:A,'Currency Balance'!B5)+SUMIFS('JP_Cash Projection - Statement'!AB:AB,'JP_Cash Projection - Statement'!E:E,'JP Code_Sheet'!$A$1,'JP_Cash Projection - Statement'!C:C,'JP Code_Sheet'!$A$33,'JP_Cash Projection - Statement'!A:A,'Currency Balance'!B5)+SUMIFS('JP_Cash Projection - Statement'!AE:AE,'JP_Cash Projection - Statement'!E:E,'JP Code_Sheet'!$A$1,'JP_Cash Projection - Statement'!C:C,'JP Code_Sheet'!$A$33,'JP_Cash Projection - Statement'!A:A,'Currency Balance'!B5) -> 0 | G5: =SUMIFS('JP_Cash Projection - Detail'!AV:AV,'JP_Cash Projection - Detail'!I:I,$A$2,'JP_Cash Projection - Detail'!K:K,B5,'JP_Cash Projection - Detail'!H:H,"PURCHASE") -> 0 | H5: =G5/Q5 -> #NAME? | I5: =SUMIFS('JP_Cash Projection - Detail'!AV:AV,'JP_Cash Projection - Detail'!I:I,$A$2,'JP_Cash Projection - Detail'!K:K,B5,'JP_Cash Projection - Detail'!H:H,"SALE") -> 0 | J5: =I5/Q5 -> #NAME? | O5: CAD | P5: =_xll.BDP(O5&" L160 Curncy","PX_LAST") -> #NAME? | Q5: =P5 -> #NAME?
B6: CHF | C6: =SUMIFS('JP_Priced Positions_custody'!AK:AK,'JP_Priced Positions_custody'!AG:AG,B6,'JP_Priced Positions_custody'!A:A,$A$2,'JP_Priced Positions_custody'!L:L,"CASH") -> 0 | D6: =SUMIFS('JP_Priced Positions_custody'!AO:AO,'JP_Priced Positions_custody'!AG:AG,B6,'JP_Priced Positions_custody'!A:A,$A$2,'JP_Priced Positions_custody'!L:L,"CASH") -> 0 | E6: =SUMIFS('JP_Cash Projection - Statement'!N:N,'JP_Cash Projection - Statement'!E:E,'JP Code_Sheet'!$A$1,'JP_Cash Projection - Statement'!C:C,'JP Code_Sheet'!$A$33,'JP_Cash Projection - Statement'!A:A,'Currency Balance'!B6)+SUMIFS('JP_Cash Projection - Statement'!O:O,'JP_Cash Projection - Statement'!E:E,'JP Code_Sheet'!$A$1,'JP_Cash Projection - Statement'!C:C,'JP Code_Sheet'!$A$33,'JP_Cash Projection - Statement'!A:A,'Currency Balance'!B6)+SUMIFS('JP_Cash Projection - Statement'!R:R,'JP_Cash Projection - Statement'!E:E,'JP Code_Sheet'!$A$1,'JP_Cash Projection - Statement'!C:C,'JP Code_Sheet'!$A$33,'JP_Cash Projection - Statement'!A:A,'Currency Balance'!B6)+SUMIFS('JP_Cash Projection - Statement'!AA:AA,'JP_Cash Projection - Statement'!E:E,'JP Code_Sheet'!$A$1,'JP_Cash Projection - Statement'!C:C,'JP Code_Sheet'!$A$33,'JP_Cash Projection - Statement'!A:A,'Currency Balance'!B6)+SUMIFS('JP_Cash Projection - Statement'!AB:AB,'JP_Cash Projection - Statement'!E:E,'JP Code_Sheet'!$A$1,'JP_Cash Projection - Statement'!C:C,'JP Code_Sheet'!$A$33,'JP_Cash Projection - Statement'!A:A,'Currency Balance'!B6)+SUMIFS('JP_Cash Projection - Statement'!AE:AE,'JP_Cash Projection - Statement'!E:E,'JP Code_Sheet'!$A$1,'JP_Cash Projection - Statement'!C:C,'JP Code_Sheet'!$A$33,'JP_Cash Projection - Statement'!A:A,'Currency Balance'!B6) -> 0 | G6: =SUMIFS('JP_Cash Projection - Detail'!AV:AV,'JP_Cash Projection - Detail'!I:I,$A$2,'JP_Cash Projection - Detail'!K:K,B6,'JP_Cash Projection - Detail'!H:H,"PURCHASE") -> 0 | H6: =G6/Q6 -> #NAME? | I6: =SUMIFS('JP_Cash Projection - Detail'!AV:AV,'JP_Cash Projection - Detail'!I:I,$A$2,'JP_Cash Projection - Detail'!K:K,B6,'JP_Cash Projection - Detail'!H:H,"SALE") -> 0 | J6: =I6/Q6 -> #NAME? | O6: CHF | P6: =_xll.BDP(O6&" L160 Curncy","PX_LAST") -> #NAME? | Q6: =P6 -> #NAME?
B7: CLP | C7: =SUMIFS('JP_Priced Positions_custody'!AK:AK,'JP_Priced Positions_custody'!AG:AG,B7,'JP_Priced Positions_custody'!A:A,$A$2,'JP_Priced Positions_custody'!L:L,"CASH") -> 0 | D7: =SUMIFS('JP_Priced Positions_custody'!AO:AO,'JP_Priced Positions_custody'!AG:AG,B7,'JP_Priced Positions_custody'!A:A,$A$2,'JP_Priced Positions_custody'!L:L,"CASH") -> 0 | E7: =SUMIFS('JP_Cash Projection - Statement'!N:N,'JP_Cash Projection - Statement'!E:E,'JP Code_Sheet'!$A$1,'JP_Cash Projection - Statement'!C:C,'JP Code_Sheet'!$A$33,'JP_Cash Projection - Statement'!A:A,'Currency Balance'!B7)+SUMIFS('JP_Cash Projection - Statement'!O:O,'JP_Cash Projection - Statement'!E:E,'JP Code_Sheet'!$A$1,'JP_Cash Projection - Statement'!C:C,'JP Code_Sheet'!$A$33,'JP_Cash Projection - Statement'!A:A,'Currency Balance'!B7)+SUMIFS('JP_Cash Projection - Statement'!R:R,'JP_Cash Projection - Statement'!E:E,'JP Code_Sheet'!$A$1,'JP_Cash Projection - Statement'!C:C,'JP Code_Sheet'!$A$33,'JP_Cash Projection - Statement'!A:A,'Currency Balance'!B7)+SUMIFS('JP_Cash Projection - Statement'!AA:AA,'JP_Cash Projection - Statement'!E:E,'JP Code_Sheet'!$A$1,'JP_Cash Projection - Statement'!C:C,'JP Code_Sheet'!$A$33,'JP_Cash Projection - Statement'!A:A,'Currency Balance'!B7)+SUMIFS('JP_Cash Projection - Statement'!AB:AB,'JP_Cash Projection - Statement'!E:E,'JP Code_Sheet'!$A$1,'JP_Cash Projection - Statement'!C:C,'JP Code_Sheet'!$A$33,'JP_Cash Projection - Statement'!A:A,'Currency Balance'!B7)+SUMIFS('JP_Cash Projection - Statement'!AE:AE,'JP_Cash Projection - Statement'!E:E,'JP Code_Sheet'!$A$1,'JP_Cash Projection - Statement'!C:C,'JP Code_Sheet'!$A$33,'JP_Cash Projection - Statement'!A:A,'Currency Balance'!B7) -> 0 | G7: =SUMIFS('JP_Cash Projection - Detail'!AV:AV,'JP_Cash Projection - Detail'!I:I,$A$2,'JP_Cash Projection - Detail'!K:K,B7,'JP_Cash Projection - Detail'!H:H,"PURCHASE") -> 0 | H7: =G7/Q7 -> #NAME? | I7: =SUMIFS('JP_Cash Projection - Detail'!AV:AV,'JP_Cash Projection - Detail'!I:I,$A$2,'JP_Cash Projection - Detail'!K:K,B7,'JP_Cash Projection - Detail'!H:H,"SALE") -> 0 | J7: =I7/Q7 -> #NAME? | O7: CLP | P7: =_xll.BDP(O7&" L160 Curncy","PX_LAST") -> #NAME? | Q7: =P7 -> #NAME?
B8: COP | C8: =SUMIFS('JP_Priced Positions_custody'!AK:AK,'JP_Priced Positions_custody'!AG:AG,B8,'JP_Priced Positions_custody'!A:A,$A$2,'JP_Priced Positions_custody'!L:L,"CASH") -> 0 | D8: =SUMIFS('JP_Priced Positions_custody'!AO:AO,'JP_Priced Positions_custody'!AG:AG,B8,'JP_Priced Positions_custody'!A:A,$A$2,'JP_Priced Positions_custody'!L:L,"CASH") -> 0 | E8: =SUMIFS('JP_Cash Projection - Statement'!N:N,'JP_Cash Projection - Statement'!E:E,'JP Code_Sheet'!$A$1,'JP_Cash Projection - Statement'!C:C,'JP Code_Sheet'!$A$33,'JP_Cash Projection - Statement'!A:A,'Currency Balance'!B8)+SUMIFS('JP_Cash Projection - Statement'!O:O,'JP_Cash Projection - Statement'!E:E,'JP Code_Sheet'!$A$1,'JP_Cash Projection - Statement'!C:C,'JP Code_Sheet'!$A$33,'JP_Cash Projection - Statement'!A:A,'Currency Balance'!B8)+SUMIFS('JP_Cash Projection - Statement'!R:R,'JP_Cash Projection - Statement'!E:E,'JP Code_Sheet'!$A$1,'JP_Cash Projection - Statement'!C:C,'JP Code_Sheet'!$A$33,'JP_Cash Projection - Statement'!A:A,'Currency Balance'!B8)+SUMIFS('JP_Cash Projection - Statement'!AA:AA,'JP_Cash Projection - Statement'!E:E,'JP Code_Sheet'!$A$1,'JP_Cash Projection - Statement'!C:C,'JP Code_Sheet'!$A$33,'JP_Cash Projection - Statement'!A:A,'Currency Balance'!B8)+SUMIFS('JP_Cash Projection - Statement'!AB:AB,'JP_Cash Projection - Statement'!E:E,'JP Code_Sheet'!$A$1,'JP_Cash Projection - Statement'!C:C,'JP Code_Sheet'!$A$33,'JP_Cash Projection - Statement'!A:A,'Currency Balance'!B8)+SUMIFS('JP_Cash Projection - Statement'!AE:AE,'JP_Cash Projection - Statement'!E:E,'JP Code_Sheet'!$A$1,'JP_Cash Projection - Statement'!C:C,'JP Code_Sheet'!$A$33,'JP_Cash Projection - Statement'!A:A,'Currency Balance'!B8) -> 0 | G8: =SUMIFS('JP_Cash Projection - Detail'!AV:AV,'JP_Cash Projection - Detail'!I:I,$A$2,'JP_Cash Projection - Detail'!K:K,B8,'JP_Cash Projection - Detail'!H:H,"PURCHASE") -> 0 | H8: =G8/Q8 -> #NAME? | I8: =SUMIFS('JP_Cash Projection - Detail'!AV:AV,'JP_Cash Projection - Detail'!I:I,$A$2,'JP_Cash Projection - Detail'!K:K,B8,'JP_Cash Projection - Detail'!H:H,"SALE") -> 0 | J8: =I8/Q8 -> #NAME? | O8: COP | P8: =_xll.BDP(O8&" L160 Curncy","PX_LAST") -> #NAME? | Q8: =P8 -> #NAME?
B9: CZK | C9: =SUMIFS('JP_Priced Positions_custody'!AK:AK,'JP_Priced Positions_custody'!AG:AG,B9,'JP_Priced Positions_custody'!A:A,$A$2,'JP_Priced Positions_custody'!L:L,"CASH") -> 0 | D9: =SUMIFS('JP_Priced Positions_custody'!AO:AO,'JP_Priced Positions_custody'!AG:AG,B9,'JP_Priced Positions_custody'!A:A,$A$2,'JP_Priced Positions_custody'!L:L,"CASH") -> 0 | E9: =SUMIFS('JP_Cash Projection - Statement'!N:N,'JP_Cash Projection - Statement'!E:E,'JP Code_Sheet'!$A$1,'JP_Cash Projection - Statement'!C:C,'JP Code_Sheet'!$A$33,'JP_Cash Projection - Statement'!A:A,'Currency Balance'!B9)+SUMIFS('JP_Cash Projection - Statement'!O:O,'JP_Cash Projection - Statement'!E:E,'JP Code_Sheet'!$A$1,'JP_Cash Projection - Statement'!C:C,'JP Code_Sheet'!$A$33,'JP_Cash Projection - Statement'!A:A,'Currency Balance'!B9)+SUMIFS('JP_Cash Projection - Statement'!R:R,'JP_Cash Projection - Statement'!E:E,'JP Code_Sheet'!$A$1,'JP_Cash Projection - Statement'!C:C,'JP Code_Sheet'!$A$33,'JP_Cash Projection - Statement'!A:A,'Currency Balance'!B9)+SUMIFS('JP_Cash Projection - Statement'!AA:AA,'JP_Cash Projection - Statement'!E:E,'JP Code_Sheet'!$A$1,'JP_Cash Projection - Statement'!C:C,'JP Code_Sheet'!$A$33,'JP_Cash Projection - Statement'!A:A,'Currency Balance'!B9)+SUMIFS('JP_Cash Projection - Statement'!AB:AB,'JP_Cash Projection - Statement'!E:E,'JP Code_Sheet'!$A$1,'JP_Cash Projection - Statement'!C:C,'JP Code_Sheet'!$A$33,'JP_Cash Projection - Statement'!A:A,'Currency Balance'!B9)+SUMIFS('JP_Cash Projection - Statement'!AE:AE,'JP_Cash Projection - Statement'!E:E,'JP Code_Sheet'!$A$1,'JP_Cash Projection - Statement'!C:C,'JP Code_Sheet'!$A$33,'JP_Cash Projection - Statement'!A:A,'Currency Balance'!B9) -> 0 | G9: =SUMIFS('JP_Cash Projection - Detail'!AV:AV,'JP_Cash Projection - Detail'!I:I,$A$2,'JP_Cash Projection - Detail'!K:K,B9,'JP_Cash Projection - Detail'!H:H,"PURCHASE") -> 0 | H9: =G9/Q9 -> #NAME? | I9: =SUMIFS('JP_Cash Projection - Detail'!AV:AV,'JP_Cash Projection - Detail'!I:I,$A$2,'JP_Cash Projection - Detail'!K:K,B9,'JP_Cash Projection - Detail'!H:H,"SALE") -> 0 | J9: =I9/Q9 -> #NAME? | O9: CZK | P9: =_xll.BDP(O9&" L160 Curncy","PX_LAST") -> #NAME? | Q9: =P9 -> #NAME?
B10: DKK | C10: =SUMIFS('JP_Priced Positions_custody'!AK:AK,'JP_Priced Positions_custody'!AG:AG,B10,'JP_Priced Positions_custody'!A:A,$A$2,'JP_Priced Positions_custody'!L:L,"CASH") -> 0 | D10: =SUMIFS('JP_Priced Positions_custody'!AO:AO,'JP_Priced Positions_custody'!AG:AG,B10,'JP_Priced Positions_custody'!A:A,$A$2,'JP_Priced Positions_custody'!L:L,"CASH") -> 0 | E10: =SUMIFS('JP_Cash Projection - Statement'!N:N,'JP_Cash Projection - Statement'!E:E,'JP Code_Sheet'!$A$1,'JP_Cash Projection - Statement'!C:C,'JP Code_Sheet'!$A$33,'JP_Cash Projection - Statement'!A:A,'Currency Balance'!B10)+SUMIFS('JP_Cash Projection - Statement'!O:O,'JP_Cash Projection - Statement'!E:E,'JP Code_Sheet'!$A$1,'JP_Cash Projection - Statement'!C:C,'JP Code_Sheet'!$A$33,'JP_Cash Projection - Statement'!A:A,'Currency Balance'!B10)+SUMIFS('JP_Cash Projection - Statement'!R:R,'JP_Cash Projection - Statement'!E:E,'JP Code_Sheet'!$A$1,'JP_Cash Projection - Statement'!C:C,'JP Code_Sheet'!$A$33,'JP_Cash Projection - Statement'!A:A,'Currency Balance'!B10)+SUMIFS('JP_Cash Projection - Statement'!AA:AA,'JP_Cash Projection - Statement'!E:E,'JP Code_Sheet'!$A$1,'JP_Cash Projection - Statement'!C:C,'JP Code_Sheet'!$A$33,'JP_Cash Projection - Statement'!A:A,'Currency Balance'!B10)+SUMIFS('JP_Cash Projection - Statement'!AB:AB,'JP_Cash Projection - Statement'!E:E,'JP Code_Sheet'!$A$1,'JP_Cash Projection - Statement'!C:C,'JP Code_Sheet'!$A$33,'JP_Cash Projection - Statement'!A:A,'Currency Balance'!B10)+SUMIFS('JP_Cash Projection - Statement'!AE:AE,'JP_Cash Projection - Statement'!E:E,'JP Code_Sheet'!$A$1,'JP_Cash Projection - Statement'!C:C,'JP Code_Sheet'!$A$33,'JP_Cash Projection - Statement'!A:A,'Currency Balance'!B10) -> 0 | G10: =SUMIFS('JP_Cash Projection - Detail'!AV:AV,'JP_Cash Projection - Detail'!I:I,$A$2,'JP_Cash Projection - Detail'!K:K,B10,'JP_Cash Projection - Detail'!H:H,"PURCHASE") -> 0 | H10: =G10/Q10 -> #NAME? | I10: =SUMIFS('JP_Cash Projection - Detail'!AV:AV,'JP_Cash Projection - Detail'!I:I,$A$2,'JP_Cash Projection - Detail'!K:K,B10,'JP_Cash Projection - Detail'!H:H,"SALE") -> 0 | J10: =I10/Q10 -> #NAME? | O10: DKK | P10: =_xll.BDP(O10&" L160 Curncy","PX_LAST") -> #NAME? | Q10: =P10 -> #NAME?
B11: EUR | C11: =SUMIFS('JP_Priced Positions_custody'!AK:AK,'JP_Priced Positions_custody'!AG:AG,B11,'JP_Priced Positions_custody'!A:A,$A$2,'JP_Priced Positions_custody'!L:L,"CASH") -> 0 | D11: =SUMIFS('JP_Priced Positions_custody'!AO:AO,'JP_Priced Positions_custody'!AG:AG,B11,'JP_Priced Positions_custody'!A:A,$A$2,'JP_Priced Positions_custody'!L:L,"CASH") -> 0 | E11: =SUMIFS('JP_Cash Projection - Statement'!N:N,'JP_Cash Projection - Statement'!E:E,'JP Code_Sheet'!$A$1,'JP_Cash Projection - Statement'!C:C,'JP Code_Sheet'!$A$33,'JP_Cash Projection - Statement'!A:A,'Currency Balance'!B11)+SUMIFS('JP_Cash Projection - Statement'!O:O,'JP_Cash Projection - Statement'!E:E,'JP Code_Sheet'!$A$1,'JP_Cash Projection - Statement'!C:C,'JP Code_Sheet'!$A$33,'JP_Cash Projection - Statement'!A:A,'Currency Balance'!B11)+SUMIFS('JP_Cash Projection - Statement'!R:R,'JP_Cash Projection - Statement'!E:E,'JP Code_Sheet'!$A$1,'JP_Cash Projection - Statement'!C:C,'JP Code_Sheet'!$A$33,'JP_Cash Projection - Statement'!A:A,'Currency Balance'!B11)+SUMIFS('JP_Cash Projection - Statement'!AA:AA,'JP_Cash Projection - Statement'!E:E,'JP Code_Sheet'!$A$1,'JP_Cash Projection - Statement'!C:C,'JP Code_Sheet'!$A$33,'JP_Cash Projection - Statement'!A:A,'Currency Balance'!B11)+SUMIFS('JP_Cash Projection - Statement'!AB:AB,'JP_Cash Projection - Statement'!E:E,'JP Code_Sheet'!$A$1,'JP_Cash Projection - Statement'!C:C,'JP Code_Sheet'!$A$33,'JP_Cash Projection - Statement'!A:A,'Currency Balance'!B11)+SUMIFS('JP_Cash Projection - Statement'!AE:AE,'JP_Cash Projection - Statement'!E:E,'JP Code_Sheet'!$A$1,'JP_Cash Projection - Statement'!C:C,'JP Code_Sheet'!$A$33,'JP_Cash Projection - Statement'!A:A,'Currency Balance'!B11) -> 0 | G11: =SUMIFS('JP_Cash Projection - Detail'!AV:AV,'JP_Cash Projection - Detail'!I:I,$A$2,'JP_Cash Projection - Detail'!K:K,B11,'JP_Cash Projection - Detail'!H:H,"PURCHASE") -> 0 | H11: =G11/Q11 -> #NAME? | I11: =SUMIFS('JP_Cash Projection - Detail'!AV:AV,'JP_Cash Projection - Detail'!I:I,$A$2,'JP_Cash Projection - Detail'!K:K,B11,'JP_Cash Projection - Detail'!H:H,"SALE") -> 0 | J11: =I11/Q11 -> #NAME? | O11: EUR | P11: =_xll.BDP(O11&" L160 Curncy","PX_LAST") -> #NAME? | Q11: =1/P11 -> #NAME?
B12: GBP | C12: =SUMIFS('JP_Priced Positions_custody'!AK:AK,'JP_Priced Positions_custody'!AG:AG,B12,'JP_Priced Positions_custody'!A:A,$A$2,'JP_Priced Positions_custody'!L:L,"CASH") -> 0 | D12: =SUMIFS('JP_Priced Positions_custody'!AO:AO,'JP_Priced Positions_custody'!AG:AG,B12,'JP_Priced Positions_custody'!A:A,$A$2,'JP_Priced Positions_custody'!L:L,"CASH") -> 0 | E12: =SUMIFS('JP_Cash Projection - Statement'!N:N,'JP_Cash Projection - Statement'!E:E,'JP Code_Sheet'!$A$1,'JP_Cash Projection - Statement'!C:C,'JP Code_Sheet'!$A$33,'JP_Cash Projection - Statement'!A:A,'Currency Balance'!B12)+SUMIFS('JP_Cash Projection - Statement'!O:O,'JP_Cash Projection - Statement'!E:E,'JP Code_Sheet'!$A$1,'JP_Cash Projection - Statement'!C:C,'JP Code_Sheet'!$A$33,'JP_Cash Projection - Statement'!A:A,'Currency Balance'!B12)+SUMIFS('JP_Cash Projection - Statement'!R:R,'JP_Cash Projection - Statement'!E:E,'JP Code_Sheet'!$A$1,'JP_Cash Projection - Statement'!C:C,'JP Code_Sheet'!$A$33,'JP_Cash Projection - Statement'!A:A,'Currency Balance'!B12)+SUMIFS('JP_Cash Projection - Statement'!AA:AA,'JP_Cash Projection - Statement'!E:E,'JP Code_Sheet'!$A$1,'JP_Cash Projection - Statement'!C:C,'JP Code_Sheet'!$A$33,'JP_Cash Projection - Statement'!A:A,'Currency Balance'!B12)+SUMIFS('JP_Cash Projection - Statement'!AB:AB,'JP_Cash Projection - Statement'!E:E,'JP Code_Sheet'!$A$1,'JP_Cash Projection - Statement'!C:C,'JP Code_Sheet'!$A$33,'JP_Cash Projection - Statement'!A:A,'Currency Balance'!B12)+SUMIFS('JP_Cash Projection - Statement'!AE:AE,'JP_Cash Projection - Statement'!E:E,'JP Code_Sheet'!$A$1,'JP_Cash Projection - Statement'!C:C,'JP Code_Sheet'!$A$33,'JP_Cash Projection - Statement'!A:A,'Currency Balance'!B12) -> 0 | G12: =SUMIFS('JP_Cash Projection - Detail'!AV:AV,'JP_Cash Projection - Detail'!I:I,$A$2,'JP_Cash Projection - Detail'!K:K,B12,'JP_Cash Projection - Detail'!H:H,"PURCHASE") -> 0 | H12: =G12/Q12 -> #NAME? | I12: =SUMIFS('JP_Cash Projection - Detail'!AV:AV,'JP_Cash Projection - Detail'!I:I,$A$2,'JP_Cash Projection - Detail'!K:K,B12,'JP_Cash Projection - Detail'!H:H,"SALE") -> 0 | J12: =I12/Q12 -> #NAME? | O12: GBP | P12: =_xll.BDP(O12&" L160 Curncy","PX_LAST") -> #NAME? | Q12: =1/P12 -> #NAME?
B13: HKD | C13: =SUMIFS('JP_Priced Positions_custody'!AK:AK,'JP_Priced Positions_custody'!AG:AG,B13,'JP_Priced Positions_custody'!A:A,$A$2,'JP_Priced Positions_custody'!L:L,"CASH") -> 0 | D13: =SUMIFS('JP_Priced Positions_custody'!AO:AO,'JP_Priced Positions_custody'!AG:AG,B13,'JP_Priced Positions_custody'!A:A,$A$2,'JP_Priced Positions_custody'!L:L,"CASH") -> 0 | E13: =SUMIFS('JP_Cash Projection - Statement'!N:N,'JP_Cash Projection - Statement'!E:E,'JP Code_Sheet'!$A$1,'JP_Cash Projection - Statement'!C:C,'JP Code_Sheet'!$A$33,'JP_Cash Projection - Statement'!A:A,'Currency Balance'!B13)+SUMIFS('JP_Cash Projection - Statement'!O:O,'JP_Cash Projection - Statement'!E:E,'JP Code_Sheet'!$A$1,'JP_Cash Projection - Statement'!C:C,'JP Code_Sheet'!$A$33,'JP_Cash Projection - Statement'!A:A,'Currency Balance'!B13)+SUMIFS('JP_Cash Projection - Statement'!R:R,'JP_Cash Projection - Statement'!E:E,'JP Code_Sheet'!$A$1,'JP_Cash Projection - Statement'!C:C,'JP Code_Sheet'!$A$33,'JP_Cash Projection - Statement'!A:A,'Currency Balance'!B13)+SUMIFS('JP_Cash Projection - Statement'!AA:AA,'JP_Cash Projection - Statement'!E:E,'JP Code_Sheet'!$A$1,'JP_Cash Projection - Statement'!C:C,'JP Code_Sheet'!$A$33,'JP_Cash Projection - Statement'!A:A,'Currency Balance'!B13)+SUMIFS('JP_Cash Projection - Statement'!AB:AB,'JP_Cash Projection - Statement'!E:E,'JP Code_Sheet'!$A$1,'JP_Cash Projection - Statement'!C:C,'JP Code_Sheet'!$A$33,'JP_Cash Projection - Statement'!A:A,'Currency Balance'!B13)+SUMIFS('JP_Cash Projection - Statement'!AE:AE,'JP_Cash Projection - Statement'!E:E,'JP Code_Sheet'!$A$1,'JP_Cash Projection - Statement'!C:C,'JP Code_Sheet'!$A$33,'JP_Cash Projection - Statement'!A:A,'Currency Balance'!B13) -> 0 | G13: =SUMIFS('JP_Cash Projection - Detail'!AV:AV,'JP_Cash Projection - Detail'!I:I,$A$2,'JP_Cash Projection - Detail'!K:K,B13,'JP_Cash Projection - Detail'!H:H,"PURCHASE") -> 0 | H13: =G13/Q13 -> #NAME? | I13: =SUMIFS('JP_Cash Projection - Detail'!AV:AV,'JP_Cash Projection - Detail'!I:I,$A$2,'JP_Cash Projection - Detail'!K:K,B13,'JP_Cash Projection - Detail'!H:H,"SALE") -> 0 | J13: =I13/Q13 -> #NAME? | O13: HKD | P13: =_xll.BDP(O13&" L160 Curncy","PX_LAST") -> #NAME? | Q13: =P13 -> #NAME?
B14: HUF | C14: =SUMIFS('JP_Priced Positions_custody'!AK:AK,'JP_Priced Positions_custody'!AG:AG,B14,'JP_Priced Positions_custody'!A:A,$A$2,'JP_Priced Positions_custody'!L:L,"CASH") -> 0 | D14: =SUMIFS('JP_Priced Positions_custody'!AO:AO,'JP_Priced Positions_custody'!AG:AG,B14,'JP_Priced Positions_custody'!A:A,$A$2,'JP_Priced Positions_custody'!L:L,"CASH") -> 0 | E14: =SUMIFS('JP_Cash Projection - Statement'!N:N,'JP_Cash Projection - Statement'!E:E,'JP Code_Sheet'!$A$1,'JP_Cash Projection - Statement'!C:C,'JP Code_Sheet'!$A$33,'JP_Cash Projection - Statement'!A:A,'Currency Balance'!B14)+SUMIFS('JP_Cash Projection - Statement'!O:O,'JP_Cash Projection - Statement'!E:E,'JP Code_Sheet'!$A$1,'JP_Cash Projection - Statement'!C:C,'JP Code_Sheet'!$A$33,'JP_Cash Projection - Statement'!A:A,'Currency Balance'!B14)+SUMIFS('JP_Cash Projection - Statement'!R:R,'JP_Cash Projection - Statement'!E:E,'JP Code_Sheet'!$A$1,'JP_Cash Projection - Statement'!C:C,'JP Code_Sheet'!$A$33,'JP_Cash Projection - Statement'!A:A,'Currency Balance'!B14)+SUMIFS('JP_Cash Projection - Statement'!AA:AA,'JP_Cash Projection - Statement'!E:E,'JP Code_Sheet'!$A$1,'JP_Cash Projection - Statement'!C:C,'JP Code_Sheet'!$A$33,'JP_Cash Projection - Statement'!A:A,'Currency Balance'!B14)+SUMIFS('JP_Cash Projection - Statement'!AB:AB,'JP_Cash Projection - Statement'!E:E,'JP Code_Sheet'!$A$1,'JP_Cash Projection - Statement'!C:C,'JP Code_Sheet'!$A$33,'JP_Cash Projection - Statement'!A:A,'Currency Balance'!B14)+SUMIFS('JP_Cash Projection - Statement'!AE:AE,'JP_Cash Projection - Statement'!E:E,'JP Code_Sheet'!$A$1,'JP_Cash Projection - Statement'!C:C,'JP Code_Sheet'!$A$33,'JP_Cash Projection - Statement'!A:A,'Currency Balance'!B14) -> 0 | G14: =SUMIFS('JP_Cash Projection - Detail'!AV:AV,'JP_Cash Projection - Detail'!I:I,$A$2,'JP_Cash Projection - Detail'!K:K,B14,'JP_Cash Projection - Detail'!H:H,"PURCHASE") -> 0 | H14: =G14/Q14 -> #NAME? | I14: =SUMIFS('JP_Cash Projection - Detail'!AV:AV,'JP_Cash Projection - Detail'!I:I,$A$2,'JP_Cash Projection - Detail'!K:K,B14,'JP_Cash Projection - Detail'!H:H,"SALE") -> 0 | J14: =I14/Q14 -> #NAME? | O14: HUF | P14: =_xll.BDP(O14&" L160 Curncy","PX_LAST") -> #NAME? | Q14: =P14 -> #NAME?
B15: IDR | C15: =SUMIFS('JP_Priced Positions_custody'!AK:AK,'JP_Priced Positions_custody'!AG:AG,B15,'JP_Priced Positions_custody'!A:A,$A$2,'JP_Priced Positions_custody'!L:L,"CASH") -> 0 | D15: =SUMIFS('JP_Priced Positions_custody'!AO:AO,'JP_Priced Positions_custody'!AG:AG,B15,'JP_Priced Positions_custody'!A:A,$A$2,'JP_Priced Positions_custody'!L:L,"CASH") -> 0 | E15: =SUMIFS('JP_Cash Projection - Statement'!N:N,'JP_Cash Projection - Statement'!E:E,'JP Code_Sheet'!$A$1,'JP_Cash Projection - Statement'!C:C,'JP Code_Sheet'!$A$33,'JP_Cash Projection - Statement'!A:A,'Currency Balance'!B15)+SUMIFS('JP_Cash Projection - Statement'!O:O,'JP_Cash Projection - Statement'!E:E,'JP Code_Sheet'!$A$1,'JP_Cash Projection - Statement'!C:C,'JP Code_Sheet'!$A$33,'JP_Cash Projection - Statement'!A:A,'Currency Balance'!B15)+SUMIFS('JP_Cash Projection - Statement'!R:R,'JP_Cash Projection - Statement'!E:E,'JP Code_Sheet'!$A$1,'JP_Cash Projection - Statement'!C:C,'JP Code_Sheet'!$A$33,'JP_Cash Projection - Statement'!A:A,'Currency Balance'!B15)+SUMIFS('JP_Cash Projection - Statement'!AA:AA,'JP_Cash Projection - Statement'!E:E,'JP Code_Sheet'!$A$1,'JP_Cash Projection - Statement'!C:C,'JP Code_Sheet'!$A$33,'JP_Cash Projection - Statement'!A:A,'Currency Balance'!B15)+SUMIFS('JP_Cash Projection - Statement'!AB:AB,'JP_Cash Projection - Statement'!E:E,'JP Code_Sheet'!$A$1,'JP_Cash Projection - Statement'!C:C,'JP Code_Sheet'!$A$33,'JP_Cash Projection - Statement'!A:A,'Currency Balance'!B15)+SUMIFS('JP_Cash Projection - Statement'!AE:AE,'JP_Cash Projection - Statement'!E:E,'JP Code_Sheet'!$A$1,'JP_Cash Projection - Statement'!C:C,'JP Code_Sheet'!$A$33,'JP_Cash Projection - Statement'!A:A,'Currency Balance'!B15) -> 0 | G15: =SUMIFS('JP_Cash Projection - Detail'!AV:AV,'JP_Cash Projection - Detail'!I:I,$A$2,'JP_Cash Projection - Detail'!K:K,B15,'JP_Cash Projection - Detail'!H:H,"PURCHASE") -> 0 | H15: =G15/Q15 -> #NAME? | I15: =SUMIFS('JP_Cash Projection - Detail'!AV:AV,'JP_Cash Projection - Detail'!I:I,$A$2,'JP_Cash Projection - Detail'!K:K,B15,'JP_Cash Projection - Detail'!H:H,"SALE") -> 0 | J15: =I15/Q15 -> #NAME? | O15: IDR | P15: =_xll.BDP(O15&" L160 Curncy","PX_LAST") -> #NAME? | Q15: =P15 -> #NAME?
B16: ILS | C16: =SUMIFS('JP_Priced Positions_custody'!AK:AK,'JP_Priced Positions_custody'!AG:AG,B16,'JP_Priced Positions_custody'!A:A,$A$2,'JP_Priced Positions_custody'!L:L,"CASH") -> 0 | D16: =SUMIFS('JP_Priced Positions_custody'!AO:AO,'JP_Priced Positions_custody'!AG:AG,B16,'JP_Priced Positions_custody'!A:A,$A$2,'JP_Priced Positions_custody'!L:L,"CASH") -> 0 | E16: =SUMIFS('JP_Cash Projection - Statement'!N:N,'JP_Cash Projection - Statement'!E:E,'JP Code_Sheet'!$A$1,'JP_Cash Projection - Statement'!C:C,'JP Code_Sheet'!$A$33,'JP_Cash Projection - Statement'!A:A,'Currency Balance'!B16)+SUMIFS('JP_Cash Projection - Statement'!O:O,'JP_Cash Projection - Statement'!E:E,'JP Code_Sheet'!$A$1,'JP_Cash Projection - Statement'!C:C,'JP Code_Sheet'!$A$33,'JP_Cash Projection - Statement'!A:A,'Currency Balance'!B16)+SUMIFS('JP_Cash Projection - Statement'!R:R,'JP_Cash Projection - Statement'!E:E,'JP Code_Sheet'!$A$1,'JP_Cash Projection - Statement'!C:C,'JP Code_Sheet'!$A$33,'JP_Cash Projection - Statement'!A:A,'Currency Balance'!B16)+SUMIFS('JP_Cash Projection - Statement'!AA:AA,'JP_Cash Projection - Statement'!E:E,'JP Code_Sheet'!$A$1,'JP_Cash Projection - Statement'!C:C,'JP Code_Sheet'!$A$33,'JP_Cash Projection - Statement'!A:A,'Currency Balance'!B16)+SUMIFS('JP_Cash Projection - Statement'!AB:AB,'JP_Cash Projection - Statement'!E:E,'JP Code_Sheet'!$A$1,'JP_Cash Projection - Statement'!C:C,'JP Code_Sheet'!$A$33,'JP_Cash Projection - Statement'!A:A,'Currency Balance'!B16)+SUMIFS('JP_Cash Projection - Statement'!AE:AE,'JP_Cash Projection - Statement'!E:E,'JP Code_Sheet'!$A$1,'JP_Cash Projection - Statement'!C:C,'JP Code_Sheet'!$A$33,'JP_Cash Projection - Statement'!A:A,'Currency Balance'!B16) -> 0 | G16: =SUMIFS('JP_Cash Projection - Detail'!AV:AV,'JP_Cash Projection - Detail'!I:I,$A$2,'JP_Cash Projection - Detail'!K:K,B16,'JP_Cash Projection - Detail'!H:H,"PURCHASE") -> 0 | H16: =G16/Q16 -> #NAME? | I16: =SUMIFS('JP_Cash Projection - Detail'!AV:AV,'JP_Cash Projection - Detail'!I:I,$A$2,'JP_Cash Projection - Detail'!K:K,B16,'JP_Cash Projection - Detail'!H:H,"SALE") -> 0 | J16: =I16/Q16 -> #NAME? | O16: ILS | P16: =_xll.BDP(O16&" L160 Curncy","PX_LAST") -> #NAME? | Q16: =P16 -> #NAME?
B17: INR | C17: =SUMIFS('JP_Priced Positions_custody'!AK:AK,'JP_Priced Positions_custody'!AG:AG,B17,'JP_Priced Positions_custody'!A:A,$A$2,'JP_Priced Positions_custody'!L:L,"CASH") -> 0 | D17: =SUMIFS('JP_Priced Positions_custody'!AO:AO,'JP_Priced Positions_custody'!AG:AG,B17,'JP_Priced Positions_custody'!A:A,$A$2,'JP_Priced Positions_custody'!L:L,"CASH") -> 0 | E17: =SUMIFS('JP_Cash Projection - Statement'!N:N,'JP_Cash Projection - Statement'!E:E,'JP Code_Sheet'!$A$1,'JP_Cash Projection - Statement'!C:C,'JP Code_Sheet'!$A$33,'JP_Cash Projection - Statement'!A:A,'Currency Balance'!B17)+SUMIFS('JP_Cash Projection - Statement'!O:O,'JP_Cash Projection - Statement'!E:E,'JP Code_Sheet'!$A$1,'JP_Cash Projection - Statement'!C:C,'JP Code_Sheet'!$A$33,'JP_Cash Projection - Statement'!A:A,'Currency Balance'!B17)+SUMIFS('JP_Cash Projection - Statement'!R:R,'JP_Cash Projection - Statement'!E:E,'JP Code_Sheet'!$A$1,'JP_Cash Projection - Statement'!C:C,'JP Code_Sheet'!$A$33,'JP_Cash Projection - Statement'!A:A,'Currency Balance'!B17)+SUMIFS('JP_Cash Projection - Statement'!AA:AA,'JP_Cash Projection - Statement'!E:E,'JP Code_Sheet'!$A$1,'JP_Cash Projection - Statement'!C:C,'JP Code_Sheet'!$A$33,'JP_Cash Projection - Statement'!A:A,'Currency Balance'!B17)+SUMIFS('JP_Cash Projection - Statement'!AB:AB,'JP_Cash Projection - Statement'!E:E,'JP Code_Sheet'!$A$1,'JP_Cash Projection - Statement'!C:C,'JP Code_Sheet'!$A$33,'JP_Cash Projection - Statement'!A:A,'Currency Balance'!B17)+SUMIFS('JP_Cash Projection - Statement'!AE:AE,'JP_Cash Projection - Statement'!E:E,'JP Code_Sheet'!$A$1,'JP_Cash Projection - Statement'!C:C,'JP Code_Sheet'!$A$33,'JP_Cash Projection - Statement'!A:A,'Currency Balance'!B17) -> 0 | G17: =SUMIFS('JP_Cash Projection - Detail'!AV:AV,'JP_Cash Projection - Detail'!I:I,$A$2,'JP_Cash Projection - Detail'!K:K,B17,'JP_Cash Projection - Detail'!H:H,"PURCHASE") -> 0 | H17: =G17/Q17 -> #NAME? | I17: =SUMIFS('JP_Cash Projection - Detail'!AV:AV,'JP_Cash Projection - Detail'!I:I,$A$2,'JP_Cash Projection - Detail'!K:K,B17,'JP_Cash Projection - Detail'!H:H,"SALE") -> 0 | J17: =I17/Q17 -> #NAME? | O17: INR | P17: =_xll.BDP(O17&" L160 Curncy","PX_LAST") -> #NAME? | Q17: =P17 -> #NAME?
B18: JPY | C18: =SUMIFS('JP_Priced Positions_custody'!AK:AK,'JP_Priced Positions_custody'!AG:AG,B18,'JP_Priced Positions_custody'!A:A,$A$2,'JP_Priced Positions_custody'!L:L,"CASH") -> 0 | D18: =SUMIFS('JP_Priced Positions_custody'!AO:AO,'JP_Priced Positions_custody'!AG:AG,B18,'JP_Priced Positions_custody'!A:A,$A$2,'JP_Priced Positions_custody'!L:L,"CASH") -> 0 | E18: =SUMIFS('JP_Cash Projection - Statement'!N:N,'JP_Cash Projection - Statement'!E:E,'JP Code_Sheet'!$A$1,'JP_Cash Projection - Statement'!C:C,'JP Code_Sheet'!$A$33,'JP_Cash Projection - Statement'!A:A,'Currency Balance'!B18)+SUMIFS('JP_Cash Projection - Statement'!O:O,'JP_Cash Projection - Statement'!E:E,'JP Code_Sheet'!$A$1,'JP_Cash Projection - Statement'!C:C,'JP Code_Sheet'!$A$33,'JP_Cash Projection - Statement'!A:A,'Currency Balance'!B18)+SUMIFS('JP_Cash Projection - Statement'!R:R,'JP_Cash Projection - Statement'!E:E,'JP Code_Sheet'!$A$1,'JP_Cash Projection - Statement'!C:C,'JP Code_Sheet'!$A$33,'JP_Cash Projection - Statement'!A:A,'Currency Balance'!B18)+SUMIFS('JP_Cash Projection - Statement'!AA:AA,'JP_Cash Projection - Statement'!E:E,'JP Code_Sheet'!$A$1,'JP_Cash Projection - Statement'!C:C,'JP Code_Sheet'!$A$33,'JP_Cash Projection - Statement'!A:A,'Currency Balance'!B18)+SUMIFS('JP_Cash Projection - Statement'!AB:AB,'JP_Cash Projection - Statement'!E:E,'JP Code_Sheet'!$A$1,'JP_Cash Projection - Statement'!C:C,'JP Code_Sheet'!$A$33,'JP_Cash Projection - Statement'!A:A,'Currency Balance'!B18)+SUMIFS('JP_Cash Projection - Statement'!AE:AE,'JP_Cash Projection - Statement'!E:E,'JP Code_Sheet'!$A$1,'JP_Cash Projection - Statement'!C:C,'JP Code_Sheet'!$A$33,'JP_Cash Projection - Statement'!A:A,'Currency Balance'!B18) -> 0 | G18: =SUMIFS('JP_Cash Projection - Detail'!AV:AV,'JP_Cash Projection - Detail'!I:I,$A$2,'JP_Cash Projection - Detail'!K:K,B18,'JP_Cash Projection - Detail'!H:H,"PURCHASE") -> 0 | H18: =G18/Q18 -> #NAME? | I18: =SUMIFS('JP_Cash Projection - Detail'!AV:AV,'JP_Cash Projection - Detail'!I:I,$A$2,'JP_Cash Projection - Detail'!K:K,B18,'JP_Cash Projection - Detail'!H:H,"SALE") -> 0 | J18: =I18/Q18 -> #NAME? | O18: JPY | P18: =_xll.BDP(O18&" L160 Curncy","PX_LAST") -> #NAME? | Q18: =P18 -> #NAME?
B19: KRW | C19: =SUMIFS('JP_Priced Positions_custody'!AK:AK,'JP_Priced Positions_custody'!AG:AG,B19,'JP_Priced Positions_custody'!A:A,$A$2,'JP_Priced Positions_custody'!L:L,"CASH") -> 0 | D19: =SUMIFS('JP_Priced Positions_custody'!AO:AO,'JP_Priced Positions_custody'!AG:AG,B19,'JP_Priced Positions_custody'!A:A,$A$2,'JP_Priced Positions_custody'!L:L,"CASH") -> 0 | E19: =SUMIFS('JP_Cash Projection - Statement'!N:N,'JP_Cash Projection - Statement'!E:E,'JP Code_Sheet'!$A$1,'JP_Cash Projection - Statement'!C:C,'JP Code_Sheet'!$A$33,'JP_Cash Projection - Statement'!A:A,'Currency Balance'!B19)+SUMIFS('JP_Cash Projection - Statement'!O:O,'JP_Cash Projection - Statement'!E:E,'JP Code_Sheet'!$A$1,'JP_Cash Projection - Statement'!C:C,'JP Code_Sheet'!$A$33,'JP_Cash Projection - Statement'!A:A,'Currency Balance'!B19)+SUMIFS('JP_Cash Projection - Statement'!R:R,'JP_Cash Projection - Statement'!E:E,'JP Code_Sheet'!$A$1,'JP_Cash Projection - Statement'!C:C,'JP Code_Sheet'!$A$33,'JP_Cash Projection - Statement'!A:A,'Currency Balance'!B19)+SUMIFS('JP_Cash Projection - Statement'!AA:AA,'JP_Cash Projection - Statement'!E:E,'JP Code_Sheet'!$A$1,'JP_Cash Projection - Statement'!C:C,'JP Code_Sheet'!$A$33,'JP_Cash Projection - Statement'!A:A,'Currency Balance'!B19)+SUMIFS('JP_Cash Projection - Statement'!AB:AB,'JP_Cash Projection - Statement'!E:E,'JP Code_Sheet'!$A$1,'JP_Cash Projection - Statement'!C:C,'JP Code_Sheet'!$A$33,'JP_Cash Projection - Statement'!A:A,'Currency Balance'!B19)+SUMIFS('JP_Cash Projection - Statement'!AE:AE,'JP_Cash Projection - Statement'!E:E,'JP Code_Sheet'!$A$1,'JP_Cash Projection - Statement'!C:C,'JP Code_Sheet'!$A$33,'JP_Cash Projection - Statement'!A:A,'Currency Balance'!B19) -> 0 | G19: =SUMIFS('JP_Cash Projection - Detail'!AV:AV,'JP_Cash Projection - Detail'!I:I,$A$2,'JP_Cash Projection - Detail'!K:K,B19,'JP_Cash Projection - Detail'!H:H,"PURCHASE") -> 0 | H19: =G19/Q19 -> #NAME? | I19: =SUMIFS('JP_Cash Projection - Detail'!AV:AV,'JP_Cash Projection - Detail'!I:I,$A$2,'JP_Cash Projection - Detail'!K:K,B19,'JP_Cash Projection - Detail'!H:H,"SALE") -> 0 | J19: =I19/Q19 -> #NAME? | O19: KRW | P19: =_xll.BDP(O19&" L160 Curncy","PX_LAST") -> #NAME? | Q19: =P19 -> #NAME?
B20: MXN | C20: =SUMIFS('JP_Priced Positions_custody'!AK:AK,'JP_Priced Positions_custody'!AG:AG,B20,'JP_Priced Positions_custody'!A:A,$A$2,'JP_Priced Positions_custody'!L:L,"CASH") -> 0 | D20: =SUMIFS('JP_Priced Positions_custody'!AO:AO,'JP_Priced Positions_custody'!AG:AG,B20,'JP_Priced Positions_custody'!A:A,$A$2,'JP_Priced Positions_custody'!L:L,"CASH") -> 0 | E20: =SUMIFS('JP_Cash Projection - Statement'!N:N,'JP_Cash Projection - Statement'!E:E,'JP Code_Sheet'!$A$1,'JP_Cash Projection - Statement'!C:C,'JP Code_Sheet'!$A$33,'JP_Cash Projection - Statement'!A:A,'Currency Balance'!B20)+SUMIFS('JP_Cash Projection - Statement'!O:O,'JP_Cash Projection - Statement'!E:E,'JP Code_Sheet'!$A$1,'JP_Cash Projection - Statement'!C:C,'JP Code_Sheet'!$A$33,'JP_Cash Projection - Statement'!A:A,'Currency Balance'!B20)+SUMIFS('JP_Cash Projection - Statement'!R:R,'JP_Cash Projection - Statement'!E:E,'JP Code_Sheet'!$A$1,'JP_Cash Projection - Statement'!C:C,'JP Code_Sheet'!$A$33,'JP_Cash Projection - Statement'!A:A,'Currency Balance'!B20)+SUMIFS('JP_Cash Projection - Statement'!AA:AA,'JP_Cash Projection - Statement'!E:E,'JP Code_Sheet'!$A$1,'JP_Cash Projection - Statement'!C:C,'JP Code_Sheet'!$A$33,'JP_Cash Projection - Statement'!A:A,'Currency Balance'!B20)+SUMIFS('JP_Cash Projection - Statement'!AB:AB,'JP_Cash Projection - Statement'!E:E,'JP Code_Sheet'!$A$1,'JP_Cash Projection - Statement'!C:C,'JP Code_Sheet'!$A$33,'JP_Cash Projection - Statement'!A:A,'Currency Balance'!B20)+SUMIFS('JP_Cash Projection - Statement'!AE:AE,'JP_Cash Projection - Statement'!E:E,'JP Code_Sheet'!$A$1,'JP_Cash Projection - Statement'!C:C,'JP Code_Sheet'!$A$33,'JP_Cash Projection - Statement'!A:A,'Currency Balance'!B20) -> 0 | G20: =SUMIFS('JP_Cash Projection - Detail'!AV:AV,'JP_Cash Projection - Detail'!I:I,$A$2,'JP_Cash Projection - Detail'!K:K,B20,'JP_Cash Projection - Detail'!H:H,"PURCHASE") -> 0 | H20: =G20/Q20 -> #NAME? | I20: =SUMIFS('JP_Cash Projection - Detail'!AV:AV,'JP_Cash Projection - Detail'!I:I,$A$2,'JP_Cash Projection - Detail'!K:K,B20,'JP_Cash Projection - Detail'!H:H,"SALE") -> 0 | J20: =I20/Q20 -> #NAME? | O20: MXN | P20: =_xll.BDP(O20&" L160 Curncy","PX_LAST") -> #NAME? | Q20: =P20 -> #NAME?
B21: MYR | C21: =SUMIFS('JP_Priced Positions_custody'!AK:AK,'JP_Priced Positions_custody'!AG:AG,B21,'JP_Priced Positions_custody'!A:A,$A$2,'JP_Priced Positions_custody'!L:L,"CASH") -> 0 | D21: =SUMIFS('JP_Priced Positions_custody'!AO:AO,'JP_Priced Positions_custody'!AG:AG,B21,'JP_Priced Positions_custody'!A:A,$A$2,'JP_Priced Positions_custody'!L:L,"CASH") -> 0 | E21: =SUMIFS('JP_Cash Projection - Statement'!N:N,'JP_Cash Projection - Statement'!E:E,'JP Code_Sheet'!$A$1,'JP_Cash Projection - Statement'!C:C,'JP Code_Sheet'!$A$33,'JP_Cash Projection - Statement'!A:A,'Currency Balance'!B21)+SUMIFS('JP_Cash Projection - Statement'!O:O,'JP_Cash Projection - Statement'!E:E,'JP Code_Sheet'!$A$1,'JP_Cash Projection - Statement'!C:C,'JP Code_Sheet'!$A$33,'JP_Cash Projection - Statement'!A:A,'Currency Balance'!B21)+SUMIFS('JP_Cash Projection - Statement'!R:R,'JP_Cash Projection - Statement'!E:E,'JP Code_Sheet'!$A$1,'JP_Cash Projection - Statement'!C:C,'JP Code_Sheet'!$A$33,'JP_Cash Projection - Statement'!A:A,'Currency Balance'!B21)+SUMIFS('JP_Cash Projection - Statement'!AA:AA,'JP_Cash Projection - Statement'!E:E,'JP Code_Sheet'!$A$1,'JP_Cash Projection - Statement'!C:C,'JP Code_Sheet'!$A$33,'JP_Cash Projection - Statement'!A:A,'Currency Balance'!B21)+SUMIFS('JP_Cash Projection - Statement'!AB:AB,'JP_Cash Projection - Statement'!E:E,'JP Code_Sheet'!$A$1,'JP_Cash Projection - Statement'!C:C,'JP Code_Sheet'!$A$33,'JP_Cash Projection - Statement'!A:A,'Currency Balance'!B21)+SUMIFS('JP_Cash Projection - Statement'!AE:AE,'JP_Cash Projection - Statement'!E:E,'JP Code_Sheet'!$A$1,'JP_Cash Projection - Statement'!C:C,'JP Code_Sheet'!$A$33,'JP_Cash Projection - Statement'!A:A,'Currency Balance'!B21) -> 0 | G21: =SUMIFS('JP_Cash Projection - Detail'!AV:AV,'JP_Cash Projection - Detail'!I:I,$A$2,'JP_Cash Projection - Detail'!K:K,B21,'JP_Cash Projection - Detail'!H:H,"PURCHASE") -> 0 | H21: =G21/Q21 -> #NAME? | I21: =SUMIFS('JP_Cash Projection - Detail'!AV:AV,'JP_Cash Projection - Detail'!I:I,$A$2,'JP_Cash Projection - Detail'!K:K,B21,'JP_Cash Projection - Detail'!H:H,"SALE") -> 0 | J21: =I21/Q21 -> #NAME? | O21: MYR | P21: =_xll.BDP(O21&" L160 Curncy","PX_LAST") -> #NAME? | Q21: =P21 -> #NAME?
B22: NOK | C22: =SUMIFS('JP_Priced Positions_custody'!AK:AK,'JP_Priced Positions_custody'!AG:AG,B22,'JP_Priced Positions_custody'!A:A,$A$2,'JP_Priced Positions_custody'!L:L,"CASH") -> 0 | D22: =SUMIFS('JP_Priced Positions_custody'!AO:AO,'JP_Priced Positions_custody'!AG:AG,B22,'JP_Priced Positions_custody'!A:A,$A$2,'JP_Priced Positions_custody'!L:L,"CASH") -> 0 | E22: =SUMIFS('JP_Cash Projection - Statement'!N:N,'JP_Cash Projection - Statement'!E:E,'JP Code_Sheet'!$A$1,'JP_Cash Projection - Statement'!C:C,'JP Code_Sheet'!$A$33,'JP_Cash Projection - Statement'!A:A,'Currency Balance'!B22)+SUMIFS('JP_Cash Projection - Statement'!O:O,'JP_Cash Projection - Statement'!E:E,'JP Code_Sheet'!$A$1,'JP_Cash Projection - Statement'!C:C,'JP Code_Sheet'!$A$33,'JP_Cash Projection - Statement'!A:A,'Currency Balance'!B22)+SUMIFS('JP_Cash Projection - Statement'!R:R,'JP_Cash Projection - Statement'!E:E,'JP Code_Sheet'!$A$1,'JP_Cash Projection - Statement'!C:C,'JP Code_Sheet'!$A$33,'JP_Cash Projection - Statement'!A:A,'Currency Balance'!B22)+SUMIFS('JP_Cash Projection - Statement'!AA:AA,'JP_Cash Projection - Statement'!E:E,'JP Code_Sheet'!$A$1,'JP_Cash Projection - Statement'!C:C,'JP Code_Sheet'!$A$33,'JP_Cash Projection - Statement'!A:A,'Currency Balance'!B22)+SUMIFS('JP_Cash Projection - Statement'!AB:AB,'JP_Cash Projection - Statement'!E:E,'JP Code_Sheet'!$A$1,'JP_Cash Projection - Statement'!C:C,'JP Code_Sheet'!$A$33,'JP_Cash Projection - Statement'!A:A,'Currency Balance'!B22)+SUMIFS('JP_Cash Projection - Statement'!AE:AE,'JP_Cash Projection - Statement'!E:E,'JP Code_Sheet'!$A$1,'JP_Cash Projection - Statement'!C:C,'JP Code_Sheet'!$A$33,'JP_Cash Projection - Statement'!A:A,'Currency Balance'!B22) -> 0 | G22: =SUMIFS('JP_Cash Projection - Detail'!AV:AV,'JP_Cash Projection - Detail'!I:I,$A$2,'JP_Cash Projection - Detail'!K:K,B22,'JP_Cash Projection - Detail'!H:H,"PURCHASE") -> 0 | H22: =G22/Q22 -> #NAME? | I22: =SUMIFS('JP_Cash Projection - Detail'!AV:AV,'JP_Cash Projection - Detail'!I:I,$A$2,'JP_Cash Projection - Detail'!K:K,B22,'JP_Cash Projection - Detail'!H:H,"SALE") -> 0 | J22: =I22/Q22 -> #NAME? | O22: NOK | P22: =_xll.BDP(O22&" L160 Curncy","PX_LAST") -> #NAME? | Q22: =P22 -> #NAME?
B23: NZD | C23: =SUMIFS('JP_Priced Positions_custody'!AK:AK,'JP_Priced Positions_custody'!AG:AG,B23,'JP_Priced Positions_custody'!A:A,$A$2,'JP_Priced Positions_custody'!L:L,"CASH") -> 0 | D23: =SUMIFS('JP_Priced Positions_custody'!AO:AO,'JP_Priced Positions_custody'!AG:AG,B23,'JP_Priced Positions_custody'!A:A,$A$2,'JP_Priced Positions_custody'!L:L,"CASH") -> 0 | E23: =SUMIFS('JP_Cash Projection - Statement'!N:N,'JP_Cash Projection - Statement'!E:E,'JP Code_Sheet'!$A$1,'JP_Cash Projection - Statement'!C:C,'JP Code_Sheet'!$A$33,'JP_Cash Projection - Statement'!A:A,'Currency Balance'!B23)+SUMIFS('JP_Cash Projection - Statement'!O:O,'JP_Cash Projection - Statement'!E:E,'JP Code_Sheet'!$A$1,'JP_Cash Projection - Statement'!C:C,'JP Code_Sheet'!$A$33,'JP_Cash Projection - Statement'!A:A,'Currency Balance'!B23)+SUMIFS('JP_Cash Projection - Statement'!R:R,'JP_Cash Projection - Statement'!E:E,'JP Code_Sheet'!$A$1,'JP_Cash Projection - Statement'!C:C,'JP Code_Sheet'!$A$33,'JP_Cash Projection - Statement'!A:A,'Currency Balance'!B23)+SUMIFS('JP_Cash Projection - Statement'!AA:AA,'JP_Cash Projection - Statement'!E:E,'JP Code_Sheet'!$A$1,'JP_Cash Projection - Statement'!C:C,'JP Code_Sheet'!$A$33,'JP_Cash Projection - Statement'!A:A,'Currency Balance'!B23)+SUMIFS('JP_Cash Projection - Statement'!AB:AB,'JP_Cash Projection - Statement'!E:E,'JP Code_Sheet'!$A$1,'JP_Cash Projection - Statement'!C:C,'JP Code_Sheet'!$A$33,'JP_Cash Projection - Statement'!A:A,'Currency Balance'!B23)+SUMIFS('JP_Cash Projection - Statement'!AE:AE,'JP_Cash Projection - Statement'!E:E,'JP Code_Sheet'!$A$1,'JP_Cash Projection - Statement'!C:C,'JP Code_Sheet'!$A$33,'JP_Cash Projection - Statement'!A:A,'Currency Balance'!B23) -> 0 | G23: =SUMIFS('JP_Cash Projection - Detail'!AV:AV,'JP_Cash Projection - Detail'!I:I,$A$2,'JP_Cash Projection - Detail'!K:K,B23,'JP_Cash Projection - Detail'!H:H,"PURCHASE") -> 0 | H23: =G23/Q23 -> #NAME? | I23: =SUMIFS('JP_Cash Projection - Detail'!AV:AV,'JP_Cash Projection - Detail'!I:I,$A$2,'JP_Cash Projection - Detail'!K:K,B23,'JP_Cash Projection - Detail'!H:H,"SALE") -> 0 | J23: =I23/Q23 -> #NAME? | O23: NZD | P23: =_xll.BDP(O23&" L160 Curncy","PX_LAST") -> #NAME? | Q23: =1/P23 -> #NAME?
B24: PHP | C24: =SUMIFS('JP_Priced Positions_custody'!AK:AK,'JP_Priced Positions_custody'!AG:AG,B24,'JP_Priced Positions_custody'!A:A,$A$2,'JP_Priced Positions_custody'!L:L,"CASH") -> 0 | D24: =SUMIFS('JP_Priced Positions_custody'!AO:AO,'JP_Priced Positions_custody'!AG:AG,B24,'JP_Priced Positions_custody'!A:A,$A$2,'JP_Priced Positions_custody'!L:L,"CASH") -> 0 | E24: =SUMIFS('JP_Cash Projection - Statement'!N:N,'JP_Cash Projection - Statement'!E:E,'JP Code_Sheet'!$A$1,'JP_Cash Projection - Statement'!C:C,'JP Code_Sheet'!$A$33,'JP_Cash Projection - Statement'!A:A,'Currency Balance'!B24)+SUMIFS('JP_Cash Projection - Statement'!O:O,'JP_Cash Projection - Statement'!E:E,'JP Code_Sheet'!$A$1,'JP_Cash Projection - Statement'!C:C,'JP Code_Sheet'!$A$33,'JP_Cash Projection - Statement'!A:A,'Currency Balance'!B24)+SUMIFS('JP_Cash Projection - Statement'!R:R,'JP_Cash Projection - Statement'!E:E,'JP Code_Sheet'!$A$1,'JP_Cash Projection - Statement'!C:C,'JP Code_Sheet'!$A$33,'JP_Cash Projection - Statement'!A:A,'Currency Balance'!B24)+SUMIFS('JP_Cash Projection - Statement'!AA:AA,'JP_Cash Projection - Statement'!E:E,'JP Code_Sheet'!$A$1,'JP_Cash Projection - Statement'!C:C,'JP Code_Sheet'!$A$33,'JP_Cash Projection - Statement'!A:A,'Currency Balance'!B24)+SUMIFS('JP_Cash Projection - Statement'!AB:AB,'JP_Cash Projection - Statement'!E:E,'JP Code_Sheet'!$A$1,'JP_Cash Projection - Statement'!C:C,'JP Code_Sheet'!$A$33,'JP_Cash Projection - Statement'!A:A,'Currency Balance'!B24)+SUMIFS('JP_Cash Projection - Statement'!AE:AE,'JP_Cash Projection - Statement'!E:E,'JP Code_Sheet'!$A$1,'JP_Cash Projection - Statement'!C:C,'JP Code_Sheet'!$A$33,'JP_Cash Projection - Statement'!A:A,'Currency Balance'!B24) -> 0 | G24: =SUMIFS('JP_Cash Projection - Detail'!AV:AV,'JP_Cash Projection - Detail'!I:I,$A$2,'JP_Cash Projection - Detail'!K:K,B24,'JP_Cash Projection - Detail'!H:H,"PURCHASE") -> 0 | H24: =G24/Q24 -> #NAME? | I24: =SUMIFS('JP_Cash Projection - Detail'!AV:AV,'JP_Cash Projection - Detail'!I:I,$A$2,'JP_Cash Projection - Detail'!K:K,B24,'JP_Cash Projection - Detail'!H:H,"SALE") -> 0 | J24: =I24/Q24 -> #NAME? | O24: PHP | P24: =_xll.BDP(O24&" L160 Curncy","PX_LAST") -> #NAME? | Q24: =P24 -> #NAME?
B25: PLN | C25: =SUMIFS('JP_Priced Positions_custody'!AK:AK,'JP_Priced Positions_custody'!AG:AG,B25,'JP_Priced Positions_custody'!A:A,$A$2,'JP_Priced Positions_custody'!L:L,"CASH") -> 0 | D25: =SUMIFS('JP_Priced Positions_custody'!AO:AO,'JP_Priced Positions_custody'!AG:AG,B25,'JP_Priced Positions_custody'!A:A,$A$2,'JP_Priced Positions_custody'!L:L,"CASH") -> 0 | E25: =SUMIFS('JP_Cash Projection - Statement'!N:N,'JP_Cash Projection - Statement'!E:E,'JP Code_Sheet'!$A$1,'JP_Cash Projection - Statement'!C:C,'JP Code_Sheet'!$A$33,'JP_Cash Projection - Statement'!A:A,'Currency Balance'!B25)+SUMIFS('JP_Cash Projection - Statement'!O:O,'JP_Cash Projection - Statement'!E:E,'JP Code_Sheet'!$A$1,'JP_Cash Projection - Statement'!C:C,'JP Code_Sheet'!$A$33,'JP_Cash Projection - Statement'!A:A,'Currency Balance'!B25)+SUMIFS('JP_Cash Projection - Statement'!R:R,'JP_Cash Projection - Statement'!E:E,'JP Code_Sheet'!$A$1,'JP_Cash Projection - Statement'!C:C,'JP Code_Sheet'!$A$33,'JP_Cash Projection - Statement'!A:A,'Currency Balance'!B25)+SUMIFS('JP_Cash Projection - Statement'!AA:AA,'JP_Cash Projection - Statement'!E:E,'JP Code_Sheet'!$A$1,'JP_Cash Projection - Statement'!C:C,'JP Code_Sheet'!$A$33,'JP_Cash Projection - Statement'!A:A,'Currency Balance'!B25)+SUMIFS('JP_Cash Projection - Statement'!AB:AB,'JP_Cash Projection - Statement'!E:E,'JP Code_Sheet'!$A$1,'JP_Cash Projection - Statement'!C:C,'JP Code_Sheet'!$A$33,'JP_Cash Projection - Statement'!A:A,'Currency Balance'!B25)+SUMIFS('JP_Cash Projection - Statement'!AE:AE,'JP_Cash Projection - Statement'!E:E,'JP Code_Sheet'!$A$1,'JP_Cash Projection - Statement'!C:C,'JP Code_Sheet'!$A$33,'JP_Cash Projection - Statement'!A:A,'Currency Balance'!B25) -> 0 | G25: =SUMIFS('JP_Cash Projection - Detail'!AV:AV,'JP_Cash Projection - Detail'!I:I,$A$2,'JP_Cash Projection - Detail'!K:K,B25,'JP_Cash Projection - Detail'!H:H,"PURCHASE") -> 0 | H25: =G25/Q25 -> #NAME? | I25: =SUMIFS('JP_Cash Projection - Detail'!AV:AV,'JP_Cash Projection - Detail'!I:I,$A$2,'JP_Cash Projection - Detail'!K:K,B25,'JP_Cash Projection - Detail'!H:H,"SALE") -> 0 | J25: =I25/Q25 -> #NAME? | O25: PLN | P25: =_xll.BDP(O25&" L160 Curncy","PX_LAST") -> #NAME? | Q25: =P25 -> #NAME?
B26: SEK | C26: =SUMIFS('JP_Priced Positions_custody'!AK:AK,'JP_Priced Positions_custody'!AG:AG,B26,'JP_Priced Positions_custody'!A:A,$A$2,'JP_Priced Positions_custody'!L:L,"CASH") -> 0 | D26: =SUMIFS('JP_Priced Positions_custody'!AO:AO,'JP_Priced Positions_custody'!AG:AG,B26,'JP_Priced Positions_custody'!A:A,$A$2,'JP_Priced Positions_custody'!L:L,"CASH") -> 0 | E26: =SUMIFS('JP_Cash Projection - Statement'!N:N,'JP_Cash Projection - Statement'!E:E,'JP Code_Sheet'!$A$1,'JP_Cash Projection - Statement'!C:C,'JP Code_Sheet'!$A$33,'JP_Cash Projection - Statement'!A:A,'Currency Balance'!B26)+SUMIFS('JP_Cash Projection - Statement'!O:O,'JP_Cash Projection - Statement'!E:E,'JP Code_Sheet'!$A$1,'JP_Cash Projection - Statement'!C:C,'JP Code_Sheet'!$A$33,'JP_Cash Projection - Statement'!A:A,'Currency Balance'!B26)+SUMIFS('JP_Cash Projection - Statement'!R:R,'JP_Cash Projection - Statement'!E:E,'JP Code_Sheet'!$A$1,'JP_Cash Projection - Statement'!C:C,'JP Code_Sheet'!$A$33,'JP_Cash Projection - Statement'!A:A,'Currency Balance'!B26)+SUMIFS('JP_Cash Projection - Statement'!AA:AA,'JP_Cash Projection - Statement'!E:E,'JP Code_Sheet'!$A$1,'JP_Cash Projection - Statement'!C:C,'JP Code_Sheet'!$A$33,'JP_Cash Projection - Statement'!A:A,'Currency Balance'!B26)+SUMIFS('JP_Cash Projection - Statement'!AB:AB,'JP_Cash Projection - Statement'!E:E,'JP Code_Sheet'!$A$1,'JP_Cash Projection - Statement'!C:C,'JP Code_Sheet'!$A$33,'JP_Cash Projection - Statement'!A:A,'Currency Balance'!B26)+SUMIFS('JP_Cash Projection - Statement'!AE:AE,'JP_Cash Projection - Statement'!E:E,'JP Code_Sheet'!$A$1,'JP_Cash Projection - Statement'!C:C,'JP Code_Sheet'!$A$33,'JP_Cash Projection - Statement'!A:A,'Currency Balance'!B26) -> 0 | G26: =SUMIFS('JP_Cash Projection - Detail'!AV:AV,'JP_Cash Projection - Detail'!I:I,$A$2,'JP_Cash Projection - Detail'!K:K,B26,'JP_Cash Projection - Detail'!H:H,"PURCHASE") -> 0 | H26: =G26/Q26 -> #NAME? | I26: =SUMIFS('JP_Cash Projection - Detail'!AV:AV,'JP_Cash Projection - Detail'!I:I,$A$2,'JP_Cash Projection - Detail'!K:K,B26,'JP_Cash Projection - Detail'!H:H,"SALE") -> 0 | J26: =I26/Q26 -> #NAME? | O26: SEK | P26: =_xll.BDP(O26&" L160 Curncy","PX_LAST") -> #NAME? | Q26: =P26 -> #NAME?
B27: SGD | C27: =SUMIFS('JP_Priced Positions_custody'!AK:AK,'JP_Priced Positions_custody'!AG:AG,B27,'JP_Priced Positions_custody'!A:A,$A$2,'JP_Priced Positions_custody'!L:L,"CASH") -> 0 | D27: =SUMIFS('JP_Priced Positions_custody'!AO:AO,'JP_Priced Positions_custody'!AG:AG,B27,'JP_Priced Positions_custody'!A:A,$A$2,'JP_Priced Positions_custody'!L:L,"CASH") -> 0 | E27: =SUMIFS('JP_Cash Projection - Statement'!N:N,'JP_Cash Projection - Statement'!E:E,'JP Code_Sheet'!$A$1,'JP_Cash Projection - Statement'!C:C,'JP Code_Sheet'!$A$33,'JP_Cash Projection - Statement'!A:A,'Currency Balance'!B27)+SUMIFS('JP_Cash Projection - Statement'!O:O,'JP_Cash Projection - Statement'!E:E,'JP Code_Sheet'!$A$1,'JP_Cash Projection - Statement'!C:C,'JP Code_Sheet'!$A$33,'JP_Cash Projection - Statement'!A:A,'Currency Balance'!B27)+SUMIFS('JP_Cash Projection - Statement'!R:R,'JP_Cash Projection - Statement'!E:E,'JP Code_Sheet'!$A$1,'JP_Cash Projection - Statement'!C:C,'JP Code_Sheet'!$A$33,'JP_Cash Projection - Statement'!A:A,'Currency Balance'!B27)+SUMIFS('JP_Cash Projection - Statement'!AA:AA,'JP_Cash Projection - Statement'!E:E,'JP Code_Sheet'!$A$1,'JP_Cash Projection - Statement'!C:C,'JP Code_Sheet'!$A$33,'JP_Cash Projection - Statement'!A:A,'Currency Balance'!B27)+SUMIFS('JP_Cash Projection - Statement'!AB:AB,'JP_Cash Projection - Statement'!E:E,'JP Code_Sheet'!$A$1,'JP_Cash Projection - Statement'!C:C,'JP Code_Sheet'!$A$33,'JP_Cash Projection - Statement'!A:A,'Currency Balance'!B27)+SUMIFS('JP_Cash Projection - Statement'!AE:AE,'JP_Cash Projection - Statement'!E:E,'JP Code_Sheet'!$A$1,'JP_Cash Projection - Statement'!C:C,'JP Code_Sheet'!$A$33,'JP_Cash Projection - Statement'!A:A,'Currency Balance'!B27) -> 0 | G27: =SUMIFS('JP_Cash Projection - Detail'!AV:AV,'JP_Cash Projection - Detail'!I:I,$A$2,'JP_Cash Projection - Detail'!K:K,B27,'JP_Cash Projection - Detail'!H:H,"PURCHASE") -> 0 | H27: =G27/Q27 -> #NAME? | I27: =SUMIFS('JP_Cash Projection - Detail'!AV:AV,'JP_Cash Projection - Detail'!I:I,$A$2,'JP_Cash Projection - Detail'!K:K,B27,'JP_Cash Projection - Detail'!H:H,"SALE") -> 0 | J27: =I27/Q27 -> #NAME? | O27: SGD | P27: =_xll.BDP(O27&" L160 Curncy","PX_LAST") -> #NAME? | Q27: =P27 -> #NAME?
B28: THB | C28: =SUMIFS('JP_Priced Positions_custody'!AK:AK,'JP_Priced Positions_custody'!AG:AG,B28,'JP_Priced Positions_custody'!A:A,$A$2,'JP_Priced Positions_custody'!L:L,"CASH") -> 0 | D28: =SUMIFS('JP_Priced Positions_custody'!AO:AO,'JP_Priced Positions_custody'!AG:AG,B28,'JP_Priced Positions_custody'!A:A,$A$2,'JP_Priced Positions_custody'!L:L,"CASH") -> 0 | E28: =SUMIFS('JP_Cash Projection - Statement'!N:N,'JP_Cash Projection - Statement'!E:E,'JP Code_Sheet'!$A$1,'JP_Cash Projection - Statement'!C:C,'JP Code_Sheet'!$A$33,'JP_Cash Projection - Statement'!A:A,'Currency Balance'!B28)+SUMIFS('JP_Cash Projection - Statement'!O:O,'JP_Cash Projection - Statement'!E:E,'JP Code_Sheet'!$A$1,'JP_Cash Projection - Statement'!C:C,'JP Code_Sheet'!$A$33,'JP_Cash Projection - Statement'!A:A,'Currency Balance'!B28)+SUMIFS('JP_Cash Projection - Statement'!R:R,'JP_Cash Projection - Statement'!E:E,'JP Code_Sheet'!$A$1,'JP_Cash Projection - Statement'!C:C,'JP Code_Sheet'!$A$33,'JP_Cash Projection - Statement'!A:A,'Currency Balance'!B28)+SUMIFS('JP_Cash Projection - Statement'!AA:AA,'JP_Cash Projection - Statement'!E:E,'JP Code_Sheet'!$A$1,'JP_Cash Projection - Statement'!C:C,'JP Code_Sheet'!$A$33,'JP_Cash Projection - Statement'!A:A,'Currency Balance'!B28)+SUMIFS('JP_Cash Projection - Statement'!AB:AB,'JP_Cash Projection - Statement'!E:E,'JP Code_Sheet'!$A$1,'JP_Cash Projection - Statement'!C:C,'JP Code_Sheet'!$A$33,'JP_Cash Projection - Statement'!A:A,'Currency Balance'!B28)+SUMIFS('JP_Cash Projection - Statement'!AE:AE,'JP_Cash Projection - Statement'!E:E,'JP Code_Sheet'!$A$1,'JP_Cash Projection - Statement'!C:C,'JP Code_Sheet'!$A$33,'JP_Cash Projection - Statement'!A:A,'Currency Balance'!B28) -> 0 | G28: =SUMIFS('JP_Cash Projection - Detail'!AV:AV,'JP_Cash Projection - Detail'!I:I,$A$2,'JP_Cash Projection - Detail'!K:K,B28,'JP_Cash Projection - Detail'!H:H,"PURCHASE") -> 0 | H28: =G28/Q28 -> #NAME? | I28: =SUMIFS('JP_Cash Projection - Detail'!AV:AV,'JP_Cash Projection - Detail'!I:I,$A$2,'JP_Cash Projection - Detail'!K:K,B28,'JP_Cash Projection - Detail'!H:H,"SALE") -> 0 | J28: =I28/Q28 -> #NAME? | O28: THB | P28: =_xll.BDP(O28&" L160 Curncy","PX_LAST") -> #NAME? | Q28: =P28 -> #NAME?
B29: TWD | C29: =SUMIFS('JP_Priced Positions_custody'!AK:AK,'JP_Priced Positions_custody'!AG:AG,B29,'JP_Priced Positions_custody'!A:A,$A$2,'JP_Priced Positions_custody'!L:L,"CASH") -> 0 | D29: =SUMIFS('JP_Priced Positions_custody'!AO:AO,'JP_Priced Positions_custody'!AG:AG,B29,'JP_Priced Positions_custody'!A:A,$A$2,'JP_Priced Positions_custody'!L:L,"CASH") -> 0 | E29: =SUMIFS('JP_Cash Projection - Statement'!N:N,'JP_Cash Projection - Statement'!E:E,'JP Code_Sheet'!$A$1,'JP_Cash Projection - Statement'!C:C,'JP Code_Sheet'!$A$33,'JP_Cash Projection - Statement'!A:A,'Currency Balance'!B29)+SUMIFS('JP_Cash Projection - Statement'!O:O,'JP_Cash Projection - Statement'!E:E,'JP Code_Sheet'!$A$1,'JP_Cash Projection - Statement'!C:C,'JP Code_Sheet'!$A$33,'JP_Cash Projection - Statement'!A:A,'Currency Balance'!B29)+SUMIFS('JP_Cash Projection - Statement'!R:R,'JP_Cash Projection - Statement'!E:E,'JP Code_Sheet'!$A$1,'JP_Cash Projection - Statement'!C:C,'JP Code_Sheet'!$A$33,'JP_Cash Projection - Statement'!A:A,'Currency Balance'!B29)+SUMIFS('JP_Cash Projection - Statement'!AA:AA,'JP_Cash Projection - Statement'!E:E,'JP Code_Sheet'!$A$1,'JP_Cash Projection - Statement'!C:C,'JP Code_Sheet'!$A$33,'JP_Cash Projection - Statement'!A:A,'Currency Balance'!B29)+SUMIFS('JP_Cash Projection - Statement'!AB:AB,'JP_Cash Projection - Statement'!E:E,'JP Code_Sheet'!$A$1,'JP_Cash Projection - Statement'!C:C,'JP Code_Sheet'!$A$33,'JP_Cash Projection - Statement'!A:A,'Currency Balance'!B29)+SUMIFS('JP_Cash Projection - Statement'!AE:AE,'JP_Cash Projection - Statement'!E:E,'JP Code_Sheet'!$A$1,'JP_Cash Projection - Statement'!C:C,'JP Code_Sheet'!$A$33,'JP_Cash Projection - Statement'!A:A,'Currency Balance'!B29) -> 0 | G29: =SUMIFS('JP_Cash Projection - Detail'!AV:AV,'JP_Cash Projection - Detail'!I:I,$A$2,'JP_Cash Projection - Detail'!K:K,B29,'JP_Cash Projection - Detail'!H:H,"PURCHASE") -> 0 | H29: =G29/Q29 -> #NAME? | I29: =SUMIFS('JP_Cash Projection - Detail'!AV:AV,'JP_Cash Projection - Detail'!I:I,$A$2,'JP_Cash Projection - Detail'!K:K,B29,'JP_Cash Projection - Detail'!H:H,"SALE") -> 0 | J29: =I29/Q29 -> #NAME? | O29: TWD | P29: =_xll.BDP(O29&" L160 Curncy","PX_LAST") -> #NAME? | Q29: =P29 -> #NAME?
B30: ZAR | C30: =SUMIFS('JP_Priced Positions_custody'!AK:AK,'JP_Priced Positions_custody'!AG:AG,B30,'JP_Priced Positions_custody'!A:A,$A$2,'JP_Priced Positions_custody'!L:L,"CASH") -> 0 | D30: =SUMIFS('JP_Priced Positions_custody'!AO:AO,'JP_Priced Positions_custody'!AG:AG,B30,'JP_Priced Positions_custody'!A:A,$A$2,'JP_Priced Positions_custody'!L:L,"CASH") -> 0 | E30: =SUMIFS('JP_Cash Projection - Statement'!N:N,'JP_Cash Projection - Statement'!E:E,'JP Code_Sheet'!$A$1,'JP_Cash Projection - Statement'!C:C,'JP Code_Sheet'!$A$33,'JP_Cash Projection - Statement'!A:A,'Currency Balance'!B30)+SUMIFS('JP_Cash Projection - Statement'!O:O,'JP_Cash Projection - Statement'!E:E,'JP Code_Sheet'!$A$1,'JP_Cash Projection - Statement'!C:C,'JP Code_Sheet'!$A$33,'JP_Cash Projection - Statement'!A:A,'Currency Balance'!B30)+SUMIFS('JP_Cash Projection - Statement'!R:R,'JP_Cash Projection - Statement'!E:E,'JP Code_Sheet'!$A$1,'JP_Cash Projection - Statement'!C:C,'JP Code_Sheet'!$A$33,'JP_Cash Projection - Statement'!A:A,'Currency Balance'!B30)+SUMIFS('JP_Cash Projection - Statement'!AA:AA,'JP_Cash Projection - Statement'!E:E,'JP Code_Sheet'!$A$1,'JP_Cash Projection - Statement'!C:C,'JP Code_Sheet'!$A$33,'JP_Cash Projection - Statement'!A:A,'Currency Balance'!B30)+SUMIFS('JP_Cash Projection - Statement'!AB:AB,'JP_Cash Projection - Statement'!E:E,'JP Code_Sheet'!$A$1,'JP_Cash Projection - Statement'!C:C,'JP Code_Sheet'!$A$33,'JP_Cash Projection - Statement'!A:A,'Currency Balance'!B30)+SUMIFS('JP_Cash Projection - Statement'!AE:AE,'JP_Cash Projection - Statement'!E:E,'JP Code_Sheet'!$A$1,'JP_Cash Projection - Statement'!C:C,'JP Code_Sheet'!$A$33,'JP_Cash Projection - Statement'!A:A,'Currency Balance'!B30) -> 0 | G30: =SUMIFS('JP_Cash Projection - Detail'!AV:AV,'JP_Cash Projection - Detail'!I:I,$A$2,'JP_Cash Projection - Detail'!K:K,B30,'JP_Cash Projection - Detail'!H:H,"PURCHASE") -> 0 | H30: =G30/Q30 -> #NAME? | I30: =SUMIFS('JP_Cash Projection - Detail'!AV:AV,'JP_Cash Projection - Detail'!I:I,$A$2,'JP_Cash Projection - Detail'!K:K,B30,'JP_Cash Projection - Detail'!H:H,"SALE") -> 0 | J30: =I30/Q30 -> #NAME? | O30: ZAR | P30: =_xll.BDP(O30&" L160 Curncy","PX_LAST") -> #NAME? | Q30: =P30 -> #NAME?
B31: TRY | C31: =SUMIFS('JP_Priced Positions_custody'!AK:AK,'JP_Priced Positions_custody'!AG:AG,B31,'JP_Priced Positions_custody'!A:A,$A$2,'JP_Priced Positions_custody'!L:L,"CASH") -> 0 | D31: =SUMIFS('JP_Priced Positions_custody'!AO:AO,'JP_Priced Positions_custody'!AG:AG,B31,'JP_Priced Positions_custody'!A:A,$A$2,'JP_Priced Positions_custody'!L:L,"CASH") -> 0 | E31: =SUMIFS('JP_Cash Projection - Statement'!N:N,'JP_Cash Projection - Statement'!E:E,'JP Code_Sheet'!$A$1,'JP_Cash Projection - Statement'!C:C,'JP Code_Sheet'!$A$33,'JP_Cash Projection - Statement'!A:A,'Currency Balance'!B31)+SUMIFS('JP_Cash Projection - Statement'!O:O,'JP_Cash Projection - Statement'!E:E,'JP Code_Sheet'!$A$1,'JP_Cash Projection - Statement'!C:C,'JP Code_Sheet'!$A$33,'JP_Cash Projection - Statement'!A:A,'Currency Balance'!B31)+SUMIFS('JP_Cash Projection - Statement'!R:R,'JP_Cash Projection - Statement'!E:E,'JP Code_Sheet'!$A$1,'JP_Cash Projection - Statement'!C:C,'JP Code_Sheet'!$A$33,'JP_Cash Projection - Statement'!A:A,'Currency Balance'!B31)+SUMIFS('JP_Cash Projection - Statement'!AA:AA,'JP_Cash Projection - Statement'!E:E,'JP Code_Sheet'!$A$1,'JP_Cash Projection - Statement'!C:C,'JP Code_Sheet'!$A$33,'JP_Cash Projection - Statement'!A:A,'Currency Balance'!B31)+SUMIFS('JP_Cash Projection - Statement'!AB:AB,'JP_Cash Projection - Statement'!E:E,'JP Code_Sheet'!$A$1,'JP_Cash Projection - Statement'!C:C,'JP Code_Sheet'!$A$33,'JP_Cash Projection - Statement'!A:A,'Currency Balance'!B31)+SUMIFS('JP_Cash Projection - Statement'!AE:AE,'JP_Cash Projection - Statement'!E:E,'JP Code_Sheet'!$A$1,'JP_Cash Projection - Statement'!C:C,'JP Code_Sheet'!$A$33,'JP_Cash Projection - Statement'!A:A,'Currency Balance'!B31) -> 0 | G31: =SUMIFS('JP_Cash Projection - Detail'!AV:AV,'JP_Cash Projection - Detail'!I:I,$A$2,'JP_Cash Projection - Detail'!K:K,B31,'JP_Cash Projection - Detail'!H:H,"PURCHASE") -> 0 | H31: =G31/Q31 -> #NAME? | I31: =SUMIFS('JP_Cash Projection - Detail'!AV:AV,'JP_Cash Projection - Detail'!I:I,$A$2,'JP_Cash Projection - Detail'!K:K,B31,'JP_Cash Projection - Detail'!H:H,"SALE") -> 0 | J31: =I31/Q31 -> #NAME? | O31: TRY | P31: =_xll.BDP(O31&" L160 Curncy","PX_LAST") -> #NAME? | Q31: =P31 -> #NAME?
B32: USD | C32: =SUMIFS('JP_Priced Positions_custody'!AK:AK,'JP_Priced Positions_custody'!AG:AG,B32,'JP_Priced Positions_custody'!A:A,$A$2,'JP_Priced Positions_custody'!L:L,"CASH") -> 0 | D32: =SUMIFS('JP_Priced Positions_custody'!AO:AO,'JP_Priced Positions_custody'!AG:AG,B32,'JP_Priced Positions_custody'!A:A,$A$2,'JP_Priced Positions_custody'!L:L,"CASH") -> 0 | E32: =SUMIFS('JP_Cash Projection - Statement'!N:N,'JP_Cash Projection - Statement'!E:E,'JP Code_Sheet'!$A$1,'JP_Cash Projection - Statement'!C:C,'JP Code_Sheet'!$A$33,'JP_Cash Projection - Statement'!A:A,'Currency Balance'!B32)+SUMIFS('JP_Cash Projection - Statement'!O:O,'JP_Cash Projection - Statement'!E:E,'JP Code_Sheet'!$A$1,'JP_Cash Projection - Statement'!C:C,'JP Code_Sheet'!$A$33,'JP_Cash Projection - Statement'!A:A,'Currency Balance'!B32)+SUMIFS('JP_Cash Projection - Statement'!R:R,'JP_Cash Projection - Statement'!E:E,'JP Code_Sheet'!$A$1,'JP_Cash Projection - Statement'!C:C,'JP Code_Sheet'!$A$33,'JP_Cash Projection - Statement'!A:A,'Currency Balance'!B32)+SUMIFS('JP_Cash Projection - Statement'!AA:AA,'JP_Cash Projection - Statement'!E:E,'JP Code_Sheet'!$A$1,'JP_Cash Projection - Statement'!C:C,'JP Code_Sheet'!$A$33,'JP_Cash Projection - Statement'!A:A,'Currency Balance'!B32)+SUMIFS('JP_Cash Projection - Statement'!AB:AB,'JP_Cash Projection - Statement'!E:E,'JP Code_Sheet'!$A$1,'JP_Cash Projection - Statement'!C:C,'JP Code_Sheet'!$A$33,'JP_Cash Projection - Statement'!A:A,'Currency Balance'!B32)+SUMIFS('JP_Cash Projection - Statement'!AE:AE,'JP_Cash Projection - Statement'!E:E,'JP Code_Sheet'!$A$1,'JP_Cash Projection - Statement'!C:C,'JP Code_Sheet'!$A$33,'JP_Cash Projection - Statement'!A:A,'Currency Balance'!B32) -> 0 | G32: =SUM(G3:G30) -> 0 | H32: =SUM(H3:H30) -> #NAME? | I32: =SUM(I3:I30) -> 0 | J32: =SUM(J3:J30) -> #NAME? | O32: USD | P32: =_xll.BDP(O32&" L160 Curncy","PX_LAST") -> #NAME? | Q32: 1
C33: =SUM(C3:C32) -> 0 | D33: =SUM(D3:D32) -> 0 | E33: =SUM(E3:E32) -> 0 | J33: =H32+J32 -> #NAME? | K33: NET
C36: Priced Positions | D36: Priced Positions | E36: Cash projection | G36: CASH PROJECTION | H36: Cash projection doesn't reflect Base | I36: CASH PROJECTION | J36: Cash projection doesn't reflect Base
G37: Will be off due to T+1 | H37: Had to custom calc | I37: Will be off due to T+1 | J37: Had to custom calc
G38: Use Eze? | I38: Use Eze?
G42: NET (LOCAL) | H42: Net (BASE)
G43: Failing Equity Trades | H43: Failing Equity Trades
B44: AUD | G44: =SUMIFS('JP_Outstanding Trades'!W:W,'JP_Outstanding Trades'!A:A,$A$2,'JP_Outstanding Trades'!C:C,B44) -> 0 | H44: =G44/Q3 -> #NAME?
B45: BRL | G45: =SUMIFS('JP_Outstanding Trades'!W:W,'JP_Outstanding Trades'!A:A,$A$2,'JP_Outstanding Trades'!C:C,B45) -> 0 | H45: =G45/Q4 -> #NAME?
B46: CAD | G46: =SUMIFS('JP_Outstanding Trades'!W:W,'JP_Outstanding Trades'!A:A,$A$2,'JP_Outstanding Trades'!C:C,B46) -> 0 | H46: =G46/Q5 -> #NAME?
B47: CHF | G47: =SUMIFS('JP_Outstanding Trades'!W:W,'JP_Outstanding Trades'!A:A,$A$2,'JP_Outstanding Trades'!C:C,B47) -> 0 | H47: =G47/Q6 -> #NAME?
B48: CLP | G48: =SUMIFS('JP_Outstanding Trades'!W:W,'JP_Outstanding Trades'!A:A,$A$2,'JP_Outstanding Trades'!C:C,B48) -> 0 | H48: =G48/Q7 -> #NAME?
B49: COP | G49: =SUMIFS('JP_Outstanding Trades'!W:W,'JP_Outstanding Trades'!A:A,$A$2,'JP_Outstanding Trades'!C:C,B49) -> 0 | H49: =G49/Q8 -> #NAME?
B50: CZK | G50: =SUMIFS('JP_Outstanding Trades'!W:W,'JP_Outstanding Trades'!A:A,$A$2,'JP_Outstanding Trades'!C:C,B50) -> 0 | H50: =G50/Q9 -> #NAME?
B51: DKK | G51: =SUMIFS('JP_Outstanding Trades'!W:W,'JP_Outstanding Trades'!A:A,$A$2,'JP_Outstanding Trades'!C:C,B51) -> 0 | H51: =G51/Q10 -> #NAME?
B52: EUR | G52: =SUMIFS('JP_Outstanding Trades'!W:W,'JP_Outstanding Trades'!A:A,$A$2,'JP_Outstanding Trades'!C:C,B52) -> 0 | H52: =G52/Q11 -> #NAME?
B53: GBP | G53: =SUMIFS('JP_Outstanding Trades'!W:W,'JP_Outstanding Trades'!A:A,$A$2,'JP_Outstanding Trades'!C:C,B53) -> 0 | H53: =G53/Q12 -> #NAME?
B54: HKD | G54: =SUMIFS('JP_Outstanding Trades'!W:W,'JP_Outstanding Trades'!A:A,$A$2,'JP_Outstanding Trades'!C:C,B54) -> 0 | H54: =G54/Q13 -> #NAME?
B55: HUF | G55: =SUMIFS('JP_Outstanding Trades'!W:W,'JP_Outstanding Trades'!A:A,$A$2,'JP_Outstanding Trades'!C:C,B55) -> 0 | H55: =G55/Q14 -> #NAME?
... B71: ZAR | G71: =SUMIFS('JP_Outstanding Trades'!W:W,'JP_Outstanding Trades'!A:A,$A$2,'JP_Outstanding Trades'!C:C,B71) -> 0 | H71: =G71/Q30 -> #NAME?
H73: =SUM(H44:H72) -> #NAME? | I73: Failed Trades

Sheet OCIO CASH
B2: ACCOUNT | C2: EQUITY MV | D2: ETF MV | E2: FUT_MV | F2: MKT VAL
B3: FOUNDLCE | E3: - | G3: =D3/F3 -> #DIV/0!
B4: GIAACWIP | G4: =D4/F4 -> #DIV/0!
B5: GIALCEP | G5: =D5/F5 -> #DIV/0!
B6: MAINSP | G6: =E6/F6 -> #DIV/0!
B7: NYLPIE | G7: =D7/F7 -> #DIV/0!
B8: VPIE | G8: =E8/F8 -> #DIV/0!
B9: GIA1902
B10: IQ50ETF
B11: IQSMAETF
B12: LINAETF
B13: NYLIC 1940
B14: NYLIC1976
B15: NYLINT
B16: NYLIQETF
B17: SSC1901
B18: NYLIM225

Sheet Websites
C2: www.jpmm.com | E2: Dakota12
C3: https://nexen.bnymellon.com/app/nxn/login | D3: ixq.gbarrato | E3: Ellahudson1212?

Sheet Eze Export_equitizer_MAINSP
A1: Portfolio:MAINSP_x000D_ Currency:USD
B2: SecType | C2: Symbol | D2: Sedol | E2: SecurityDesc | F2: IQCLOSE | G2: Shares | H2: CurrentMktVal* | I2: CurrentMktVal% | J2: FinalMktValue* | K2: BuyChangeAmount | L2: SellChangeAmount

Sheet Equitizer_Mainsp_CALC
A1: MAINSP
D3: Prior Day Price | E3: Ticker | F3: Contracts | G3: Price | H3: Mkt Val | I3: Prior day close | L3: Mkt Val After trades (T+0)
C4: 44722 | E4: =Francis!AH2 -> 0 | H4: =F4*G4*50 -> 0 | J4: =D4*50*F4 -> 0 | K4: =H4-J4 -> 0
D5: {=_xll.BDP(E5&" INDEX","px_close_2d")} -> #NAME? | E5: =Francis!AH2 -> 0 | F5: =SUMIFS('Eze Export_equitizer_MAINSP'!G:G,'Eze Export_equitizer_MAINSP'!C:C,E5) -> 0 | G5: {=_xll.BDP(E5&" index","PX_YEST_CLOSE")} -> #NAME? | H5: =F5*G5*50 -> #NAME? | J5: =D5*50*F5 -> #NAME? | K5: =H5-J5 -> #NAME?
A6: Futures | B6: FUT | H6: =SUMIF('Eze Export_equitizer_MAINSP'!B:B,B6,'Eze Export_equitizer_MAINSP'!H:H) -> 0 | K6: =SUM(K4:K5) -> #NAME? | L6: =H6-H25 -> #N/A
M7: Equity Basket Live | O7: Futures | P7: SPY
F8: MOC Trade (T+1)
F9: SOD | H9: =Francis!E2 -> #N/A
F10: Income | H10: =Francis!I2 -> #N/A
F11: Sweep | H11: =Francis!J2 -> #N/A
F12: Sub/Red | H12: =Francis!R2 -> #N/A
F13: Futures Variation | H13: =K6 -> #NAME?
E14: =TODAY() -> 45467 | F14: Pending Trades (TO) | H14: =Francis!G2 -> #N/A
A15: CASH | H15: =SUM(H9:H14) -> #N/A
A17: T BIL | B17: TBUS | H17: =SUMIF('Eze Export_equitizer_MAINSP'!B:B,B17,'Eze Export_equitizer_MAINSP'!H:H) -> 0 | L17: =H17-H21 -> #N/A
A18: ETF | B18: SPY | F18: =SUMIFS('Eze Export_equitizer_MAINSP'!G:G,'Eze Export_equitizer_MAINSP'!C:C,B18) -> 0 | G18: {=_xll.BDP(B18&" equity","PX_YEST_CLOSE")} -> #NAME? | H18: =F18*G18 -> #NAME?
A20: Trades | D20: Last Price | E20: Security | F20: Direction | G20: Shares
E21: T Bill (T+0) | F21: =IF(H21<0,"BUY","Sell") -> #N/A | H21: =-ROUNDDOWN(H15/100000,0)*100000 -> #N/A
D22: {=_xll.BDP("spy equity","PX_LAST")} -> #NAME? | E22: SPY (T+1) | F22: =IF(H22<0,"BUY","Sell") -> #N/A | G22: =H22/D22 -> #N/A | H22: =-H15-H21 -> #N/A | L22: =IF(F18-G22<0,"Not Enough to Sell, increase T Bill trade ","Trade") -> #N/A
F23: =IF(H23>0,"RAISE","SPEND") -> #N/A | H23: =SUM(H21:H22) -> #N/A
A25: Investible | C25: =L17-H6 -> #N/A | D25: {=_xll.BDP(E25&" index","PX_LAST")} -> #NAME? | E25: =E5 -> 0 | F25: =IF(G25<0,"BUY","Sell") -> #N/A | G25: =-ROUNDDOWN(C25/(1*50*D25),0) -> #N/A | H25: =G25*50*D25 -> #N/A
D28: Fund Market Val | E28: T+1 Cash Projection | F28: T+1 Investable | G28: Futures Mrkt Val | H28: T BIL Mrkt Val
D29: =SUMIFS('Eze Export_equitizer_MAINSP'!J:J,'Eze Export_equitizer_MAINSP'!B:B,"FUT")+SUMIFS('Eze Export_equitizer_MAINSP'!J:J,'Eze Export_equitizer_MAINSP'!B:B,"CSUS")+SUMIFS('Eze Export_equitizer_MAINSP'!J:J,'Eze Export_equitizer_MAINSP'!B:B,"TBUS") -> 0 | E29: =H23+H15 -> #N/A | F29: =H29-G29 -> #N/A | G29: =L6 -> #N/A | H29: =L17 -> #N/A
E30: =E29/D29 -> #N/A | G30: =G29/D29 -> #N/A | H30: =H29/D29 -> #N/A
D34: Pending Trades (exclude futures?)

Sheet Eze Export_equitizer_VPIE
A1: Portfolio:VPIE_x000D_ Currency:USD
B2: SecType | C2: Symbol | D2: Sedol | E2: SecurityDesc | F2: IQCLOSE | G2: Shares | H2: CurrentMktVal* | I2: CurrentMktVal% | J2: FinalMktValue* | K2: BuyChangeAmount | L2: SellChangeAmount

Sheet Equitizer_VPIE_CALC
A1: VPIE
D3: Prior Day Price | E3: Ticker | F3: Contracts (EZE) | G3: Price | H3: Mkt Val | I3: Prior day close | L3: Mkt Val After trades (T+0)
E4: =Francis!AH3 -> 0 | H4: =F4*G4*50 -> 0 | K4: =H4-J4 -> 0
D5: {=_xll.BDP(E5&" INDEX","px_close_2d")} -> #NAME? | E5: =Francis!AH3 -> 0 | F5: =SUMIFS('Eze Export_equitizer_VPIE'!G:G,'Eze Export_equitizer_VPIE'!C:C,E5) -> 0 | G5: {=_xll.BDP(E5&" index","PX_YEST_CLOSE")} -> #NAME? | H5: =F5*G5*50 -> #NAME? | J5: =D5*50*F5 -> #NAME? | K5: =H5-J5 -> #NAME?
A6: Futures | B6: FUT | H6: =SUMIF('Eze Export_equitizer_VPIE'!B:B,B6,'Eze Export_equitizer_VPIE'!H:H) -> 0 | K6: =SUM(K4:K5) -> #NAME? | L6: =H6-H25 -> #N/A
M7: Equity Basket Live | O7: Futures | P7: SPY
F8: MOC Trade (T+1) | L8: =H8/D29 -> #DIV/0!
F9: SOD | H9: =Francis!E3 -> #N/A
F10: Income | H10: =Francis!I3 -> #N/A
F11: Sweep | H11: =Francis!J3 -> #N/A
F12: Sub/Red | H12: =Francis!R3 -> #N/A
F13: Futures Variation | H13: =K6 -> #NAME?
E14: =TODAY() -> 45467 | F14: Pending Trades (TO) | H14: =Francis!G3 -> #N/A
A15: CASH | H15: =SUM(H9:H14) -> #N/A
A17: T BIL | B17: TBUS | H17: =SUMIF('Eze Export_equitizer_VPIE'!B:B,B17,'Eze Export_equitizer_VPIE'!H:H) -> 0 | L17: =H17-H21 -> #N/A
A18: ETF | B18: SPY | F18: =SUMIFS('Eze Export_equitizer_VPIE'!G:G,'Eze Export_equitizer_VPIE'!C:C,B18) -> 0 | G18: {=_xll.BDP(B18&" equity","PX_YEST_CLOSE")} -> #NAME? | H18: =F18*G18 -> #NAME?
A20: Trades | D20: Last Price | E20: Security | F20: Direction | G20: Shares
E21: T Bill (T+0) | F21: =IF(H21<0,"BUY","Sell") -> #N/A | H21: =-ROUNDDOWN(H15/100000,0)*100000 -> #N/A
D22: {=_xll.BDP("spy equity","PX_LAST")} -> #NAME? | E22: SPY (T+1) | F22: =IF(H22<0,"BUY","Sell") -> #N/A | G22: =H22/D22 -> #N/A | H22: =-H15-H21 -> #N/A | L22: =IF(F18-G22<0,"Not Enough to Sell, increase T Bill trade ","Trade") -> #N/A
F23: =IF(H23>0,"RAISE","SPEND") -> #N/A | H23: =SUM(H21:H22) -> #N/A
A25: Investible | C25: =L17-H6 -> #N/A | D25: {=_xll.BDP(E25&" index","PX_LAST")} -> #NAME? | E25: =E5 -> 0 | F25: =IF(G25<0,"BUY","Sell") -> #N/A | G25: =-ROUNDDOWN(C25/(1*50*D25),0) -> #N/A | H25: =G25*50*D25 -> #N/A
D28: Fund Market Val | E28: T+1 Cash Projection | F28: T+1 Investable | G28: Futures Mrkt Val | H28: T BIL Mrkt Val
D29: =SUMIFS('Eze Export_equitizer_VPIE'!J:J,'Eze Export_equitizer_VPIE'!B:B,"FUT")+SUMIFS('Eze Export_equitizer_VPIE'!J:J,'Eze Export_equitizer_VPIE'!B:B,"CSUS")+SUMIFS('Eze Export_equitizer_VPIE'!J:J,'Eze Export_equitizer_VPIE'!B:B,"TBUS") -> 0 | E29: =H23+H15 -> #N/A | F29: =H29-G29 -> #N/A | G29: =L6 -> #N/A | H29: =L17 -> #N/A
E30: =E29/D29 -> #N/A | G30: =G29/D29 -> #N/A | H30: =H29/D29 -> #N/A
D34: Pending Trades (exclude futures?)

Sheet Detailed Net Asset Valuation

Sheet IQ
B1: =TODAY() -> 45467 | C1: Drives Sheet | G1: (Global & Domestic) | O1: Target | T1: TOTAL_NUMBER_OF_HOLDINGS_IN_PORT | W1: Income | AJ1: EOW
A2: Custody # | B2: Portfolio | C2: Name of Fund | D2: SOD Cash(USD: cash projections) | E2: SOD Cash FX (base) | F2: Pending Trades +Failing (JP/BNY) | G2: Income (projections today) | H2: Total Cash | I2: Equity MV (priced positions) | J2: Total Assets | K2: Percent Cash | M2: P5 AUM | N2: % of Custody Cash | O2: 0.0006 | P2: Trade | Q2: Target Trade $ | R2: Direction | S2: Fund | T2: Holdings In Portfolio | U2: Equitize Options | W2: =E24 -> 45468 | X2: =F24 -> 45469 | Y2: =G24 -> 45470 | Z2: =H24 -> 45471 | AA2: =I24 -> 45472 | AB2: =J24 -> 45473 | AC2: Total Projected Income (paydate) | AD2: % of AUM | AG2: =D24 -> 45467 | AH2: Today Income Impact | AJ2: Projected Cash % | AO2: NAV | AP2: EQY_SH_OUT_REAL | AQ2: P5
